Workbook
Name Settings.AllowCalibrationUpdates: SETTINGS!$C$10
Name Settings.BloombergPCS: SETTINGS!$C$6
Name Settings.COB: SETTINGS!$C$4
Name Settings.CurveSide.MidBidAsk: SETTINGS!$C$7
Name Settings.EnableCurveChart: SETTINGS!$C$9
Name Settings.Futures.Convexity.HW1F.Vol: SETTINGS!$C$8
Name Settings.isCOBToday: SETTINGS!$C$3
Name Settings.SwapCurve.Interpolation: SETTINGS!$C$11

Sheet SETTINGS
U1: … Curve Display
B2: Settings | E2: AUD Curve Chart | N2: Curve Display Settings | Q2: {=IF(AND($C$9,'AUD CURVE'!$D$99),_xll.meLWOCurveForwardRatesTable($N$8,$O$8:$O$10,$O$3,$O$4,,,,$O$5),NA())} -> Fixing Dates | R2: AUDOIS | S2: AUD3ML | T2: AUD6ML
B3: isCOBToday | C3: =IF(ISBLANK(C5),TRUE,FALSE) -> TRUE | N3: Start | O3: 0Y | Q3: 43278 | R3: 0.015 | S3: 0.021153 | T3: 0.0223
B4: CloseOfBusiness (COB) | C4: =IF(Settings.isCOBToday,TODAY(),$C$5) -> 43278 | N4: Maturity | O4: 20Y | Q4: 43370 | R4: 0.014954485 | S4: 0.020788961 | T4: 0.021441746
B5: OverrideDate | N5: Frequency | O5: QUARTERLY | Q5: 43461 | R5: 0.015027709 | S5: 0.020491992 | T5: 0.021345432
B6: PricingSource (PCS) | C6: BGN | Q6: 43551 | R6: 0.015289466 | S6: 0.020367846 | T6: 0.02170144
B7: CurveSide (Bid-Offer) | C7: PX_MID | N7: CurveCollection | O7: CurveIndices | Q7: 43643 | R7: 0.015863105 | S7: 0.020419166 | T7: 0.022348053
B8: Futures.Convexity.HW1F.Vol (%) | C8: 0.02 | N8: AUDYC | O8: AUDOIS | Q8: 43735 | R8: 0.016600308 | S8: 0.020640007 | T8: 0.022948639
B9: EnableCurveChart | C9: TRUE | O9: AUD3ML | Q9: 43826 | R9: 0.017254182 | S9: 0.020977274 | T9: 0.023407493
B10: AllowCalibrationUpdates | C10: FALSE | O10: AUD6ML | Q10: 43917 | R10: 0.017790877 | S10: 0.021543652 | T10: 0.023729701
B11: SwapCurve.Interpolation | C11: SPLINE | Q11: 44011 | R11: 0.018316948 | S11: 0.02226326 | T11: 0.024042487
Q12: 44102 | R12: 0.018799749 | S12: 0.022913696 | T12: 0.024447276
Q13: 44193 | R13: 0.019285888 | S13: 0.023530049 | T13: 0.024953811
B14: Curve Data Monitor | Q14: 44284 | R14: 0.019831035 | S14: 0.024010958 | T14: 0.025531549
B15: Curve | C15: MissingDataPts | Q15: 44375 | R15: 0.020327109 | S15: 0.024418316 | T15: 0.026133814
B16: AUDOIS | C16: ='AUD CURVE TICKERS'!C4 -> 0 | Q16: 44466 | R16: 0.02083202 | S16: 0.02486447 | T16: 0.026720478
B17: AUD3ML | C17: ='AUD CURVE TICKERS'!F4 -> 0 | Q17: 44557 | R17: 0.021350917 | S17: 0.025367018 | T17: 0.027286785
B18: AUD6ML | C18: ='AUD CURVE TICKERS'!I4 -> 0 | Q18: 44648 | R18: 0.021884216 | S18: 0.025949751 | T18: 0.027832051
Q19: 44739 | R19: 0.022432355 | S19: 0.026564769 | T19: 0.028335252
B20: Fixing.Data | C20: ='AUD CURVE TICKERS'!F5 -> 0 | Q20: 44831 | R20: 0.022940234 | S20: 0.027123631 | T20: 0.02878062
B21: Futures.Data | C21: ='AUD CURVE TICKERS'!F6 -> 0 | Q21: 44922 | R21: 0.023333547 | S21: 0.027593418 | T21: 0.029163872
B22: Futures.Dates | C22: ='AUD CURVE TICKERS'!F7 -> 0 | Q22: 45012 | R22: 0.023613422 | S22: 0.027985809 | T22: 0.029495957
Q23: 45104 | R23: 0.023784712 | S23: 0.028308267 | T23: 0.029785106
Q24: 45196 | R24: 0.023918999 | S24: 0.028607558 | T24: 0.030025859
Q25: 45287 | R25: 0.024097479 | S25: 0.028820954 | T25: 0.030249303
Q26: 45378 | R26: 0.024255351 | S26: 0.029101383 | T26: 0.030492581
Q27: 45470 | R27: 0.024529527 | S27: 0.029389068 | T27: 0.030772257
Q28: 45562 | R28: 0.024848783 | S28: 0.029679871 | T28: 0.031086879
Q29: 45653 | R29: 0.025190074 | S29: 0.030083128 | T29: 0.031407979
Q30: 45743 | R30: 0.025623039 | S30: 0.030440108 | T30: 0.031705474
Q31: 45835 | R31: 0.02603979 | S31: 0.030788082 | T31: 0.031955201
Q32: 45929 | R32: 0.026416834 | S32: 0.031049469 | T32: 0.032123427
Q33: 46020 | R33: 0.026678602 | S33: 0.031184148 | T33: 0.032194169
Q34: 46108 | R34: 0.026829487 | S34: 0.03120182 | T34: 0.032187726
... Q83: 50584 | R83: 0.025420904 | S83: 0.030003636 | T83: 0.031180663
Q84: #N/A | R84: #N/A | S84: #N/A | T84: #N/A
Q85: #N/A | R85: #N/A | S85: #N/A | T85: #N/A
Q86: #N/A | R86: #N/A | S86: #N/A | T86: #N/A
Q87: #N/A | R87: #N/A | S87: #N/A | T87: #N/A
Q88: #N/A | R88: #N/A | S88: #N/A | T88: #N/A
Q89: #N/A | R89: #N/A | S89: #N/A | T89: #N/A
Q90: #N/A | R90: #N/A | S90: #N/A | T90: #N/A
Q91: #N/A | R91: #N/A | S91: #N/A | T91: #N/A
Q92: #N/A | R92: #N/A | S92: #N/A | T92: #N/A
Q93: #N/A | R93: #N/A | S93: #N/A | T93: #N/A
Q94: #N/A | R94: #N/A | S94: #N/A | T94: #N/A
Q95: #N/A | R95: #N/A | S95: #N/A | T95: #N/A
... Q199: #N/A | R199: #N/A | S199: #N/A | T199: #N/A

Sheet AUD CURVE TICKERS
B2: Check for Missing Instrument Data
B4: AUDOIS | C4: =SUM(C5:C8) -> 0 | E4: AUD3ML | F4: =SUM(F5:F9) -> 0 | H4: AUD6ML | I4: =SUM(I5:I7) -> 0
B5: OIS.Outrights | C5: =COUNTA(B14:B36)-COUNT(J14:J36) -> 0 | E5: Swap3M.LiborFixings | F5: =COUNTA(B44:B66)-COUNT(J44:J66) -> 0 | H5: Swap6M.Fixings | I5: =F5 -> 0
B6: OIS.LiborOIS | C6: =COUNTA(L14:L36)-COUNT(T14:T36) -> 0 | E6: Swap3M.Futures | F6: =COUNTA(L44:L66)-COUNT(T44:T66) -> 0 | H6: Swap6M.FRAs | I6: =COUNTA(B74:B76)-COUNT(J74:J76) -> 0
B7: OIS.TenorBasis | C7: =COUNTA(AI44:AI66)-COUNT(AQ44:AQ66) -> 0 | E7: Swap3M.Futures.Dates | F7: =COUNTA(L44:L49)-COUNTA(V44:V49)+COUNTA(L44:L49)-COUNTA(W44:W49) -> 0 | H7: Swap6M.IRS | I7: =COUNTA(L74:L88)-COUNTA(T74:T88) -> 0
B8: OIS.IRS | C8: =COUNTA(Y44:Y66)-COUNT(AG44:AG66) -> 0 | E8: Swap3M.IRS | F8: =COUNTA(Y44:Y66)-COUNT(AG44:AG66) -> 0
E9: Swap3M.TenorBasis | F9: =COUNTA(AI44:AI66)-COUNT(AQ44:AQ66) -> 0
B12: OIS | L12: LIBOROISBASISSPREADS
B13: Term | C13: InstrumentID | D13: Broker | E13: Used | F13: Database | G13: Ticker | H13: Side | I13: Used | J13: Result | L13: Term | M13: InstrumentID | N13: Broker | O13: Used | P13: Database | Q13: Ticker | R13: Side | S13: Used | T13: Result
B14: ON | C14: RBACOR | E14: =IF(ISBLANK(D14),Settings.BloombergPCS,D14) -> BGN | F14: Index | G14: =C14&" "&E14&" "&F14 -> RBACOR BGN Index | H14: PX_MID | I14: =IF(ISBLANK(H14),Settings.CurveSide.MidBidAsk,'AUD CURVE TICKERS'!H14) -> PX_MID | J14: =IF(Settings.isCOBToday,_xll.BDP(G14,'AUD CURVE TICKERS'!I14),_xll.BDH(G14,'AUD CURVE TICKERS'!I14,Settings.COB,Settings.COB)) -> 1.5 | L14: 1Y | M14: ADBBCO1 | O14: =IF(ISBLANK(N14),Settings.BloombergPCS,N14) -> BGN | P14: Curncy | Q14: =M14&" "&O14&" "&P14 -> ADBBCO1 BGN Curncy | S14: =IF(ISBLANK(R14),Settings.CurveSide.MidBidAsk,'AUD CURVE TICKERS'!R14) -> PX_MID | T14: =IF(Settings.isCOBToday,_xll.BDP(Q14,'AUD CURVE TICKERS'!S14),_xll.BDH(Q14,'AUD CURVE TICKERS'!S14,Settings.COB,Settings.COB)) -> 51
B15: 1W | C15: ADSO1Z | E15: =IF(ISBLANK(D15),Settings.BloombergPCS,D15) -> BGN | F15: Curncy | G15: =C15&" "&E15&" "&F15 -> ADSO1Z BGN Curncy | I15: =IF(ISBLANK(H15),Settings.CurveSide.MidBidAsk,'AUD CURVE TICKERS'!H15) -> PX_MID | J15: =IF(Settings.isCOBToday,_xll.BDP(G15,'AUD CURVE TICKERS'!I15),_xll.BDH(G15,'AUD CURVE TICKERS'!I15,Settings.COB,Settings.COB)) -> 1.5 | L15: 2Y | M15: ADBBCO2 | O15: =IF(ISBLANK(N15),Settings.BloombergPCS,N15) -> BGN | P15: Curncy | Q15: =M15&" "&O15&" "&P15 -> ADBBCO2 BGN Curncy | S15: =IF(ISBLANK(R15),Settings.CurveSide.MidBidAsk,'AUD CURVE TICKERS'!R15) -> PX_MID | T15: =IF(Settings.isCOBToday,_xll.BDP(Q15,'AUD CURVE TICKERS'!S15),_xll.BDH(Q15,'AUD CURVE TICKERS'!S15,Settings.COB,Settings.COB)) -> 47.25
B16: 1M | C16: ADSOA | E16: =IF(ISBLANK(D16),Settings.BloombergPCS,D16) -> BGN | F16: Curncy | G16: =C16&" "&E16&" "&F16 -> ADSOA BGN Curncy | I16: =IF(ISBLANK(H16),Settings.CurveSide.MidBidAsk,'AUD CURVE TICKERS'!H16) -> PX_MID | J16: =IF(Settings.isCOBToday,_xll.BDP(G16,'AUD CURVE TICKERS'!I16),_xll.BDH(G16,'AUD CURVE TICKERS'!I16,Settings.COB,Settings.COB)) -> 1.499 | L16: 3Y | M16: ADBBCO3 | O16: =IF(ISBLANK(N16),Settings.BloombergPCS,N16) -> BGN | P16: Curncy | Q16: =M16&" "&O16&" "&P16 -> ADBBCO3 BGN Curncy | S16: =IF(ISBLANK(R16),Settings.CurveSide.MidBidAsk,'AUD CURVE TICKERS'!R16) -> PX_MID | T16: =IF(Settings.isCOBToday,_xll.BDP(Q16,'AUD CURVE TICKERS'!S16),_xll.BDH(Q16,'AUD CURVE TICKERS'!S16,Settings.COB,Settings.COB)) -> 43.75
B17: 2M | C17: ADSOB | E17: =IF(ISBLANK(D17),Settings.BloombergPCS,D17) -> BGN | F17: Curncy | G17: =C17&" "&E17&" "&F17 -> ADSOB BGN Curncy | I17: =IF(ISBLANK(H17),Settings.CurveSide.MidBidAsk,'AUD CURVE TICKERS'!H17) -> PX_MID | J17: =IF(Settings.isCOBToday,_xll.BDP(G17,'AUD CURVE TICKERS'!I17),_xll.BDH(G17,'AUD CURVE TICKERS'!I17,Settings.COB,Settings.COB)) -> 1.5 | L17: 4Y | M17: ADBBCO4 | O17: =IF(ISBLANK(N17),Settings.BloombergPCS,N17) -> BGN | P17: Curncy | Q17: =M17&" "&O17&" "&P17 -> ADBBCO4 BGN Curncy | S17: =IF(ISBLANK(R17),Settings.CurveSide.MidBidAsk,'AUD CURVE TICKERS'!R17) -> PX_MID | T17: =IF(Settings.isCOBToday,_xll.BDP(Q17,'AUD CURVE TICKERS'!S17),_xll.BDH(Q17,'AUD CURVE TICKERS'!S17,Settings.COB,Settings.COB)) -> 42.375
B18: 3M | C18: ADSOC | E18: =IF(ISBLANK(D18),Settings.BloombergPCS,D18) -> BGN | F18: Curncy | G18: =C18&" "&E18&" "&F18 -> ADSOC BGN Curncy | I18: =IF(ISBLANK(H18),Settings.CurveSide.MidBidAsk,'AUD CURVE TICKERS'!H18) -> PX_MID | J18: =IF(Settings.isCOBToday,_xll.BDP(G18,'AUD CURVE TICKERS'!I18),_xll.BDH(G18,'AUD CURVE TICKERS'!I18,Settings.COB,Settings.COB)) -> 1.5 | L18: 5Y | M18: ADBBCO5 | O18: =IF(ISBLANK(N18),Settings.BloombergPCS,N18) -> BGN | P18: Curncy | Q18: =M18&" "&O18&" "&P18 -> ADBBCO5 BGN Curncy | S18: =IF(ISBLANK(R18),Settings.CurveSide.MidBidAsk,'AUD CURVE TICKERS'!R18) -> PX_MID | T18: =IF(Settings.isCOBToday,_xll.BDP(Q18,'AUD CURVE TICKERS'!S18),_xll.BDH(Q18,'AUD CURVE TICKERS'!S18,Settings.COB,Settings.COB)) -> 42
B19: 4M | C19: ADSOD | E19: =IF(ISBLANK(D19),Settings.BloombergPCS,D19) -> BGN | F19: Curncy | G19: =C19&" "&E19&" "&F19 -> ADSOD BGN Curncy | I19: =IF(ISBLANK(H19),Settings.CurveSide.MidBidAsk,'AUD CURVE TICKERS'!H19) -> PX_MID | J19: =IF(Settings.isCOBToday,_xll.BDP(G19,'AUD CURVE TICKERS'!I19),_xll.BDH(G19,'AUD CURVE TICKERS'!I19,Settings.COB,Settings.COB)) -> 1.501 | L19: 6Y | M19: ADBBCO6 | O19: =IF(ISBLANK(N19),Settings.BloombergPCS,N19) -> BGN | P19: Curncy | Q19: =M19&" "&O19&" "&P19 -> ADBBCO6 BGN Curncy | S19: =IF(ISBLANK(R19),Settings.CurveSide.MidBidAsk,'AUD CURVE TICKERS'!R19) -> PX_MID | T19: =IF(Settings.isCOBToday,_xll.BDP(Q19,'AUD CURVE TICKERS'!S19),_xll.BDH(Q19,'AUD CURVE TICKERS'!S19,Settings.COB,Settings.COB)) -> 42.625
B20: 5M | C20: ADSOE | E20: =IF(ISBLANK(D20),Settings.BloombergPCS,D20) -> BGN | F20: Curncy | G20: =C20&" "&E20&" "&F20 -> ADSOE BGN Curncy | I20: =IF(ISBLANK(H20),Settings.CurveSide.MidBidAsk,'AUD CURVE TICKERS'!H20) -> PX_MID | J20: =IF(Settings.isCOBToday,_xll.BDP(G20,'AUD CURVE TICKERS'!I20),_xll.BDH(G20,'AUD CURVE TICKERS'!I20,Settings.COB,Settings.COB)) -> 1.5025 | L20: 7Y | M20: ADBBCO7 | O20: =IF(ISBLANK(N20),Settings.BloombergPCS,N20) -> BGN | P20: Curncy | Q20: =M20&" "&O20&" "&P20 -> ADBBCO7 BGN Curncy | S20: =IF(ISBLANK(R20),Settings.CurveSide.MidBidAsk,'AUD CURVE TICKERS'!R20) -> PX_MID | T20: =IF(Settings.isCOBToday,_xll.BDP(Q20,'AUD CURVE TICKERS'!S20),_xll.BDH(Q20,'AUD CURVE TICKERS'!S20,Settings.COB,Settings.COB)) -> 43.125
B21: 6M | C21: ADSOF | E21: =IF(ISBLANK(D21),Settings.BloombergPCS,D21) -> BGN | F21: Curncy | G21: =C21&" "&E21&" "&F21 -> ADSOF BGN Curncy | I21: =IF(ISBLANK(H21),Settings.CurveSide.MidBidAsk,'AUD CURVE TICKERS'!H21) -> PX_MID | J21: =IF(Settings.isCOBToday,_xll.BDP(G21,'AUD CURVE TICKERS'!I21),_xll.BDH(G21,'AUD CURVE TICKERS'!I21,Settings.COB,Settings.COB)) -> 1.504 | L21: 8Y | M21: ADBBCO8 | O21: =IF(ISBLANK(N21),Settings.BloombergPCS,N21) -> BGN | P21: Curncy | Q21: =M21&" "&O21&" "&P21 -> ADBBCO8 BGN Curncy | S21: =IF(ISBLANK(R21),Settings.CurveSide.MidBidAsk,'AUD CURVE TICKERS'!R21) -> PX_MID | T21: =IF(Settings.isCOBToday,_xll.BDP(Q21,'AUD CURVE TICKERS'!S21),_xll.BDH(Q21,'AUD CURVE TICKERS'!S21,Settings.COB,Settings.COB)) -> 43.25
B22: 9M | C22: ADSOI | E22: =IF(ISBLANK(D22),Settings.BloombergPCS,D22) -> BGN | F22: Curncy | G22: =C22&" "&E22&" "&F22 -> ADSOI BGN Curncy | I22: =IF(ISBLANK(H22),Settings.CurveSide.MidBidAsk,'AUD CURVE TICKERS'!H22) -> PX_MID | J22: =IF(Settings.isCOBToday,_xll.BDP(G22,'AUD CURVE TICKERS'!I22),_xll.BDH(G22,'AUD CURVE TICKERS'!I22,Settings.COB,Settings.COB)) -> 1.512 | L22: 9Y | M22: ADBBCO9 | O22: =IF(ISBLANK(N22),Settings.BloombergPCS,N22) -> BGN | P22: Curncy | Q22: =M22&" "&O22&" "&P22 -> ADBBCO9 BGN Curncy | S22: =IF(ISBLANK(R22),Settings.CurveSide.MidBidAsk,'AUD CURVE TICKERS'!R22) -> PX_MID | T22: =IF(Settings.isCOBToday,_xll.BDP(Q22,'AUD CURVE TICKERS'!S22),_xll.BDH(Q22,'AUD CURVE TICKERS'!S22,Settings.COB,Settings.COB)) -> 43.125
B23: 1Y | C23: ADSO1 | E23: =IF(ISBLANK(D23),Settings.BloombergPCS,D23) -> BGN | F23: Curncy | G23: =C23&" "&E23&" "&F23 -> ADSO1 BGN Curncy | I23: =IF(ISBLANK(H23),Settings.CurveSide.MidBidAsk,'AUD CURVE TICKERS'!H23) -> PX_MID | J23: =IF(Settings.isCOBToday,_xll.BDP(G23,'AUD CURVE TICKERS'!I23),_xll.BDH(G23,'AUD CURVE TICKERS'!I23,Settings.COB,Settings.COB)) -> 1.528 | L23: 10Y | M23: ADBBCO10 | O23: =IF(ISBLANK(N23),Settings.BloombergPCS,N23) -> BGN | P23: Curncy | Q23: =M23&" "&O23&" "&P23 -> ADBBCO10 BGN Curncy | S23: =IF(ISBLANK(R23),Settings.CurveSide.MidBidAsk,'AUD CURVE TICKERS'!R23) -> PX_MID | T23: =IF(Settings.isCOBToday,_xll.BDP(Q23,'AUD CURVE TICKERS'!S23),_xll.BDH(Q23,'AUD CURVE TICKERS'!S23,Settings.COB,Settings.COB)) -> 43.125
B24: 2Y | C24: ADSO2 | E24: =IF(ISBLANK(D24),Settings.BloombergPCS,D24) -> BGN | F24: Curncy | G24: =C24&" "&E24&" "&F24 -> ADSO2 BGN Curncy | I24: =IF(ISBLANK(H24),Settings.CurveSide.MidBidAsk,'AUD CURVE TICKERS'!H24) -> PX_MID | J24: =IF(Settings.isCOBToday,_xll.BDP(G24,'AUD CURVE TICKERS'!I24),_xll.BDH(G24,'AUD CURVE TICKERS'!I24,Settings.COB,Settings.COB)) -> 1.63 | L24: 15Y | M24: ADBBCO15 | O24: =IF(ISBLANK(N24),Settings.BloombergPCS,N24) -> BGN | P24: Curncy | Q24: =M24&" "&O24&" "&P24 -> ADBBCO15 BGN Curncy | S24: =IF(ISBLANK(R24),Settings.CurveSide.MidBidAsk,'AUD CURVE TICKERS'!R24) -> PX_MID | T24: =IF(Settings.isCOBToday,_xll.BDP(Q24,'AUD CURVE TICKERS'!S24),_xll.BDH(Q24,'AUD CURVE TICKERS'!S24,Settings.COB,Settings.COB)) -> 43.375
B25: 3Y | C25: ADSO3 | E25: =IF(ISBLANK(D25),Settings.BloombergPCS,D25) -> BGN | F25: Curncy | G25: =C25&" "&E25&" "&F25 -> ADSO3 BGN Curncy | I25: =IF(ISBLANK(H25),Settings.CurveSide.MidBidAsk,'AUD CURVE TICKERS'!H25) -> PX_MID | J25: =IF(Settings.isCOBToday,_xll.BDP(G25,'AUD CURVE TICKERS'!I25),_xll.BDH(G25,'AUD CURVE TICKERS'!I25,Settings.COB,Settings.COB)) -> 1.733 | L25: 20Y | M25: ADBBCO20 | O25: =IF(ISBLANK(N25),Settings.BloombergPCS,N25) -> BGN | P25: Curncy | Q25: =M25&" "&O25&" "&P25 -> ADBBCO20 BGN Curncy | S25: =IF(ISBLANK(R25),Settings.CurveSide.MidBidAsk,'AUD CURVE TICKERS'!R25) -> PX_MID | T25: =IF(Settings.isCOBToday,_xll.BDP(Q25,'AUD CURVE TICKERS'!S25),_xll.BDH(Q25,'AUD CURVE TICKERS'!S25,Settings.COB,Settings.COB)) -> 43.625
B26: 4Y | C26: ADSO4 | E26: =IF(ISBLANK(D26),Settings.BloombergPCS,D26) -> BGN | F26: Curncy | G26: =C26&" "&E26&" "&F26 -> ADSO4 BGN Curncy | I26: =IF(ISBLANK(H26),Settings.CurveSide.MidBidAsk,'AUD CURVE TICKERS'!H26) -> PX_MID | J26: =IF(Settings.isCOBToday,_xll.BDP(G26,'AUD CURVE TICKERS'!I26),_xll.BDH(G26,'AUD CURVE TICKERS'!I26,Settings.COB,Settings.COB)) -> 1.848 | L26: 25Y | M26: ADBBCO25 | O26: =IF(ISBLANK(N26),Settings.BloombergPCS,N26) -> BGN | P26: Curncy | Q26: =M26&" "&O26&" "&P26 -> ADBBCO25 BGN Curncy | S26: =IF(ISBLANK(R26),Settings.CurveSide.MidBidAsk,'AUD CURVE TICKERS'!R26) -> PX_MID | T26: =IF(Settings.isCOBToday,_xll.BDP(Q26,'AUD CURVE TICKERS'!S26),_xll.BDH(Q26,'AUD CURVE TICKERS'!S26,Settings.COB,Settings.COB)) -> 44
B27: 5Y | C27: ADSO5 | E27: =IF(ISBLANK(D27),Settings.BloombergPCS,D27) -> BGN | F27: Curncy | G27: =C27&" "&E27&" "&F27 -> ADSO5 BGN Curncy | I27: =IF(ISBLANK(H27),Settings.CurveSide.MidBidAsk,'AUD CURVE TICKERS'!H27) -> PX_MID | J27: =IF(Settings.isCOBToday,_xll.BDP(G27,'AUD CURVE TICKERS'!I27),_xll.BDH(G27,'AUD CURVE TICKERS'!I27,Settings.COB,Settings.COB)) -> 1.948 | L27: 30Y | M27: ADBBCO30 | O27: =IF(ISBLANK(N27),Settings.BloombergPCS,N27) -> BGN | P27: Curncy | Q27: =M27&" "&O27&" "&P27 -> ADBBCO30 BGN Curncy | S27: =IF(ISBLANK(R27),Settings.CurveSide.MidBidAsk,'AUD CURVE TICKERS'!R27) -> PX_MID | T27: =IF(Settings.isCOBToday,_xll.BDP(Q27,'AUD CURVE TICKERS'!S27),_xll.BDH(Q27,'AUD CURVE TICKERS'!S27,Settings.COB,Settings.COB)) -> 44.375
B28: 6Y | C28: ADSO6 | E28: =IF(ISBLANK(D28),Settings.BloombergPCS,D28) -> BGN | F28: Curncy | G28: =C28&" "&E28&" "&F28 -> ADSO6 BGN Curncy | I28: =IF(ISBLANK(H28),Settings.CurveSide.MidBidAsk,'AUD CURVE TICKERS'!H28) -> PX_MID | J28: =IF(Settings.isCOBToday,_xll.BDP(G28,'AUD CURVE TICKERS'!I28),_xll.BDH(G28,'AUD CURVE TICKERS'!I28,Settings.COB,Settings.COB)) -> 2.025
B29: 7Y | C29: ADSO7 | E29: =IF(ISBLANK(D29),Settings.BloombergPCS,D29) -> BGN | F29: Curncy | G29: =C29&" "&E29&" "&F29 -> ADSO7 BGN Curncy | I29: =IF(ISBLANK(H29),Settings.CurveSide.MidBidAsk,'AUD CURVE TICKERS'!H29) -> PX_MID | J29: =IF(Settings.isCOBToday,_xll.BDP(G29,'AUD CURVE TICKERS'!I29),_xll.BDH(G29,'AUD CURVE TICKERS'!I29,Settings.COB,Settings.COB)) -> 2.1015
B30: 8Y | C30: ADSO8 | E30: =IF(ISBLANK(D30),Settings.BloombergPCS,D30) -> BGN | F30: Curncy | G30: =C30&" "&E30&" "&F30 -> ADSO8 BGN Curncy | I30: =IF(ISBLANK(H30),Settings.CurveSide.MidBidAsk,'AUD CURVE TICKERS'!H30) -> PX_MID | J30: =IF(Settings.isCOBToday,_xll.BDP(G30,'AUD CURVE TICKERS'!I30),_xll.BDH(G30,'AUD CURVE TICKERS'!I30,Settings.COB,Settings.COB)) -> 2.163
B31: 9Y | C31: ADSO9 | E31: =IF(ISBLANK(D31),Settings.BloombergPCS,D31) -> BGN | F31: Curncy | G31: =C31&" "&E31&" "&F31 -> ADSO9 BGN Curncy | I31: =IF(ISBLANK(H31),Settings.CurveSide.MidBidAsk,'AUD CURVE TICKERS'!H31) -> PX_MID | J31: =IF(Settings.isCOBToday,_xll.BDP(G31,'AUD CURVE TICKERS'!I31),_xll.BDH(G31,'AUD CURVE TICKERS'!I31,Settings.COB,Settings.COB)) -> 2.225
B32: 10Y | C32: ADSO10 | E32: =IF(ISBLANK(D32),Settings.BloombergPCS,D32) -> BGN | F32: Curncy | G32: =C32&" "&E32&" "&F32 -> ADSO10 BGN Curncy | I32: =IF(ISBLANK(H32),Settings.CurveSide.MidBidAsk,'AUD CURVE TICKERS'!H32) -> PX_MID | J32: =IF(Settings.isCOBToday,_xll.BDP(G32,'AUD CURVE TICKERS'!I32),_xll.BDH(G32,'AUD CURVE TICKERS'!I32,Settings.COB,Settings.COB)) -> 2.285
B33: 15Y | C33: ADSO15 | E33: =IF(ISBLANK(D33),Settings.BloombergPCS,D33) -> BGN | F33: Curncy | G33: =C33&" "&E33&" "&F33 -> ADSO15 BGN Curncy | I33: =IF(ISBLANK(H33),Settings.CurveSide.MidBidAsk,'AUD CURVE TICKERS'!H33) -> PX_MID | J33: =IF(Settings.isCOBToday,_xll.BDP(G33,'AUD CURVE TICKERS'!I33),_xll.BDH(G33,'AUD CURVE TICKERS'!I33,Settings.COB,Settings.COB)) -> 2.46
B34: 20Y | C34: ADSO20 | E34: =IF(ISBLANK(D34),Settings.BloombergPCS,D34) -> BGN | F34: Curncy | G34: =C34&" "&E34&" "&F34 -> ADSO20 BGN Curncy | I34: =IF(ISBLANK(H34),Settings.CurveSide.MidBidAsk,'AUD CURVE TICKERS'!H34) -> PX_MID | J34: =IF(Settings.isCOBToday,_xll.BDP(G34,'AUD CURVE TICKERS'!I34),_xll.BDH(G34,'AUD CURVE TICKERS'!I34,Settings.COB,Settings.COB)) -> 2.461
B35: 25Y | C35: ADSO25 | E35: =IF(ISBLANK(D35),Settings.BloombergPCS,D35) -> BGN | F35: Curncy | G35: =C35&" "&E35&" "&F35 -> ADSO25 BGN Curncy | I35: =IF(ISBLANK(H35),Settings.CurveSide.MidBidAsk,'AUD CURVE TICKERS'!H35) -> PX_MID | J35: =IF(Settings.isCOBToday,_xll.BDP(G35,'AUD CURVE TICKERS'!I35),_xll.BDH(G35,'AUD CURVE TICKERS'!I35,Settings.COB,Settings.COB)) -> 2.508
B36: 30Y | C36: ADSO30 | E36: =IF(ISBLANK(D36),Settings.BloombergPCS,D36) -> BGN | F36: Curncy | G36: =C36&" "&E36&" "&F36 -> ADSO30 BGN Curncy | I36: =IF(ISBLANK(H36),Settings.CurveSide.MidBidAsk,'AUD CURVE TICKERS'!H36) -> PX_MID | J36: =IF(Settings.isCOBToday,_xll.BDP(G36,'AUD CURVE TICKERS'!I36),_xll.BDH(G36,'AUD CURVE TICKERS'!I36,Settings.COB,Settings.COB)) -> 2.404
A40: << AUDOIS
B42: LIBORFIXINGS | L42: FUTURES | V42: FUTURES.DATES | Y42: SWAPS | AI42: BASISSWAPS
B43: Term | C43: InstrumentID | D43: Broker | E43: Used | F43: Database | G43: Ticker | H43: Side | I43: Used | J43: Result | L43: Term | M43: InstrumentID | N43: Broker | O43: Used | P43: Database | Q43: Ticker | R43: Side | S43: Used | T43: Result | V43: StartDate | W43: EndDate | Y43: Term | Z43: InstrumentID | AA43: Broker | AB43: Used | AC43: Database | AD43: Ticker | AE43: Side | AF43: Used | AG43: Result | AI43: Term | AJ43: InstrumentID | AK43: Broker | AL43: Used | AM43: Database | AN43: Ticker | AO43: Side | AP43: Used | AQ43: Result
B44: 1M | C44: ADBB1M | E44: =IF(ISBLANK(D44),Settings.BloombergPCS,D44) | F44: Curncy | G44: =C44&" "&E44&" "&F44 -> ADBB1M Curncy | I44: =IF(ISBLANK(H44),Settings.CurveSide.MidBidAsk,'AUD CURVE TICKERS'!H44) -> PX_MID | J44: =IF(Settings.isCOBToday,_xll.BDP(G44,'AUD CURVE TICKERS'!I44),_xll.BDH(G44,'AUD CURVE TICKERS'!I44,Settings.COB,Settings.COB)) -> 2.01 | L44: IR1 | M44: IR1 | O44: =IF(ISBLANK(N44),Settings.BloombergPCS,N44) | P44: Comdty | Q44: =M44&" "&O44&" "&P44 -> IR1 Comdty | S44: =IF(ISBLANK(R44),Settings.CurveSide.MidBidAsk,'AUD CURVE TICKERS'!R44) -> PX_MID | T44: =IF(Settings.isCOBToday,_xll.BDP(Q44,'AUD CURVE TICKERS'!S44),_xll.BDH(Q44,'AUD CURVE TICKERS'!S44,Settings.COB,Settings.COB)) -> 98.015 | V44: =IF(Settings.isCOBToday,_xll.BDP(Q44,$V$51),_xll.BDH(Q44,$V$51,Settings.COB,Settings.COB)) -> 14/09/2018 | W44: =IF(Settings.isCOBToday,_xll.BDP(Q44,$V$52),_xll.BDH(Q44,$V$52,Settings.COB,Settings.COB)) -> 14/12/2018 | Y44: 1Y | Z44: ADSW1Q | AB44: =IF(ISBLANK(AA44),Settings.BloombergPCS,AA44) -> BGN | AC44: Curncy | AD44: =Z44&" "&AB44&" "&AC44 -> ADSW1Q BGN Curncy | AF44: =IF(ISBLANK(AE44),Settings.CurveSide.MidBidAsk,'AUD CURVE TICKERS'!AE44) -> PX_MID | AG44: =IF(Settings.isCOBToday,_xll.BDP(AD44,'AUD CURVE TICKERS'!AF44),_xll.BDH(AD44,'AUD CURVE TICKERS'!AF44,Settings.COB,Settings.COB)) -> 2.0295 | AI44: 1Y | AJ44: ADBBCF1 | AL44: =IF(ISBLANK(AK44),Settings.BloombergPCS,AK44) -> BGN | AM44: Curncy | AN44: =AJ44&" "&AL44&" "&AM44 -> ADBBCF1 BGN Curncy | AP44: =IF(ISBLANK(AO44),Settings.CurveSide.MidBidAsk,'AUD CURVE TICKERS'!AO44) -> PX_MID | AQ44: =IF(Settings.isCOBToday,_xll.BDP(AN44,'AUD CURVE TICKERS'!AP44),_xll.BDH(AN44,'AUD CURVE TICKERS'!AP44,Settings.COB,Settings.COB)) -> 14.75
B45: 3M | C45: ADBB3M | E45: =IF(ISBLANK(D45),Settings.BloombergPCS,D45) | F45: Curncy | G45: =C45&" "&E45&" "&F45 -> ADBB3M Curncy | I45: =IF(ISBLANK(H45),Settings.CurveSide.MidBidAsk,'AUD CURVE TICKERS'!H45) -> PX_MID | J45: =IF(Settings.isCOBToday,_xll.BDP(G45,'AUD CURVE TICKERS'!I45),_xll.BDH(G45,'AUD CURVE TICKERS'!I45,Settings.COB,Settings.COB)) -> 2.1153 | L45: IR2 | M45: IR2 | O45: =IF(ISBLANK(N45),Settings.BloombergPCS,N45) | P45: Comdty | Q45: =M45&" "&O45&" "&P45 -> IR2 Comdty | S45: =IF(ISBLANK(R45),Settings.CurveSide.MidBidAsk,'AUD CURVE TICKERS'!R45) -> PX_MID | T45: =IF(Settings.isCOBToday,_xll.BDP(Q45,'AUD CURVE TICKERS'!S45),_xll.BDH(Q45,'AUD CURVE TICKERS'!S45,Settings.COB,Settings.COB)) -> 98.005 | V45: =IF(Settings.isCOBToday,_xll.BDP(Q45,$V$51),_xll.BDH(Q45,$V$51,Settings.COB,Settings.COB)) -> 14/12/2018 | W45: =IF(Settings.isCOBToday,_xll.BDP(Q45,$V$52),_xll.BDH(Q45,$V$52,Settings.COB,Settings.COB)) -> 08/03/2019 | Y45: 2Y | Z45: ADSW2Q | AB45: =IF(ISBLANK(AA45),Settings.BloombergPCS,AA45) -> BGN | AC45: Curncy | AD45: =Z45&" "&AB45&" "&AC45 -> ADSW2Q BGN Curncy | AF45: =IF(ISBLANK(AE45),Settings.CurveSide.MidBidAsk,'AUD CURVE TICKERS'!AE45) -> PX_MID | AG45: =IF(Settings.isCOBToday,_xll.BDP(AD45,'AUD CURVE TICKERS'!AF45),_xll.BDH(AD45,'AUD CURVE TICKERS'!AF45,Settings.COB,Settings.COB)) -> 2.08 | AI45: 2Y | AJ45: ADBBCF2 | AL45: =IF(ISBLANK(AK45),Settings.BloombergPCS,AK45) -> BGN | AM45: Curncy | AN45: =AJ45&" "&AL45&" "&AM45 -> ADBBCF2 BGN Curncy | AP45: =IF(ISBLANK(AO45),Settings.CurveSide.MidBidAsk,'AUD CURVE TICKERS'!AO45) -> PX_MID | AQ45: =IF(Settings.isCOBToday,_xll.BDP(AN45,'AUD CURVE TICKERS'!AP45),_xll.BDH(AN45,'AUD CURVE TICKERS'!AP45,Settings.COB,Settings.COB)) -> 14.725
B46: 6M | C46: ADBB6M | E46: =IF(ISBLANK(D46),Settings.BloombergPCS,D46) | F46: Curncy | G46: =C46&" "&E46&" "&F46 -> ADBB6M Curncy | I46: =IF(ISBLANK(H46),Settings.CurveSide.MidBidAsk,'AUD CURVE TICKERS'!H46) -> PX_MID | J46: =IF(Settings.isCOBToday,_xll.BDP(G46,'AUD CURVE TICKERS'!I46),_xll.BDH(G46,'AUD CURVE TICKERS'!I46,Settings.COB,Settings.COB)) -> 2.23 | L46: IR3 | M46: IR3 | O46: =IF(ISBLANK(N46),Settings.BloombergPCS,N46) | P46: Comdty | Q46: =M46&" "&O46&" "&P46 -> IR3 Comdty | S46: =IF(ISBLANK(R46),Settings.CurveSide.MidBidAsk,'AUD CURVE TICKERS'!R46) -> PX_MID | T46: =IF(Settings.isCOBToday,_xll.BDP(Q46,'AUD CURVE TICKERS'!S46),_xll.BDH(Q46,'AUD CURVE TICKERS'!S46,Settings.COB,Settings.COB)) -> 97.975 | V46: =IF(Settings.isCOBToday,_xll.BDP(Q46,$V$51),_xll.BDH(Q46,$V$51,Settings.COB,Settings.COB)) -> 08/03/2019 | W46: =IF(Settings.isCOBToday,_xll.BDP(Q46,$V$52),_xll.BDH(Q46,$V$52,Settings.COB,Settings.COB)) -> 14/06/2019 | Y46: 3Y | Z46: ADSW3Q | AB46: =IF(ISBLANK(AA46),Settings.BloombergPCS,AA46) -> BGN | AC46: Curncy | AD46: =Z46&" "&AB46&" "&AC46 -> ADSW3Q BGN Curncy | AF46: =IF(ISBLANK(AE46),Settings.CurveSide.MidBidAsk,'AUD CURVE TICKERS'!AE46) -> PX_MID | AG46: =IF(Settings.isCOBToday,_xll.BDP(AD46,'AUD CURVE TICKERS'!AF46),_xll.BDH(AD46,'AUD CURVE TICKERS'!AF46,Settings.COB,Settings.COB)) -> 2.1575 | AI46: 3Y | AJ46: ADBBCF3 | AL46: =IF(ISBLANK(AK46),Settings.BloombergPCS,AK46) -> BGN | AM46: Curncy | AN46: =AJ46&" "&AL46&" "&AM46 -> ADBBCF3 BGN Curncy | AP46: =IF(ISBLANK(AO46),Settings.CurveSide.MidBidAsk,'AUD CURVE TICKERS'!AO46) -> PX_MID | AQ46: =IF(Settings.isCOBToday,_xll.BDP(AN46,'AUD CURVE TICKERS'!AP46),_xll.BDH(AN46,'AUD CURVE TICKERS'!AP46,Settings.COB,Settings.COB)) -> 14.5
L47: IR4 | M47: IR4 | O47: =IF(ISBLANK(N47),Settings.BloombergPCS,N47) | P47: Comdty | Q47: =M47&" "&O47&" "&P47 -> IR4 Comdty | S47: =IF(ISBLANK(R47),Settings.CurveSide.MidBidAsk,'AUD CURVE TICKERS'!R47) -> PX_MID | T47: =IF(Settings.isCOBToday,_xll.BDP(Q47,'AUD CURVE TICKERS'!S47),_xll.BDH(Q47,'AUD CURVE TICKERS'!S47,Settings.COB,Settings.COB)) -> 97.945 | V47: =IF(Settings.isCOBToday,_xll.BDP(Q47,$V$51),_xll.BDH(Q47,$V$51,Settings.COB,Settings.COB)) -> 14/06/2019 | W47: =IF(Settings.isCOBToday,_xll.BDP(Q47,$V$52),_xll.BDH(Q47,$V$52,Settings.COB,Settings.COB)) -> 13/09/2019 | Y47: 4Y | Z47: ADSW4 | AB47: =IF(ISBLANK(AA47),Settings.BloombergPCS,AA47) -> BGN | AC47: Curncy | AD47: =Z47&" "&AB47&" "&AC47 -> ADSW4 BGN Curncy | AF47: =IF(ISBLANK(AE47),Settings.CurveSide.MidBidAsk,'AUD CURVE TICKERS'!AE47) -> PX_MID | AG47: =IF(Settings.isCOBToday,_xll.BDP(AD47,'AUD CURVE TICKERS'!AF47),_xll.BDH(AD47,'AUD CURVE TICKERS'!AF47,Settings.COB,Settings.COB)) -> 2.39375 | AI47: 4Y | AJ47: ADBBCF4 | AL47: =IF(ISBLANK(AK47),Settings.BloombergPCS,AK47) -> BGN | AM47: Curncy | AN47: =AJ47&" "&AL47&" "&AM47 -> ADBBCF4 BGN Curncy | AP47: =IF(ISBLANK(AO47),Settings.CurveSide.MidBidAsk,'AUD CURVE TICKERS'!AO47) -> PX_MID | AQ47: =IF(Settings.isCOBToday,_xll.BDP(AN47,'AUD CURVE TICKERS'!AP47),_xll.BDH(AN47,'AUD CURVE TICKERS'!AP47,Settings.COB,Settings.COB)) -> 14.4
L48: IR5 | M48: IR5 | O48: =IF(ISBLANK(N48),Settings.BloombergPCS,N48) | P48: Comdty | Q48: =M48&" "&O48&" "&P48 -> IR5 Comdty | S48: =IF(ISBLANK(R48),Settings.CurveSide.MidBidAsk,'AUD CURVE TICKERS'!R48) -> PX_MID | T48: =IF(Settings.isCOBToday,_xll.BDP(Q48,'AUD CURVE TICKERS'!S48),_xll.BDH(Q48,'AUD CURVE TICKERS'!S48,Settings.COB,Settings.COB)) -> 97.895 | V48: =IF(Settings.isCOBToday,_xll.BDP(Q48,$V$51),_xll.BDH(Q48,$V$51,Settings.COB,Settings.COB)) -> 13/09/2019 | W48: =IF(Settings.isCOBToday,_xll.BDP(Q48,$V$52),_xll.BDH(Q48,$V$52,Settings.COB,Settings.COB)) -> 13/12/2019 | Y48: 5Y | Z48: ADSW5 | AB48: =IF(ISBLANK(AA48),Settings.BloombergPCS,AA48) -> BGN | AC48: Curncy | AD48: =Z48&" "&AB48&" "&AC48 -> ADSW5 BGN Curncy | AF48: =IF(ISBLANK(AE48),Settings.CurveSide.MidBidAsk,'AUD CURVE TICKERS'!AE48) -> PX_MID | AG48: =IF(Settings.isCOBToday,_xll.BDP(AD48,'AUD CURVE TICKERS'!AF48),_xll.BDH(AD48,'AUD CURVE TICKERS'!AF48,Settings.COB,Settings.COB)) -> 2.486 | AI48: 5Y | AJ48: ADBBCF5 | AL48: =IF(ISBLANK(AK48),Settings.BloombergPCS,AK48) -> BGN | AM48: Curncy | AN48: =AJ48&" "&AL48&" "&AM48 -> ADBBCF5 BGN Curncy | AP48: =IF(ISBLANK(AO48),Settings.CurveSide.MidBidAsk,'AUD CURVE TICKERS'!AO48) -> PX_MID | AQ48: =IF(Settings.isCOBToday,_xll.BDP(AN48,'AUD CURVE TICKERS'!AP48),_xll.BDH(AN48,'AUD CURVE TICKERS'!AP48,Settings.COB,Settings.COB)) -> 14.225
L49: IR6 | M49: IR6 | O49: =IF(ISBLANK(N49),Settings.BloombergPCS,N49) | P49: Comdty | Q49: =M49&" "&O49&" "&P49 -> IR6 Comdty | S49: =IF(ISBLANK(R49),Settings.CurveSide.MidBidAsk,'AUD CURVE TICKERS'!R49) -> PX_MID | T49: =IF(Settings.isCOBToday,_xll.BDP(Q49,'AUD CURVE TICKERS'!S49),_xll.BDH(Q49,'AUD CURVE TICKERS'!S49,Settings.COB,Settings.COB)) -> 97.845 | V49: =IF(Settings.isCOBToday,_xll.BDP(Q49,$V$51),_xll.BDH(Q49,$V$51,Settings.COB,Settings.COB)) -> 13/12/2019 | W49: =IF(Settings.isCOBToday,_xll.BDP(Q49,$V$52),_xll.BDH(Q49,$V$52,Settings.COB,Settings.COB)) -> 13/03/2020 | Y49: 6Y | Z49: ADSW6 | AB49: =IF(ISBLANK(AA49),Settings.BloombergPCS,AA49) -> BGN | AC49: Curncy | AD49: =Z49&" "&AB49&" "&AC49 -> ADSW6 BGN Curncy | AF49: =IF(ISBLANK(AE49),Settings.CurveSide.MidBidAsk,'AUD CURVE TICKERS'!AE49) -> PX_MID | AG49: =IF(Settings.isCOBToday,_xll.BDP(AD49,'AUD CURVE TICKERS'!AF49),_xll.BDH(AD49,'AUD CURVE TICKERS'!AF49,Settings.COB,Settings.COB)) -> 2.5675 | AI49: 6Y | AJ49: ADBBCF6 | AL49: =IF(ISBLANK(AK49),Settings.BloombergPCS,AK49) -> BGN | AM49: Curncy | AN49: =AJ49&" "&AL49&" "&AM49 -> ADBBCF6 BGN Curncy | AP49: =IF(ISBLANK(AO49),Settings.CurveSide.MidBidAsk,'AUD CURVE TICKERS'!AO49) -> PX_MID | AQ49: =IF(Settings.isCOBToday,_xll.BDP(AN49,'AUD CURVE TICKERS'!AP49),_xll.BDH(AN49,'AUD CURVE TICKERS'!AP49,Settings.COB,Settings.COB)) -> 13.9
Y50: 7Y | Z50: ADSW7 | AB50: =IF(ISBLANK(AA50),Settings.BloombergPCS,AA50) -> BGN | AC50: Curncy | AD50: =Z50&" "&AB50&" "&AC50 -> ADSW7 BGN Curncy | AF50: =IF(ISBLANK(AE50),Settings.CurveSide.MidBidAsk,'AUD CURVE TICKERS'!AE50) -> PX_MID | AG50: =IF(Settings.isCOBToday,_xll.BDP(AD50,'AUD CURVE TICKERS'!AF50),_xll.BDH(AD50,'AUD CURVE TICKERS'!AF50,Settings.COB,Settings.COB)) -> 2.64 | AI50: 7Y | AJ50: ADBBCF7 | AL50: =IF(ISBLANK(AK50),Settings.BloombergPCS,AK50) -> BGN | AM50: Curncy | AN50: =AJ50&" "&AL50&" "&AM50 -> ADBBCF7 BGN Curncy | AP50: =IF(ISBLANK(AO50),Settings.CurveSide.MidBidAsk,'AUD CURVE TICKERS'!AO50) -> PX_MID | AQ50: =IF(Settings.isCOBToday,_xll.BDP(AN50,'AUD CURVE TICKERS'!AP50),_xll.BDH(AN50,'AUD CURVE TICKERS'!AP50,Settings.COB,Settings.COB)) -> 13.5
V51: INT_RATE_FUT_START_DT | Y51: 8Y | Z51: ADSW8 | AB51: =IF(ISBLANK(AA51),Settings.BloombergPCS,AA51) -> BGN | AC51: Curncy | AD51: =Z51&" "&AB51&" "&AC51 -> ADSW8 BGN Curncy | AF51: =IF(ISBLANK(AE51),Settings.CurveSide.MidBidAsk,'AUD CURVE TICKERS'!AE51) -> PX_MID | AG51: =IF(Settings.isCOBToday,_xll.BDP(AD51,'AUD CURVE TICKERS'!AF51),_xll.BDH(AD51,'AUD CURVE TICKERS'!AF51,Settings.COB,Settings.COB)) -> 2.705 | AI51: 8Y | AJ51: ADBBCF8 | AL51: =IF(ISBLANK(AK51),Settings.BloombergPCS,AK51) -> BGN | AM51: Curncy | AN51: =AJ51&" "&AL51&" "&AM51 -> ADBBCF8 BGN Curncy | AP51: =IF(ISBLANK(AO51),Settings.CurveSide.MidBidAsk,'AUD CURVE TICKERS'!AO51) -> PX_MID | AQ51: =IF(Settings.isCOBToday,_xll.BDP(AN51,'AUD CURVE TICKERS'!AP51),_xll.BDH(AN51,'AUD CURVE TICKERS'!AP51,Settings.COB,Settings.COB)) -> 13
V52: INT_RATE_FUT_END_DT | Y52: 9Y | Z52: ADSW9 | AB52: =IF(ISBLANK(AA52),Settings.BloombergPCS,AA52) -> BGN | AC52: Curncy | AD52: =Z52&" "&AB52&" "&AC52 -> ADSW9 BGN Curncy | AF52: =IF(ISBLANK(AE52),Settings.CurveSide.MidBidAsk,'AUD CURVE TICKERS'!AE52) -> PX_MID | AG52: =IF(Settings.isCOBToday,_xll.BDP(AD52,'AUD CURVE TICKERS'!AF52),_xll.BDH(AD52,'AUD CURVE TICKERS'!AF52,Settings.COB,Settings.COB)) -> 2.7575 | AI52: 9Y | AJ52: ADBBCF9 | AL52: =IF(ISBLANK(AK52),Settings.BloombergPCS,AK52) -> BGN | AM52: Curncy | AN52: =AJ52&" "&AL52&" "&AM52 -> ADBBCF9 BGN Curncy | AP52: =IF(ISBLANK(AO52),Settings.CurveSide.MidBidAsk,'AUD CURVE TICKERS'!AO52) -> PX_MID | AQ52: =IF(Settings.isCOBToday,_xll.BDP(AN52,'AUD CURVE TICKERS'!AP52),_xll.BDH(AN52,'AUD CURVE TICKERS'!AP52,Settings.COB,Settings.COB)) -> 12.625
Y53: 10Y | Z53: ADSW10 | AB53: =IF(ISBLANK(AA53),Settings.BloombergPCS,AA53) -> BGN | AC53: Curncy | AD53: =Z53&" "&AB53&" "&AC53 -> ADSW10 BGN Curncy | AF53: =IF(ISBLANK(AE53),Settings.CurveSide.MidBidAsk,'AUD CURVE TICKERS'!AE53) -> PX_MID | AG53: =IF(Settings.isCOBToday,_xll.BDP(AD53,'AUD CURVE TICKERS'!AF53),_xll.BDH(AD53,'AUD CURVE TICKERS'!AF53,Settings.COB,Settings.COB)) -> 2.8065 | AI53: 10Y | AJ53: ADBBCF10 | AL53: =IF(ISBLANK(AK53),Settings.BloombergPCS,AK53) -> BGN | AM53: Curncy | AN53: =AJ53&" "&AL53&" "&AM53 -> ADBBCF10 BGN Curncy | AP53: =IF(ISBLANK(AO53),Settings.CurveSide.MidBidAsk,'AUD CURVE TICKERS'!AO53) -> PX_MID | AQ53: =IF(Settings.isCOBToday,_xll.BDP(AN53,'AUD CURVE TICKERS'!AP53),_xll.BDH(AN53,'AUD CURVE TICKERS'!AP53,Settings.COB,Settings.COB)) -> 12.25
Y54: 15Y | Z54: ADSW15 | AB54: =IF(ISBLANK(AA54),Settings.BloombergPCS,AA54) -> BGN | AC54: Curncy | AD54: =Z54&" "&AB54&" "&AC54 -> ADSW15 BGN Curncy | AF54: =IF(ISBLANK(AE54),Settings.CurveSide.MidBidAsk,'AUD CURVE TICKERS'!AE54) -> PX_MID | AG54: =IF(Settings.isCOBToday,_xll.BDP(AD54,'AUD CURVE TICKERS'!AF54),_xll.BDH(AD54,'AUD CURVE TICKERS'!AF54,Settings.COB,Settings.COB)) -> 2.973 | AI54: 15Y | AJ54: ADBBCF15 | AL54: =IF(ISBLANK(AK54),Settings.BloombergPCS,AK54) -> BGN | AM54: Curncy | AN54: =AJ54&" "&AL54&" "&AM54 -> ADBBCF15 BGN Curncy | AP54: =IF(ISBLANK(AO54),Settings.CurveSide.MidBidAsk,'AUD CURVE TICKERS'!AO54) -> PX_MID | AQ54: =IF(Settings.isCOBToday,_xll.BDP(AN54,'AUD CURVE TICKERS'!AP54),_xll.BDH(AN54,'AUD CURVE TICKERS'!AP54,Settings.COB,Settings.COB)) -> 11
Y55: 20Y | Z55: ADSW20 | AB55: =IF(ISBLANK(AA55),Settings.BloombergPCS,AA55) -> BGN | AC55: Curncy | AD55: =Z55&" "&AB55&" "&AC55 -> ADSW20 BGN Curncy | AF55: =IF(ISBLANK(AE55),Settings.CurveSide.MidBidAsk,'AUD CURVE TICKERS'!AE55) -> PX_MID | AG55: =IF(Settings.isCOBToday,_xll.BDP(AD55,'AUD CURVE TICKERS'!AF55),_xll.BDH(AD55,'AUD CURVE TICKERS'!AF55,Settings.COB,Settings.COB)) -> 3.025 | AI55: 20Y | AJ55: ADBBCF20 | AL55: =IF(ISBLANK(AK55),Settings.BloombergPCS,AK55) -> BGN | AM55: Curncy | AN55: =AJ55&" "&AL55&" "&AM55 -> ADBBCF20 BGN Curncy | AP55: =IF(ISBLANK(AO55),Settings.CurveSide.MidBidAsk,'AUD CURVE TICKERS'!AO55) -> PX_MID | AQ55: =IF(Settings.isCOBToday,_xll.BDP(AN55,'AUD CURVE TICKERS'!AP55),_xll.BDH(AN55,'AUD CURVE TICKERS'!AP55,Settings.COB,Settings.COB)) -> 10.75
Y56: 25Y | Z56: ADSW25 | AB56: =IF(ISBLANK(AA56),Settings.BloombergPCS,AA56) -> BGN | AC56: Curncy | AD56: =Z56&" "&AB56&" "&AC56 -> ADSW25 BGN Curncy | AF56: =IF(ISBLANK(AE56),Settings.CurveSide.MidBidAsk,'AUD CURVE TICKERS'!AE56) -> PX_MID | AG56: =IF(Settings.isCOBToday,_xll.BDP(AD56,'AUD CURVE TICKERS'!AF56),_xll.BDH(AD56,'AUD CURVE TICKERS'!AF56,Settings.COB,Settings.COB)) -> 3.02375 | AI56: 25Y | AJ56: ADBBCF25 | AL56: =IF(ISBLANK(AK56),Settings.BloombergPCS,AK56) -> BGN | AM56: Curncy | AN56: =AJ56&" "&AL56&" "&AM56 -> ADBBCF25 BGN Curncy | AP56: =IF(ISBLANK(AO56),Settings.CurveSide.MidBidAsk,'AUD CURVE TICKERS'!AO56) -> PX_MID | AQ56: =IF(Settings.isCOBToday,_xll.BDP(AN56,'AUD CURVE TICKERS'!AP56),_xll.BDH(AN56,'AUD CURVE TICKERS'!AP56,Settings.COB,Settings.COB)) -> 11
Y57: 30Y | Z57: ADSW30 | AB57: =IF(ISBLANK(AA57),Settings.BloombergPCS,AA57) -> BGN | AC57: Curncy | AD57: =Z57&" "&AB57&" "&AC57 -> ADSW30 BGN Curncy | AF57: =IF(ISBLANK(AE57),Settings.CurveSide.MidBidAsk,'AUD CURVE TICKERS'!AE57) -> PX_MID | AG57: =IF(Settings.isCOBToday,_xll.BDP(AD57,'AUD CURVE TICKERS'!AF57),_xll.BDH(AD57,'AUD CURVE TICKERS'!AF57,Settings.COB,Settings.COB)) -> 2.99625 | AI57: 30Y | AJ57: ADBBCF30 | AL57: =IF(ISBLANK(AK57),Settings.BloombergPCS,AK57) -> BGN | AM57: Curncy | AN57: =AJ57&" "&AL57&" "&AM57 -> ADBBCF30 BGN Curncy | AP57: =IF(ISBLANK(AO57),Settings.CurveSide.MidBidAsk,'AUD CURVE TICKERS'!AO57) -> PX_MID | AQ57: =IF(Settings.isCOBToday,_xll.BDP(AN57,'AUD CURVE TICKERS'!AP57),_xll.BDH(AN57,'AUD CURVE TICKERS'!AP57,Settings.COB,Settings.COB)) -> 11.4
A70: << AUD3ML
B72: FRAS | L72: SWAPS
B73: Term | C73: InstrumentID | D73: Broker | E73: Used | F73: Database | G73: Ticker | H73: Side | I73: Used | J73: Result | L73: Term | M73: InstrumentID | N73: Broker | O73: Used | P73: Database | Q73: Ticker | R73: Side | S73: Used | T73: Result
B74: 1x7 | C74: ADFR0AG | E74: =IF(ISBLANK(D74),Settings.BloombergPCS,D74) | F74: Curncy | G74: =C74&" "&E74&" "&F74 -> ADFR0AG Curncy | I74: =IF(ISBLANK(H74),Settings.CurveSide.MidBidAsk,'AUD CURVE TICKERS'!H74) -> PX_MID | J74: =IF(Settings.isCOBToday,_xll.BDP(G74,'AUD CURVE TICKERS'!I74),_xll.BDH(G74,'AUD CURVE TICKERS'!I74,Settings.COB,Settings.COB)) -> 2.159 | L74: 1Y | M74: ADSW1 | O74: =IF(ISBLANK(N74),Settings.BloombergPCS,N74) | P74: Curncy | Q74: =M74&" "&O74&" "&P74 -> ADSW1 Curncy | S74: =IF(ISBLANK(R74),Settings.CurveSide.MidBidAsk,'AUD CURVE TICKERS'!R74) -> PX_MID | T74: =IF(Settings.isCOBToday,_xll.BDP(Q74,'AUD CURVE TICKERS'!S74),_xll.BDH(Q74,'AUD CURVE TICKERS'!S74,Settings.COB,Settings.COB)) -> 2.1825
B75: 2x8 | C75: ADFR0BH | E75: =IF(ISBLANK(D75),Settings.BloombergPCS,D75) | F75: Curncy | G75: =C75&" "&E75&" "&F75 -> ADFR0BH Curncy | I75: =IF(ISBLANK(H75),Settings.CurveSide.MidBidAsk,'AUD CURVE TICKERS'!H75) -> PX_MID | J75: =IF(Settings.isCOBToday,_xll.BDP(G75,'AUD CURVE TICKERS'!I75),_xll.BDH(G75,'AUD CURVE TICKERS'!I75,Settings.COB,Settings.COB)) -> 2.146 | L75: 2Y | M75: ADSW2 | O75: =IF(ISBLANK(N75),Settings.BloombergPCS,N75) | P75: Curncy | Q75: =M75&" "&O75&" "&P75 -> ADSW2 Curncy | S75: =IF(ISBLANK(R75),Settings.CurveSide.MidBidAsk,'AUD CURVE TICKERS'!R75) -> PX_MID | T75: =IF(Settings.isCOBToday,_xll.BDP(Q75,'AUD CURVE TICKERS'!S75),_xll.BDH(Q75,'AUD CURVE TICKERS'!S75,Settings.COB,Settings.COB)) -> 2.235
B76: 3x9 | C76: ADFR0CI | E76: =IF(ISBLANK(D76),Settings.BloombergPCS,D76) | F76: Curncy | G76: =C76&" "&E76&" "&F76 -> ADFR0CI Curncy | I76: =IF(ISBLANK(H76),Settings.CurveSide.MidBidAsk,'AUD CURVE TICKERS'!H76) -> PX_MID | J76: =IF(Settings.isCOBToday,_xll.BDP(G76,'AUD CURVE TICKERS'!I76),_xll.BDH(G76,'AUD CURVE TICKERS'!I76,Settings.COB,Settings.COB)) -> 2.144 | L76: 3Y | M76: ADSW3 | O76: =IF(ISBLANK(N76),Settings.BloombergPCS,N76) | P76: Curncy | Q76: =M76&" "&O76&" "&P76 -> ADSW3 Curncy | S76: =IF(ISBLANK(R76),Settings.CurveSide.MidBidAsk,'AUD CURVE TICKERS'!R76) -> PX_MID | T76: =IF(Settings.isCOBToday,_xll.BDP(Q76,'AUD CURVE TICKERS'!S76),_xll.BDH(Q76,'AUD CURVE TICKERS'!S76,Settings.COB,Settings.COB)) -> 2.305
L77: 4Y | M77: ADSW4 | O77: =IF(ISBLANK(N77),Settings.BloombergPCS,N77) -> BGN | P77: Curncy | Q77: =M77&" "&O77&" "&P77 -> ADSW4 BGN Curncy | S77: =IF(ISBLANK(R77),Settings.CurveSide.MidBidAsk,'AUD CURVE TICKERS'!R77) -> PX_MID | T77: =IF(Settings.isCOBToday,_xll.BDP(Q77,'AUD CURVE TICKERS'!S77),_xll.BDH(Q77,'AUD CURVE TICKERS'!S77,Settings.COB,Settings.COB)) -> 2.39375
L78: 5Y | M78: ADSW5 | O78: =IF(ISBLANK(N78),Settings.BloombergPCS,N78) -> BGN | P78: Curncy | Q78: =M78&" "&O78&" "&P78 -> ADSW5 BGN Curncy | S78: =IF(ISBLANK(R78),Settings.CurveSide.MidBidAsk,'AUD CURVE TICKERS'!R78) -> PX_MID | T78: =IF(Settings.isCOBToday,_xll.BDP(Q78,'AUD CURVE TICKERS'!S78),_xll.BDH(Q78,'AUD CURVE TICKERS'!S78,Settings.COB,Settings.COB)) -> 2.486
L79: 6Y | M79: ADSW6 | O79: =IF(ISBLANK(N79),Settings.BloombergPCS,N79) -> BGN | P79: Curncy | Q79: =M79&" "&O79&" "&P79 -> ADSW6 BGN Curncy | S79: =IF(ISBLANK(R79),Settings.CurveSide.MidBidAsk,'AUD CURVE TICKERS'!R79) -> PX_MID | T79: =IF(Settings.isCOBToday,_xll.BDP(Q79,'AUD CURVE TICKERS'!S79),_xll.BDH(Q79,'AUD CURVE TICKERS'!S79,Settings.COB,Settings.COB)) -> 2.5675
L80: 7Y | M80: ADSW7 | O80: =IF(ISBLANK(N80),Settings.BloombergPCS,N80) -> BGN | P80: Curncy | Q80: =M80&" "&O80&" "&P80 -> ADSW7 BGN Curncy | S80: =IF(ISBLANK(R80),Settings.CurveSide.MidBidAsk,'AUD CURVE TICKERS'!R80) -> PX_MID | T80: =IF(Settings.isCOBToday,_xll.BDP(Q80,'AUD CURVE TICKERS'!S80),_xll.BDH(Q80,'AUD CURVE TICKERS'!S80,Settings.COB,Settings.COB)) -> 2.64
L81: 8Y | M81: ADSW8 | O81: =IF(ISBLANK(N81),Settings.BloombergPCS,N81) -> BGN | P81: Curncy | Q81: =M81&" "&O81&" "&P81 -> ADSW8 BGN Curncy | S81: =IF(ISBLANK(R81),Settings.CurveSide.MidBidAsk,'AUD CURVE TICKERS'!R81) -> PX_MID | T81: =IF(Settings.isCOBToday,_xll.BDP(Q81,'AUD CURVE TICKERS'!S81),_xll.BDH(Q81,'AUD CURVE TICKERS'!S81,Settings.COB,Settings.COB)) -> 2.705
L82: 9Y | M82: ADSW9 | O82: =IF(ISBLANK(N82),Settings.BloombergPCS,N82) -> BGN | P82: Curncy | Q82: =M82&" "&O82&" "&P82 -> ADSW9 BGN Curncy | S82: =IF(ISBLANK(R82),Settings.CurveSide.MidBidAsk,'AUD CURVE TICKERS'!R82) -> PX_MID | T82: =IF(Settings.isCOBToday,_xll.BDP(Q82,'AUD CURVE TICKERS'!S82),_xll.BDH(Q82,'AUD CURVE TICKERS'!S82,Settings.COB,Settings.COB)) -> 2.7575
L83: 10Y | M83: ADSW10 | O83: =IF(ISBLANK(N83),Settings.BloombergPCS,N83) -> BGN | P83: Curncy | Q83: =M83&" "&O83&" "&P83 -> ADSW10 BGN Curncy | S83: =IF(ISBLANK(R83),Settings.CurveSide.MidBidAsk,'AUD CURVE TICKERS'!R83) -> PX_MID | T83: =IF(Settings.isCOBToday,_xll.BDP(Q83,'AUD CURVE TICKERS'!S83),_xll.BDH(Q83,'AUD CURVE TICKERS'!S83,Settings.COB,Settings.COB)) -> 2.8065
L84: 12Y | M84: ADSW12 | O84: =IF(ISBLANK(N84),Settings.BloombergPCS,N84) -> BGN | P84: Curncy | Q84: =M84&" "&O84&" "&P84 -> ADSW12 BGN Curncy | S84: =IF(ISBLANK(R84),Settings.CurveSide.MidBidAsk,'AUD CURVE TICKERS'!R84) -> PX_MID | T84: =IF(Settings.isCOBToday,_xll.BDP(Q84,'AUD CURVE TICKERS'!S84),_xll.BDH(Q84,'AUD CURVE TICKERS'!S84,Settings.COB,Settings.COB)) -> 2.89
L85: 15Y | M85: ADSW15 | O85: =IF(ISBLANK(N85),Settings.BloombergPCS,N85) -> BGN | P85: Curncy | Q85: =M85&" "&O85&" "&P85 -> ADSW15 BGN Curncy | S85: =IF(ISBLANK(R85),Settings.CurveSide.MidBidAsk,'AUD CURVE TICKERS'!R85) -> PX_MID | T85: =IF(Settings.isCOBToday,_xll.BDP(Q85,'AUD CURVE TICKERS'!S85),_xll.BDH(Q85,'AUD CURVE TICKERS'!S85,Settings.COB,Settings.COB)) -> 2.973
L86: 20Y | M86: ADSW20 | O86: =IF(ISBLANK(N86),Settings.BloombergPCS,N86) -> BGN | P86: Curncy | Q86: =M86&" "&O86&" "&P86 -> ADSW20 BGN Curncy | S86: =IF(ISBLANK(R86),Settings.CurveSide.MidBidAsk,'AUD CURVE TICKERS'!R86) -> PX_MID | T86: =IF(Settings.isCOBToday,_xll.BDP(Q86,'AUD CURVE TICKERS'!S86),_xll.BDH(Q86,'AUD CURVE TICKERS'!S86,Settings.COB,Settings.COB)) -> 3.025
L87: 25Y | M87: ADSW25 | O87: =IF(ISBLANK(N87),Settings.BloombergPCS,N87) -> BGN | P87: Curncy | Q87: =M87&" "&O87&" "&P87 -> ADSW25 BGN Curncy | S87: =IF(ISBLANK(R87),Settings.CurveSide.MidBidAsk,'AUD CURVE TICKERS'!R87) -> PX_MID | T87: =IF(Settings.isCOBToday,_xll.BDP(Q87,'AUD CURVE TICKERS'!S87),_xll.BDH(Q87,'AUD CURVE TICKERS'!S87,Settings.COB,Settings.COB)) -> 3.02375
L88: 30Y | M88: ADSW30 | O88: =IF(ISBLANK(N88),Settings.BloombergPCS,N88) -> BGN | P88: Curncy | Q88: =M88&" "&O88&" "&P88 -> ADSW30 BGN Curncy | S88: =IF(ISBLANK(R88),Settings.CurveSide.MidBidAsk,'AUD CURVE TICKERS'!R88) -> PX_MID | T88: =IF(Settings.isCOBToday,_xll.BDP(Q88,'AUD CURVE TICKERS'!S88),_xll.BDH(Q88,'AUD CURVE TICKERS'!S88,Settings.COB,Settings.COB)) -> 2.99625
A100: << AUD6ML

Sheet AUD CURVE
AP1: … Curve Generator Templtes
B2: AUD OIS | AB2: AUDOIS - GENERATOR TEMPLATE | AG2: AUD3ML - GENERATOR TEMPLATE | AL2: AUD6ML - GENERATOR TEMPLATE
C4: MARKETDATAPROPERTIES | F4: OIS | L4: OISFIXINGS | R4: LIBOROISBASISSPREADS | V4: SWAPS | AC4: CREATE GENERATOR | AH4: CREATE GENERATOR | AM4: CREATE GENERATOR
F5: Term | G5: Rate | H5: StartDate | I5: EndDate | J5: Use | L5: BaseDate | M5: Rate | O5: Libor-OIS Q | P5: Basis 3X6 | R5: Term | S5: Rate | V5: Term | W5: Rate | AC5: HandleName | AD5: AUD_OIS_CURVE_GENERATOR | AH5: HandleName | AI5: AUD_3ML_CURVE_GENERATOR | AM5: HandleName | AN5: AUD_6ML_CURVE_GENERATOR
C6: Currency | D6: AUD | F6: ='AUD CURVE TICKERS'!B14 -> ON | G6: ='AUD CURVE TICKERS'!J14% -> 0.015 | J6: TRUE | O6: ='AUD CURVE TICKERS'!T14/10000 -> 0.0051 | P6: ='AUD CURVE TICKERS'!AQ44/10000 -> 0.001475 | R6: ='AUD CURVE TICKERS'!L14 -> 1Y | S6: =O6 -> 0.0051 | T6: 3ML | V6: ='AUD CURVE TICKERS'!Y44 -> 1Y | W6: ='AUD CURVE TICKERS'!AG44% -> 0.020295 | AC6: Create Curve Generator | AD6: =_xll.meLWOCurveGeneratorCreate(AD5,AC8,AC9:AD15,AC18,AC19:AD35,AC38,AC39:AD40,AC44,AC45:AD51) -> AUD_OIS_CURVE_GENERATOR@1:38 | AH6: Create Curve Generator | AI6: =_xll.meLWOCurveGeneratorCreate(AI5,AH8,AH9:AI23,AH26,AH27:AI29,AH32,AH33:AI37,AH40,AH41:AI46,AH49,AH50:AI56,AH59,AH60:AI80,AH83,AH84:AI115) -> AUD_3ML_CURVE_GENERATOR@4:38 | AM6: Create Curve Generator | AN6: =_xll.meLWOCurveGeneratorCreate(AN5,AM8,AM9:AN23,AM26,AM27:AN29,AM32,AM33:AN37,AM40,AM41:AN46,AM49,AM50:AN56,AM59,AM60:AN73,AM83,AM84:AN84) -> AUD_6ML_CURVE_GENERATOR@7:38
C7: CurveType | D7: OIS | F7: ='AUD CURVE TICKERS'!B15 -> 1W | G7: ='AUD CURVE TICKERS'!J15% -> 0.015 | J7: TRUE | O7: ='AUD CURVE TICKERS'!T15/10000 -> 0.004725 | P7: ='AUD CURVE TICKERS'!AQ45/10000 -> 0.0014725 | R7: ='AUD CURVE TICKERS'!L15 -> 2Y | S7: =O7 -> 0.004725 | T7: 3ML | V7: ='AUD CURVE TICKERS'!Y45 -> 2Y | W7: ='AUD CURVE TICKERS'!AG45% -> 0.0208
C8: CurveIndexFrequency | D8: DAILY | F8: ='AUD CURVE TICKERS'!B16 -> 1M | G8: ='AUD CURVE TICKERS'!J16% -> 0.01499 | J8: TRUE | O8: ='AUD CURVE TICKERS'!T16/10000 -> 0.004375 | P8: ='AUD CURVE TICKERS'!AQ46/10000 -> 0.00145 | R8: ='AUD CURVE TICKERS'!L16 -> 3Y | S8: =O8 -> 0.004375 | T8: 3ML | V8: ='AUD CURVE TICKERS'!Y46 -> 3Y | W8: ='AUD CURVE TICKERS'!AG46% -> 0.021575 | AC8: CURVEPROPERTIES | AH8: CURVEPROPERTIES | AM8: CURVEPROPERTIES
C9: AsOfDate | D9: =Settings.COB -> 43278 | F9: ='AUD CURVE TICKERS'!B17 -> 2M | G9: ='AUD CURVE TICKERS'!J17% -> 0.015 | J9: TRUE | O9: ='AUD CURVE TICKERS'!T17/10000 -> 0.0042375 | P9: ='AUD CURVE TICKERS'!AQ47/10000 -> 0.00144 | R9: ='AUD CURVE TICKERS'!L17 -> 4Y | S9: =O9+P9 -> 0.0056775 | T9: 6ML | V9: ='AUD CURVE TICKERS'!Y47 -> 4Y | W9: ='AUD CURVE TICKERS'!AG47% -> 0.0239375 | AC9: CurveType | AD9: OIS | AH9: CurveType | AI9: SWAP | AM9: CurveType | AN9: SWAP
F10: ='AUD CURVE TICKERS'!B18 -> 3M | G10: ='AUD CURVE TICKERS'!J18% -> 0.015 | J10: TRUE | O10: ='AUD CURVE TICKERS'!T18/10000 -> 0.0042 | P10: ='AUD CURVE TICKERS'!AQ48/10000 -> 0.0014225 | R10: ='AUD CURVE TICKERS'!L18 -> 5Y | S10: =O10+P10 -> 0.0056225 | T10: 6ML | V10: ='AUD CURVE TICKERS'!Y48 -> 5Y | W10: ='AUD CURVE TICKERS'!AG48% -> 0.02486 | AC10: CurveIndexFrequency | AD10: DAILY | AH10: CurveIndexFrequency | AI10: QUARTERLY | AM10: CurveIndexFrequency | AN10: SEMI-ANNUAL
F11: ='AUD CURVE TICKERS'!B19 -> 4M | G11: ='AUD CURVE TICKERS'!J19% -> 0.01501 | J11: TRUE | O11: ='AUD CURVE TICKERS'!T19/10000 -> 0.0042625 | P11: ='AUD CURVE TICKERS'!AQ49/10000 -> 0.00139 | R11: ='AUD CURVE TICKERS'!L19 -> 6Y | S11: =O11+P11 -> 0.0056525 | T11: 6ML | V11: ='AUD CURVE TICKERS'!Y49 -> 6Y | W11: ='AUD CURVE TICKERS'!AG49% -> 0.025675 | AC11: StaticDataTable | AD11: OIS | AH11: StaticDataTable | AI11: STD | AM11: StaticDataTable | AN11: AUD6ML
C12: Create Market Data Handle | F12: ='AUD CURVE TICKERS'!B20 -> 5M | G12: ='AUD CURVE TICKERS'!J20% -> 0.015025 | J12: TRUE | O12: ='AUD CURVE TICKERS'!T20/10000 -> 0.0043125 | P12: ='AUD CURVE TICKERS'!AQ50/10000 -> 0.00135 | R12: ='AUD CURVE TICKERS'!L20 -> 7Y | S12: =O12+P12 -> 0.0056625 | T12: 6ML | V12: ='AUD CURVE TICKERS'!Y50 -> 7Y | W12: ='AUD CURVE TICKERS'!AG50% -> 0.0264 | AC12: IndexName | AD12: OIS:AUDOIS:AUDDF:AUDDF_AUDCSA:AUDDF_NOCSA | AH12: IndexName | AI12: STD:AUD3ML | AM12: IndexName | AN12: AUD6ML
C13: Handle Name | D13: AUD_OIS_CURVE_MARKETDATA | F13: ='AUD CURVE TICKERS'!B21 -> 6M | G13: ='AUD CURVE TICKERS'!J21% -> 0.01504 | J13: TRUE | O13: ='AUD CURVE TICKERS'!T21/10000 -> 0.004325 | P13: ='AUD CURVE TICKERS'!AQ51/10000 -> 0.0013 | R13: ='AUD CURVE TICKERS'!L21 -> 8Y | S13: =O13+P13 -> 0.005625 | T13: 6ML | V13: ='AUD CURVE TICKERS'!Y51 -> 8Y | W13: ='AUD CURVE TICKERS'!AG51% -> 0.02705 | AC13: Currency | AD13: AUD | AH13: Currency | AI13: AUD | AM13: Currency | AN13: AUD
C14: Market Data Handle | D14: =_xll.meLWOCurveMarketDataCreate(D13,C4,C6:D9,F4,F6:J31,L4,L6:M31,R4,R6:S31,V4,V6:W31) -> AUD_OIS_CURVE_MARKETDATA@2:37 | F14: ='AUD CURVE TICKERS'!B22 -> 9M | G14: ='AUD CURVE TICKERS'!J22% -> 0.01512 | J14: TRUE | O14: ='AUD CURVE TICKERS'!T22/10000 -> 0.0043125 | P14: ='AUD CURVE TICKERS'!AQ52/10000 -> 0.0012625 | R14: ='AUD CURVE TICKERS'!L22 -> 9Y | S14: =O14+P14 -> 0.005575 | T14: 6ML | V14: ='AUD CURVE TICKERS'!Y52 -> 9Y | W14: ='AUD CURVE TICKERS'!AG52% -> 0.027575 | AC14: interpolation | AD14: FN_SPLINEINTERPOLATION | AH14: interpolation | AI14: =IF(Settings.SwapCurve.Interpolation="LINEAR-SPLINE","FN_LINEARSPLINEINTERPOLATION","FN_SPLINEINTERPOLATION") -> FN_SPLINEINTERPOLATION | AM14: interpolation | AN14: =IF(Settings.SwapCurve.Interpolation="LINEAR-SPLINE","FN_LINEARSPLINEINTERPOLATION","FN_SPLINEINTERPOLATION") -> FN_SPLINEINTERPOLATION
F15: ='AUD CURVE TICKERS'!B23 -> 1Y | G15: ='AUD CURVE TICKERS'!J23% -> 0.01528 | J15: TRUE | O15: ='AUD CURVE TICKERS'!T23/10000 -> 0.0043125 | P15: ='AUD CURVE TICKERS'!AQ53/10000 -> 0.001225 | R15: ='AUD CURVE TICKERS'!L23 -> 10Y | S15: =O15+P15 -> 0.0055375 | T15: 6ML | V15: ='AUD CURVE TICKERS'!Y53 -> 10Y | W15: ='AUD CURVE TICKERS'!AG53% -> 0.028065 | AC15: yieldgen.interpolation | AD15: FN_SPLINEINTERPOLATION | AH15: yieldgen.interpolation | AI15: =IF(Settings.SwapCurve.Interpolation="LINEAR-SPLINE","FN_LINEARSPLINEINTERPOLATION","FN_SPLINEINTERPOLATION") -> FN_SPLINEINTERPOLATION | AM15: yieldgen.interpolation | AN15: =IF(Settings.SwapCurve.Interpolation="LINEAR-SPLINE","FN_LINEARSPLINEINTERPOLATION","FN_SPLINEINTERPOLATION") -> FN_SPLINEINTERPOLATION
F16: ='AUD CURVE TICKERS'!B24 -> 2Y | G16: ='AUD CURVE TICKERS'!J24% -> 0.0163 | J16: TRUE | O16: ='AUD CURVE TICKERS'!T24/10000 -> 0.0043375 | P16: ='AUD CURVE TICKERS'!AQ54/10000 -> 0.0011 | R16: ='AUD CURVE TICKERS'!L24 -> 15Y | S16: =O16+P16 -> 0.0054375 | T16: 6ML | V16: ='AUD CURVE TICKERS'!Y54 -> 15Y | W16: ='AUD CURVE TICKERS'!AG54% -> 0.02973 | AH16: isfrause | AI16: FALSE | AM16: isfraUse | AN16: TRUE
F17: ='AUD CURVE TICKERS'!B25 -> 3Y | G17: ='AUD CURVE TICKERS'!J25% -> 0.01733 | J17: TRUE | O17: ='AUD CURVE TICKERS'!T25/10000 -> 0.0043625 | P17: ='AUD CURVE TICKERS'!AQ55/10000 -> 0.001075 | R17: ='AUD CURVE TICKERS'!L25 -> 20Y | S17: =O17+P17 -> 0.0054375 | T17: 6ML | V17: ='AUD CURVE TICKERS'!Y55 -> 20Y | W17: ='AUD CURVE TICKERS'!AG55% -> 0.03025 | AH17: isfutureuse | AI17: TRUE | AM17: isfutureUse | AN17: FALSE
F18: ='AUD CURVE TICKERS'!B26 -> 4Y | G18: ='AUD CURVE TICKERS'!J26% -> 0.01848 | J18: TRUE | O18: ='AUD CURVE TICKERS'!T26/10000 -> 0.0044 | P18: ='AUD CURVE TICKERS'!AQ56/10000 -> 0.0011 | R18: ='AUD CURVE TICKERS'!L26 -> 25Y | S18: =O18+P18 -> 0.0055 | T18: 6ML | V18: ='AUD CURVE TICKERS'!Y56 -> 25Y | W18: ='AUD CURVE TICKERS'!AG56% -> 0.0302375 | AC18: OIS | AH18: future.interpolation | AI18: =IF(Settings.SwapCurve.Interpolation="LINEAR-SPLINE","FN_LINEARSPLINEINTERPOLATION","FN_LINEARINTERPOLATION") -> FN_LINEARINTERPOLATION | AM18: future.interpolation | AN18: =IF(Settings.SwapCurve.Interpolation="LINEAR-SPLINE","FN_LINEARSPLINEINTERPOLATION","FN_LINEARINTERPOLATION") -> FN_LINEARINTERPOLATION
C19: Curve Dictionary | F19: ='AUD CURVE TICKERS'!B27 -> 5Y | G19: ='AUD CURVE TICKERS'!J27% -> 0.01948 | J19: TRUE | O19: ='AUD CURVE TICKERS'!T27/10000 -> 0.0044375 | P19: ='AUD CURVE TICKERS'!AQ57/10000 -> 0.00114 | R19: ='AUD CURVE TICKERS'!L27 -> 30Y | S19: =O19+P19 -> 0.0055775 | T19: 6ML | V19: ='AUD CURVE TICKERS'!Y57 -> 30Y | W19: ='AUD CURVE TICKERS'!AG57% -> 0.0299625 | AC19: calendar | AD19: SYB:LNB | AH19: Frequency | AI19: SIMPLE | AM19: Frequency | AN19: SIMPLE
C20: Handle Name | D20: AUD_OIS_CURVE | F20: ='AUD CURVE TICKERS'!B28 -> 6Y | G20: ='AUD CURVE TICKERS'!J28% -> 0.02025 | J20: TRUE | AC20: daycount | AD20: ACT/365 | AH20: dfcurvename | AI20: OIS | AM20: dfcurvename | AN20: OIS
C21: Curve Generator | D21: =$AD$6 -> AUD_OIS_CURVE_GENERATOR@1:38 | F21: ='AUD CURVE TICKERS'!B29 -> 7Y | G21: ='AUD CURVE TICKERS'!J29% -> 0.021015 | J21: TRUE | AC21: frequency | AD21: ANNUAL | AH21: IsSwapTenorAdjust | AI21: TRUE | AM21: IsSwapTenorAdjust | AN21: FALSE
C22: Domestic Curve Collection | D22: AUDYC | F22: ='AUD CURVE TICKERS'!B30 -> 8Y | G22: ='AUD CURVE TICKERS'!J30% -> 0.02163 | J22: TRUE | AC22: generatemethod | AD22: DAILYCOMPOUNDING | AH22: TenorSwapName | AI22: 3M6MBasis | AM22: FastRebuild | AN22: TRUE
C23: Foreign Curve Collection | F23: ='AUD CURVE TICKERS'!B31 -> 9Y | G23: ='AUD CURVE TICKERS'!J31% -> 0.02225 | J23: TRUE | AC23: resetlag | AD23: 1D | AH23: FastRebuild | AI23: TRUE
F24: ='AUD CURVE TICKERS'!B32 -> 10Y | G24: ='AUD CURVE TICKERS'!J32% -> 0.02285 | J24: TRUE | AC24: firstrate | AD24: SHORTMARKET
F25: ='AUD CURVE TICKERS'!B33 -> 15Y | G25: ='AUD CURVE TICKERS'!J33% -> 0.0246 | J25: TRUE | AC25: slidingrule | AD25: MOD_FOLLOWING
C26: Curve Build | F26: ='AUD CURVE TICKERS'!B34 -> 20Y | G26: ='AUD CURVE TICKERS'!J34% -> 0.02461 | J26: TRUE | AC26: eomday | AD26: 31 | AH26: MONEYMARKET | AM26: MONEYMARKET
C27: Handle Name | D27: {=_xll.meLWOCurveCalibrate(D20,D21,D14,D22,D23)} -> AUD_OIS_CURVE@3:37 | F27: ='AUD CURVE TICKERS'!B35 -> 25Y | G27: ='AUD CURVE TICKERS'!J35% -> 0.02508 | J27: TRUE | AC27: iseomroll | AD27: TRUE | AH27: Calendar | AI27: SYB:LnB | AM27: Calendar | AN27: SYB:LnB
C28: Curve Collection | D28: AUDYC | F28: ='AUD CURVE TICKERS'!B36 -> 30Y | G28: ='AUD CURVE TICKERS'!J36% -> 0.02404 | J28: TRUE | AC28: shorttermconvention | AD28: ARITHMETICAVERAGE | AH28: DayCount | AI28: ACT/365 | AM28: DayCount | AN28: ACT/365
C29: Curve Index | D29: OIS:AUDOIS:AUDDF:AUDDF_AUDCSA:AUDDF_NOCSA | AC29: longtermconvention | AD29: LOBASIS | AH29: Slidingrule | AI29: FOLLOWING | AM29: Slidingrule | AN29: FOLLOWING
C30: Calibration Time Taken | D30: 0.01500 sec | AC30: longterm | AD30: 3Y
C31: Curve Loaded | D31: =LEFT($D$27,3)=LEFT($D$20,3) -> TRUE | AC31: longterm.generatemethod | AD31: NONE
AC32: Epsilon | AD32: 1e-10 | AH32: LIBORFIXINGS | AM32: LIBORFIXINGS
AC33: MaxLoop | AD33: 1000 | AH33: Calendar | AI33: SYB:LnB | AM33: Calendar | AN33: SYB:LnB
AC34: CompoundingMethod | AD34: GEOMETRIC | AH34: Daycount | AI34: ACT/365 | AM34: Daycount | AN34: ACT/365
B35: AUD 3ML | AC35: SmoothShortEnd | AD35: FALSE | AH35: Frequency | AI35: Simple | AM35: Frequency | AN35: Simple
AH36: Resetlag | AI36: 0 | AM36: Resetlag | AN36: 0
C37: MARKETDATAPROPERTIES | F37: LIBORFIXINGS | I37: FRAS | L37: FUTURES | R37: SWAPS | V37: BASISSWAPS | AH37: SlidingRule | AI37: MOD_FOLLOWING | AM37: SlidingRule | AN37: MOD_FOLLOWING
C38: Currency | D38: AUD | F38: Term | G38: Rate | I38: Term | J38: Rate | L38: Term | M38: StartDate | N38: EndDate | O38: Rate | P38: Volatility | R38: Term | S38: Rate | T38: Use | V38: Term | W38: Rate | X38: Use | AC38: LIBOROISBASIS | AD38: OIS FLOAT LEG CONVENTIONS
C39: CurveType | D39: SWAP | F39: ='AUD CURVE TICKERS'!B45 -> 3M | G39: ='AUD CURVE TICKERS'!J45% -> 0.021153 | L39: ='AUD CURVE TICKERS'!L44 -> IR1 | M39: ='AUD CURVE TICKERS'!V44 -> 14/09/2018 | N39: ='AUD CURVE TICKERS'!W44 -> 14/12/2018 | O39: ='AUD CURVE TICKERS'!T44 -> 98.015 | P39: =Settings.Futures.Convexity.HW1F.Vol -> 0.02 | R39: ='AUD CURVE TICKERS'!Y45 -> 2Y | S39: ='AUD CURVE TICKERS'!AG45% -> 0.0208 | T39: TRUE | V39: ='AUD CURVE TICKERS'!AI45 -> 2Y | W39: ='AUD CURVE TICKERS'!AQ45/10000 -> 0.0014725 | X39: TRUE | AC39: frequency | AD39: ANNUAL
C40: CurveIndexFrequency | D40: QUARTERLY | L40: ='AUD CURVE TICKERS'!L45 -> IR2 | M40: ='AUD CURVE TICKERS'!V45 -> 14/12/2018 | N40: ='AUD CURVE TICKERS'!W45 -> 08/03/2019 | O40: ='AUD CURVE TICKERS'!T45 -> 98.005 | P40: =Settings.Futures.Convexity.HW1F.Vol -> 0.02 | R40: ='AUD CURVE TICKERS'!Y46 -> 3Y | S40: ='AUD CURVE TICKERS'!AG46% -> 0.021575 | T40: TRUE | V40: ='AUD CURVE TICKERS'!AI46 -> 3Y | W40: ='AUD CURVE TICKERS'!AQ46/10000 -> 0.00145 | X40: TRUE | AC40: slidingRule | AD40: MOD_FOLLOWING | AH40: FRAS | AM40: FRAS
C41: AsOfDate | D41: =Settings.COB -> 43278 | L41: ='AUD CURVE TICKERS'!L46 -> IR3 | M41: ='AUD CURVE TICKERS'!V46 -> 08/03/2019 | N41: ='AUD CURVE TICKERS'!W46 -> 14/06/2019 | O41: ='AUD CURVE TICKERS'!T46 -> 97.975 | P41: =Settings.Futures.Convexity.HW1F.Vol -> 0.02 | R41: ='AUD CURVE TICKERS'!Y47 -> 4Y | S41: ='AUD CURVE TICKERS'!AG47% -> 0.0239375 | T41: TRUE | V41: ='AUD CURVE TICKERS'!AI47 -> 4Y | W41: ='AUD CURVE TICKERS'!AQ47/10000 -> 0.00144 | X41: TRUE | AH41: Calendar | AI41: SYB:LnB | AM41: Calendar | AN41: SYB:LnB
L42: ='AUD CURVE TICKERS'!L47 -> IR4 | M42: ='AUD CURVE TICKERS'!V47 -> 14/06/2019 | N42: ='AUD CURVE TICKERS'!W47 -> 13/09/2019 | O42: ='AUD CURVE TICKERS'!T47 -> 97.945 | P42: =Settings.Futures.Convexity.HW1F.Vol -> 0.02 | R42: ='AUD CURVE TICKERS'!Y48 -> 5Y | S42: ='AUD CURVE TICKERS'!AG48% -> 0.02486 | T42: TRUE | V42: ='AUD CURVE TICKERS'!AI48 -> 5Y | W42: ='AUD CURVE TICKERS'!AQ48/10000 -> 0.0014225 | X42: TRUE | AH42: DayCount | AI42: ACT/365 | AM42: DayCount | AN42: ACT/365
L43: ='AUD CURVE TICKERS'!L48 -> IR5 | M43: ='AUD CURVE TICKERS'!V48 -> 13/09/2019 | N43: ='AUD CURVE TICKERS'!W48 -> 13/12/2019 | O43: ='AUD CURVE TICKERS'!T48 -> 97.895 | P43: =Settings.Futures.Convexity.HW1F.Vol -> 0.02 | R43: ='AUD CURVE TICKERS'!Y49 -> 6Y | S43: ='AUD CURVE TICKERS'!AG49% -> 0.025675 | T43: TRUE | V43: ='AUD CURVE TICKERS'!AI49 -> 6Y | W43: ='AUD CURVE TICKERS'!AQ49/10000 -> 0.00139 | X43: TRUE | AH43: ResetLag | AI43: 1 | AM43: ResetLag | AN43: 1
L44: ='AUD CURVE TICKERS'!L49 -> IR6 | M44: ='AUD CURVE TICKERS'!V49 -> 13/12/2019 | N44: ='AUD CURVE TICKERS'!W49 -> 13/03/2020 | O44: ='AUD CURVE TICKERS'!T49 -> 97.845 | P44: =Settings.Futures.Convexity.HW1F.Vol -> 0.02 | R44: ='AUD CURVE TICKERS'!Y50 -> 7Y | S44: ='AUD CURVE TICKERS'!AG50% -> 0.0264 | T44: TRUE | V44: ='AUD CURVE TICKERS'!AI50 -> 7Y | W44: ='AUD CURVE TICKERS'!AQ50/10000 -> 0.00135 | X44: TRUE | AC44: SWAPS | AD44: LIBOR SWAP CONVENTIONS - FIXED LEG | AH44: SlidingRule | AI44: MOD_FOLLOWING | AM44: SlidingRule | AN44: MOD_FOLLOWING
C45: Create Market Data Handle | R45: ='AUD CURVE TICKERS'!Y51 -> 8Y | S45: ='AUD CURVE TICKERS'!AG51% -> 0.02705 | T45: TRUE | V45: ='AUD CURVE TICKERS'!AI51 -> 8Y | W45: ='AUD CURVE TICKERS'!AQ51/10000 -> 0.0013 | X45: TRUE | AC45: calendar | AD45: SYB:LnB | AH45: ApplyTension | AI45: FALSE | AM45: ApplyTension | AN45: FALSE
C46: Handle Name | D46: AUD_SWAP_3ML_CURVE_MARKETDATA | R46: ='AUD CURVE TICKERS'!Y52 -> 9Y | S46: ='AUD CURVE TICKERS'!AG52% -> 0.027575 | T46: TRUE | V46: ='AUD CURVE TICKERS'!AI52 -> 9Y | W46: ='AUD CURVE TICKERS'!AQ52/10000 -> 0.0012625 | X46: TRUE | AC46: daycountfix | AD46: ACT/365 | AH46: TensionGap | AI46: 2 | AM46: TensionGap | AN46: 2
C47: Market Data Handle | D47: =_xll.meLWOCurveMarketDataCreate(D46,C37,C38:D43,F37,F39:G43,I37,I39:J64,L37,L39:P64,R37,R39:T64,V37,V39:X64) -> AUD_SWAP_3ML_CURVE_MARKETDATA@5:37 | R47: ='AUD CURVE TICKERS'!Y53 -> 10Y | S47: ='AUD CURVE TICKERS'!AG53% -> 0.028065 | T47: TRUE | V47: ='AUD CURVE TICKERS'!AI53 -> 10Y | W47: ='AUD CURVE TICKERS'!AQ53/10000 -> 0.001225 | X47: TRUE | AC47: frequencyfix | AD47: Semi-Annual
R48: ='AUD CURVE TICKERS'!Y54 -> 15Y | S48: ='AUD CURVE TICKERS'!AG54% -> 0.02973 | T48: TRUE | V48: ='AUD CURVE TICKERS'!AI54 -> 15Y | W48: ='AUD CURVE TICKERS'!AQ54/10000 -> 0.0011 | X48: TRUE | AC48: frequencyfix.1y | AD48: QUARTERLY
R49: ='AUD CURVE TICKERS'!Y55 -> 20Y | S49: ='AUD CURVE TICKERS'!AG55% -> 0.03025 | T49: TRUE | V49: ='AUD CURVE TICKERS'!AI55 -> 20Y | W49: ='AUD CURVE TICKERS'!AQ55/10000 -> 0.001075 | X49: TRUE | AC49: frequencyfix.2y | AD49: QUARTERLY | AH49: FUTURES | AM49: FUTURES
R50: ='AUD CURVE TICKERS'!Y56 -> 25Y | S50: ='AUD CURVE TICKERS'!AG56% -> 0.0302375 | T50: TRUE | V50: ='AUD CURVE TICKERS'!AI56 -> 25Y | W50: ='AUD CURVE TICKERS'!AQ56/10000 -> 0.0011 | X50: TRUE | AC50: frequencyfix.3y | AD50: QUARTERLY | AH50: calendar | AI50: SYB:LnB
R51: ='AUD CURVE TICKERS'!Y57 -> 30Y | S51: ='AUD CURVE TICKERS'!AG57% -> 0.0299625 | T51: TRUE | V51: ='AUD CURVE TICKERS'!AI57 -> 30Y | W51: ='AUD CURVE TICKERS'!AQ57/10000 -> 0.00114 | X51: TRUE | AC51: slidingrule | AD51: MOD_FOLLOWING | AH51: daycount | AI51: Act/360
AH52: resetlag | AI52: 2
C53: Curve Dictionary | AH53: slidingrule | AI53: MOD_FOLLOWING
C54: Handle Name | D54: AUD_SWAP_3M_CURVE | AH54: MeanReversion | AI54: 0.03
C55: Curve Generator | D55: =$AI$6 -> AUD_3ML_CURVE_GENERATOR@4:38 | AH55: ApplyTension | AI55: FALSE
C56: Domestic Curve Collection | D56: AUDYC | AH56: TensionGap | AI56: 2
C57: Foreign Curve Collection
AH59: SWAPS | AM59: SWAPS
C60: Curve Build | AH60: Calendar | AI60: SYB:LnB | AM60: Calendar | AN60: SYB:LnB
C61: Handle Name | D61: {=IF($D$31,_xll.meLWOCurveCalibrate(D54,D55,D47,D56),"#Error: Dependency Curve not Built")} -> AUD_SWAP_3M_CURVE@6:37 | AH61: DayCount | AI61: ACT/365 | AM61: DayCount | AN61: ACT/365
C62: Curve Collection | D62: AUDYC | AH62: DayCountFix | AI62: ACT/365 | AM62: DayCountFix | AN62: ACT/365
C63: Curve Index | D63: STD:AUD3ML | AH63: DayCountFloat | AI63: ACT/365 | AM63: DayCountFloat | AN63: ACT/365
C64: Calibration Time Taken | D64: 0.00800 sec | AH64: Frequency | AI64: SEMI-ANNUAL | AM64: Frequency | AN64: Semi-Annual
C65: Curve Loaded | D65: =LEFT(D61,3)=LEFT(D61,3) -> TRUE | AH65: FrequencyFix.1y | AI65: QUARTERLY | AM65: FrequencyFloat | AN65: Semi-Annual
AH66: FrequencyFix.2y | AI66: QUARTERLY | AM66: SlidingRule | AN66: MOD_FOLLOWING
AH67: FrequencyFix.3y | AI67: QUARTERLY | AM67: IsNewtonraphson | AN67: TRUE
AH68: FrequencyFloat | AI68: SEMI-ANNUAL | AM68: issimultaneouseq | AN68: TRUE
B69: AUD 6ML | AH69: FrequencyFloat.1y | AI69: QUARTERLY | AM69: Epsilon | AN69: 1e-09
AH70: FrequencyFloat.2y | AI70: QUARTERLY | AM70: MaxLoop | AN70: 1000
C71: MARKETDATAPROPERTIES | F71: LIBORFIXINGS | I71: FRAS | L71: FUTURES | R71: SWAPS | V71: BASISSWAPS | AH71: FrequencyFloat.3y | AI71: QUARTERLY | AM71: ResetLag | AN71: 1
C72: Currency | D72: AUD | F72: Term | G72: Rate | I72: Term | J72: Rate | L72: Term | M72: StartDate | N72: EndDate | O72: Rate | P72: Volatility | R72: Term | S72: Rate | T72: Use | V72: Term | W72: Rate | X72: Use | AH72: interpolation | AI72: FN_LINEARSPLINEINTERPOLATION | AM72: IsEomRoll | AN72: TRUE
C73: CurveType | D73: SWAP | F73: ='AUD CURVE TICKERS'!B46 -> 6M | G73: ='AUD CURVE TICKERS'!J46% -> 0.0223 | I73: ='AUD CURVE TICKERS'!B74 -> 1x7 | J73: ='AUD CURVE TICKERS'!J74% -> 0.02159 | R73: ='AUD CURVE TICKERS'!L74 -> 1Y | S73: ='AUD CURVE TICKERS'!T74% -> 0.021825 | T73: TRUE | AH73: SlidingRule | AI73: MOD_FOLLOWING
C74: CurveIndexFrequency | D74: SEMI-ANNUAL | I74: ='AUD CURVE TICKERS'!B75 -> 2x8 | J74: ='AUD CURVE TICKERS'!J75% -> 0.02146 | R74: ='AUD CURVE TICKERS'!L75 -> 2Y | S74: ='AUD CURVE TICKERS'!T75% -> 0.02235 | T74: TRUE | AH74: IsNewtonraphson | AI74: TRUE
C75: AsOfDate | D75: =Settings.COB -> 43278 | I75: ='AUD CURVE TICKERS'!B76 -> 3x9 | J75: ='AUD CURVE TICKERS'!J76% -> 0.02144 | R75: ='AUD CURVE TICKERS'!L76 -> 3Y | S75: ='AUD CURVE TICKERS'!T76% -> 0.02305 | T75: TRUE | AH75: issimultaneouseq | AI75: TRUE
R76: ='AUD CURVE TICKERS'!L77 -> 4Y | S76: ='AUD CURVE TICKERS'!T77% -> 0.0239375 | T76: TRUE | AH76: Epsilon | AI76: 1e-09
R77: ='AUD CURVE TICKERS'!L78 -> 5Y | S77: ='AUD CURVE TICKERS'!T78% -> 0.02486 | T77: TRUE | AH77: MaxLoop | AI77: 1000
R78: ='AUD CURVE TICKERS'!L79 -> 6Y | S78: ='AUD CURVE TICKERS'!T79% -> 0.025675 | T78: TRUE | AH78: ResetLag | AI78: 1
C79: Create Market Data Handle | R79: ='AUD CURVE TICKERS'!L80 -> 7Y | S79: ='AUD CURVE TICKERS'!T80% -> 0.0264 | T79: TRUE | AH79: BaseFrequencyFloat | AI79: QUARTERLY
C80: Handle Name | D80: AUD_SWAP_6ML_CURVE_MARKETDATA | R80: ='AUD CURVE TICKERS'!L81 -> 8Y | S80: ='AUD CURVE TICKERS'!T81% -> 0.02705 | T80: TRUE | AH80: IsEomRoll | AI80: TRUE
C81: Market Data Handle | D81: =_xll.meLWOCurveMarketDataCreate(D80,C71,C72:D77,F71,F73:G77,I71,I73:J98,L71,L73:P98,R71,R73:T98,V71,V73:X98) -> AUD_SWAP_6ML_CURVE_MARKETDATA@8:37 | R81: ='AUD CURVE TICKERS'!L82 -> 9Y | S81: ='AUD CURVE TICKERS'!T82% -> 0.027575 | T81: TRUE
R82: ='AUD CURVE TICKERS'!L83 -> 10Y | S82: ='AUD CURVE TICKERS'!T83% -> 0.028065 | T82: TRUE
R83: ='AUD CURVE TICKERS'!L84 -> 12Y | S83: ='AUD CURVE TICKERS'!T84% -> 0.0289 | T83: TRUE | AH83: BASISSWAPS | AM83: BASISSWAPS
R84: ='AUD CURVE TICKERS'!L85 -> 15Y | S84: ='AUD CURVE TICKERS'!T85% -> 0.02973 | T84: TRUE | AH84: IsLeg1Spread | AI84: FALSE
R85: ='AUD CURVE TICKERS'!L86 -> 20Y | S85: ='AUD CURVE TICKERS'!T86% -> 0.03025 | T85: TRUE | AH85: Leg1cashlet.calendar | AI85: SYB:LnB
R86: ='AUD CURVE TICKERS'!L87 -> 25Y | S86: ='AUD CURVE TICKERS'!T87% -> 0.0302375 | T86: TRUE | AH86: Leg1cashlet.daycount | AI86: ACT/365
C87: Curve Dictionary | R87: ='AUD CURVE TICKERS'!L88 -> 30Y | S87: ='AUD CURVE TICKERS'!T88% -> 0.0299625 | T87: TRUE | AH87: Leg1cashlet.frequency | AI87: Semi-Annual
C88: Handle Name | D88: AUD_SWAP_6M_CURVE | AH88: Leg1cashlet.slidingrule | AI88: MOD_FOLLOWING
C89: Curve Generator | D89: =$AN$6 -> AUD_6ML_CURVE_GENERATOR@7:38 | AH89: Leg1cashlet.spotlag | AI89: 1
C90: Domestic Curve Collection | D90: AUDYC | AH90: Leg1discount | AI90: OIS
C91: Foreign Curve Collection | AH91: Leg1forecast | AI91: STD
AH92: Leg1index.accessary | AI92: 6M
AH93: Leg1index.daycount | AI93: ACT/365
C94: Curve Build | AH94: Leg1index.fixing.calendar | AI94: SYB:LnB
C95: Handle Name | D95: {=IF($D$65,_xll.meLWOCurveCalibrate(D88,D89,D81,D90),"#Error: Dependency Curve not Built")} -> AUD_SWAP_6M_CURVE@9:1 | AH95: Leg1index.frequency | AI95: Simple
C96: Curve Collection | D96: AUDYC | AH96: Leg1index.payment.calendar | AI96: SYB
C97: Curve Index | D97: AUD6ML | AH97: Leg1index.resetlag | AI97: 1
C98: Calibration Time Taken | D98: 0.00500 sec | AH98: Leg1index.slidingrule | AI98: MOD_FOLLOWING
C99: Curve Loaded | D99: =LEFT(D95,3)=LEFT(D95,3) -> TRUE | AH99: Leg2cashlet.calendar | AI99: SYB:LnB
AH100: Leg2cashlet.daycount | AI100: ACT/365
AH101: Leg2cashlet.frequency | AI101: Quarterly
AH102: Leg2cashlet.slidingrule | AI102: MOD_FOLLOWING
...

Sheet AUD REPRICING
B2: Trade Dates | E2: SWAPS: AUDOIS
C3: Unadjusted
B4: EffectiveDate | C4: MaturityDate | E4: EffectiveDate | F4: Maturity | G4: Generator | H4: PayRec | I4: Notional | J4: FixedRate | K4: Spread | M4: CreateSwap | N4: CurveCollection | O4: ParRate | P4: Curve | Q4: +/- (Bps)
B5: =_xll.meDateFromTenor(Settings.COB,E5,"MOD_FOLLOWING","SYB:LNB","") -> 43279 | C5: =_xll.meDateFromTenor(B5,F5,) -> 43286 | E5: 1D | F5: 1W | G5: AUD_OIS | H5: PAY | I5: 1000000 | J5: 0.01 | K5: 0 | L5: 1 | M5: =_xll.meLWOSwapCreateFromGenerator("AUDOIS"&L5,G5,H5,I5,B5,C5,J5,K5,,,,,Settings.AllowCalibrationUpdates) -> AUDOIS1@50:0 | N5: AUDYC | O5: =_xll.meLWOSwapParRate(M5,N5) -> 0.015 | P5: ='AUD CURVE'!G7 -> 0.015 | Q5: =(O5-P5)*10000 -> -5.9832139e-08
B6: =_xll.meDateFromTenor(Settings.COB,E6,"MOD_FOLLOWING","SYB:LNB","") -> 43279 | C6: =_xll.meDateFromTenor(B6,F6,) -> 43309 | E6: 1D | F6: 1M | G6: AUD_OIS | H6: PAY | I6: 1000000 | J6: 0.01 | K6: 0 | L6: 2 | M6: =_xll.meLWOSwapCreateFromGenerator("AUDOIS"&L6,G6,H6,I6,B6,C6,J6,K6,,,,,Settings.AllowCalibrationUpdates) -> AUDOIS2@55:0 | N6: AUDYC | O6: =_xll.meLWOSwapParRate(M6,N6) -> 0.01499 | P6: ='AUD CURVE'!G8 -> 0.01499 | Q6: =(O6-P6)*10000 -> 3.3002056e-08
B7: =_xll.meDateFromTenor(Settings.COB,E7,"MOD_FOLLOWING","SYB:LNB","") -> 43279 | C7: =_xll.meDateFromTenor(B7,F7,) -> 43340 | E7: 1D | F7: 2M | G7: AUD_OIS | H7: PAY | I7: 1000000 | J7: 0.01 | K7: 0 | L7: 3 | M7: =_xll.meLWOSwapCreateFromGenerator("AUDOIS"&L7,G7,H7,I7,B7,C7,J7,K7,,,,,Settings.AllowCalibrationUpdates) -> AUDOIS3@48:0 | N7: AUDYC | O7: =_xll.meLWOSwapParRate(M7,N7) -> 0.015 | P7: ='AUD CURVE'!G9 -> 0.015 | Q7: =(O7-P7)*10000 -> 1.9936761e-08
B8: =_xll.meDateFromTenor(Settings.COB,E8,"MOD_FOLLOWING","SYB:LNB","") -> 43279 | C8: =_xll.meDateFromTenor(B8,F8,) -> 43371 | E8: 1D | F8: 3M | G8: AUD_OIS | H8: PAY | I8: 1000000 | J8: 0.01 | K8: 0 | L8: 4 | M8: =_xll.meLWOSwapCreateFromGenerator("AUDOIS"&L8,G8,H8,I8,B8,C8,J8,K8,,,,,Settings.AllowCalibrationUpdates) -> AUDOIS4@51:0 | N8: AUDYC | O8: =_xll.meLWOSwapParRate(M8,N8) -> 0.015 | P8: ='AUD CURVE'!G10 -> 0.015 | Q8: =(O8-P8)*10000 -> 1.2570733e-07
B9: =_xll.meDateFromTenor(Settings.COB,E9,"MOD_FOLLOWING","SYB:LNB","") -> 43279 | C9: =_xll.meDateFromTenor(B9,F9,) -> 43401 | E9: 1D | F9: 4M | G9: AUD_OIS | H9: PAY | I9: 1000000 | J9: 0.01 | K9: 0 | L9: 5 | M9: =_xll.meLWOSwapCreateFromGenerator("AUDOIS"&L9,G9,H9,I9,B9,C9,J9,K9,,,,,Settings.AllowCalibrationUpdates) -> AUDOIS5@46:0 | N9: AUDYC | O9: =_xll.meLWOSwapParRate(M9,N9) -> 0.01501 | P9: ='AUD CURVE'!G11 -> 0.01501 | Q9: =(O9-P9)*10000 -> 1.2490413e-07
B10: =_xll.meDateFromTenor(Settings.COB,E10,"MOD_FOLLOWING","SYB:LNB","") -> 43279 | C10: =_xll.meDateFromTenor(B10,F10,) -> 43432 | E10: 1D | F10: 5M | G10: AUD_OIS | H10: PAY | I10: 1000000 | J10: 0.01 | K10: 0 | L10: 6 | M10: =_xll.meLWOSwapCreateFromGenerator("AUDOIS"&L10,G10,H10,I10,B10,C10,J10,K10,,,,,Settings.AllowCalibrationUpdates) -> AUDOIS6@59:0 | N10: AUDYC | O10: =_xll.meLWOSwapParRate(M10,N10) -> 0.015025 | P10: ='AUD CURVE'!G12 -> 0.015025 | Q10: =(O10-P10)*10000 -> 1.3737221e-07
B11: =_xll.meDateFromTenor(Settings.COB,E11,"MOD_FOLLOWING","SYB:LNB","") -> 43279 | C11: =_xll.meDateFromTenor(B11,F11,) -> 43462 | E11: 1D | F11: 6M | G11: AUD_OIS | H11: PAY | I11: 1000000 | J11: 0.01 | K11: 0 | L11: 7 | M11: =_xll.meLWOSwapCreateFromGenerator("AUDOIS"&L11,G11,H11,I11,B11,C11,J11,K11,,,,,Settings.AllowCalibrationUpdates) -> AUDOIS7@42:0 | N11: AUDYC | O11: =_xll.meLWOSwapParRate(M11,N11) -> 0.01504 | P11: ='AUD CURVE'!G13 -> 0.01504 | Q11: =(O11-P11)*10000 -> 1.6655214e-07
B12: =_xll.meDateFromTenor(Settings.COB,E12,"MOD_FOLLOWING","SYB:LNB","") -> 43279 | C12: =_xll.meDateFromTenor(B12,F12,) -> 43552 | E12: 1D | F12: 9M | G12: AUD_OIS | H12: PAY | I12: 1000000 | J12: 0.01 | K12: 0 | L12: 8 | M12: =_xll.meLWOSwapCreateFromGenerator("AUDOIS"&L12,G12,H12,I12,B12,C12,J12,K12,,,,,Settings.AllowCalibrationUpdates) -> AUDOIS8@58:0 | N12: AUDYC | O12: =_xll.meLWOSwapParRate(M12,N12) -> 0.01512 | P12: ='AUD CURVE'!G14 -> 0.01512 | Q12: =(O12-P12)*10000 -> 1.250965e-07
B13: =_xll.meDateFromTenor(Settings.COB,E13,"MOD_FOLLOWING","SYB:LNB","") -> 43279 | C13: =_xll.meDateFromTenor(B13,F13,) -> 43644 | E13: 1D | F13: 1Y | G13: AUD_OIS | H13: PAY | I13: 1000000 | J13: 0.01 | K13: 0 | L13: 9 | M13: =_xll.meLWOSwapCreateFromGenerator("AUDOIS"&L13,G13,H13,I13,B13,C13,J13,K13,,,,,Settings.AllowCalibrationUpdates) -> AUDOIS9@63:0 | N13: AUDYC | O13: =_xll.meLWOSwapParRate(M13,N13) -> 0.01528 | P13: ='AUD CURVE'!G15 -> 0.01528 | Q13: =(O13-P13)*10000 -> 1.3299362e-07
B14: =_xll.meDateFromTenor(Settings.COB,E14,"MOD_FOLLOWING","SYB:LNB","") -> 43279 | C14: =_xll.meDateFromTenor(B14,F14,) -> 44010 | E14: 1D | F14: 2Y | G14: AUD_OIS | H14: PAY | I14: 1000000 | J14: 0.01 | K14: 0 | L14: 10 | M14: =_xll.meLWOSwapCreateFromGenerator("AUDOIS"&L14,G14,H14,I14,B14,C14,J14,K14,,,,,Settings.AllowCalibrationUpdates) -> AUDOIS10@45:0 | N14: AUDYC | O14: =_xll.meLWOSwapParRate(M14,N14) -> 0.0163 | P14: ='AUD CURVE'!G16 -> 0.0163 | Q14: =(O14-P14)*10000 -> 1.0439639e-07
B17: Trade Dates | E17: SWAPS:AUD3ML/AUD6ML
C18: Unadjusted
B19: EffectiveDate | C19: MaturityDate | E19: EffectiveDate | F19: Maturity | G19: Generator | H19: PayRec | I19: Notional | J19: FixedRate | K19: Spread | M19: CreateSwap | N19: CurveCollection | O19: ParRate | P19: Curve | Q19: +/- (Bps)
B20: =_xll.meDateFromTenor(Settings.COB,E20,"MOD_FOLLOWING","SYB:LNB","") -> 43279 | C20: =_xll.meDateFromTenor(B20,F20,) -> 44010 | E20: 1D | F20: 2Y | G20: AUD_3ML | H20: PAY | I20: 1000000 | J20: 0.01 | K20: 0 | L20: 1 | M20: =_xll.meLWOSwapCreateFromGenerator("AUDIRS"&L20,G20,H20,I20,B20,C20,J20,K20,,,,,Settings.AllowCalibrationUpdates) -> AUDIRS1@54:0 | N20: AUDYC | O20: =_xll.meLWOSwapParRate(M20,N20) -> 0.0208 | P20: ='AUD CURVE'!S39 -> 0.0208 | Q20: =(O20-P20)*10000 -> -4.510281e-13
B21: =_xll.meDateFromTenor(Settings.COB,E21,"MOD_FOLLOWING","SYB:LNB","") -> 43279 | C21: =_xll.meDateFromTenor(B21,F21,) -> 44375 | E21: 1D | F21: 3Y | G21: AUD_3ML | H21: PAY | I21: 1000000 | J21: 0.01 | K21: 0 | L21: 2 | M21: =_xll.meLWOSwapCreateFromGenerator("AUDIRS"&L21,G21,H21,I21,B21,C21,J21,K21,,,,,Settings.AllowCalibrationUpdates) -> AUDIRS2@43:0 | N21: AUDYC | O21: =_xll.meLWOSwapParRate(M21,N21) -> 0.021575 | P21: ='AUD CURVE'!S40 -> 0.021575 | Q21: =(O21-P21)*10000 -> -1.7347235e-13
B22: =_xll.meDateFromTenor(Settings.COB,E22,"MOD_FOLLOWING","SYB:LNB","") -> 43279 | C22: =_xll.meDateFromTenor(B22,F22,) -> 43644 | E22: 1D | F22: 1Y | G22: AUD_6ML | H22: PAY | I22: 1000000 | J22: 0.01 | K22: 0 | L22: 3 | M22: =_xll.meLWOSwapCreateFromGenerator("AUDIRS"&L22,G22,H22,I22,B22,C22,J22,K22,,,,,Settings.AllowCalibrationUpdates) -> AUDIRS3@44:0 | N22: AUDYC | O22: =_xll.meLWOSwapParRate(M22,N22) -> 0.021825 | P22: ='AUD CURVE'!S73 -> 0.021825 | Q22: =(O22-P22)*10000 -> 1.179612e-12
B23: =_xll.meDateFromTenor(Settings.COB,E23,"MOD_FOLLOWING","SYB:LNB","") -> 43279 | C23: =_xll.meDateFromTenor(B23,F23,) -> 44010 | E23: 1D | F23: 2Y | G23: AUD_6ML | H23: PAY | I23: 1000000 | J23: 0.01 | K23: 0 | L23: 4 | M23: =_xll.meLWOSwapCreateFromGenerator("AUDIRS"&L23,G23,H23,I23,B23,C23,J23,K23,,,,,Settings.AllowCalibrationUpdates) -> AUDIRS4@66:0 | N23: AUDYC | O23: =_xll.meLWOSwapParRate(M23,N23) -> 0.02235 | P23: ='AUD CURVE'!S74 -> 0.02235 | Q23: =(O23-P23)*10000 -> 5.2041704e-13
B24: =_xll.meDateFromTenor(Settings.COB,E24,"MOD_FOLLOWING","SYB:LNB","") -> 43279 | C24: =_xll.meDateFromTenor(B24,F24,) -> 44375 | E24: 1D | F24: 3Y | G24: AUD_6ML | H24: PAY | I24: 1000000 | J24: 0.01 | K24: 0 | L24: 5 | M24: =_xll.meLWOSwapCreateFromGenerator("AUDIRS"&L24,G24,H24,I24,B24,C24,J24,K24,,,,,Settings.AllowCalibrationUpdates) -> AUDIRS5@53:0 | N24: AUDYC | O24: =_xll.meLWOSwapParRate(M24,N24) -> 0.02305 | P24: ='AUD CURVE'!S75 -> 0.02305 | Q24: =(O24-P24)*10000 -> 3.8163916e-13
B25: =_xll.meDateFromTenor(Settings.COB,E25,"MOD_FOLLOWING","SYB:LNB","") -> 43279 | C25: =_xll.meDateFromTenor(B25,F25,) -> 44740 | E25: 1D | F25: 4Y | G25: AUD_6ML | H25: PAY | I25: 1000000 | J25: 0.01 | K25: 0 | L25: 6 | M25: =_xll.meLWOSwapCreateFromGenerator("AUDIRS"&L25,G25,H25,I25,B25,C25,J25,K25,,,,,Settings.AllowCalibrationUpdates) -> AUDIRS6@41:0 | N25: AUDYC | O25: =_xll.meLWOSwapParRate(M25,N25) -> 0.0239375 | P25: ='AUD CURVE'!S76 -> 0.0239375 | Q25: =(O25-P25)*10000 -> 0
B26: =_xll.meDateFromTenor(Settings.COB,E26,"MOD_FOLLOWING","SYB:LNB","") -> 43279 | C26: =_xll.meDateFromTenor(B26,F26,) -> 45105 | E26: 1D | F26: 5Y | G26: AUD_6ML | H26: PAY | I26: 1000000 | J26: 0.01 | K26: 0 | L26: 7 | M26: =_xll.meLWOSwapCreateFromGenerator("AUDIRS"&L26,G26,H26,I26,B26,C26,J26,K26,,,,,Settings.AllowCalibrationUpdates) -> AUDIRS7@64:0 | N26: AUDYC | O26: =_xll.meLWOSwapParRate(M26,N26) -> 0.02486 | P26: ='AUD CURVE'!S77 -> 0.02486 | Q26: =(O26-P26)*10000 -> -1.0408341e-13
B27: =_xll.meDateFromTenor(Settings.COB,E27,"MOD_FOLLOWING","SYB:LNB","") -> 43279 | C27: =_xll.meDateFromTenor(B27,F27,) -> 45471 | E27: 1D | F27: 6Y | G27: AUD_6ML | H27: PAY | I27: 1000000 | J27: 0.01 | K27: 0 | L27: 8 | M27: =_xll.meLWOSwapCreateFromGenerator("AUDIRS"&L27,G27,H27,I27,B27,C27,J27,K27,,,,,Settings.AllowCalibrationUpdates) -> AUDIRS8@49:0 | N27: AUDYC | O27: =_xll.meLWOSwapParRate(M27,N27) -> 0.025675 | P27: ='AUD CURVE'!S78 -> 0.025675 | Q27: =(O27-P27)*10000 -> -2.0816682e-13
B28: =_xll.meDateFromTenor(Settings.COB,E28,"MOD_FOLLOWING","SYB:LNB","") -> 43279 | C28: =_xll.meDateFromTenor(B28,F28,) -> 45836 | E28: 1D | F28: 7Y | G28: AUD_6ML | H28: PAY | I28: 1000000 | J28: 0.01 | K28: 0 | L28: 9 | M28: =_xll.meLWOSwapCreateFromGenerator("AUDIRS"&L28,G28,H28,I28,B28,C28,J28,K28,,,,,Settings.AllowCalibrationUpdates) -> AUDIRS9@47:0 | N28: AUDYC | O28: =_xll.meLWOSwapParRate(M28,N28) -> 0.0264 | P28: ='AUD CURVE'!S79 -> 0.0264 | Q28: =(O28-P28)*10000 -> -3.469447e-14
B29: =_xll.meDateFromTenor(Settings.COB,E29,"MOD_FOLLOWING","SYB:LNB","") -> 43279 | C29: =_xll.meDateFromTenor(B29,F29,) -> 46201 | E29: 1D | F29: 8Y | G29: AUD_6ML | H29: PAY | I29: 1000000 | J29: 0.01 | K29: 0 | L29: 10 | M29: =_xll.meLWOSwapCreateFromGenerator("AUDIRS"&L29,G29,H29,I29,B29,C29,J29,K29,,,,,Settings.AllowCalibrationUpdates) -> AUDIRS10@60:0 | N29: AUDYC | O29: =_xll.meLWOSwapParRate(M29,N29) -> 0.02705 | P29: ='AUD CURVE'!S80 -> 0.02705 | Q29: =(O29-P29)*10000 -> 6.9388939e-14
B30: =_xll.meDateFromTenor(Settings.COB,E30,"MOD_FOLLOWING","SYB:LNB","") -> 43279 | C30: =_xll.meDateFromTenor(B30,F30,) -> 46566 | E30: 1D | F30: 9Y | G30: AUD_6ML | H30: PAY | I30: 1000000 | J30: 0.01 | K30: 0 | L30: 11 | M30: =_xll.meLWOSwapCreateFromGenerator("AUDIRS"&L30,G30,H30,I30,B30,C30,J30,K30,,,,,Settings.AllowCalibrationUpdates) -> AUDIRS11@65:0 | N30: AUDYC | O30: =_xll.meLWOSwapParRate(M30,N30) -> 0.027575 | P30: ='AUD CURVE'!S81 -> 0.027575 | Q30: =(O30-P30)*10000 -> -3.469447e-14
B31: =_xll.meDateFromTenor(Settings.COB,E31,"MOD_FOLLOWING","SYB:LNB","") -> 43279 | C31: =_xll.meDateFromTenor(B31,F31,) -> 46932 | E31: 1D | F31: 10Y | G31: AUD_6ML | H31: PAY | I31: 1000000 | J31: 0.01 | K31: 0 | L31: 12 | M31: =_xll.meLWOSwapCreateFromGenerator("AUDIRS"&L31,G31,H31,I31,B31,C31,J31,K31,,,,,Settings.AllowCalibrationUpdates) -> AUDIRS12@56:0 | N31: AUDYC | O31: =_xll.meLWOSwapParRate(M31,N31) -> 0.028065 | P31: ='AUD CURVE'!S82 -> 0.028065 | Q31: =(O31-P31)*10000 -> 6.9388939e-14
B32: =_xll.meDateFromTenor(Settings.COB,E32,"MOD_FOLLOWING","SYB:LNB","") -> 43279 | C32: =_xll.meDateFromTenor(B32,F32,) -> 47662 | E32: 1D | F32: 12Y | G32: AUD_6ML | H32: PAY | I32: 1000000 | J32: 0.01 | K32: 0 | L32: 13 | M32: =_xll.meLWOSwapCreateFromGenerator("AUDIRS"&L32,G32,H32,I32,B32,C32,J32,K32,,,,,Settings.AllowCalibrationUpdates) -> AUDIRS13@61:0 | N32: AUDYC | O32: =_xll.meLWOSwapParRate(M32,N32) -> 0.0289 | P32: ='AUD CURVE'!S83 -> 0.0289 | Q32: =(O32-P32)*10000 -> 3.469447e-14
B33: =_xll.meDateFromTenor(Settings.COB,E33,"MOD_FOLLOWING","SYB:LNB","") -> 43279 | C33: =_xll.meDateFromTenor(B33,F33,) -> 48758 | E33: 1D | F33: 15Y | G33: AUD_6ML | H33: PAY | I33: 1000000 | J33: 0.01 | K33: 0 | L33: 14 | M33: =_xll.meLWOSwapCreateFromGenerator("AUDIRS"&L33,G33,H33,I33,B33,C33,J33,K33,,,,,Settings.AllowCalibrationUpdates) -> AUDIRS14@40:0 | N33: AUDYC | O33: =_xll.meLWOSwapParRate(M33,N33) -> 0.02973 | P33: ='AUD CURVE'!S84 -> 0.02973 | Q33: =(O33-P33)*10000 -> -6.9388939e-14
... B35: =_xll.meDateFromTenor(Settings.COB,E35,"MOD_FOLLOWING","SYB:LNB","") -> 43279 | C35: =_xll.meDateFromTenor(B35,F35,) -> 52410 | E35: 1D | F35: 25Y | G35: AUD_6ML | H35: PAY | I35: 1000000 | J35: 0.01 | K35: 0 | L35: 16 | M35: =_xll.meLWOSwapCreateFromGenerator("AUDIRS"&L35,G35,H35,I35,B35,C35,J35,K35,,,,,Settings.AllowCalibrationUpdates) -> AUDIRS16@57:0 | N35: AUDYC | O35: =_xll.meLWOSwapParRate(M35,N35) -> 0.0302375 | P35: ='AUD CURVE'!S86 -> 0.0302375 | Q35: =(O35-P35)*10000 -> -3.469447e-14
B36: =_xll.meDateFromTenor(Settings.COB,E36,"MOD_FOLLOWING","SYB:LNB","") -> 43279 | C36: =_xll.meDateFromTenor(B36,F36,) -> 54237 | E36: 1D | F36: 30Y | G36: AUD_6ML | H36: PAY | I36: 1000000 | J36: 0.01 | K36: 0 | L36: 17 | M36: =_xll.meLWOSwapCreateFromGenerator("AUDIRS"&L36,G36,H36,I36,B36,C36,J36,K36,,,,,Settings.AllowCalibrationUpdates) -> AUDIRS17@52:0 | N36: AUDYC | O36: =_xll.meLWOSwapParRate(M36,N36) -> 0.029963068 | P36: ='AUD CURVE'!S87 -> 0.0299625 | Q36: =(O36-P36)*10000 -> 0.0056753827 | R36: *
M37: * Bug fix required for recalibration of final calibration instrument

Sheet SYNDICATE AUD IRS
N1: … BENCHMARK LEVEL | Z1: … FIXING INFO
B3: SETTLEMENT DATE | E3: BENCHMARK LEVEL | N3: SWAP
B4: AsOfDay | C4: =Settings.COB -> 43278 | J4: =$C$32 -> MID | N4: Handle Name | O4: AUD_SWAP
B5: ValuationLag | C5: 2D | E5: 3Y Bond Future | F5: Rate | G5: Bid | H5: Ask | I5: Mid | J5: Use | N5: Create Swap | O5: =IF('AUD CURVE'!$D$99,_xll.meLWOSwapCreate(O4,N8:P40),"#LOAD CURVE") -> AUD_SWAP@39:27
B6: BusDayAdjustment | C6: MOD_FOLLOWING | E6: YMA Comdty | F6: =(100-J6)% -> 0.020875 | G6: =_xll.BDP($E$6,$G$5) -> 97.91 | H6: =_xll.BDP($E$6,$H$5) -> 97.915 | I6: =AVERAGE(G6:H6) -> 97.9125 | J6: =IF($J$4="BID",G6,IF($J$4="ASK",H6,I6)) -> 97.9125
B7: Calendar | C7: SYB | J7: =$C$32 -> MID | N7: SWAP | O7: BOND LEG | P7: FUNDING LEG
B8: ValuationDate | C8: =_xll.meDateFromTenor(C4,C5,C6,C7) -> 43280 | E8: 10Y Bond Future | G8: Bid | H8: Ask | I8: Mid | J8: Use | N8: LegType | O8: Leg1:Fixed | P8: Leg2:Float
E9: XMA Comdty | F9: =(100-J9)% -> 0.026225 | G9: =_xll.BDP($E$9,$G$5) -> 97.375 | H9: =_xll.BDP($E$9,$H$5) -> 97.38 | I9: =AVERAGE(G9:H9) -> 97.3775 | J9: =IF($J$7="BID",G9,IF($J$7="ASK",H9,I9)) -> 97.3775 | N9: Notional | O9: =$C$12 -> 1000000 | P9: =$C$12 -> 1000000
B10: BOND SPECIFICATION | N10: NotionalExchange | O10: START_AND_END | P10: START_AND_END
B11: BondIdentifier | C11: MYNEWBOND | E11: Exchange for Physical, EFP | J11: =$C$32 -> MID | N11: PayReceive | O11: PAY | P11: RECEIVE | T11: RESET LOOKUP
B12: FaceValue | C12: 1000000 | E12: Tenor | F12: Ticker | G12: Bid | H12: Ask | I12: Mid | J12: Use | K12: SWP Q | L12: SWP S | N12: ForecastCurve | P12: =IF(P24="QUARTERLY","AUD3ML","AUD6ML") -> AUD3ML | T12: =IF(P24="QUARTERLY",X41,X42) -> ADBB3M CMPN Curncy
B13: BondAccrualFrequency | C13: SEMI-ANNUAL | E13: 1Y | F13: ADSF1Q WBCA Curncy | G13: =_xll.BDP($F13,$G$12) -> -5.75 | H13: =_xll.BDP($F13,$H$12) -> -5.75 | I13: =AVERAGE(G13:H13) -> -5.75 | J13: =IF($J$11="BID",G13,IF($J$11="ASK",H13,I13)) -> -5.75 | K13: =IF(COUNT($F$6,J13)=2,$F$6+J13/10000,"#WAIT: BBG") -> 0.0203 | L13: =IF(COUNT(K13,J31)=2,K13+J31/10000,"#WAIT: BBG") -> 0.021775 | N13: DiscountCurve | O13: AUDOIS | P13: AUDOIS | T13: PX_ASK
B14: BondPaymentFrequency | C14: SEMI-ANNUAL | E14: 2Y | F14: ADSF2Q IAUS Curncy | G14: =_xll.BDP($F14,$G$12) -> -3.75 | H14: =_xll.BDP($F14,$H$12) -> 1.25 | I14: =AVERAGE(G14:H14) -> -1.25 | J14: =IF($J$11="BID",G14,IF($J$11="ASK",H14,I14)) -> -1.25 | K14: =IF(COUNT($F$6,J14)=2,$F$6+J14/10000,"#WAIT: BBG") -> 0.02075 | L14: =IF(COUNT(K14,J32)=2,K14+J32/10000,"#WAIT: BBG") -> 0.0222125 | N14: Currency | O14: AUD | P14: AUD | T14: 2D
B15: Daycount | C15: ACT/ACT | E15: 3Y | F15: ADSF3Q IAUS Curncy | G15: =_xll.BDP($F15,$G$12) -> 4.25 | H15: =_xll.BDP($F15,$H$12) -> 9.25 | I15: =AVERAGE(G15:H15) -> 6.75 | J15: =IF($J$11="BID",G15,IF($J$11="ASK",H15,I15)) -> 6.75 | K15: =IF(COUNT($F$6,J15)=2,$F$6+J15/10000,"#WAIT: BBG") -> 0.02155 | L15: =IF(COUNT(K15,J33)=2,K15+J33/10000,"#WAIT: BBG") -> 0.0229875 | N15: Leverage | O15: 1 | P15: 1 | R15: RESET RATE | T15: =_xll.meDateFromTenor(P22,"-"&T14,"MOD_FOLLOWING","LNB:SYB") -> 43278
B16: ForwardStartTenor | E16: 4Y | F16: ADSF4 IAUS Curncy | G16: =_xll.BDP($F16,$G$12) -> 28 | H16: =_xll.BDP($F16,$H$12) -> 33 | I16: =AVERAGE(G16:H16) -> 30.5 | J16: =IF($J$11="BID",G16,IF($J$11="ASK",H16,I16)) -> 30.5 | K16: =IF(COUNT($F$6,J16)=2,$F$6+J16/10000,"#WAIT: BBG") -> 0.023925 | L16: =IF(COUNT(K16,J34)=2,K16+J34/10000,"#WAIT: BBG") -> 0.0253625 | N16: FixedRate | O16: 0 | R16: =IF(COUNT(T16)=1,T16%,"WAIT: BBG Data Loading") -> 0.021153 | T16: =_xll.BDH(T12,T13,T15,T15) -> 2.1153
B17: AccrualStartDate | C17: =IF(ISBLANK($C$16),C8,_xll.meDateFromTenor(Settings.COB,$C$16,$C$6,$C$7)) -> 43280 | E17: 5Y | F17: ADSF5 IAUS Curncy | G17: =_xll.BDP($F17,$G$12) -> 37.375 | H17: =_xll.BDP($F17,$H$12) -> 42.375 | I17: =AVERAGE(G17:H17) -> 39.875 | J17: =IF($J$11="BID",G17,IF($J$11="ASK",H17,I17)) -> 39.875 | K17: =IF(COUNT($F$6,J17)=2,$F$6+J17/10000,"#WAIT: BBG") -> 0.0248625 | L17: =IF(COUNT(K17,J35)=2,K17+J35/10000,"#WAIT: BBG") -> 0.0262875 | N17: FirstStubCurveIndex | P17: NATURAL
B18: MaturityOrTenor | C18: 10Y | E18: 6Y | F18: ADSF6 IAUS Curncy | G18: =_xll.BDP($F18,$G$12) -> -7.75 | H18: =_xll.BDP($F18,$H$12) -> -2.75 | I18: =AVERAGE(G18:H18) -> -5.25 | J18: =IF($J$11="BID",G18,IF($J$11="ASK",H18,I18)) -> -5.25 | K18: =IF(COUNT($F$6,J18)=2,$F$6+J18/10000,"#WAIT: BBG") -> 0.02035 | L18: =IF(COUNT(K18,J36)=2,K18+J36/10000,"#WAIT: BBG") -> 0.0217375 | N18: LastStubCurveIndex | P18: NATURAL | R18: FIXING OVERRIDE
E19: 7Y | F19: ADSF7 IAUS Curncy | G19: =_xll.BDP($F19,$G$12) -> -0.5 | H19: =_xll.BDP($F19,$H$12) -> 4.5 | I19: =AVERAGE(G19:H19) -> 2 | J19: =IF($J$11="BID",G19,IF($J$11="ASK",H19,I19)) -> 2 | K19: =IF(COUNT(L19,J37)=2,L19-J37/10000,"#WAIT: BBG") -> 0.0250875 | L19: =IF(COUNT($F$9,J19)=2,$F$9+J19/10000,"#WAIT: BBG") -> 0.026425 | N19: FirstFixing | P19: =IF(ISBLANK($R$19),"",$R$19)
B20: SWAP SPECIFICATION | E20: 8Y | F20: ADSF8 IAUS Curncy | G20: =_xll.BDP($F20,$G$12) -> 5.875 | H20: =_xll.BDP($F20,$H$12) -> 10.875 | I20: =AVERAGE(G20:H20) -> 8.375 | J20: =IF($J$11="BID",G20,IF($J$11="ASK",H20,I20)) -> 8.375 | K20: =IF(COUNT(L20,J38)=2,L20-J38/10000,"#WAIT: BBG") -> 0.0257625 | L20: =IF(COUNT($F$9,J20)=2,$F$9+J20/10000,"#WAIT: BBG") -> 0.0270625 | N20: LastFixing
B21: FundingAccrualFrequency | C21: QUARTERLY | E21: 9Y | F21: ADSF9 IAUS Curncy | G21: =_xll.BDP($F21,$G$12) -> 11.375 | H21: =_xll.BDP($F21,$H$12) -> 16.375 | I21: =AVERAGE(G21:H21) -> 13.875 | J21: =IF($J$11="BID",G21,IF($J$11="ASK",H21,I21)) -> 13.875 | K21: =IF(COUNT(L21,J39)=2,L21-J39/10000,"#WAIT: BBG") -> 0.02635 | L21: =IF(COUNT($F$9,J21)=2,$F$9+J21/10000,"#WAIT: BBG") -> 0.0276125 | N21: FloatSpread | P21: =$C$36 -> 90 | R21: STUB RATE | T21: STUB RATE FLOAT LEG LVB
B22: FundingPaymentFrequency | C22: SEMI-ANNUAL | E22: 10Y | F22: ADSF10 IAUS Curncy | G22: =_xll.BDP($F22,$G$12) -> 16.25 | H22: =_xll.BDP($F22,$H$12) -> 21.25 | I22: =AVERAGE(G22:H22) -> 18.75 | J22: =IF($J$11="BID",G22,IF($J$11="ASK",H22,I22)) -> 18.75 | K22: =IF(COUNT(L22,J40)=2,L22-J40/10000,"#WAIT: BBG") -> 0.0268875 | L22: =IF(COUNT($F$9,J22)=2,$F$9+J22/10000,"#WAIT: BBG") -> 0.0281 | N22: EffectiveDate | O22: =C17 -> 43280 | P22: =$C$17 -> 43280 | R22: =IF(U22<C4,"RESET REQUIRED",IF(AND(COUNT(V38:V43)=6,'AUD CURVE'!$D$99),_xll.meProductSwapStubRate($U$38:$U$43,$T$38:$T$43,$V$38:$V$43,$T$22:$U$34),"WAIT: BBG Data Loading")) -> 0.021153 | T22: EffectiveDate | U22: =P22 -> 43280
B23: IncludeAccrued | C23: FALSE | E23: 12Y | F23: ADSF12 IAUS Curncy | G23: =_xll.BDP($F23,$G$12) -> 24 | H23: =_xll.BDP($F23,$H$12) -> 30 | I23: =AVERAGE(G23:H23) -> 27 | J23: =IF($J$11="BID",G23,IF($J$11="ASK",H23,I23)) -> 27 | K23: =IF(COUNT(L23,J41)=2,L23-J41/10000,"#WAIT: BBG") -> 0.027775 | L23: =IF(COUNT($F$9,J23)=2,$F$9+J23/10000,"#WAIT: BBG") -> 0.028925 | N23: MaturityDate | O23: =$C$18 -> 10Y | P23: =$C$18 -> 10Y | T23: MaturityDate | U23: =P23 -> 10Y
E24: 15Y | F24: ADSF15 IAUS Curncy | G24: =_xll.BDP($F24,$G$12) -> 32.25 | H24: =_xll.BDP($F24,$H$12) -> 38.25 | I24: =AVERAGE(G24:H24) -> 35.25 | J24: =IF($J$11="BID",G24,IF($J$11="ASK",H24,I24)) -> 35.25 | K24: =IF(COUNT(L24,J42)=2,L24-J42/10000,"#WAIT: BBG") -> 0.02865 | L24: =IF(COUNT($F$9,J24)=2,$F$9+J24/10000,"#WAIT: BBG") -> 0.02975 | N24: AccrualFrequency | O24: =$C$13 -> SEMI-ANNUAL | P24: =$C$21 -> QUARTERLY | T24: CurveCollection | U24: =$C$29 -> AUDYC
E25: 20Y | F25: ADSF20 IAUS Curncy | G25: =_xll.BDP($F25,$G$12) -> 37.5 | H25: =_xll.BDP($F25,$H$12) -> 43.5 | I25: =AVERAGE(G25:H25) -> 40.5 | J25: =IF($J$11="BID",G25,IF($J$11="ASK",H25,I25)) -> 40.5 | K25: =IF(COUNT(L25,J43)=2,L25-J43/10000,"#WAIT: BBG") -> 0.0292125 | L25: =IF(COUNT($F$9,J25)=2,$F$9+J25/10000,"#WAIT: BBG") -> 0.030275 | N25: PaymentFrequency | O25: =$C$14 -> SEMI-ANNUAL | P25: =$C$22 -> SEMI-ANNUAL | T25: UseCurveIndex | U25: =P17 -> NATURAL
E26: 25Y | F26: ADSF25 IAUS Curncy | G26: =_xll.BDP($F26,$G$12) -> 37.5 | H26: =_xll.BDP($F26,$H$12) -> 43.5 | I26: =AVERAGE(G26:H26) -> 40.5 | J26: =IF($J$11="BID",G26,IF($J$11="ASK",H26,I26)) -> 40.5 | K26: =IF(COUNT(L26,J44)=2,L26-J44/10000,"#WAIT: BBG") -> 0.0291875 | L26: =IF(COUNT($F$9,J26)=2,$F$9+J26/10000,"#WAIT: BBG") -> 0.030275 | N26: Daycount | O26: =$C$15 -> ACT/ACT | P26: ACT/365 | T26: FloatFrequency | U26: =P24 -> QUARTERLY
B27: VALUATION SETTINGS | E27: 30Y | F27: ADSF30 IAUS Curncy | G27: =_xll.BDP($F27,$G$12) -> 34.625 | H27: =_xll.BDP($F27,$H$12) -> 40.625 | I27: =AVERAGE(G27:H27) -> 37.625 | J27: =IF($J$11="BID",G27,IF($J$11="ASK",H27,I27)) -> 37.625 | K27: =IF(COUNT(L27,J45)=2,L27-J45/10000,"#WAIT: BBG") -> 0.02885 | L27: =IF(COUNT($F$9,J27)=2,$F$9+J27/10000,"#WAIT: BBG") -> 0.0299875 | N27: FixingBusinessDayAdjustment | P27: MOD_FOLLOWING | T27: FloatDaycount | U27: =P26 -> ACT/365
B28: ValuationDate | C28: =C8 -> 43280 | N28: FixingCalendar | P28: SYB | T28: FloatBusinessDayAdjustment | U28: =P29 -> MOD_FOLLOWING
B29: CurveCollection | C29: AUDYC | E29: Tenor Basis 3M vs 6M | J29: =$C$32 -> MID | N29: AccrualBusinessDayAdjustment | O29: MOD_FOLLOWING | P29: MOD_FOLLOWING | T29: FloatCalendar | U29: =P28 -> SYB
E30: Tenor | F30: Ticker | G30: Bid | H30: Ask | I30: Mid | J30: Use | N30: AccrualCalendar | O30: SYB | P30: SYB | T30: FloatRollDay
B31: PRICING INPUTS | E31: 1Y | F31: ADBBCF1 IAUS Curncy | G31: =_xll.BDP($F31,G$30) -> 13.75 | H31: =_xll.BDP($F31,H$30) -> 15.75 | I31: =AVERAGE(G31:H31) -> 14.75 | J31: =IF($J$29="BID",G31,IF($J$29="ASK",H31,I31)) -> 14.75 | N31: PaymentBusinessDayAdjustment | O31: MOD_FOLLOWING | P31: MOD_FOLLOWING | T31: FloatFixingLag | U31: =P36 -> 0D
B32: Benchmark Side | C32: MID | E32: 2Y | F32: ADBBCF2 IAUS Curncy | G32: =_xll.BDP($F32,G$30) -> 13.625 | H32: =_xll.BDP($F32,H$30) -> 15.625 | I32: =AVERAGE(G32:H32) -> 14.625 | J32: =IF($J$29="BID",G32,IF($J$29="ASK",H32,I32)) -> 14.625 | N32: PaymentCalendar | O32: SYB | P32: SYB | T32: FloatFirstStubDate | U32: =IF(ISBLANK($P$33),"",$P$33)
B33: Benchmark Tenor | C33: 10Y | E33: 3Y | F33: ADBBCF3 IAUS Curncy | G33: =_xll.BDP($F33,G$30) -> 13.375 | H33: =_xll.BDP($F33,H$30) -> 15.375 | I33: =AVERAGE(G33:H33) -> 14.375 | J33: =IF($J$29="BID",G33,IF($J$29="ASK",H33,I33)) -> 14.375 | N33: FirstStubDate | T33: FloatLastStubDate | U33: =IF(ISBLANK($P$34),"",$P$34)
B34: Benchmark Level (%) | C34: =IF(ISNUMBER(C35),C35,VLOOKUP($C$33,$E$13:$L$27,IF($C$13="QUARTERLY",7,8),FALSE)) -> 0.0281 | E34: 4Y | F34: ADBBCF4 IAUS Curncy | G34: =_xll.BDP($F34,G$30) -> 13.375 | H34: =_xll.BDP($F34,H$30) -> 15.375 | I34: =AVERAGE(G34:H34) -> 14.375 | J34: =IF($J$29="BID",G34,IF($J$29="ASK",H34,I34)) -> 14.375 | N34: LastStubDate | T34: FloatStubType | U34: =IF(ISBLANK(P40),"",P40) -> SHORTSTART
B35: Override Benchmark (%) | E35: 5Y | F35: ADBBCF5 IAUS Curncy | G35: =_xll.BDP($F35,G$30) -> 13.25 | H35: =_xll.BDP($F35,H$30) -> 15.25 | I35: =AVERAGE(G35:H35) -> 14.25 | J35: =IF($J$29="BID",G35,IF($J$29="ASK",H35,I35)) -> 14.25 | N35: RollDay
B36: Credit Spread (bps) | C36: 90 | E36: 6Y | F36: ADBBCF6 IAUS Curncy | G36: =_xll.BDP($F36,G$30) -> 12.875 | H36: =_xll.BDP($F36,H$30) -> 14.875 | I36: =AVERAGE(G36:H36) -> 13.875 | J36: =IF($J$29="BID",G36,IF($J$29="ASK",H36,I36)) -> 13.875 | N36: FixingLag | P36: 0D | T36: STUB RATE TABLE | X36: STUB TICKERS
B37: New Issue Yield Approx (%) | C37: =IF(ISNUMBER($C$35),$C$35,$C$34+$C$36/10000) -> 0.0371 | E37: 7Y | F37: ADBBCF7 IAUS Curncy | G37: =_xll.BDP($F37,G$30) -> 12.375 | H37: =_xll.BDP($F37,H$30) -> 14.375 | I37: =AVERAGE(G37:H37) -> 13.375 | J37: =IF($J$29="BID",G37,IF($J$29="ASK",H37,I37)) -> 13.375 | N37: FirstFixingLag | T37: Tenor | U37: CurveIndex | V37: ResetRate | X37: BloombergTicker | Y37: Field
E38: 8Y | F38: ADBBCF8 IAUS Curncy | G38: =_xll.BDP($F38,G$30) -> 12 | H38: =_xll.BDP($F38,H$30) -> 14 | I38: =AVERAGE(G38:H38) -> 13 | J38: =IF($J$29="BID",G38,IF($J$29="ASK",H38,I38)) -> 13 | N38: PaymentLag | O38: 0D | P38: 0D | T38: 1D | U38: AUDOIS | V38: =_xll.BDP(X38,Y38)% -> 0.015 | X38: RBACOR Index | Y38: PX_LAST
B39: RESULT | E39: 9Y | F39: ADBBCF9 IAUS Curncy | G39: =_xll.BDP($F39,G$30) -> 11.625 | H39: =_xll.BDP($F39,H$30) -> 13.625 | I39: =AVERAGE(G39:H39) -> 12.625 | J39: =IF($J$29="BID",G39,IF($J$29="ASK",H39,I39)) -> 12.625 | N39: CompoundMethod | P39: FLAT | T39: 1M | U39: AUD1ML | V39: =_xll.BDP(X39,Y39)% -> 0.02 | X39: ADBB1M CMPN Curncy | Y39: PX_ASK
B40: ParRate (%) | C40: =_xll.meLWOSwapParRate(O5,B28:C29) -> 0.035908467 | E40: 10Y | F40: ADBBCF10 IAUS Curncy | G40: =_xll.BDP($F40,G$30) -> 11.125 | H40: =_xll.BDP($F40,H$30) -> 13.125 | I40: =AVERAGE(G40:H40) -> 12.125 | J40: =IF($J$29="BID",G40,IF($J$29="ASK",H40,I40)) -> 12.125 | N40: StubType | O40: SHORTSTART | P40: SHORTSTART | T40: 2M | U40: AUD2ML | V40: =_xll.BDP(X40,Y40)% -> 0.0206 | X40: ADBB2M CMPN Curncy | Y40: PX_ASK
E41: 12Y | F41: ADBBCF12 IAUS Curncy | G41: =_xll.BDP($F41,G$30) -> 10 | H41: =_xll.BDP($F41,H$30) -> 13 | I41: =AVERAGE(G41:H41) -> 11.5 | J41: =IF($J$29="BID",G41,IF($J$29="ASK",H41,I41)) -> 11.5 | T41: 3M | U41: AUD3ML | V41: =_xll.BDP(X41,Y41)% -> 0.021153 | X41: ADBB3M CMPN Curncy | Y41: PX_ASK
E42: 15Y | F42: ADBBCF15 IAUS Curncy | G42: =_xll.BDP($F42,G$30) -> 9.5 | H42: =_xll.BDP($F42,H$30) -> 12.5 | I42: =AVERAGE(G42:H42) -> 11 | J42: =IF($J$29="BID",G42,IF($J$29="ASK",H42,I42)) -> 11 | T42: 6M | U42: AUD6ML | V42: =_xll.BDP(X42,Y42)% -> 0.0222 | X42: ADBB6M CMPN Curncy | Y42: PX_ASK
E43: 20Y | F43: ADBBCF20 IAUS Curncy | G43: =_xll.BDP($F43,G$30) -> 9.125 | H43: =_xll.BDP($F43,H$30) -> 12.125 | I43: =AVERAGE(G43:H43) -> 10.625 | J43: =IF($J$29="BID",G43,IF($J$29="ASK",H43,I43)) -> 10.625 | T43: 12M | U43: AUD12ML | V43: =_xll.BDP(X43,Y43)% -> 0.0221 | X43: ADBB12M CMPN Curncy | Y43: PX_ASK
E44: 25Y | F44: ADBBCF25 IAUS Curncy | G44: =_xll.BDP($F44,G$30) -> 9.375 | H44: =_xll.BDP($F44,H$30) -> 12.375 | I44: =AVERAGE(G44:H44) -> 10.875 | J44: =IF($J$29="BID",G44,IF($J$29="ASK",H44,I44)) -> 10.875
E45: 30Y | F45: ADBBCF30 IAUS Curncy | G45: =_xll.BDP($F45,G$30) -> 9.875 | H45: =_xll.BDP($F45,H$30) -> 12.875 | I45: =AVERAGE(G45:H45) -> 11.375 | J45: =IF($J$29="BID",G45,IF($J$29="ASK",H45,I45)) -> 11.375

Sheet TAP AUD ASW
T1: … FIXING INFO
B2: SETTLEMENT DATE | E2: BOND | H2: ASSET SWAP
B3: AsOfDate | C3: =Settings.COB -> 43278 | E3: Handle Name | F3: =F10 -> AU000XCLWAR9 | H3: Handle Name | I3: AUD_ASSET_SWAP
B4: SettlementLag | C4: 2D | E4: Create Bond | F4: =IF('AUD CURVE'!$D$99,_xll.meLWOBondCreateFromLVB(F3,E7:F33),"#LOAD Curve") -> AU000XCLWAR9@11:31 | H4: Create Asset Swap | I4: =IF('AUD CURVE'!$D$99,_xll.meLWOSwapCreate(I3,H7:J41),"#LOAD Curve") -> AUD_ASSET_SWAP@10:21
B5: BusDayAdjustment | C5: MOD_FOLLOWING
B6: Calendar | C6: SYB | E6: BOND SPECIFICATION | H6: ASSET SWAP | I6: BOND LEG | J6: FUNDING LEG
B7: SettlementDate | C7: =_xll.meDateFromTenor(C3,C4,C5,C6) -> 43280 | E7: BondDescription | F7: =C12 -> AU000XCLWAR9 Govt | H7: LegType | I7: Leg1:FixedBond | J7: Leg2:Float
E8: BondType | F8: FIXED | H8: Notional | I8: =F16 -> 1000000 | J8: =F16 -> 1000000
B9: PRICING PARAMETERS | E9: Currency | F9: AUD | H9: NotionalExchange | I9: NONE | J9: =I9 -> NONE
B10: Side: Bid/Ask | C10: MID | E10: ISIN | F10: =LEFT(C12,12) -> AU000XCLWAR9 | H10: PayReceive | I10: PAY | J10: RECEIVE | N10: RESET LOOKUP
B11: Type: Govt/Corp | C11: GOVT | E11: YieldType | F11: YIELD-TO-MATURITY | H11: ForecastCurve | J11: =IF(J23="QUARTERLY","AUD3ML","AUD6ML") -> AUD3ML | N11: =IF(J23="QUARTERLY",R40,R41) -> ADBB3M CMPN Curncy
B12: Bloomberg ID | C12: AU000XCLWAR9 Govt | E12: IsCleanPrice | F12: =$C$15="CLEAN" -> TRUE | H12: DiscountCurve | I12: AUDOIS | J12: AUDOIS | N12: PX_ASK
B13: Bloomberg Yield | C13: =IF($C$14="",_xll.BDP($C$12,"YAS_BOND_YLD"),$C$14) -> 2.623033 | E13: BondQuoteConvention | F13: QUOTE_TO_3_DECIMAL_PLACES | H13: Currency | I13: AUD | J13: AUD | N13: 2D
B14: Yield Override | E14: PayReceive | F14: RECEIVE | H14: Leverage | I14: 1 | J14: 1 | L14: RESET RATE | N14: =_xll.meDateFromTenor(J21,"-"&N13,"MOD_FOLLOWING","LNB:SYB") -> 43278
B15: BondQuoteCleanOrDirty | C15: CLEAN | E15: NotionalExchange | F15: START_AND_END | H15: FixedRate | I15: =F22 -> 0.0225 | L15: =IF(COUNT(N15)=1,N15%,"WAIT: BBG Data Loading") -> 0.021153 | N15: =_xll.BDH(N11,N12,N14,N14) -> 2.1153
B16: BondFrequency | C16: SEMI-ANNUAL | E16: FaceValue | F16: 1000000 | H16: FirstStubCurveIndex | J16: NATURAL
B17: BondDaycount | C17: ACT/ACT | E17: IssueDate | F17: =VALUE(_xll.BDP($C$12,"ISSUE_DT")) -> 42509 | H17: LastStubCurveIndex | J17: NATURAL | L17: FIXING OVERRIDE
B18: FundingAccrualFrequency | C18: QUARTERLY | E18: AccrualStartDate | F18: =VALUE(_xll.BDP($C$12,"START_ACC_DT")) -> 42329 | H18: FirstFixing | J18: =IF(ISBLANK($L$18),"",$L$18)
B19: FundingPaymentFrequency | C19: QUARTERLY | E19: FirstCouponDate | F19: =VALUE(_xll.BDP($C$12,"FIRST_CPN_DT")) -> 42511 | H19: LastFixing
B20: FundingIncludeAccrued | C20: FALSE | E20: LastCouponDate | F20: =VALUE(_xll.BDP($C$12,"PENULTIMATE_CPN_DT")) -> 46712 | H20: FloatSpread | L20: STUB RATE | N20: STUB RATE FLOAT LEG LVB
E21: MaturityDate | F21: =VALUE(_xll.BDP($C$12,"MATURITY")) -> 46894 | H21: EffectiveDate | I21: =F34 -> 43241 | J21: =IF($C$20,$I$21,$C$7) -> 43280 | L21: =IF($O$21<$C$3,"RESET REQUIRED",IF(AND(COUNT($P$37:$P$42)=6,'AUD CURVE'!$D$99),_xll.meProductSwapStubRate($O$37:$O$42,$N$37:$N$42,$P$37:$P$42,$N$21:$O$33),"WAIT: BBG Data Loading")) -> 0.020454545 | N21: EffectiveDate | O21: =$J$21 -> 43280
B22: BOND RESULTS | E22: Coupon | F22: =_xll.BDP($C$12,"CPN")/100 -> 0.0225 | H22: MaturityDate | I22: =F21 -> 46894 | J22: =I22 -> 46894 | N22: MaturityDate | O22: =$J$22 -> 46894
B23: Yield | C23: =IF(ISNUMBER($C$13),$C$13%,"#WAIT Loading BB Data") -> 0.02623033 | E23: Frequency | F23: =$C$16 -> SEMI-ANNUAL | H23: AccrualFrequency | I23: =$C$16 -> SEMI-ANNUAL | J23: =$C$18 -> QUARTERLY | N23: CurveCollection | O23: =$C$41 -> AUDYC
B24: Quote Price | C24: =IF(ISNUMBER($C$13),_xll.meLWOBondPrice($F$4,$C$7,$C$23),"#WAIT Loading BB Data") -> 96.767 | E24: AccrualBusinessDayAdjustment | F24: NO_CHANGE | H24: PaymentFrequency | I24: =$C$16 -> SEMI-ANNUAL | J24: =$C$19 -> QUARTERLY | N24: UseCurveIndex | O24: =$J$16 -> NATURAL
B25: Clean Price | C25: =IF(ISNUMBER($C$13),_xll.meLWOBondCleanPrice($F$4,$C$7,$C$23),"#WAIT Loading BB Data") -> 96.767 | E25: AccrualCalendar | F25: SYB | H25: Daycount | I25: =F29 -> ACT/ACT | J25: ACT/365 | N25: FloatFrequency | O25: =$J$23 -> QUARTERLY
B26: Dirty Price | C26: =IF(ISNUMBER($C$13),_xll.meLWOBondDirtyPrice($F$4,$C$7,$C$23),"#WAIT Loading BB Data") -> 97.005 | E26: PaymentBusinessDayAdjustment | F26: NO_CHANGE | H26: FixingBusinessDayAdjustment | J26: PRECEDING | N26: FloatDaycount | O26: =$J$25 -> ACT/365
B27: AccruedInterestDays | C27: =_xll.meLWOBondAccruedInterestDays($F$4,$C$7) -> 39 | E27: PaymentCalendar | F27: SYB | H27: FixingCalendar | J27: LNB:SYB | N27: FloatBusinessDayAdjustment | O27: =$J$26 -> PRECEDING
B28: AccruedInterest | C28: =_xll.meLWOBondAccruedInterest($F$4,$C$7) -> 2380 | E28: PaymentLag | F28: 0D | H28: AccrualBusinessDayAdjustment | I28: NO_CHANGE | J28: NO_CHANGE | N28: FloatCalendar | O28: =$J$27 -> LNB:SYB
B29: ModifiedDuration | C29: =IF(ISNUMBER($C$13),_xll.meLWOBondModifiedDuration($F$4,$C$7,$C$23),"#WAIT Loading BB Data") -> 8.7687541 | E29: DayCount | F29: =$C$17 -> ACT/ACT | H29: AccrualCalendar | I29: SYB | J29: SYB | N29: FloatRollDay
B30: DV01 | C30: =IF(ISNUMBER($C$13),_xll.meLWOBondDV01($F$4,$C$7,$C$23),"#WAIT Loading BB Data") -> 850.61299 | E30: Rollday | H30: PaymentBusinessDayAdjustment | I30: NO_CHANGE | J30: NO_CHANGE | N30: FloatFixingLag | O30: =$J$35 -> 0D
E31: CalculationType | F31: ="TYPE"&_xll.BDP($C$12,"CALC_TYP") -> TYPE23 | H31: PaymentCalendar | I31: SYB | J31: SYB | N31: FloatFirstStubDate | O31: =IF(ISBLANK($J$33),"",$J$33)
B32: BOND Z-SPREAD | E32: ExdividendTenor | F32: 7D | H32: FirstStubDate | I32: =F35 -> 43425 | N32: FloatLastStubDate | O32: =IF(ISBLANK($J$34),"",$J$34)
B33: BondName | C33: =$F$4 -> AU000XCLWAR9@11:31 | E33: ExdividendBusinessDayAdjustment | F33: NO_CHANGE | H33: LastStubDate | I33: =F20 -> 46712 | N33: FloatStubType | O33: =$J$38 -> SHORTSTART
B34: SettlementDate | C34: =$C$7 -> 43280 | E34: PrevCouponDate | F34: =VALUE(_xll.BDP($C$12,"PREV_CPN_DT")) -> 43241 | H34: RollDay | I34: =IF(F30="","",F30)
B35: BondPrice | C35: =$C$24 -> 96.767 | E35: NextCouponDate | F35: =VALUE(_xll.BDP($C$12,"NXT_CPN_DT")) -> 43425 | H35: FixingLag | J35: 0D | N35: STUB RATE TABLE | R35: STUB TICKERS
B36: CurveCollection | C36: =$C$41 -> AUDYC | H36: FirstFixingLag | N36: Tenor | O36: CurveIndex | P36: ResetRate | R36: BloombergTicker | S36: Field
B37: ForecastCurve | C37: =$J$11 -> AUD3ML | H37: PaymentLag | I37: 0D | J37: 0D | N37: 1D | O37: AUDOIS | P37: =_xll.BDP(R37,S37)% -> 0.015 | R37: RBACOR Index | S37: PX_LAST
B38: Z-Spread | C38: =IF(ISNUMBER($C$13),_xll.meLWOBondZSpread(C33,C34,C35,C36,C37),"#WAIT Loading BB Data") -> -5.779931 | H38: StubType | J38: SHORTSTART | N38: 1M | O38: AUD1ML | P38: =_xll.BDP(R38,S38)% -> 0.02 | R38: ADBB1M CMPN Curncy | S38: PX_ASK
H39: CalculationType | I39: =F31 -> TYPE23 | N39: 2M | O39: AUD2ML | P39: =_xll.BDP(R39,S39)% -> 0.0206 | R39: ADBB2M CMPN Curncy | S39: PX_ASK
B40: ASSET SWAP RESULTS | H40: ExdividendTenor | I40: =F32 -> 7D | N40: 3M | O40: AUD3ML | P40: =_xll.BDP(R40,S40)% -> 0.021153 | R40: ADBB3M CMPN Curncy | S40: PX_ASK
B41: CurveCollection | C41: AUDYC | H41: ExdividendBusinessDayAdjustment | I41: =F33 -> NO_CHANGE | N41: 6M | O41: AUD6ML | P41: =_xll.BDP(R41,S41)% -> 0.0222 | R41: ADBB6M CMPN Curncy | S41: PX_ASK
B42: ValuationDate | C42: =C7 -> 43280 | N42: 12M | O42: AUD12ML | P42: =_xll.BDP(R42,S42)% -> 0.0221 | R42: ADBB12M CMPN Curncy | S42: PX_ASK
B43: Asset Swap Spread (Bps) | C43: =IF($C$44,$C$44,_xll.meLWOAssetSwapSpread($I$4,$F$4,$C$24,$B$41:$C$42)) -> -6.3247527
B44: Override ASW Spread (Bps)
B45: FromAssetSwapToBondCleanPrice | C45: =_xll.meLWOAssetSwapSpreadToCleanPrice(I4,C43,$B$41:$C$42) -> 96.767
B46: BondYield | C46: =_xll.meLWOBondYield($F$4,$C$7,C45,TRUE) -> 0.026230335
