Workbook
Name Settings.AllowCalibrationUpdates: SETTINGS!$C$10
Name Settings.BloombergPCS: SETTINGS!$C$6
Name Settings.COB: SETTINGS!$C$4
Name Settings.CurveSide.MidBidAsk: SETTINGS!$C$7
Name Settings.EnableCurveChart: SETTINGS!$C$9
Name Settings.Futures.Convexity.HW1F.Vol: SETTINGS!$C$8
Name Settings.isCOBToday: SETTINGS!$C$3
Name Settings.SwapCurve.Interpolation: SETTINGS!$C$11

Sheet SETTINGS
U1: … Curve Display
B2: Settings | E2: AUD Curve Chart | N2: Curve Display Settings | Q2: Curve Forward Rates
B3: isCOBToday | C3: =IF(ISBLANK(C5),TRUE,FALSE) -> TRUE | N3: Start | O3: 0Y | Q3: {=IF(AND($C$9,'AUD CURVE'!$D$99),_xll.meLWOCurveForwardRatesTable($N$8,$O$8:$O$10,$O$3,$O$4,,,,$O$5),NA())} -> Fixing Dates | R3: AUDOIS | S3: AUD3ML | T3: AUD6ML
B4: CloseOfBusiness (COB) | C4: =IF(Settings.isCOBToday,TODAY(),$C$5) -> 43420 | N4: Maturity | O4: 20Y | Q4: 43420 | R4: 0.015 | S4: 0.0193 | T4: 0.0211
B5: OverrideDate | N5: Frequency | O5: QUARTERLY | Q5: 43514 | R5: 0.014991402 | S5: 0.019657708 | T5: 0.021297863
B6: PricingSource (PCS) | C6: IAUS | Q6: 43601 | R6: 0.015262621 | S6: 0.020097695 | T6: 0.021765164
B7: CurveSide (Bid-Offer) | C7: PX_MID | N7: CurveCollection | O7: CurveIndices | Q7: 43693 | R7: 0.015595062 | S7: 0.02057507 | T7: 0.022448271
B8: Futures.Convexity.HW1F.Vol (%) | C8: 0.02 | N8: AUDYC | O8: AUDOIS | Q8: 43787 | R8: 0.016418902 | S8: 0.021052197 | T8: 0.023074495
B9: EnableCurveChart | C9: TRUE | O9: AUD3ML | Q9: 43878 | R9: 0.017205574 | S9: 0.021528665 | T9: 0.023520048
B10: AllowCalibrationUpdates | C10: FALSE | O10: AUD6ML | Q10: 43969 | R10: 0.017935832 | S10: 0.022064813 | T10: 0.02392398
B11: SwapCurve.Interpolation | C11: SPLINE | Q11: 44060 | R11: 0.018564484 | S11: 0.022613546 | T11: 0.024414994
Q12: 44151 | R12: 0.019089888 | S12: 0.023207109 | T12: 0.024953311
Q13: 44243 | R13: 0.019607841 | S13: 0.023763348 | T13: 0.025475295
B14: Curve Data Monitor | Q14: 44333 | R14: 0.020039445 | S14: 0.024258928 | T14: 0.025953367
B15: Curve | C15: MissingDataPts | Q15: 44424 | R15: 0.020450783 | S15: 0.024707461 | T15: 0.026411531
B16: AUDOIS | C16: ='AUD CURVE TICKERS'!C4 -> 0 | Q16: 44516 | R16: 0.020840571 | S16: 0.025134804 | T16: 0.026870268
B17: AUD3ML | C17: ='AUD CURVE TICKERS'!F4 -> 0 | Q17: 44608 | R17: 0.021230641 | S17: 0.025556314 | T17: 0.027342381
B18: AUD6ML | C18: ='AUD CURVE TICKERS'!I4 -> 0 | Q18: 44697 | R18: 0.021637086 | S18: 0.025996521 | T18: 0.027799109
Q19: 44789 | R19: 0.02208804 | S19: 0.026477839 | T19: 0.028255959
B20: Fixing.Data | C20: ='AUD CURVE TICKERS'!F5 -> 0 | Q20: 44881 | R20: 0.022571081 | S20: 0.02696377 | T20: 0.028709833
B21: Futures.Data | C21: ='AUD CURVE TICKERS'!F6 -> 0 | Q21: 44973 | R21: 0.023067413 | S21: 0.027456374 | T21: 0.029172752
B22: Futures.Dates | C22: ='AUD CURVE TICKERS'!F7 -> 0 | Q22: 45062 | R22: 0.023537866 | S22: 0.027948809 | T22: 0.029604279
Q23: 45154 | R23: 0.024013946 | S23: 0.028440777 | T23: 0.030005313
Q24: 45246 | R24: 0.024479452 | S24: 0.028886286 | T24: 0.030370082
Q25: 45338 | R25: 0.024852543 | S25: 0.029283025 | T25: 0.030714707
Q26: 45428 | R26: 0.025219487 | S26: 0.029653994 | T26: 0.031034126
Q27: 45520 | R27: 0.025552655 | S27: 0.029969344 | T27: 0.031341253
Q28: 45614 | R28: 0.025825835 | S28: 0.030287836 | T28: 0.031636237
Q29: 45705 | R29: 0.026153314 | S29: 0.030589208 | T29: 0.031905952
Q30: 45793 | R30: 0.026436616 | S30: 0.030880712 | T30: 0.032152163
Q31: 45887 | R31: 0.026761274 | S31: 0.031204067 | T31: 0.032398987
Q32: 45978 | R32: 0.027113881 | S32: 0.031525144 | T32: 0.032622724
Q33: 46069 | R33: 0.027448383 | S33: 0.031791249 | T33: 0.032830187
Q34: 46160 | R34: 0.027708589 | S34: 0.0320122 | T34: 0.033010771
... Q84: 50725 | R84: 0.027429509 | S84: 0.031920567 | T84: 0.033170299
Q85: #N/A | R85: #N/A | S85: #N/A | T85: #N/A
Q86: #N/A | R86: #N/A | S86: #N/A | T86: #N/A
Q87: #N/A | R87: #N/A | S87: #N/A | T87: #N/A
Q88: #N/A | R88: #N/A | S88: #N/A | T88: #N/A
Q89: #N/A | R89: #N/A | S89: #N/A | T89: #N/A
Q90: #N/A | R90: #N/A | S90: #N/A | T90: #N/A
Q91: #N/A | R91: #N/A | S91: #N/A | T91: #N/A
Q92: #N/A | R92: #N/A | S92: #N/A | T92: #N/A
Q93: #N/A | R93: #N/A | S93: #N/A | T93: #N/A
Q94: #N/A | R94: #N/A | S94: #N/A | T94: #N/A
Q95: #N/A | R95: #N/A | S95: #N/A | T95: #N/A
Q96: #N/A | R96: #N/A | S96: #N/A | T96: #N/A
... Q200: #N/A | R200: #N/A | S200: #N/A | T200: #N/A

Sheet AUD CURVE TICKERS
B2: Check for Missing Instrument Data
B4: AUDOIS | C4: =SUM(C5:C8) -> 0 | E4: AUD3ML | F4: =SUM(F5:F9) -> 0 | H4: AUD6ML | I4: =SUM(I5:I7) -> 0
B5: OIS.Outrights | C5: =COUNTA(B15:B37)-COUNT(J15:J37) -> 0 | E5: Swap3M.LiborFixings | F5: =COUNTA(B45:B67)-COUNT(J45:J67) -> 0 | H5: Swap6M.Fixings | I5: =F5 -> 0
B6: OIS.LiborOIS | C6: =COUNTA(L15:L37)-COUNT(T15:T37) -> 0 | E6: Swap3M.Futures | F6: =COUNTA(L45:L67)-COUNT(T45:T67) -> 0 | H6: Swap6M.FRAs | I6: =COUNTA(B75:B77)-COUNT(J75:J77) -> 0
B7: OIS.TenorBasis | C7: =COUNTA(AI45:AI67)-COUNT(AQ45:AQ67) -> 0 | E7: Swap3M.Futures.Dates | F7: =COUNTA(L45:L50)-COUNTA(V45:V50)+COUNTA(L45:L50)-COUNTA(W45:W50) -> 0 | H7: Swap6M.IRS | I7: =COUNTA(L75:L89)-COUNTA(T75:T89) -> 0
B8: OIS.IRS | C8: =COUNTA(Y45:Y67)-COUNT(AG45:AG67) -> 0 | E8: Swap3M.IRS | F8: =COUNTA(Y45:Y67)-COUNT(AG45:AG67) -> 0
E9: Swap3M.TenorBasis | F9: =COUNTA(AI45:AI67)-COUNT(AQ45:AQ67) -> 0
B13: OIS | L13: LIBOROISBASISSPREADS
B14: Term | C14: InstrumentID | D14: Broker | E14: Used | F14: Database | G14: Ticker | H14: Side | I14: Used | J14: Result | L14: Term | M14: InstrumentID | N14: Broker | O14: Used | P14: Database | Q14: Ticker | R14: Side | S14: Used | T14: Result
B15: ON | C15: RBACOR | E15: =IF(ISBLANK(D15),Settings.BloombergPCS,D15) -> IAUS | F15: Index | G15: =C15&" "&E15&" "&F15 -> RBACOR IAUS Index | H15: PX_MID | I15: =IF(ISBLANK(H15),Settings.CurveSide.MidBidAsk,'AUD CURVE TICKERS'!H15) -> PX_MID | J15: =IF(Settings.isCOBToday,_xll.BDP(G15,'AUD CURVE TICKERS'!I15),_xll.BDH(G15,'AUD CURVE TICKERS'!I15,Settings.COB,Settings.COB)) -> 1.5 | L15: 1Y | M15: ADBBCO1 | O15: =IF(ISBLANK(N15),Settings.BloombergPCS,N15) -> IAUS | P15: Curncy | Q15: =M15&" "&O15&" "&P15 -> ADBBCO1 IAUS Curncy | S15: =IF(ISBLANK(R15),Settings.CurveSide.MidBidAsk,'AUD CURVE TICKERS'!R15) -> PX_MID | T15: =IF(Settings.isCOBToday,_xll.BDP(Q15,'AUD CURVE TICKERS'!S15),_xll.BDH(Q15,'AUD CURVE TICKERS'!S15,Settings.COB,Settings.COB)) -> 43.5
B16: 1W | C16: ADSO1Z | E16: =IF(ISBLANK(D16),Settings.BloombergPCS,D16) -> IAUS | F16: Curncy | G16: =C16&" "&E16&" "&F16 -> ADSO1Z IAUS Curncy | I16: =IF(ISBLANK(H16),Settings.CurveSide.MidBidAsk,'AUD CURVE TICKERS'!H16) -> PX_MID | J16: =IF(Settings.isCOBToday,_xll.BDP(G16,'AUD CURVE TICKERS'!I16),_xll.BDH(G16,'AUD CURVE TICKERS'!I16,Settings.COB,Settings.COB)) -> 1.5 | L16: 2Y | M16: ADBBCO2 | O16: =IF(ISBLANK(N16),Settings.BloombergPCS,N16) -> IAUS | P16: Curncy | Q16: =M16&" "&O16&" "&P16 -> ADBBCO2 IAUS Curncy | S16: =IF(ISBLANK(R16),Settings.CurveSide.MidBidAsk,'AUD CURVE TICKERS'!R16) -> PX_MID | T16: =IF(Settings.isCOBToday,_xll.BDP(Q16,'AUD CURVE TICKERS'!S16),_xll.BDH(Q16,'AUD CURVE TICKERS'!S16,Settings.COB,Settings.COB)) -> 42.25
B17: 1M | C17: ADSOA | E17: =IF(ISBLANK(D17),Settings.BloombergPCS,D17) -> IAUS | F17: Curncy | G17: =C17&" "&E17&" "&F17 -> ADSOA IAUS Curncy | I17: =IF(ISBLANK(H17),Settings.CurveSide.MidBidAsk,'AUD CURVE TICKERS'!H17) -> PX_MID | J17: =IF(Settings.isCOBToday,_xll.BDP(G17,'AUD CURVE TICKERS'!I17),_xll.BDH(G17,'AUD CURVE TICKERS'!I17,Settings.COB,Settings.COB)) -> 1.5 | L17: 3Y | M17: ADBBCO3 | O17: =IF(ISBLANK(N17),Settings.BloombergPCS,N17) -> IAUS | P17: Curncy | Q17: =M17&" "&O17&" "&P17 -> ADBBCO3 IAUS Curncy | S17: =IF(ISBLANK(R17),Settings.CurveSide.MidBidAsk,'AUD CURVE TICKERS'!R17) -> PX_MID | T17: =IF(Settings.isCOBToday,_xll.BDP(Q17,'AUD CURVE TICKERS'!S17),_xll.BDH(Q17,'AUD CURVE TICKERS'!S17,Settings.COB,Settings.COB)) -> 41.5
B18: 2M | C18: ADSOB | E18: =IF(ISBLANK(D18),Settings.BloombergPCS,D18) -> IAUS | F18: Curncy | G18: =C18&" "&E18&" "&F18 -> ADSOB IAUS Curncy | I18: =IF(ISBLANK(H18),Settings.CurveSide.MidBidAsk,'AUD CURVE TICKERS'!H18) -> PX_MID | J18: =IF(Settings.isCOBToday,_xll.BDP(G18,'AUD CURVE TICKERS'!I18),_xll.BDH(G18,'AUD CURVE TICKERS'!I18,Settings.COB,Settings.COB)) -> 1.5 | L18: 4Y | M18: ADBBCO4 | O18: =IF(ISBLANK(N18),Settings.BloombergPCS,N18) -> IAUS | P18: Curncy | Q18: =M18&" "&O18&" "&P18 -> ADBBCO4 IAUS Curncy | S18: =IF(ISBLANK(R18),Settings.CurveSide.MidBidAsk,'AUD CURVE TICKERS'!R18) -> PX_MID | T18: =IF(Settings.isCOBToday,_xll.BDP(Q18,'AUD CURVE TICKERS'!S18),_xll.BDH(Q18,'AUD CURVE TICKERS'!S18,Settings.COB,Settings.COB)) -> 41.5
B19: 3M | C19: ADSOC | E19: =IF(ISBLANK(D19),Settings.BloombergPCS,D19) -> IAUS | F19: Curncy | G19: =C19&" "&E19&" "&F19 -> ADSOC IAUS Curncy | I19: =IF(ISBLANK(H19),Settings.CurveSide.MidBidAsk,'AUD CURVE TICKERS'!H19) -> PX_MID | J19: =IF(Settings.isCOBToday,_xll.BDP(G19,'AUD CURVE TICKERS'!I19),_xll.BDH(G19,'AUD CURVE TICKERS'!I19,Settings.COB,Settings.COB)) -> 1.5005 | L19: 5Y | M19: ADBBCO5 | O19: =IF(ISBLANK(N19),Settings.BloombergPCS,N19) -> IAUS | P19: Curncy | Q19: =M19&" "&O19&" "&P19 -> ADBBCO5 IAUS Curncy | S19: =IF(ISBLANK(R19),Settings.CurveSide.MidBidAsk,'AUD CURVE TICKERS'!R19) -> PX_MID | T19: =IF(Settings.isCOBToday,_xll.BDP(Q19,'AUD CURVE TICKERS'!S19),_xll.BDH(Q19,'AUD CURVE TICKERS'!S19,Settings.COB,Settings.COB)) -> 41.5
B20: 4M | C20: ADSOD | E20: =IF(ISBLANK(D20),Settings.BloombergPCS,D20) -> IAUS | F20: Curncy | G20: =C20&" "&E20&" "&F20 -> ADSOD IAUS Curncy | I20: =IF(ISBLANK(H20),Settings.CurveSide.MidBidAsk,'AUD CURVE TICKERS'!H20) -> PX_MID | J20: =IF(Settings.isCOBToday,_xll.BDP(G20,'AUD CURVE TICKERS'!I20),_xll.BDH(G20,'AUD CURVE TICKERS'!I20,Settings.COB,Settings.COB)) -> 1.502 | L20: 6Y | M20: ADBBCO6 | O20: =IF(ISBLANK(N20),Settings.BloombergPCS,N20) -> IAUS | P20: Curncy | Q20: =M20&" "&O20&" "&P20 -> ADBBCO6 IAUS Curncy | S20: =IF(ISBLANK(R20),Settings.CurveSide.MidBidAsk,'AUD CURVE TICKERS'!R20) -> PX_MID | T20: =IF(Settings.isCOBToday,_xll.BDP(Q20,'AUD CURVE TICKERS'!S20),_xll.BDH(Q20,'AUD CURVE TICKERS'!S20,Settings.COB,Settings.COB)) -> 41.625
B21: 5M | C21: ADSOE | E21: =IF(ISBLANK(D21),Settings.BloombergPCS,D21) -> IAUS | F21: Curncy | G21: =C21&" "&E21&" "&F21 -> ADSOE IAUS Curncy | I21: =IF(ISBLANK(H21),Settings.CurveSide.MidBidAsk,'AUD CURVE TICKERS'!H21) -> PX_MID | J21: =IF(Settings.isCOBToday,_xll.BDP(G21,'AUD CURVE TICKERS'!I21),_xll.BDH(G21,'AUD CURVE TICKERS'!I21,Settings.COB,Settings.COB)) -> 1.50375 | L21: 7Y | M21: ADBBCO7 | O21: =IF(ISBLANK(N21),Settings.BloombergPCS,N21) -> IAUS | P21: Curncy | Q21: =M21&" "&O21&" "&P21 -> ADBBCO7 IAUS Curncy | S21: =IF(ISBLANK(R21),Settings.CurveSide.MidBidAsk,'AUD CURVE TICKERS'!R21) -> PX_MID | T21: =IF(Settings.isCOBToday,_xll.BDP(Q21,'AUD CURVE TICKERS'!S21),_xll.BDH(Q21,'AUD CURVE TICKERS'!S21,Settings.COB,Settings.COB)) -> 41.75
B22: 6M | C22: ADSOF | E22: =IF(ISBLANK(D22),Settings.BloombergPCS,D22) -> IAUS | F22: Curncy | G22: =C22&" "&E22&" "&F22 -> ADSOF IAUS Curncy | I22: =IF(ISBLANK(H22),Settings.CurveSide.MidBidAsk,'AUD CURVE TICKERS'!H22) -> PX_MID | J22: =IF(Settings.isCOBToday,_xll.BDP(G22,'AUD CURVE TICKERS'!I22),_xll.BDH(G22,'AUD CURVE TICKERS'!I22,Settings.COB,Settings.COB)) -> 1.508 | L22: 8Y | M22: ADBBCO8 | O22: =IF(ISBLANK(N22),Settings.BloombergPCS,N22) -> IAUS | P22: Curncy | Q22: =M22&" "&O22&" "&P22 -> ADBBCO8 IAUS Curncy | S22: =IF(ISBLANK(R22),Settings.CurveSide.MidBidAsk,'AUD CURVE TICKERS'!R22) -> PX_MID | T22: =IF(Settings.isCOBToday,_xll.BDP(Q22,'AUD CURVE TICKERS'!S22),_xll.BDH(Q22,'AUD CURVE TICKERS'!S22,Settings.COB,Settings.COB)) -> 41.75
B23: 9M | C23: ADSOI | E23: =IF(ISBLANK(D23),Settings.BloombergPCS,D23) -> IAUS | F23: Curncy | G23: =C23&" "&E23&" "&F23 -> ADSOI IAUS Curncy | I23: =IF(ISBLANK(H23),Settings.CurveSide.MidBidAsk,'AUD CURVE TICKERS'!H23) -> PX_MID | J23: =IF(Settings.isCOBToday,_xll.BDP(G23,'AUD CURVE TICKERS'!I23),_xll.BDH(G23,'AUD CURVE TICKERS'!I23,Settings.COB,Settings.COB)) -> 1.5225 | L23: 9Y | M23: ADBBCO9 | O23: =IF(ISBLANK(N23),Settings.BloombergPCS,N23) -> IAUS | P23: Curncy | Q23: =M23&" "&O23&" "&P23 -> ADBBCO9 IAUS Curncy | S23: =IF(ISBLANK(R23),Settings.CurveSide.MidBidAsk,'AUD CURVE TICKERS'!R23) -> PX_MID | T23: =IF(Settings.isCOBToday,_xll.BDP(Q23,'AUD CURVE TICKERS'!S23),_xll.BDH(Q23,'AUD CURVE TICKERS'!S23,Settings.COB,Settings.COB)) -> 41.75
B24: 1Y | C24: ADSO1 | E24: =IF(ISBLANK(D24),Settings.BloombergPCS,D24) -> IAUS | F24: Curncy | G24: =C24&" "&E24&" "&F24 -> ADSO1 IAUS Curncy | I24: =IF(ISBLANK(H24),Settings.CurveSide.MidBidAsk,'AUD CURVE TICKERS'!H24) -> PX_MID | J24: =IF(Settings.isCOBToday,_xll.BDP(G24,'AUD CURVE TICKERS'!I24),_xll.BDH(G24,'AUD CURVE TICKERS'!I24,Settings.COB,Settings.COB)) -> 1.5475 | L24: 10Y | M24: ADBBCO10 | O24: =IF(ISBLANK(N24),Settings.BloombergPCS,N24) -> IAUS | P24: Curncy | Q24: =M24&" "&O24&" "&P24 -> ADBBCO10 IAUS Curncy | S24: =IF(ISBLANK(R24),Settings.CurveSide.MidBidAsk,'AUD CURVE TICKERS'!R24) -> PX_MID | T24: =IF(Settings.isCOBToday,_xll.BDP(Q24,'AUD CURVE TICKERS'!S24),_xll.BDH(Q24,'AUD CURVE TICKERS'!S24,Settings.COB,Settings.COB)) -> 41.625
B25: 2Y | C25: ADSO2 | E25: =IF(ISBLANK(D25),Settings.BloombergPCS,D25) -> IAUS | F25: Curncy | G25: =C25&" "&E25&" "&F25 -> ADSO2 IAUS Curncy | I25: =IF(ISBLANK(H25),Settings.CurveSide.MidBidAsk,'AUD CURVE TICKERS'!H25) -> PX_MID | J25: =IF(Settings.isCOBToday,_xll.BDP(G25,'AUD CURVE TICKERS'!I25),_xll.BDH(G25,'AUD CURVE TICKERS'!I25,Settings.COB,Settings.COB)) -> 1.675 | L25: 15Y | M25: ADBBCO15 | O25: =IF(ISBLANK(N25),Settings.BloombergPCS,N25) -> IAUS | P25: Curncy | Q25: =M25&" "&O25&" "&P25 -> ADBBCO15 IAUS Curncy | S25: =IF(ISBLANK(R25),Settings.CurveSide.MidBidAsk,'AUD CURVE TICKERS'!R25) -> PX_MID | T25: =IF(Settings.isCOBToday,_xll.BDP(Q25,'AUD CURVE TICKERS'!S25),_xll.BDH(Q25,'AUD CURVE TICKERS'!S25,Settings.COB,Settings.COB)) -> 42
B26: 3Y | C26: ADSO3 | E26: =IF(ISBLANK(D26),Settings.BloombergPCS,D26) -> IAUS | F26: Curncy | G26: =C26&" "&E26&" "&F26 -> ADSO3 IAUS Curncy | I26: =IF(ISBLANK(H26),Settings.CurveSide.MidBidAsk,'AUD CURVE TICKERS'!H26) -> PX_MID | J26: =IF(Settings.isCOBToday,_xll.BDP(G26,'AUD CURVE TICKERS'!I26),_xll.BDH(G26,'AUD CURVE TICKERS'!I26,Settings.COB,Settings.COB)) -> 1.785 | L26: 20Y | M26: ADBBCO20 | O26: =IF(ISBLANK(N26),Settings.BloombergPCS,N26) -> IAUS | P26: Curncy | Q26: =M26&" "&O26&" "&P26 -> ADBBCO20 IAUS Curncy | S26: =IF(ISBLANK(R26),Settings.CurveSide.MidBidAsk,'AUD CURVE TICKERS'!R26) -> PX_MID | T26: =IF(Settings.isCOBToday,_xll.BDP(Q26,'AUD CURVE TICKERS'!S26),_xll.BDH(Q26,'AUD CURVE TICKERS'!S26,Settings.COB,Settings.COB)) -> 42.25
B27: 4Y | C27: ADSO4 | E27: =IF(ISBLANK(D27),Settings.BloombergPCS,D27) -> IAUS | F27: Curncy | G27: =C27&" "&E27&" "&F27 -> ADSO4 IAUS Curncy | I27: =IF(ISBLANK(H27),Settings.CurveSide.MidBidAsk,'AUD CURVE TICKERS'!H27) -> PX_MID | J27: =IF(Settings.isCOBToday,_xll.BDP(G27,'AUD CURVE TICKERS'!I27),_xll.BDH(G27,'AUD CURVE TICKERS'!I27,Settings.COB,Settings.COB)) -> 1.883 | L27: 25Y | M27: ADBBCO25 | O27: =IF(ISBLANK(N27),Settings.BloombergPCS,N27) -> IAUS | P27: Curncy | Q27: =M27&" "&O27&" "&P27 -> ADBBCO25 IAUS Curncy | S27: =IF(ISBLANK(R27),Settings.CurveSide.MidBidAsk,'AUD CURVE TICKERS'!R27) -> PX_MID | T27: =IF(Settings.isCOBToday,_xll.BDP(Q27,'AUD CURVE TICKERS'!S27),_xll.BDH(Q27,'AUD CURVE TICKERS'!S27,Settings.COB,Settings.COB)) -> 42.625
B28: 5Y | C28: ADSO5 | E28: =IF(ISBLANK(D28),Settings.BloombergPCS,D28) -> IAUS | F28: Curncy | G28: =C28&" "&E28&" "&F28 -> ADSO5 IAUS Curncy | I28: =IF(ISBLANK(H28),Settings.CurveSide.MidBidAsk,'AUD CURVE TICKERS'!H28) -> PX_MID | J28: =IF(Settings.isCOBToday,_xll.BDP(G28,'AUD CURVE TICKERS'!I28),_xll.BDH(G28,'AUD CURVE TICKERS'!I28,Settings.COB,Settings.COB)) -> 1.978 | L28: 30Y | M28: ADBBCO30 | O28: =IF(ISBLANK(N28),Settings.BloombergPCS,N28) -> IAUS | P28: Curncy | Q28: =M28&" "&O28&" "&P28 -> ADBBCO30 IAUS Curncy | S28: =IF(ISBLANK(R28),Settings.CurveSide.MidBidAsk,'AUD CURVE TICKERS'!R28) -> PX_MID | T28: =IF(Settings.isCOBToday,_xll.BDP(Q28,'AUD CURVE TICKERS'!S28),_xll.BDH(Q28,'AUD CURVE TICKERS'!S28,Settings.COB,Settings.COB)) -> 43
B29: 6Y | C29: ADSO6 | E29: =IF(ISBLANK(D29),Settings.BloombergPCS,D29) -> IAUS | F29: Curncy | G29: =C29&" "&E29&" "&F29 -> ADSO6 IAUS Curncy | I29: =IF(ISBLANK(H29),Settings.CurveSide.MidBidAsk,'AUD CURVE TICKERS'!H29) -> PX_MID | J29: =IF(Settings.isCOBToday,_xll.BDP(G29,'AUD CURVE TICKERS'!I29),_xll.BDH(G29,'AUD CURVE TICKERS'!I29,Settings.COB,Settings.COB)) -> 2.063
B30: 7Y | C30: ADSO7 | E30: =IF(ISBLANK(D30),Settings.BloombergPCS,D30) -> IAUS | F30: Curncy | G30: =C30&" "&E30&" "&F30 -> ADSO7 IAUS Curncy | I30: =IF(ISBLANK(H30),Settings.CurveSide.MidBidAsk,'AUD CURVE TICKERS'!H30) -> PX_MID | J30: =IF(Settings.isCOBToday,_xll.BDP(G30,'AUD CURVE TICKERS'!I30),_xll.BDH(G30,'AUD CURVE TICKERS'!I30,Settings.COB,Settings.COB)) -> 2.148
B31: 8Y | C31: ADSO8 | E31: =IF(ISBLANK(D31),Settings.BloombergPCS,D31) -> IAUS | F31: Curncy | G31: =C31&" "&E31&" "&F31 -> ADSO8 IAUS Curncy | I31: =IF(ISBLANK(H31),Settings.CurveSide.MidBidAsk,'AUD CURVE TICKERS'!H31) -> PX_MID | J31: =IF(Settings.isCOBToday,_xll.BDP(G31,'AUD CURVE TICKERS'!I31),_xll.BDH(G31,'AUD CURVE TICKERS'!I31,Settings.COB,Settings.COB)) -> 2.215
B32: 9Y | C32: ADSO9 | E32: =IF(ISBLANK(D32),Settings.BloombergPCS,D32) -> IAUS | F32: Curncy | G32: =C32&" "&E32&" "&F32 -> ADSO9 IAUS Curncy | I32: =IF(ISBLANK(H32),Settings.CurveSide.MidBidAsk,'AUD CURVE TICKERS'!H32) -> PX_MID | J32: =IF(Settings.isCOBToday,_xll.BDP(G32,'AUD CURVE TICKERS'!I32),_xll.BDH(G32,'AUD CURVE TICKERS'!I32,Settings.COB,Settings.COB)) -> 2.28
B33: 10Y | C33: ADSO10 | E33: =IF(ISBLANK(D33),Settings.BloombergPCS,D33) -> IAUS | F33: Curncy | G33: =C33&" "&E33&" "&F33 -> ADSO10 IAUS Curncy | I33: =IF(ISBLANK(H33),Settings.CurveSide.MidBidAsk,'AUD CURVE TICKERS'!H33) -> PX_MID | J33: =IF(Settings.isCOBToday,_xll.BDP(G33,'AUD CURVE TICKERS'!I33),_xll.BDH(G33,'AUD CURVE TICKERS'!I33,Settings.COB,Settings.COB)) -> 2.348
B34: 15Y | C34: ADSO15 | E34: =IF(ISBLANK(D34),Settings.BloombergPCS,D34) -> IAUS | F34: Curncy | G34: =C34&" "&E34&" "&F34 -> ADSO15 IAUS Curncy | I34: =IF(ISBLANK(H34),Settings.CurveSide.MidBidAsk,'AUD CURVE TICKERS'!H34) -> PX_MID | J34: =IF(Settings.isCOBToday,_xll.BDP(G34,'AUD CURVE TICKERS'!I34),_xll.BDH(G34,'AUD CURVE TICKERS'!I34,Settings.COB,Settings.COB)) -> 2.548
B35: 20Y | C35: ADSO20 | E35: =IF(ISBLANK(D35),Settings.BloombergPCS,D35) -> IAUS | F35: Curncy | G35: =C35&" "&E35&" "&F35 -> ADSO20 IAUS Curncy | I35: =IF(ISBLANK(H35),Settings.CurveSide.MidBidAsk,'AUD CURVE TICKERS'!H35) -> PX_MID | J35: =IF(Settings.isCOBToday,_xll.BDP(G35,'AUD CURVE TICKERS'!I35),_xll.BDH(G35,'AUD CURVE TICKERS'!I35,Settings.COB,Settings.COB)) -> 2.615
B36: 25Y | C36: ADSO25 | E36: =IF(ISBLANK(D36),Settings.BloombergPCS,D36) -> IAUS | F36: Curncy | G36: =C36&" "&E36&" "&F36 -> ADSO25 IAUS Curncy | I36: =IF(ISBLANK(H36),Settings.CurveSide.MidBidAsk,'AUD CURVE TICKERS'!H36) -> PX_MID | J36: =IF(Settings.isCOBToday,_xll.BDP(G36,'AUD CURVE TICKERS'!I36),_xll.BDH(G36,'AUD CURVE TICKERS'!I36,Settings.COB,Settings.COB)) -> 2.62
B37: 30Y | C37: ADSO30 | E37: =IF(ISBLANK(D37),Settings.BloombergPCS,D37) -> IAUS | F37: Curncy | G37: =C37&" "&E37&" "&F37 -> ADSO30 IAUS Curncy | I37: =IF(ISBLANK(H37),Settings.CurveSide.MidBidAsk,'AUD CURVE TICKERS'!H37) -> PX_MID | J37: =IF(Settings.isCOBToday,_xll.BDP(G37,'AUD CURVE TICKERS'!I37),_xll.BDH(G37,'AUD CURVE TICKERS'!I37,Settings.COB,Settings.COB)) -> 2.583
A40: << AUDOIS
B43: LIBORFIXINGS | L43: FUTURES | V43: FUTURES.DATES | Y43: SWAPS | AI43: BASISSWAPS
B44: Term | C44: InstrumentID | D44: Broker | E44: Used | F44: Database | G44: Ticker | H44: Side | I44: Used | J44: Result | L44: Term | M44: InstrumentID | N44: Broker | O44: Used | P44: Database | Q44: Ticker | R44: Side | S44: Used | T44: Result | V44: StartDate | W44: EndDate | Y44: Term | Z44: InstrumentID | AA44: Broker | AB44: Used | AC44: Database | AD44: Ticker | AE44: Side | AF44: Used | AG44: Result | AI44: Term | AJ44: InstrumentID | AK44: Broker | AL44: Used | AM44: Database | AN44: Ticker | AO44: Side | AP44: Used | AQ44: Result
B45: 1M | C45: ADBB1M | E45: =IF(ISBLANK(D45),Settings.BloombergPCS,D45) | F45: Curncy | G45: =C45&" "&E45&" "&F45 -> ADBB1M Curncy | H45: PX_ASK | I45: =IF(ISBLANK(H45),Settings.CurveSide.MidBidAsk,'AUD CURVE TICKERS'!H45) -> PX_ASK | J45: =IF(Settings.isCOBToday,_xll.BDP(G45,'AUD CURVE TICKERS'!I45),_xll.BDH(G45,'AUD CURVE TICKERS'!I45,Settings.COB,Settings.COB)) -> 1.86 | L45: IR1 | M45: IR1 | O45: =IF(ISBLANK(N45),Settings.BloombergPCS,N45) | P45: Comdty | Q45: =M45&" "&O45&" "&P45 -> IR1 Comdty | S45: =IF(ISBLANK(R45),Settings.CurveSide.MidBidAsk,'AUD CURVE TICKERS'!R45) -> PX_MID | T45: =IF(Settings.isCOBToday,_xll.BDP(Q45,'AUD CURVE TICKERS'!S45),_xll.BDH(Q45,'AUD CURVE TICKERS'!S45,Settings.COB,Settings.COB)) -> 98.025 | V45: =IF(Settings.isCOBToday,_xll.BDP(Q45,$V$52),_xll.BDH(Q45,$V$52,Settings.COB,Settings.COB)) -> 14/12/2018 | W45: =IF(Settings.isCOBToday,_xll.BDP(Q45,$V$53),_xll.BDH(Q45,$V$53,Settings.COB,Settings.COB)) -> 08/03/2019 | Y45: 1Y | Z45: ADSW1Q | AB45: =IF(ISBLANK(AA45),Settings.BloombergPCS,AA45) -> IAUS | AC45: Curncy | AD45: =Z45&" "&AB45&" "&AC45 -> ADSW1Q IAUS Curncy | AF45: =IF(ISBLANK(AE45),Settings.CurveSide.MidBidAsk,'AUD CURVE TICKERS'!AE45) -> PX_MID | AG45: =IF(Settings.isCOBToday,_xll.BDP(AD45,'AUD CURVE TICKERS'!AF45),_xll.BDH(AD45,'AUD CURVE TICKERS'!AF45,Settings.COB,Settings.COB)) -> 1.9775 | AI45: 1Y | AJ45: ADBBCF1 | AL45: =IF(ISBLANK(AK45),Settings.BloombergPCS,AK45) -> IAUS | AM45: Curncy | AN45: =AJ45&" "&AL45&" "&AM45 -> ADBBCF1 IAUS Curncy | AP45: =IF(ISBLANK(AO45),Settings.CurveSide.MidBidAsk,'AUD CURVE TICKERS'!AO45) -> PX_MID | AQ45: =IF(Settings.isCOBToday,_xll.BDP(AN45,'AUD CURVE TICKERS'!AP45),_xll.BDH(AN45,'AUD CURVE TICKERS'!AP45,Settings.COB,Settings.COB)) -> 16.125
B46: 3M | C46: ADBB3M | E46: =IF(ISBLANK(D46),Settings.BloombergPCS,D46) | F46: Curncy | G46: =C46&" "&E46&" "&F46 -> ADBB3M Curncy | H46: PX_ASK | I46: =IF(ISBLANK(H46),Settings.CurveSide.MidBidAsk,'AUD CURVE TICKERS'!H46) -> PX_ASK | J46: =IF(Settings.isCOBToday,_xll.BDP(G46,'AUD CURVE TICKERS'!I46),_xll.BDH(G46,'AUD CURVE TICKERS'!I46,Settings.COB,Settings.COB)) -> 1.93 | L46: IR2 | M46: IR2 | O46: =IF(ISBLANK(N46),Settings.BloombergPCS,N46) | P46: Comdty | Q46: =M46&" "&O46&" "&P46 -> IR2 Comdty | S46: =IF(ISBLANK(R46),Settings.CurveSide.MidBidAsk,'AUD CURVE TICKERS'!R46) -> PX_MID | T46: =IF(Settings.isCOBToday,_xll.BDP(Q46,'AUD CURVE TICKERS'!S46),_xll.BDH(Q46,'AUD CURVE TICKERS'!S46,Settings.COB,Settings.COB)) -> 98.045 | V46: =IF(Settings.isCOBToday,_xll.BDP(Q46,$V$52),_xll.BDH(Q46,$V$52,Settings.COB,Settings.COB)) -> 08/03/2019 | W46: =IF(Settings.isCOBToday,_xll.BDP(Q46,$V$53),_xll.BDH(Q46,$V$53,Settings.COB,Settings.COB)) -> 14/06/2019 | Y46: 2Y | Z46: ADSW2Q | AB46: =IF(ISBLANK(AA46),Settings.BloombergPCS,AA46) -> IAUS | AC46: Curncy | AD46: =Z46&" "&AB46&" "&AC46 -> ADSW2Q IAUS Curncy | AF46: =IF(ISBLANK(AE46),Settings.CurveSide.MidBidAsk,'AUD CURVE TICKERS'!AE46) -> PX_MID | AG46: =IF(Settings.isCOBToday,_xll.BDP(AD46,'AUD CURVE TICKERS'!AF46),_xll.BDH(AD46,'AUD CURVE TICKERS'!AF46,Settings.COB,Settings.COB)) -> 2.08625 | AI46: 2Y | AJ46: ADBBCF2 | AL46: =IF(ISBLANK(AK46),Settings.BloombergPCS,AK46) -> IAUS | AM46: Curncy | AN46: =AJ46&" "&AL46&" "&AM46 -> ADBBCF2 IAUS Curncy | AP46: =IF(ISBLANK(AO46),Settings.CurveSide.MidBidAsk,'AUD CURVE TICKERS'!AO46) -> PX_MID | AQ46: =IF(Settings.isCOBToday,_xll.BDP(AN46,'AUD CURVE TICKERS'!AP46),_xll.BDH(AN46,'AUD CURVE TICKERS'!AP46,Settings.COB,Settings.COB)) -> 15.625
B47: 6M | C47: ADBB6M | E47: =IF(ISBLANK(D47),Settings.BloombergPCS,D47) | F47: Curncy | G47: =C47&" "&E47&" "&F47 -> ADBB6M Curncy | H47: PX_ASK | I47: =IF(ISBLANK(H47),Settings.CurveSide.MidBidAsk,'AUD CURVE TICKERS'!H47) -> PX_ASK | J47: =IF(Settings.isCOBToday,_xll.BDP(G47,'AUD CURVE TICKERS'!I47),_xll.BDH(G47,'AUD CURVE TICKERS'!I47,Settings.COB,Settings.COB)) -> 2.11 | L47: IR3 | M47: IR3 | O47: =IF(ISBLANK(N47),Settings.BloombergPCS,N47) | P47: Comdty | Q47: =M47&" "&O47&" "&P47 -> IR3 Comdty | S47: =IF(ISBLANK(R47),Settings.CurveSide.MidBidAsk,'AUD CURVE TICKERS'!R47) -> PX_MID | T47: =IF(Settings.isCOBToday,_xll.BDP(Q47,'AUD CURVE TICKERS'!S47),_xll.BDH(Q47,'AUD CURVE TICKERS'!S47,Settings.COB,Settings.COB)) -> 98.005 | V47: =IF(Settings.isCOBToday,_xll.BDP(Q47,$V$52),_xll.BDH(Q47,$V$52,Settings.COB,Settings.COB)) -> 14/06/2019 | W47: =IF(Settings.isCOBToday,_xll.BDP(Q47,$V$53),_xll.BDH(Q47,$V$53,Settings.COB,Settings.COB)) -> 13/09/2019 | Y47: 3Y | Z47: ADSW3Q | AB47: =IF(ISBLANK(AA47),Settings.BloombergPCS,AA47) -> IAUS | AC47: Curncy | AD47: =Z47&" "&AB47&" "&AC47 -> ADSW3Q IAUS Curncy | AF47: =IF(ISBLANK(AE47),Settings.CurveSide.MidBidAsk,'AUD CURVE TICKERS'!AE47) -> PX_MID | AG47: =IF(Settings.isCOBToday,_xll.BDP(AD47,'AUD CURVE TICKERS'!AF47),_xll.BDH(AD47,'AUD CURVE TICKERS'!AF47,Settings.COB,Settings.COB)) -> 2.18875 | AI47: 3Y | AJ47: ADBBCF3 | AL47: =IF(ISBLANK(AK47),Settings.BloombergPCS,AK47) -> IAUS | AM47: Curncy | AN47: =AJ47&" "&AL47&" "&AM47 -> ADBBCF3 IAUS Curncy | AP47: =IF(ISBLANK(AO47),Settings.CurveSide.MidBidAsk,'AUD CURVE TICKERS'!AO47) -> PX_MID | AQ47: =IF(Settings.isCOBToday,_xll.BDP(AN47,'AUD CURVE TICKERS'!AP47),_xll.BDH(AN47,'AUD CURVE TICKERS'!AP47,Settings.COB,Settings.COB)) -> 15.125
L48: IR4 | M48: IR4 | O48: =IF(ISBLANK(N48),Settings.BloombergPCS,N48) | P48: Comdty | Q48: =M48&" "&O48&" "&P48 -> IR4 Comdty | S48: =IF(ISBLANK(R48),Settings.CurveSide.MidBidAsk,'AUD CURVE TICKERS'!R48) -> PX_MID | T48: =IF(Settings.isCOBToday,_xll.BDP(Q48,'AUD CURVE TICKERS'!S48),_xll.BDH(Q48,'AUD CURVE TICKERS'!S48,Settings.COB,Settings.COB)) -> 97.935 | V48: =IF(Settings.isCOBToday,_xll.BDP(Q48,$V$52),_xll.BDH(Q48,$V$52,Settings.COB,Settings.COB)) -> 13/09/2019 | W48: =IF(Settings.isCOBToday,_xll.BDP(Q48,$V$53),_xll.BDH(Q48,$V$53,Settings.COB,Settings.COB)) -> 13/12/2019 | Y48: 4Y | Z48: ADSW4 | AB48: =IF(ISBLANK(AA48),Settings.BloombergPCS,AA48) -> IAUS | AC48: Curncy | AD48: =Z48&" "&AB48&" "&AC48 -> ADSW4 IAUS Curncy | AF48: =IF(ISBLANK(AE48),Settings.CurveSide.MidBidAsk,'AUD CURVE TICKERS'!AE48) -> PX_MID | AG48: =IF(Settings.isCOBToday,_xll.BDP(AD48,'AUD CURVE TICKERS'!AF48),_xll.BDH(AD48,'AUD CURVE TICKERS'!AF48,Settings.COB,Settings.COB)) -> 2.44 | AI48: 4Y | AJ48: ADBBCF4 | AL48: =IF(ISBLANK(AK48),Settings.BloombergPCS,AK48) -> IAUS | AM48: Curncy | AN48: =AJ48&" "&AL48&" "&AM48 -> ADBBCF4 IAUS Curncy | AP48: =IF(ISBLANK(AO48),Settings.CurveSide.MidBidAsk,'AUD CURVE TICKERS'!AO48) -> PX_MID | AQ48: =IF(Settings.isCOBToday,_xll.BDP(AN48,'AUD CURVE TICKERS'!AP48),_xll.BDH(AN48,'AUD CURVE TICKERS'!AP48,Settings.COB,Settings.COB)) -> 15
L49: IR5 | M49: IR5 | O49: =IF(ISBLANK(N49),Settings.BloombergPCS,N49) | P49: Comdty | Q49: =M49&" "&O49&" "&P49 -> IR5 Comdty | S49: =IF(ISBLANK(R49),Settings.CurveSide.MidBidAsk,'AUD CURVE TICKERS'!R49) -> PX_MID | T49: =IF(Settings.isCOBToday,_xll.BDP(Q49,'AUD CURVE TICKERS'!S49),_xll.BDH(Q49,'AUD CURVE TICKERS'!S49,Settings.COB,Settings.COB)) -> 97.875 | V49: =IF(Settings.isCOBToday,_xll.BDP(Q49,$V$52),_xll.BDH(Q49,$V$52,Settings.COB,Settings.COB)) -> 13/12/2019 | W49: =IF(Settings.isCOBToday,_xll.BDP(Q49,$V$53),_xll.BDH(Q49,$V$53,Settings.COB,Settings.COB)) -> 13/03/2020 | Y49: 5Y | Z49: ADSW5 | AB49: =IF(ISBLANK(AA49),Settings.BloombergPCS,AA49) -> IAUS | AC49: Curncy | AD49: =Z49&" "&AB49&" "&AC49 -> ADSW5 IAUS Curncy | AF49: =IF(ISBLANK(AE49),Settings.CurveSide.MidBidAsk,'AUD CURVE TICKERS'!AE49) -> PX_MID | AG49: =IF(Settings.isCOBToday,_xll.BDP(AD49,'AUD CURVE TICKERS'!AF49),_xll.BDH(AD49,'AUD CURVE TICKERS'!AF49,Settings.COB,Settings.COB)) -> 2.53125 | AI49: 5Y | AJ49: ADBBCF5 | AL49: =IF(ISBLANK(AK49),Settings.BloombergPCS,AK49) -> IAUS | AM49: Curncy | AN49: =AJ49&" "&AL49&" "&AM49 -> ADBBCF5 IAUS Curncy | AP49: =IF(ISBLANK(AO49),Settings.CurveSide.MidBidAsk,'AUD CURVE TICKERS'!AO49) -> PX_MID | AQ49: =IF(Settings.isCOBToday,_xll.BDP(AN49,'AUD CURVE TICKERS'!AP49),_xll.BDH(AN49,'AUD CURVE TICKERS'!AP49,Settings.COB,Settings.COB)) -> 14.75
L50: IR6 | M50: IR6 | O50: =IF(ISBLANK(N50),Settings.BloombergPCS,N50) | P50: Comdty | Q50: =M50&" "&O50&" "&P50 -> IR6 Comdty | S50: =IF(ISBLANK(R50),Settings.CurveSide.MidBidAsk,'AUD CURVE TICKERS'!R50) -> PX_MID | T50: =IF(Settings.isCOBToday,_xll.BDP(Q50,'AUD CURVE TICKERS'!S50),_xll.BDH(Q50,'AUD CURVE TICKERS'!S50,Settings.COB,Settings.COB)) -> 97.815 | V50: =IF(Settings.isCOBToday,_xll.BDP(Q50,$V$52),_xll.BDH(Q50,$V$52,Settings.COB,Settings.COB)) -> 13/03/2020 | W50: =IF(Settings.isCOBToday,_xll.BDP(Q50,$V$53),_xll.BDH(Q50,$V$53,Settings.COB,Settings.COB)) -> 12/06/2020 | Y50: 6Y | Z50: ADSW6 | AB50: =IF(ISBLANK(AA50),Settings.BloombergPCS,AA50) -> IAUS | AC50: Curncy | AD50: =Z50&" "&AB50&" "&AC50 -> ADSW6 IAUS Curncy | AF50: =IF(ISBLANK(AE50),Settings.CurveSide.MidBidAsk,'AUD CURVE TICKERS'!AE50) -> PX_MID | AG50: =IF(Settings.isCOBToday,_xll.BDP(AD50,'AUD CURVE TICKERS'!AF50),_xll.BDH(AD50,'AUD CURVE TICKERS'!AF50,Settings.COB,Settings.COB)) -> 2.61625 | AI50: 6Y | AJ50: ADBBCF6 | AL50: =IF(ISBLANK(AK50),Settings.BloombergPCS,AK50) -> IAUS | AM50: Curncy | AN50: =AJ50&" "&AL50&" "&AM50 -> ADBBCF6 IAUS Curncy | AP50: =IF(ISBLANK(AO50),Settings.CurveSide.MidBidAsk,'AUD CURVE TICKERS'!AO50) -> PX_MID | AQ50: =IF(Settings.isCOBToday,_xll.BDP(AN50,'AUD CURVE TICKERS'!AP50),_xll.BDH(AN50,'AUD CURVE TICKERS'!AP50,Settings.COB,Settings.COB)) -> 14.25
Y51: 7Y | Z51: ADSW7 | AB51: =IF(ISBLANK(AA51),Settings.BloombergPCS,AA51) -> IAUS | AC51: Curncy | AD51: =Z51&" "&AB51&" "&AC51 -> ADSW7 IAUS Curncy | AF51: =IF(ISBLANK(AE51),Settings.CurveSide.MidBidAsk,'AUD CURVE TICKERS'!AE51) -> PX_MID | AG51: =IF(Settings.isCOBToday,_xll.BDP(AD51,'AUD CURVE TICKERS'!AF51),_xll.BDH(AD51,'AUD CURVE TICKERS'!AF51,Settings.COB,Settings.COB)) -> 2.6925 | AI51: 7Y | AJ51: ADBBCF7 | AL51: =IF(ISBLANK(AK51),Settings.BloombergPCS,AK51) -> IAUS | AM51: Curncy | AN51: =AJ51&" "&AL51&" "&AM51 -> ADBBCF7 IAUS Curncy | AP51: =IF(ISBLANK(AO51),Settings.CurveSide.MidBidAsk,'AUD CURVE TICKERS'!AO51) -> PX_MID | AQ51: =IF(Settings.isCOBToday,_xll.BDP(AN51,'AUD CURVE TICKERS'!AP51),_xll.BDH(AN51,'AUD CURVE TICKERS'!AP51,Settings.COB,Settings.COB)) -> 13.75
V52: INT_RATE_FUT_START_DT | Y52: 8Y | Z52: ADSW8 | AB52: =IF(ISBLANK(AA52),Settings.BloombergPCS,AA52) -> IAUS | AC52: Curncy | AD52: =Z52&" "&AB52&" "&AC52 -> ADSW8 IAUS Curncy | AF52: =IF(ISBLANK(AE52),Settings.CurveSide.MidBidAsk,'AUD CURVE TICKERS'!AE52) -> PX_MID | AG52: =IF(Settings.isCOBToday,_xll.BDP(AD52,'AUD CURVE TICKERS'!AF52),_xll.BDH(AD52,'AUD CURVE TICKERS'!AF52,Settings.COB,Settings.COB)) -> 2.76 | AI52: 8Y | AJ52: ADBBCF8 | AL52: =IF(ISBLANK(AK52),Settings.BloombergPCS,AK52) -> IAUS | AM52: Curncy | AN52: =AJ52&" "&AL52&" "&AM52 -> ADBBCF8 IAUS Curncy | AP52: =IF(ISBLANK(AO52),Settings.CurveSide.MidBidAsk,'AUD CURVE TICKERS'!AO52) -> PX_MID | AQ52: =IF(Settings.isCOBToday,_xll.BDP(AN52,'AUD CURVE TICKERS'!AP52),_xll.BDH(AN52,'AUD CURVE TICKERS'!AP52,Settings.COB,Settings.COB)) -> 13.125
V53: INT_RATE_FUT_END_DT | Y53: 9Y | Z53: ADSW9 | AB53: =IF(ISBLANK(AA53),Settings.BloombergPCS,AA53) -> IAUS | AC53: Curncy | AD53: =Z53&" "&AB53&" "&AC53 -> ADSW9 IAUS Curncy | AF53: =IF(ISBLANK(AE53),Settings.CurveSide.MidBidAsk,'AUD CURVE TICKERS'!AE53) -> PX_MID | AG53: =IF(Settings.isCOBToday,_xll.BDP(AD53,'AUD CURVE TICKERS'!AF53),_xll.BDH(AD53,'AUD CURVE TICKERS'!AF53,Settings.COB,Settings.COB)) -> 2.81875 | AI53: 9Y | AJ53: ADBBCF9 | AL53: =IF(ISBLANK(AK53),Settings.BloombergPCS,AK53) -> IAUS | AM53: Curncy | AN53: =AJ53&" "&AL53&" "&AM53 -> ADBBCF9 IAUS Curncy | AP53: =IF(ISBLANK(AO53),Settings.CurveSide.MidBidAsk,'AUD CURVE TICKERS'!AO53) -> PX_MID | AQ53: =IF(Settings.isCOBToday,_xll.BDP(AN53,'AUD CURVE TICKERS'!AP53),_xll.BDH(AN53,'AUD CURVE TICKERS'!AP53,Settings.COB,Settings.COB)) -> 12.625
Y54: 10Y | Z54: ADSW10 | AB54: =IF(ISBLANK(AA54),Settings.BloombergPCS,AA54) -> IAUS | AC54: Curncy | AD54: =Z54&" "&AB54&" "&AC54 -> ADSW10 IAUS Curncy | AF54: =IF(ISBLANK(AE54),Settings.CurveSide.MidBidAsk,'AUD CURVE TICKERS'!AE54) -> PX_MID | AG54: =IF(Settings.isCOBToday,_xll.BDP(AD54,'AUD CURVE TICKERS'!AF54),_xll.BDH(AD54,'AUD CURVE TICKERS'!AF54,Settings.COB,Settings.COB)) -> 2.87125 | AI54: 10Y | AJ54: ADBBCF10 | AL54: =IF(ISBLANK(AK54),Settings.BloombergPCS,AK54) -> IAUS | AM54: Curncy | AN54: =AJ54&" "&AL54&" "&AM54 -> ADBBCF10 IAUS Curncy | AP54: =IF(ISBLANK(AO54),Settings.CurveSide.MidBidAsk,'AUD CURVE TICKERS'!AO54) -> PX_MID | AQ54: =IF(Settings.isCOBToday,_xll.BDP(AN54,'AUD CURVE TICKERS'!AP54),_xll.BDH(AN54,'AUD CURVE TICKERS'!AP54,Settings.COB,Settings.COB)) -> 12
Y55: 15Y | Z55: ADSW15 | AB55: =IF(ISBLANK(AA55),Settings.BloombergPCS,AA55) -> IAUS | AC55: Curncy | AD55: =Z55&" "&AB55&" "&AC55 -> ADSW15 IAUS Curncy | AF55: =IF(ISBLANK(AE55),Settings.CurveSide.MidBidAsk,'AUD CURVE TICKERS'!AE55) -> PX_MID | AG55: =IF(Settings.isCOBToday,_xll.BDP(AD55,'AUD CURVE TICKERS'!AF55),_xll.BDH(AD55,'AUD CURVE TICKERS'!AF55,Settings.COB,Settings.COB)) -> 3.05875 | AI55: 15Y | AJ55: ADBBCF15 | AL55: =IF(ISBLANK(AK55),Settings.BloombergPCS,AK55) -> IAUS | AM55: Curncy | AN55: =AJ55&" "&AL55&" "&AM55 -> ADBBCF15 IAUS Curncy | AP55: =IF(ISBLANK(AO55),Settings.CurveSide.MidBidAsk,'AUD CURVE TICKERS'!AO55) -> PX_MID | AQ55: =IF(Settings.isCOBToday,_xll.BDP(AN55,'AUD CURVE TICKERS'!AP55),_xll.BDH(AN55,'AUD CURVE TICKERS'!AP55,Settings.COB,Settings.COB)) -> 10.5
Y56: 20Y | Z56: ADSW20 | AB56: =IF(ISBLANK(AA56),Settings.BloombergPCS,AA56) -> IAUS | AC56: Curncy | AD56: =Z56&" "&AB56&" "&AC56 -> ADSW20 IAUS Curncy | AF56: =IF(ISBLANK(AE56),Settings.CurveSide.MidBidAsk,'AUD CURVE TICKERS'!AE56) -> PX_MID | AG56: =IF(Settings.isCOBToday,_xll.BDP(AD56,'AUD CURVE TICKERS'!AF56),_xll.BDH(AD56,'AUD CURVE TICKERS'!AF56,Settings.COB,Settings.COB)) -> 3.12625 | AI56: 20Y | AJ56: ADBBCF20 | AL56: =IF(ISBLANK(AK56),Settings.BloombergPCS,AK56) -> IAUS | AM56: Curncy | AN56: =AJ56&" "&AL56&" "&AM56 -> ADBBCF20 IAUS Curncy | AP56: =IF(ISBLANK(AO56),Settings.CurveSide.MidBidAsk,'AUD CURVE TICKERS'!AO56) -> PX_MID | AQ56: =IF(Settings.isCOBToday,_xll.BDP(AN56,'AUD CURVE TICKERS'!AP56),_xll.BDH(AN56,'AUD CURVE TICKERS'!AP56,Settings.COB,Settings.COB)) -> 10.375
Y57: 25Y | Z57: ADSW25 | AB57: =IF(ISBLANK(AA57),Settings.BloombergPCS,AA57) -> IAUS | AC57: Curncy | AD57: =Z57&" "&AB57&" "&AC57 -> ADSW25 IAUS Curncy | AF57: =IF(ISBLANK(AE57),Settings.CurveSide.MidBidAsk,'AUD CURVE TICKERS'!AE57) -> PX_MID | AG57: =IF(Settings.isCOBToday,_xll.BDP(AD57,'AUD CURVE TICKERS'!AF57),_xll.BDH(AD57,'AUD CURVE TICKERS'!AF57,Settings.COB,Settings.COB)) -> 3.13625 | AI57: 25Y | AJ57: ADBBCF25 | AL57: =IF(ISBLANK(AK57),Settings.BloombergPCS,AK57) -> IAUS | AM57: Curncy | AN57: =AJ57&" "&AL57&" "&AM57 -> ADBBCF25 IAUS Curncy | AP57: =IF(ISBLANK(AO57),Settings.CurveSide.MidBidAsk,'AUD CURVE TICKERS'!AO57) -> PX_MID | AQ57: =IF(Settings.isCOBToday,_xll.BDP(AN57,'AUD CURVE TICKERS'!AP57),_xll.BDH(AN57,'AUD CURVE TICKERS'!AP57,Settings.COB,Settings.COB)) -> 10.625
Y58: 30Y | Z58: ADSW30 | AB58: =IF(ISBLANK(AA58),Settings.BloombergPCS,AA58) -> IAUS | AC58: Curncy | AD58: =Z58&" "&AB58&" "&AC58 -> ADSW30 IAUS Curncy | AF58: =IF(ISBLANK(AE58),Settings.CurveSide.MidBidAsk,'AUD CURVE TICKERS'!AE58) -> PX_MID | AG58: =IF(Settings.isCOBToday,_xll.BDP(AD58,'AUD CURVE TICKERS'!AF58),_xll.BDH(AD58,'AUD CURVE TICKERS'!AF58,Settings.COB,Settings.COB)) -> 3.10375 | AI58: 30Y | AJ58: ADBBCF30 | AL58: =IF(ISBLANK(AK58),Settings.BloombergPCS,AK58) -> IAUS | AM58: Curncy | AN58: =AJ58&" "&AL58&" "&AM58 -> ADBBCF30 IAUS Curncy | AP58: =IF(ISBLANK(AO58),Settings.CurveSide.MidBidAsk,'AUD CURVE TICKERS'!AO58) -> PX_MID | AQ58: =IF(Settings.isCOBToday,_xll.BDP(AN58,'AUD CURVE TICKERS'!AP58),_xll.BDH(AN58,'AUD CURVE TICKERS'!AP58,Settings.COB,Settings.COB)) -> 10.625
A70: << AUD3ML
B73: FRAS | L73: SWAPS
B74: Term | C74: InstrumentID | D74: Broker | E74: Used | F74: Database | G74: Ticker | H74: Side | I74: Used | J74: Result | L74: Term | M74: InstrumentID | N74: Broker | O74: Used | P74: Database | Q74: Ticker | R74: Side | S74: Used | T74: Result
B75: 1x7 | C75: ADFR0AG | E75: =IF(ISBLANK(D75),Settings.BloombergPCS,D75) | F75: Curncy | G75: =C75&" "&E75&" "&F75 -> ADFR0AG Curncy | I75: =IF(ISBLANK(H75),Settings.CurveSide.MidBidAsk,'AUD CURVE TICKERS'!H75) -> PX_MID | J75: =IF(Settings.isCOBToday,_xll.BDP(G75,'AUD CURVE TICKERS'!I75),_xll.BDH(G75,'AUD CURVE TICKERS'!I75,Settings.COB,Settings.COB)) -> 2.131 | L75: 1Y | M75: ADSW1 | O75: =IF(ISBLANK(N75),Settings.BloombergPCS,N75) | P75: Curncy | Q75: =M75&" "&O75&" "&P75 -> ADSW1 Curncy | S75: =IF(ISBLANK(R75),Settings.CurveSide.MidBidAsk,'AUD CURVE TICKERS'!R75) -> PX_MID | T75: =IF(Settings.isCOBToday,_xll.BDP(Q75,'AUD CURVE TICKERS'!S75),_xll.BDH(Q75,'AUD CURVE TICKERS'!S75,Settings.COB,Settings.COB)) -> 2.145
B76: 2x8 | C76: ADFR0BH | E76: =IF(ISBLANK(D76),Settings.BloombergPCS,D76) | F76: Curncy | G76: =C76&" "&E76&" "&F76 -> ADFR0BH Curncy | I76: =IF(ISBLANK(H76),Settings.CurveSide.MidBidAsk,'AUD CURVE TICKERS'!H76) -> PX_MID | J76: =IF(Settings.isCOBToday,_xll.BDP(G76,'AUD CURVE TICKERS'!I76),_xll.BDH(G76,'AUD CURVE TICKERS'!I76,Settings.COB,Settings.COB)) -> 2.129 | L76: 2Y | M76: ADSW2 | O76: =IF(ISBLANK(N76),Settings.BloombergPCS,N76) | P76: Curncy | Q76: =M76&" "&O76&" "&P76 -> ADSW2 Curncy | S76: =IF(ISBLANK(R76),Settings.CurveSide.MidBidAsk,'AUD CURVE TICKERS'!R76) -> PX_MID | T76: =IF(Settings.isCOBToday,_xll.BDP(Q76,'AUD CURVE TICKERS'!S76),_xll.BDH(Q76,'AUD CURVE TICKERS'!S76,Settings.COB,Settings.COB)) -> 2.247
B77: 3x9 | C77: ADFR0CI | E77: =IF(ISBLANK(D77),Settings.BloombergPCS,D77) | F77: Curncy | G77: =C77&" "&E77&" "&F77 -> ADFR0CI Curncy | I77: =IF(ISBLANK(H77),Settings.CurveSide.MidBidAsk,'AUD CURVE TICKERS'!H77) -> PX_MID | J77: =IF(Settings.isCOBToday,_xll.BDP(G77,'AUD CURVE TICKERS'!I77),_xll.BDH(G77,'AUD CURVE TICKERS'!I77,Settings.COB,Settings.COB)) -> 2.13 | L77: 3Y | M77: ADSW3 | O77: =IF(ISBLANK(N77),Settings.BloombergPCS,N77) | P77: Curncy | Q77: =M77&" "&O77&" "&P77 -> ADSW3 Curncy | S77: =IF(ISBLANK(R77),Settings.CurveSide.MidBidAsk,'AUD CURVE TICKERS'!R77) -> PX_MID | T77: =IF(Settings.isCOBToday,_xll.BDP(Q77,'AUD CURVE TICKERS'!S77),_xll.BDH(Q77,'AUD CURVE TICKERS'!S77,Settings.COB,Settings.COB)) -> 2.345
L78: 4Y | M78: ADSW4 | O78: =IF(ISBLANK(N78),Settings.BloombergPCS,N78) -> IAUS | P78: Curncy | Q78: =M78&" "&O78&" "&P78 -> ADSW4 IAUS Curncy | S78: =IF(ISBLANK(R78),Settings.CurveSide.MidBidAsk,'AUD CURVE TICKERS'!R78) -> PX_MID | T78: =IF(Settings.isCOBToday,_xll.BDP(Q78,'AUD CURVE TICKERS'!S78),_xll.BDH(Q78,'AUD CURVE TICKERS'!S78,Settings.COB,Settings.COB)) -> 2.44
L79: 5Y | M79: ADSW5 | O79: =IF(ISBLANK(N79),Settings.BloombergPCS,N79) -> IAUS | P79: Curncy | Q79: =M79&" "&O79&" "&P79 -> ADSW5 IAUS Curncy | S79: =IF(ISBLANK(R79),Settings.CurveSide.MidBidAsk,'AUD CURVE TICKERS'!R79) -> PX_MID | T79: =IF(Settings.isCOBToday,_xll.BDP(Q79,'AUD CURVE TICKERS'!S79),_xll.BDH(Q79,'AUD CURVE TICKERS'!S79,Settings.COB,Settings.COB)) -> 2.53125
L80: 6Y | M80: ADSW6 | O80: =IF(ISBLANK(N80),Settings.BloombergPCS,N80) -> IAUS | P80: Curncy | Q80: =M80&" "&O80&" "&P80 -> ADSW6 IAUS Curncy | S80: =IF(ISBLANK(R80),Settings.CurveSide.MidBidAsk,'AUD CURVE TICKERS'!R80) -> PX_MID | T80: =IF(Settings.isCOBToday,_xll.BDP(Q80,'AUD CURVE TICKERS'!S80),_xll.BDH(Q80,'AUD CURVE TICKERS'!S80,Settings.COB,Settings.COB)) -> 2.61625
L81: 7Y | M81: ADSW7 | O81: =IF(ISBLANK(N81),Settings.BloombergPCS,N81) -> IAUS | P81: Curncy | Q81: =M81&" "&O81&" "&P81 -> ADSW7 IAUS Curncy | S81: =IF(ISBLANK(R81),Settings.CurveSide.MidBidAsk,'AUD CURVE TICKERS'!R81) -> PX_MID | T81: =IF(Settings.isCOBToday,_xll.BDP(Q81,'AUD CURVE TICKERS'!S81),_xll.BDH(Q81,'AUD CURVE TICKERS'!S81,Settings.COB,Settings.COB)) -> 2.6925
L82: 8Y | M82: ADSW8 | O82: =IF(ISBLANK(N82),Settings.BloombergPCS,N82) -> IAUS | P82: Curncy | Q82: =M82&" "&O82&" "&P82 -> ADSW8 IAUS Curncy | S82: =IF(ISBLANK(R82),Settings.CurveSide.MidBidAsk,'AUD CURVE TICKERS'!R82) -> PX_MID | T82: =IF(Settings.isCOBToday,_xll.BDP(Q82,'AUD CURVE TICKERS'!S82),_xll.BDH(Q82,'AUD CURVE TICKERS'!S82,Settings.COB,Settings.COB)) -> 2.76
L83: 9Y | M83: ADSW9 | O83: =IF(ISBLANK(N83),Settings.BloombergPCS,N83) -> IAUS | P83: Curncy | Q83: =M83&" "&O83&" "&P83 -> ADSW9 IAUS Curncy | S83: =IF(ISBLANK(R83),Settings.CurveSide.MidBidAsk,'AUD CURVE TICKERS'!R83) -> PX_MID | T83: =IF(Settings.isCOBToday,_xll.BDP(Q83,'AUD CURVE TICKERS'!S83),_xll.BDH(Q83,'AUD CURVE TICKERS'!S83,Settings.COB,Settings.COB)) -> 2.81875
L84: 10Y | M84: ADSW10 | O84: =IF(ISBLANK(N84),Settings.BloombergPCS,N84) -> IAUS | P84: Curncy | Q84: =M84&" "&O84&" "&P84 -> ADSW10 IAUS Curncy | S84: =IF(ISBLANK(R84),Settings.CurveSide.MidBidAsk,'AUD CURVE TICKERS'!R84) -> PX_MID | T84: =IF(Settings.isCOBToday,_xll.BDP(Q84,'AUD CURVE TICKERS'!S84),_xll.BDH(Q84,'AUD CURVE TICKERS'!S84,Settings.COB,Settings.COB)) -> 2.87125
L85: 12Y | M85: ADSW12 | O85: =IF(ISBLANK(N85),Settings.BloombergPCS,N85) -> IAUS | P85: Curncy | Q85: =M85&" "&O85&" "&P85 -> ADSW12 IAUS Curncy | S85: =IF(ISBLANK(R85),Settings.CurveSide.MidBidAsk,'AUD CURVE TICKERS'!R85) -> PX_MID | T85: =IF(Settings.isCOBToday,_xll.BDP(Q85,'AUD CURVE TICKERS'!S85),_xll.BDH(Q85,'AUD CURVE TICKERS'!S85,Settings.COB,Settings.COB)) -> 2.96375
L86: 15Y | M86: ADSW15 | O86: =IF(ISBLANK(N86),Settings.BloombergPCS,N86) -> IAUS | P86: Curncy | Q86: =M86&" "&O86&" "&P86 -> ADSW15 IAUS Curncy | S86: =IF(ISBLANK(R86),Settings.CurveSide.MidBidAsk,'AUD CURVE TICKERS'!R86) -> PX_MID | T86: =IF(Settings.isCOBToday,_xll.BDP(Q86,'AUD CURVE TICKERS'!S86),_xll.BDH(Q86,'AUD CURVE TICKERS'!S86,Settings.COB,Settings.COB)) -> 3.05875
L87: 20Y | M87: ADSW20 | O87: =IF(ISBLANK(N87),Settings.BloombergPCS,N87) -> IAUS | P87: Curncy | Q87: =M87&" "&O87&" "&P87 -> ADSW20 IAUS Curncy | S87: =IF(ISBLANK(R87),Settings.CurveSide.MidBidAsk,'AUD CURVE TICKERS'!R87) -> PX_MID | T87: =IF(Settings.isCOBToday,_xll.BDP(Q87,'AUD CURVE TICKERS'!S87),_xll.BDH(Q87,'AUD CURVE TICKERS'!S87,Settings.COB,Settings.COB)) -> 3.12625
L88: 25Y | M88: ADSW25 | O88: =IF(ISBLANK(N88),Settings.BloombergPCS,N88) -> IAUS | P88: Curncy | Q88: =M88&" "&O88&" "&P88 -> ADSW25 IAUS Curncy | S88: =IF(ISBLANK(R88),Settings.CurveSide.MidBidAsk,'AUD CURVE TICKERS'!R88) -> PX_MID | T88: =IF(Settings.isCOBToday,_xll.BDP(Q88,'AUD CURVE TICKERS'!S88),_xll.BDH(Q88,'AUD CURVE TICKERS'!S88,Settings.COB,Settings.COB)) -> 3.13625
L89: 30Y | M89: ADSW30 | O89: =IF(ISBLANK(N89),Settings.BloombergPCS,N89) -> IAUS | P89: Curncy | Q89: =M89&" "&O89&" "&P89 -> ADSW30 IAUS Curncy | S89: =IF(ISBLANK(R89),Settings.CurveSide.MidBidAsk,'AUD CURVE TICKERS'!R89) -> PX_MID | T89: =IF(Settings.isCOBToday,_xll.BDP(Q89,'AUD CURVE TICKERS'!S89),_xll.BDH(Q89,'AUD CURVE TICKERS'!S89,Settings.COB,Settings.COB)) -> 3.10375
A100: << AUD6ML

Sheet AUD CURVE
AP1: … Curve Generator Templtes
B2: AUD OIS | AB2: AUDOIS - GENERATOR TEMPLATE | AG2: AUD3ML - GENERATOR TEMPLATE | AL2: AUD6ML - GENERATOR TEMPLATE
C4: MARKETDATAPROPERTIES | F4: OIS | L4: OISFIXINGS | R4: LIBOROISBASISSPREADS | V4: SWAPS | AC4: CREATE GENERATOR | AH4: CREATE GENERATOR | AM4: CREATE GENERATOR
F5: Term | G5: Rate | H5: StartDate | I5: EndDate | J5: Use | L5: BaseDate | M5: Rate | O5: Libor-OIS Q | P5: Basis 3X6 | R5: Term | S5: Rate | V5: Term | W5: Rate | AC5: HandleName | AD5: AUD_OIS_CURVE_GENERATOR | AH5: HandleName | AI5: AUD_3ML_CURVE_GENERATOR | AM5: HandleName | AN5: AUD_6ML_CURVE_GENERATOR
C6: Currency | D6: AUD | F6: ='AUD CURVE TICKERS'!B15 -> ON | G6: ='AUD CURVE TICKERS'!J15% -> 0.015 | J6: TRUE | O6: ='AUD CURVE TICKERS'!T15/10000 -> 0.00435 | P6: ='AUD CURVE TICKERS'!AQ45/10000 -> 0.0016125 | R6: ='AUD CURVE TICKERS'!L15 -> 1Y | S6: =O6 -> 0.00435 | T6: 3ML | V6: ='AUD CURVE TICKERS'!Y45 -> 1Y | W6: ='AUD CURVE TICKERS'!AG45% -> 0.019775 | AC6: Create Curve Generator | AD6: =_xll.meLWOCurveGeneratorCreate(AD5,AC8,AC9:AD15,AC18,AC19:AD35,AC38,AC39:AD40,AC44,AC45:AD51) -> AUD_OIS_CURVE_GENERATOR@5:3 | AH6: Create Curve Generator | AI6: =_xll.meLWOCurveGeneratorCreate(AI5,AH8,AH9:AI23,AH26,AH27:AI29,AH32,AH33:AI37,AH40,AH41:AI46,AH49,AH50:AI56,AH59,AH60:AI80,AH83,AH84:AI115) -> AUD_3ML_CURVE_GENERATOR@1:3 | AM6: Create Curve Generator | AN6: =_xll.meLWOCurveGeneratorCreate(AN5,AM8,AM9:AN23,AM26,AM27:AN29,AM32,AM33:AN37,AM40,AM41:AN46,AM59,AM60:AN73) -> AUD_6ML_CURVE_GENERATOR@2:3
C7: CurveType | D7: OIS | F7: ='AUD CURVE TICKERS'!B16 -> 1W | G7: ='AUD CURVE TICKERS'!J16% -> 0.015 | J7: TRUE | O7: ='AUD CURVE TICKERS'!T16/10000 -> 0.004225 | P7: ='AUD CURVE TICKERS'!AQ46/10000 -> 0.0015625 | R7: ='AUD CURVE TICKERS'!L16 -> 2Y | S7: =O7 -> 0.004225 | T7: 3ML | V7: ='AUD CURVE TICKERS'!Y46 -> 2Y | W7: ='AUD CURVE TICKERS'!AG46% -> 0.0208625
C8: CurveIndexFrequency | D8: DAILY | F8: ='AUD CURVE TICKERS'!B17 -> 1M | G8: ='AUD CURVE TICKERS'!J17% -> 0.015 | J8: TRUE | O8: ='AUD CURVE TICKERS'!T17/10000 -> 0.00415 | P8: ='AUD CURVE TICKERS'!AQ47/10000 -> 0.0015125 | R8: ='AUD CURVE TICKERS'!L17 -> 3Y | S8: =O8 -> 0.00415 | T8: 3ML | V8: ='AUD CURVE TICKERS'!Y47 -> 3Y | W8: ='AUD CURVE TICKERS'!AG47% -> 0.0218875 | AC8: CURVEPROPERTIES | AH8: CURVEPROPERTIES | AM8: CURVEPROPERTIES
C9: AsOfDate | D9: =Settings.COB -> 43420 | F9: ='AUD CURVE TICKERS'!B18 -> 2M | G9: ='AUD CURVE TICKERS'!J18% -> 0.015 | J9: TRUE | O9: ='AUD CURVE TICKERS'!T18/10000 -> 0.00415 | P9: ='AUD CURVE TICKERS'!AQ48/10000 -> 0.0015 | R9: ='AUD CURVE TICKERS'!L18 -> 4Y | S9: =O9+P9 -> 0.00565 | T9: 6ML | V9: ='AUD CURVE TICKERS'!Y48 -> 4Y | W9: ='AUD CURVE TICKERS'!AG48% -> 0.0244 | AC9: CurveType | AD9: OIS | AH9: CurveType | AI9: SWAP | AM9: CurveType | AN9: SWAP
F10: ='AUD CURVE TICKERS'!B19 -> 3M | G10: ='AUD CURVE TICKERS'!J19% -> 0.015005 | J10: TRUE | O10: ='AUD CURVE TICKERS'!T19/10000 -> 0.00415 | P10: ='AUD CURVE TICKERS'!AQ49/10000 -> 0.001475 | R10: ='AUD CURVE TICKERS'!L19 -> 5Y | S10: =O10+P10 -> 0.005625 | T10: 6ML | V10: ='AUD CURVE TICKERS'!Y49 -> 5Y | W10: ='AUD CURVE TICKERS'!AG49% -> 0.0253125 | AC10: CurveIndexFrequency | AD10: DAILY | AH10: CurveIndexFrequency | AI10: QUARTERLY | AM10: CurveIndexFrequency | AN10: SEMI-ANNUAL
F11: ='AUD CURVE TICKERS'!B20 -> 4M | G11: ='AUD CURVE TICKERS'!J20% -> 0.01502 | J11: TRUE | O11: ='AUD CURVE TICKERS'!T20/10000 -> 0.0041625 | P11: ='AUD CURVE TICKERS'!AQ50/10000 -> 0.001425 | R11: ='AUD CURVE TICKERS'!L20 -> 6Y | S11: =O11+P11 -> 0.0055875 | T11: 6ML | V11: ='AUD CURVE TICKERS'!Y50 -> 6Y | W11: ='AUD CURVE TICKERS'!AG50% -> 0.0261625 | AC11: StaticDataTable | AD11: OIS | AH11: StaticDataTable | AI11: STD | AM11: StaticDataTable | AN11: AUD6ML
C12: Create Market Data Handle | F12: ='AUD CURVE TICKERS'!B21 -> 5M | G12: ='AUD CURVE TICKERS'!J21% -> 0.0150375 | J12: TRUE | O12: ='AUD CURVE TICKERS'!T21/10000 -> 0.004175 | P12: ='AUD CURVE TICKERS'!AQ51/10000 -> 0.001375 | R12: ='AUD CURVE TICKERS'!L21 -> 7Y | S12: =O12+P12 -> 0.00555 | T12: 6ML | V12: ='AUD CURVE TICKERS'!Y51 -> 7Y | W12: ='AUD CURVE TICKERS'!AG51% -> 0.026925 | AC12: IndexName | AD12: OIS:AUDOIS:AUDDF:AUDDF_AUDCSA:AUDDF_NOCSA | AH12: IndexName | AI12: STD:AUD3ML | AM12: IndexName | AN12: AUD6ML
C13: Handle Name | D13: AUD_OIS_CURVE_MARKETDATA | F13: ='AUD CURVE TICKERS'!B22 -> 6M | G13: ='AUD CURVE TICKERS'!J22% -> 0.01508 | J13: TRUE | O13: ='AUD CURVE TICKERS'!T22/10000 -> 0.004175 | P13: ='AUD CURVE TICKERS'!AQ52/10000 -> 0.0013125 | R13: ='AUD CURVE TICKERS'!L22 -> 8Y | S13: =O13+P13 -> 0.0054875 | T13: 6ML | V13: ='AUD CURVE TICKERS'!Y52 -> 8Y | W13: ='AUD CURVE TICKERS'!AG52% -> 0.0276 | AC13: Currency | AD13: AUD | AH13: Currency | AI13: AUD | AM13: Currency | AN13: AUD
C14: Market Data Handle | D14: =_xll.meLWOCurveMarketDataCreate(D13,C4,C6:D9,F4,F6:J31,L4,L6:M31,R4,R6:S31,V4,V6:W31) -> AUD_OIS_CURVE_MARKETDATA@63:3 | F14: ='AUD CURVE TICKERS'!B23 -> 9M | G14: ='AUD CURVE TICKERS'!J23% -> 0.015225 | J14: TRUE | O14: ='AUD CURVE TICKERS'!T23/10000 -> 0.004175 | P14: ='AUD CURVE TICKERS'!AQ53/10000 -> 0.0012625 | R14: ='AUD CURVE TICKERS'!L23 -> 9Y | S14: =O14+P14 -> 0.0054375 | T14: 6ML | V14: ='AUD CURVE TICKERS'!Y53 -> 9Y | W14: ='AUD CURVE TICKERS'!AG53% -> 0.0281875 | AC14: interpolation | AD14: FN_SPLINEINTERPOLATION | AH14: interpolation | AI14: =IF(Settings.SwapCurve.Interpolation="LINEAR-SPLINE","FN_LINEARSPLINEINTERPOLATION","FN_SPLINEINTERPOLATION") -> FN_SPLINEINTERPOLATION | AM14: interpolation | AN14: =IF(Settings.SwapCurve.Interpolation="LINEAR-SPLINE","FN_LINEARSPLINEINTERPOLATION","FN_SPLINEINTERPOLATION") -> FN_SPLINEINTERPOLATION
F15: ='AUD CURVE TICKERS'!B24 -> 1Y | G15: ='AUD CURVE TICKERS'!J24% -> 0.015475 | J15: TRUE | O15: ='AUD CURVE TICKERS'!T24/10000 -> 0.0041625 | P15: ='AUD CURVE TICKERS'!AQ54/10000 -> 0.0012 | R15: ='AUD CURVE TICKERS'!L24 -> 10Y | S15: =O15+P15 -> 0.0053625 | T15: 6ML | V15: ='AUD CURVE TICKERS'!Y54 -> 10Y | W15: ='AUD CURVE TICKERS'!AG54% -> 0.0287125 | AC15: yieldgen.interpolation | AD15: FN_SPLINEINTERPOLATION | AH15: yieldgen.interpolation | AI15: =IF(Settings.SwapCurve.Interpolation="LINEAR-SPLINE","FN_LINEARSPLINEINTERPOLATION","FN_SPLINEINTERPOLATION") -> FN_SPLINEINTERPOLATION | AM15: yieldgen.interpolation | AN15: =IF(Settings.SwapCurve.Interpolation="LINEAR-SPLINE","FN_LINEARSPLINEINTERPOLATION","FN_SPLINEINTERPOLATION") -> FN_SPLINEINTERPOLATION
F16: ='AUD CURVE TICKERS'!B25 -> 2Y | G16: ='AUD CURVE TICKERS'!J25% -> 0.01675 | J16: TRUE | O16: ='AUD CURVE TICKERS'!T25/10000 -> 0.0042 | P16: ='AUD CURVE TICKERS'!AQ55/10000 -> 0.00105 | R16: ='AUD CURVE TICKERS'!L25 -> 15Y | S16: =O16+P16 -> 0.00525 | T16: 6ML | V16: ='AUD CURVE TICKERS'!Y55 -> 15Y | W16: ='AUD CURVE TICKERS'!AG55% -> 0.0305875 | AH16: isfrause | AI16: FALSE | AM16: isfraUse | AN16: TRUE
F17: ='AUD CURVE TICKERS'!B26 -> 3Y | G17: ='AUD CURVE TICKERS'!J26% -> 0.01785 | J17: TRUE | O17: ='AUD CURVE TICKERS'!T26/10000 -> 0.004225 | P17: ='AUD CURVE TICKERS'!AQ56/10000 -> 0.0010375 | R17: ='AUD CURVE TICKERS'!L26 -> 20Y | S17: =O17+P17 -> 0.0052625 | T17: 6ML | V17: ='AUD CURVE TICKERS'!Y56 -> 20Y | W17: ='AUD CURVE TICKERS'!AG56% -> 0.0312625 | AH17: isfutureuse | AI17: TRUE | AM17: isfutureUse | AN17: FALSE
F18: ='AUD CURVE TICKERS'!B27 -> 4Y | G18: ='AUD CURVE TICKERS'!J27% -> 0.01883 | J18: TRUE | O18: ='AUD CURVE TICKERS'!T27/10000 -> 0.0042625 | P18: ='AUD CURVE TICKERS'!AQ57/10000 -> 0.0010625 | R18: ='AUD CURVE TICKERS'!L27 -> 25Y | S18: =O18+P18 -> 0.005325 | T18: 6ML | V18: ='AUD CURVE TICKERS'!Y57 -> 25Y | W18: ='AUD CURVE TICKERS'!AG57% -> 0.0313625 | AC18: OIS | AH18: future.interpolation | AI18: =IF(Settings.SwapCurve.Interpolation="LINEAR-SPLINE","FN_LINEARSPLINEINTERPOLATION","FN_LINEARINTERPOLATION") -> FN_LINEARINTERPOLATION | AM18: future.interpolation | AN18: =IF(Settings.SwapCurve.Interpolation="LINEAR-SPLINE","FN_LINEARSPLINEINTERPOLATION","FN_LINEARINTERPOLATION") -> FN_LINEARINTERPOLATION
C19: Curve Dictionary | F19: ='AUD CURVE TICKERS'!B28 -> 5Y | G19: ='AUD CURVE TICKERS'!J28% -> 0.01978 | J19: TRUE | O19: ='AUD CURVE TICKERS'!T28/10000 -> 0.0043 | P19: ='AUD CURVE TICKERS'!AQ58/10000 -> 0.0010625 | R19: ='AUD CURVE TICKERS'!L28 -> 30Y | S19: =O19+P19 -> 0.0053625 | T19: 6ML | V19: ='AUD CURVE TICKERS'!Y58 -> 30Y | W19: ='AUD CURVE TICKERS'!AG58% -> 0.0310375 | AC19: calendar | AD19: SYB:LNB | AH19: Frequency | AI19: SIMPLE | AM19: Frequency | AN19: SIMPLE
C20: Handle Name | D20: AUD_OIS_CURVE | F20: ='AUD CURVE TICKERS'!B29 -> 6Y | G20: ='AUD CURVE TICKERS'!J29% -> 0.02063 | J20: TRUE | R20: 40Y | S20: =S19 -> 0.0053625 | T20: Extrapolation | V20: 40Y | W20: =W19 -> 0.0310375 | X20: Extrapolation | AC20: daycount | AD20: ACT/365 | AH20: dfcurvename | AI20: OIS | AM20: dfcurvename | AN20: OIS
C21: Curve Generator | D21: =$AD$6 -> AUD_OIS_CURVE_GENERATOR@5:3 | F21: ='AUD CURVE TICKERS'!B30 -> 7Y | G21: ='AUD CURVE TICKERS'!J30% -> 0.02148 | J21: TRUE | R21: 50Y | S21: =S20 -> 0.0053625 | T21: Extrapolation | V21: 50Y | W21: =W20 -> 0.0310375 | X21: Extrapolation | AC21: frequency | AD21: ANNUAL | AH21: IsSwapTenorAdjust | AI21: TRUE | AM21: IsSwapTenorAdjust | AN21: FALSE
C22: Domestic Curve Collection | D22: AUDYC | F22: ='AUD CURVE TICKERS'!B31 -> 8Y | G22: ='AUD CURVE TICKERS'!J31% -> 0.02215 | J22: TRUE | AC22: generatemethod | AD22: DAILYCOMPOUNDING | AH22: TenorSwapName | AI22: 3M6MBasis | AM22: FastRebuild | AN22: TRUE
C23: Foreign Curve Collection | F23: ='AUD CURVE TICKERS'!B32 -> 9Y | G23: ='AUD CURVE TICKERS'!J32% -> 0.0228 | J23: TRUE | AC23: resetlag | AD23: 1D | AH23: FastRebuild | AI23: TRUE
F24: ='AUD CURVE TICKERS'!B33 -> 10Y | G24: ='AUD CURVE TICKERS'!J33% -> 0.02348 | J24: TRUE | AC24: firstrate | AD24: SHORTMARKET
F25: ='AUD CURVE TICKERS'!B34 -> 15Y | G25: ='AUD CURVE TICKERS'!J34% -> 0.02548 | J25: TRUE | AC25: slidingrule | AD25: MOD_FOLLOWING
C26: Curve Build | F26: ='AUD CURVE TICKERS'!B35 -> 20Y | G26: ='AUD CURVE TICKERS'!J35% -> 0.02615 | J26: TRUE | AC26: eomday | AD26: 31 | AH26: MONEYMARKET | AM26: MONEYMARKET
C27: Handle Name | D27: {=_xll.meLWOCurveCalibrate(D20,D21,D14,D22,D23)} -> AUD_OIS_CURVE@64:3 | F27: ='AUD CURVE TICKERS'!B36 -> 25Y | G27: ='AUD CURVE TICKERS'!J36% -> 0.0262 | J27: TRUE | AC27: iseomroll | AD27: TRUE | AH27: Calendar | AI27: SYB:LnB | AM27: Calendar | AN27: SYB:LnB
C28: Curve Collection | D28: AUDYC | F28: ='AUD CURVE TICKERS'!B37 -> 30Y | G28: ='AUD CURVE TICKERS'!J37% -> 0.02583 | J28: TRUE | AC28: shorttermconvention | AD28: ARITHMETICAVERAGE | AH28: DayCount | AI28: ACT/365 | AM28: DayCount | AN28: ACT/365
C29: Curve Index | D29: OIS:AUDOIS:AUDDF:AUDDF_AUDCSA:AUDDF_NOCSA | AC29: longtermconvention | AD29: LOBASIS | AH29: Slidingrule | AI29: FOLLOWING | AM29: Slidingrule | AN29: FOLLOWING
C30: Calibration Time Taken | D30: 0.01500 sec | AC30: longterm | AD30: 3Y
C31: Curve Loaded | D31: =LEFT($D$27,3)=LEFT($D$20,3) -> TRUE | AC31: longterm.generatemethod | AD31: NONE
AC32: Epsilon | AD32: 1e-10 | AH32: LIBORFIXINGS | AM32: LIBORFIXINGS
AC33: MaxLoop | AD33: 1000 | AH33: Calendar | AI33: SYB:LnB | AM33: Calendar | AN33: SYB:LnB
AC34: CompoundingMethod | AD34: GEOMETRIC | AH34: Daycount | AI34: ACT/365 | AM34: Daycount | AN34: ACT/365
B35: AUD 3ML | AC35: SmoothShortEnd | AD35: FALSE | AH35: Frequency | AI35: Simple | AM35: Frequency | AN35: Simple
AH36: Resetlag | AI36: 0 | AM36: Resetlag | AN36: 0
C37: MARKETDATAPROPERTIES | F37: LIBORFIXINGS | I37: FRAS | L37: FUTURES | R37: SWAPS | V37: BASISSWAPS | AH37: SlidingRule | AI37: MOD_FOLLOWING | AM37: SlidingRule | AN37: MOD_FOLLOWING
C38: Currency | D38: AUD | F38: Term | G38: Rate | I38: Term | J38: Rate | L38: Term | M38: StartDate | N38: EndDate | O38: Rate | P38: Volatility | R38: Term | S38: Rate | T38: Use | V38: Term | W38: Rate | X38: Use | AC38: LIBOROISBASIS | AD38: OIS FLOAT LEG CONVENTIONS
C39: CurveType | D39: SWAP | F39: ='AUD CURVE TICKERS'!B46 -> 3M | G39: ='AUD CURVE TICKERS'!J46% -> 0.0193 | L39: ='AUD CURVE TICKERS'!L45 -> IR1 | M39: ='AUD CURVE TICKERS'!V45 -> 14/12/2018 | N39: ='AUD CURVE TICKERS'!W45 -> 08/03/2019 | O39: ='AUD CURVE TICKERS'!T45 -> 98.025 | P39: =Settings.Futures.Convexity.HW1F.Vol -> 0.02 | R39: ='AUD CURVE TICKERS'!Y46 -> 2Y | S39: ='AUD CURVE TICKERS'!AG46% -> 0.0208625 | T39: TRUE | V39: ='AUD CURVE TICKERS'!AI46 -> 2Y | W39: ='AUD CURVE TICKERS'!AQ46/10000 -> 0.0015625 | X39: TRUE | AC39: frequency | AD39: ANNUAL
C40: CurveIndexFrequency | D40: QUARTERLY | L40: ='AUD CURVE TICKERS'!L46 -> IR2 | M40: ='AUD CURVE TICKERS'!V46 -> 08/03/2019 | N40: ='AUD CURVE TICKERS'!W46 -> 14/06/2019 | O40: ='AUD CURVE TICKERS'!T46 -> 98.045 | P40: =Settings.Futures.Convexity.HW1F.Vol -> 0.02 | R40: ='AUD CURVE TICKERS'!Y47 -> 3Y | S40: ='AUD CURVE TICKERS'!AG47% -> 0.0218875 | T40: TRUE | V40: ='AUD CURVE TICKERS'!AI47 -> 3Y | W40: ='AUD CURVE TICKERS'!AQ47/10000 -> 0.0015125 | X40: TRUE | AC40: slidingRule | AD40: MOD_FOLLOWING | AH40: FRAS | AM40: FRAS
C41: AsOfDate | D41: =Settings.COB -> 43420 | L41: ='AUD CURVE TICKERS'!L47 -> IR3 | M41: ='AUD CURVE TICKERS'!V47 -> 14/06/2019 | N41: ='AUD CURVE TICKERS'!W47 -> 13/09/2019 | O41: ='AUD CURVE TICKERS'!T47 -> 98.005 | P41: =Settings.Futures.Convexity.HW1F.Vol -> 0.02 | R41: ='AUD CURVE TICKERS'!Y48 -> 4Y | S41: ='AUD CURVE TICKERS'!AG48% -> 0.0244 | T41: TRUE | V41: ='AUD CURVE TICKERS'!AI48 -> 4Y | W41: ='AUD CURVE TICKERS'!AQ48/10000 -> 0.0015 | X41: TRUE | AH41: Calendar | AI41: SYB:LnB | AM41: Calendar | AN41: SYB:LnB
L42: ='AUD CURVE TICKERS'!L48 -> IR4 | M42: ='AUD CURVE TICKERS'!V48 -> 13/09/2019 | N42: ='AUD CURVE TICKERS'!W48 -> 13/12/2019 | O42: ='AUD CURVE TICKERS'!T48 -> 97.935 | P42: =Settings.Futures.Convexity.HW1F.Vol -> 0.02 | R42: ='AUD CURVE TICKERS'!Y49 -> 5Y | S42: ='AUD CURVE TICKERS'!AG49% -> 0.0253125 | T42: TRUE | V42: ='AUD CURVE TICKERS'!AI49 -> 5Y | W42: ='AUD CURVE TICKERS'!AQ49/10000 -> 0.001475 | X42: TRUE | AH42: DayCount | AI42: ACT/365 | AM42: DayCount | AN42: ACT/365
L43: ='AUD CURVE TICKERS'!L49 -> IR5 | M43: ='AUD CURVE TICKERS'!V49 -> 13/12/2019 | N43: ='AUD CURVE TICKERS'!W49 -> 13/03/2020 | O43: ='AUD CURVE TICKERS'!T49 -> 97.875 | P43: =Settings.Futures.Convexity.HW1F.Vol -> 0.02 | R43: ='AUD CURVE TICKERS'!Y50 -> 6Y | S43: ='AUD CURVE TICKERS'!AG50% -> 0.0261625 | T43: TRUE | V43: ='AUD CURVE TICKERS'!AI50 -> 6Y | W43: ='AUD CURVE TICKERS'!AQ50/10000 -> 0.001425 | X43: TRUE | AH43: ResetLag | AI43: 1 | AM43: ResetLag | AN43: 1
L44: ='AUD CURVE TICKERS'!L50 -> IR6 | M44: ='AUD CURVE TICKERS'!V50 -> 13/03/2020 | N44: ='AUD CURVE TICKERS'!W50 -> 12/06/2020 | O44: ='AUD CURVE TICKERS'!T50 -> 97.815 | P44: =Settings.Futures.Convexity.HW1F.Vol -> 0.02 | R44: ='AUD CURVE TICKERS'!Y51 -> 7Y | S44: ='AUD CURVE TICKERS'!AG51% -> 0.026925 | T44: TRUE | V44: ='AUD CURVE TICKERS'!AI51 -> 7Y | W44: ='AUD CURVE TICKERS'!AQ51/10000 -> 0.001375 | X44: TRUE | AC44: SWAPS | AD44: LIBOR SWAP CONVENTIONS - FIXED LEG | AH44: SlidingRule | AI44: MOD_FOLLOWING | AM44: SlidingRule | AN44: MOD_FOLLOWING
C45: Create Market Data Handle | R45: ='AUD CURVE TICKERS'!Y52 -> 8Y | S45: ='AUD CURVE TICKERS'!AG52% -> 0.0276 | T45: TRUE | V45: ='AUD CURVE TICKERS'!AI52 -> 8Y | W45: ='AUD CURVE TICKERS'!AQ52/10000 -> 0.0013125 | X45: TRUE | AC45: calendar | AD45: SYB:LnB | AH45: ApplyTension | AI45: FALSE | AM45: ApplyTension | AN45: FALSE
C46: Handle Name | D46: AUD_SWAP_3ML_CURVE_MARKETDATA | R46: ='AUD CURVE TICKERS'!Y53 -> 9Y | S46: ='AUD CURVE TICKERS'!AG53% -> 0.0281875 | T46: TRUE | V46: ='AUD CURVE TICKERS'!AI53 -> 9Y | W46: ='AUD CURVE TICKERS'!AQ53/10000 -> 0.0012625 | X46: TRUE | AC46: daycountfix | AD46: ACT/365 | AH46: TensionGap | AI46: 2 | AM46: TensionGap | AN46: 2
C47: Market Data Handle | D47: =_xll.meLWOCurveMarketDataCreate(D46,C37,C38:D43,F37,F39:G43,I37,I39:J64,L37,L39:P64,R37,R39:T64,V37,V39:X64) -> AUD_SWAP_3ML_CURVE_MARKETDATA@62:3 | R47: ='AUD CURVE TICKERS'!Y54 -> 10Y | S47: ='AUD CURVE TICKERS'!AG54% -> 0.0287125 | T47: TRUE | V47: ='AUD CURVE TICKERS'!AI54 -> 10Y | W47: ='AUD CURVE TICKERS'!AQ54/10000 -> 0.0012 | X47: TRUE | AC47: frequencyfix | AD47: Semi-Annual
R48: ='AUD CURVE TICKERS'!Y55 -> 15Y | S48: ='AUD CURVE TICKERS'!AG55% -> 0.0305875 | T48: TRUE | V48: ='AUD CURVE TICKERS'!AI55 -> 15Y | W48: ='AUD CURVE TICKERS'!AQ55/10000 -> 0.00105 | X48: TRUE | AC48: frequencyfix.1y | AD48: QUARTERLY
R49: ='AUD CURVE TICKERS'!Y56 -> 20Y | S49: ='AUD CURVE TICKERS'!AG56% -> 0.0312625 | T49: TRUE | V49: ='AUD CURVE TICKERS'!AI56 -> 20Y | W49: ='AUD CURVE TICKERS'!AQ56/10000 -> 0.0010375 | X49: TRUE | AC49: frequencyfix.2y | AD49: QUARTERLY | AH49: FUTURES | AM49: FUTURES
R50: ='AUD CURVE TICKERS'!Y57 -> 25Y | S50: ='AUD CURVE TICKERS'!AG57% -> 0.0313625 | T50: TRUE | V50: ='AUD CURVE TICKERS'!AI57 -> 25Y | W50: ='AUD CURVE TICKERS'!AQ57/10000 -> 0.0010625 | X50: TRUE | AC50: frequencyfix.3y | AD50: QUARTERLY | AH50: calendar | AI50: SYB:LnB
R51: ='AUD CURVE TICKERS'!Y58 -> 30Y | S51: ='AUD CURVE TICKERS'!AG58% -> 0.0310375 | T51: TRUE | V51: ='AUD CURVE TICKERS'!AI58 -> 30Y | W51: ='AUD CURVE TICKERS'!AQ58/10000 -> 0.0010625 | X51: TRUE | AC51: slidingrule | AD51: MOD_FOLLOWING | AH51: daycount | AI51: Act/360
R52: 40Y | S52: =S51 -> 0.0310375 | T52: TRUE | V52: 40Y | W52: =W51 -> 0.0010625 | X52: TRUE | Y52: Extrapolation | AH52: resetlag | AI52: 2
C53: Curve Dictionary | R53: 50Y | S53: =S52 -> 0.0310375 | T53: TRUE | V53: 50Y | W53: =W52 -> 0.0010625 | X53: TRUE | Y53: Extrapolation | AH53: slidingrule | AI53: MOD_FOLLOWING
C54: Handle Name | D54: AUD_SWAP_3M_CURVE | AH54: MeanReversion | AI54: 0.03
C55: Curve Generator | D55: =$AI$6 -> AUD_3ML_CURVE_GENERATOR@1:3 | AH55: ApplyTension | AI55: FALSE
C56: Domestic Curve Collection | D56: AUDYC | AH56: TensionGap | AI56: 2
C57: Foreign Curve Collection
AH59: SWAPS | AM59: SWAPS
C60: Curve Build | AH60: Calendar | AI60: SYB:LnB | AM60: Calendar | AN60: SYB:LnB
C61: Handle Name | D61: {=IF($D$31,_xll.meLWOCurveCalibrate(D54,D55,D47,D56),"#Error: Dependency Curve not Built")} -> AUD_SWAP_3M_CURVE@65:3 | AH61: DayCount | AI61: ACT/365 | AM61: DayCount | AN61: ACT/365
C62: Curve Collection | D62: AUDYC | AH62: DayCountFix | AI62: ACT/365 | AM62: DayCountFix | AN62: ACT/365
C63: Curve Index | D63: STD:AUD3ML | AH63: DayCountFloat | AI63: ACT/365 | AM63: DayCountFloat | AN63: ACT/365
C64: Calibration Time Taken | D64: 0.01000 sec | AH64: Frequency | AI64: SEMI-ANNUAL | AM64: Frequency | AN64: Semi-Annual
C65: Curve Loaded | D65: =LEFT(D61,3)=LEFT(D61,3) -> TRUE | AH65: FrequencyFix.1y | AI65: QUARTERLY | AM65: FrequencyFloat | AN65: Semi-Annual
AH66: FrequencyFix.2y | AI66: QUARTERLY | AM66: SlidingRule | AN66: MOD_FOLLOWING
AH67: FrequencyFix.3y | AI67: QUARTERLY | AM67: IsNewtonraphson | AN67: TRUE
AH68: FrequencyFloat | AI68: SEMI-ANNUAL | AM68: issimultaneouseq | AN68: TRUE
B69: AUD 6ML | AH69: FrequencyFloat.1y | AI69: QUARTERLY | AM69: Epsilon | AN69: 1e-09
AH70: FrequencyFloat.2y | AI70: QUARTERLY | AM70: MaxLoop | AN70: 1000
C71: MARKETDATAPROPERTIES | F71: LIBORFIXINGS | I71: FRAS | L71: FUTURES | R71: SWAPS | V71: BASISSWAPS | AH71: FrequencyFloat.3y | AI71: QUARTERLY | AM71: ResetLag | AN71: 1
C72: Currency | D72: AUD | F72: Term | G72: Rate | I72: Term | J72: Rate | L72: Term | M72: StartDate | N72: EndDate | O72: Rate | P72: Volatility | R72: Term | S72: Rate | T72: Use | V72: Term | W72: Rate | X72: Use | AH72: interpolation | AI72: FN_LINEARSPLINEINTERPOLATION | AM72: IsEomRoll | AN72: TRUE
C73: CurveType | D73: SWAP | F73: ='AUD CURVE TICKERS'!B47 -> 6M | G73: ='AUD CURVE TICKERS'!J47% -> 0.0211 | I73: ='AUD CURVE TICKERS'!B75 -> 1x7 | J73: ='AUD CURVE TICKERS'!J75% -> 0.02131 | R73: ='AUD CURVE TICKERS'!L75 -> 1Y | S73: ='AUD CURVE TICKERS'!T75% -> 0.02145 | T73: TRUE | AH73: SlidingRule | AI73: MOD_FOLLOWING
C74: CurveIndexFrequency | D74: SEMI-ANNUAL | I74: ='AUD CURVE TICKERS'!B76 -> 2x8 | J74: ='AUD CURVE TICKERS'!J76% -> 0.02129 | R74: ='AUD CURVE TICKERS'!L76 -> 2Y | S74: ='AUD CURVE TICKERS'!T76% -> 0.02247 | T74: TRUE | AH74: IsNewtonraphson | AI74: TRUE
C75: AsOfDate | D75: =Settings.COB -> 43420 | I75: ='AUD CURVE TICKERS'!B77 -> 3x9 | J75: ='AUD CURVE TICKERS'!J77% -> 0.0213 | R75: ='AUD CURVE TICKERS'!L77 -> 3Y | S75: ='AUD CURVE TICKERS'!T77% -> 0.02345 | T75: TRUE | AH75: issimultaneouseq | AI75: TRUE
R76: ='AUD CURVE TICKERS'!L78 -> 4Y | S76: ='AUD CURVE TICKERS'!T78% -> 0.0244 | T76: TRUE | AH76: Epsilon | AI76: 1e-09
R77: ='AUD CURVE TICKERS'!L79 -> 5Y | S77: ='AUD CURVE TICKERS'!T79% -> 0.0253125 | T77: TRUE | AH77: MaxLoop | AI77: 1000
R78: ='AUD CURVE TICKERS'!L80 -> 6Y | S78: ='AUD CURVE TICKERS'!T80% -> 0.0261625 | T78: TRUE | AH78: ResetLag | AI78: 1
C79: Create Market Data Handle | R79: ='AUD CURVE TICKERS'!L81 -> 7Y | S79: ='AUD CURVE TICKERS'!T81% -> 0.026925 | T79: TRUE | AH79: BaseFrequencyFloat | AI79: QUARTERLY
C80: Handle Name | D80: AUD_SWAP_6ML_CURVE_MARKETDATA | R80: ='AUD CURVE TICKERS'!L82 -> 8Y | S80: ='AUD CURVE TICKERS'!T82% -> 0.0276 | T80: TRUE | AH80: IsEomRoll | AI80: TRUE
C81: Market Data Handle | D81: =_xll.meLWOCurveMarketDataCreate(D80,C71,C72:D77,F71,F73:G77,I71,I73:J98,L71,L73:P98,R71,R73:T98,V71,V73:X98) -> AUD_SWAP_6ML_CURVE_MARKETDATA@66:3 | R81: ='AUD CURVE TICKERS'!L83 -> 9Y | S81: ='AUD CURVE TICKERS'!T83% -> 0.0281875 | T81: TRUE
R82: ='AUD CURVE TICKERS'!L84 -> 10Y | S82: ='AUD CURVE TICKERS'!T84% -> 0.0287125 | T82: TRUE
R83: ='AUD CURVE TICKERS'!L85 -> 12Y | S83: ='AUD CURVE TICKERS'!T85% -> 0.0296375 | T83: TRUE | AH83: BASISSWAPS | AM83: BASISSWAPS
R84: ='AUD CURVE TICKERS'!L86 -> 15Y | S84: ='AUD CURVE TICKERS'!T86% -> 0.0305875 | T84: TRUE | AH84: IsLeg1Spread | AI84: FALSE
R85: ='AUD CURVE TICKERS'!L87 -> 20Y | S85: ='AUD CURVE TICKERS'!T87% -> 0.0312625 | T85: TRUE | AH85: Leg1cashlet.calendar | AI85: SYB:LnB
R86: ='AUD CURVE TICKERS'!L88 -> 25Y | S86: ='AUD CURVE TICKERS'!T88% -> 0.0313625 | T86: TRUE | AH86: Leg1cashlet.daycount | AI86: ACT/365
C87: Curve Dictionary | R87: ='AUD CURVE TICKERS'!L89 -> 30Y | S87: ='AUD CURVE TICKERS'!T89% -> 0.0310375 | T87: TRUE | AH87: Leg1cashlet.frequency | AI87: Semi-Annual
C88: Handle Name | D88: AUD_SWAP_6M_CURVE | R88: 40Y | S88: =S87 -> 0.0310375 | T88: TRUE | U88: Extrapolation | AH88: Leg1cashlet.slidingrule | AI88: MOD_FOLLOWING
C89: Curve Generator | D89: =$AN$6 -> AUD_6ML_CURVE_GENERATOR@2:3 | R89: 50Y | S89: =S88 -> 0.0310375 | T89: TRUE | U89: Extrapolation | AH89: Leg1cashlet.spotlag | AI89: 1
C90: Domestic Curve Collection | D90: AUDYC | AH90: Leg1discount | AI90: OIS
C91: Foreign Curve Collection | AH91: Leg1forecast | AI91: STD
AH92: Leg1index.accessary | AI92: 6M
AH93: Leg1index.daycount | AI93: ACT/365
C94: Curve Build | AH94: Leg1index.fixing.calendar | AI94: SYB:LnB
C95: Handle Name | D95: {=IF($D$65,_xll.meLWOCurveCalibrate(D88,D89,D81,D90),"#Error: Dependency Curve not Built")} -> AUD_SWAP_6M_CURVE@67:3 | AH95: Leg1index.frequency | AI95: Simple
C96: Curve Collection | D96: AUDYC | AH96: Leg1index.payment.calendar | AI96: SYB
C97: Curve Index | D97: AUD6ML | AH97: Leg1index.resetlag | AI97: 1
C98: Calibration Time Taken | D98: 0.00600 sec | AH98: Leg1index.slidingrule | AI98: MOD_FOLLOWING
C99: Curve Loaded | D99: =LEFT(D95,3)=LEFT(D95,3) -> TRUE | AH99: Leg2cashlet.calendar | AI99: SYB:LnB
AH100: Leg2cashlet.daycount | AI100: ACT/365
AH101: Leg2cashlet.frequency | AI101: Quarterly
AH102: Leg2cashlet.slidingrule | AI102: MOD_FOLLOWING
...

Sheet AUD REPRICING
B2: Trade Dates | E2: SWAPS: AUDOIS
C3: Unadjusted
B4: EffectiveDate | C4: MaturityDate | E4: EffectiveDate | F4: Maturity | G4: Generator | H4: PayRec | I4: Notional | J4: FixedRate | K4: Spread | M4: CreateSwap | N4: CurveCollection | O4: ParRate | P4: Curve | Q4: +/- (Bps)
B5: =_xll.meDateFromTenor(Settings.COB,E5,"MOD_FOLLOWING","SYB:LNB","") -> 43423 | C5: =_xll.meDateFromTenor(B5,F5,) -> 43430 | E5: 1D | F5: 1W | G5: AUD_OIS | H5: PAY | I5: 1000000 | J5: 0.01 | K5: 0 | L5: 1 | M5: =_xll.meLWOSwapCreateFromGenerator("AUDOIS"&L5,G5,H5,I5,B5,C5,J5,K5,,,,,Settings.AllowCalibrationUpdates) -> AUDOIS1@15:0 | N5: AUDYC | O5: =_xll.meLWOSwapParRate(M5,N5) -> 0.015 | P5: ='AUD CURVE'!G7 -> 0.015 | Q5: =(O5-P5)*10000 -> -1.0533383e-07
B6: =_xll.meDateFromTenor(Settings.COB,E6,"MOD_FOLLOWING","SYB:LNB","") -> 43423 | C6: =_xll.meDateFromTenor(B6,F6,) -> 43453 | E6: 1D | F6: 1M | G6: AUD_OIS | H6: PAY | I6: 1000000 | J6: 0.01 | K6: 0 | L6: 2 | M6: =_xll.meLWOSwapCreateFromGenerator("AUDOIS"&L6,G6,H6,I6,B6,C6,J6,K6,,,,,Settings.AllowCalibrationUpdates) -> AUDOIS2@27:0 | N6: AUDYC | O6: =_xll.meLWOSwapParRate(M6,N6) -> 0.015 | P6: ='AUD CURVE'!G8 -> 0.015 | Q6: =(O6-P6)*10000 -> -8.2899486e-08
B7: =_xll.meDateFromTenor(Settings.COB,E7,"MOD_FOLLOWING","SYB:LNB","") -> 43423 | C7: =_xll.meDateFromTenor(B7,F7,) -> 43484 | E7: 1D | F7: 2M | G7: AUD_OIS | H7: PAY | I7: 1000000 | J7: 0.01 | K7: 0 | L7: 3 | M7: =_xll.meLWOSwapCreateFromGenerator("AUDOIS"&L7,G7,H7,I7,B7,C7,J7,K7,,,,,Settings.AllowCalibrationUpdates) -> AUDOIS3@12:0 | N7: AUDYC | O7: =_xll.meLWOSwapParRate(M7,N7) -> 0.015 | P7: ='AUD CURVE'!G9 -> 0.015 | Q7: =(O7-P7)*10000 -> -5.9754892e-08
B8: =_xll.meDateFromTenor(Settings.COB,E8,"MOD_FOLLOWING","SYB:LNB","") -> 43423 | C8: =_xll.meDateFromTenor(B8,F8,) -> 43515 | E8: 1D | F8: 3M | G8: AUD_OIS | H8: PAY | I8: 1000000 | J8: 0.01 | K8: 0 | L8: 4 | M8: =_xll.meLWOSwapCreateFromGenerator("AUDOIS"&L8,G8,H8,I8,B8,C8,J8,K8,,,,,Settings.AllowCalibrationUpdates) -> AUDOIS4@25:0 | N8: AUDYC | O8: =_xll.meLWOSwapParRate(M8,N8) -> 0.015005 | P8: ='AUD CURVE'!G10 -> 0.015005 | Q8: =(O8-P8)*10000 -> -2.4258217e-08
B9: =_xll.meDateFromTenor(Settings.COB,E9,"MOD_FOLLOWING","SYB:LNB","") -> 43423 | C9: =_xll.meDateFromTenor(B9,F9,) -> 43543 | E9: 1D | F9: 4M | G9: AUD_OIS | H9: PAY | I9: 1000000 | J9: 0.01 | K9: 0 | L9: 5 | M9: =_xll.meLWOSwapCreateFromGenerator("AUDOIS"&L9,G9,H9,I9,B9,C9,J9,K9,,,,,Settings.AllowCalibrationUpdates) -> AUDOIS5@4:0 | N9: AUDYC | O9: =_xll.meLWOSwapParRate(M9,N9) -> 0.01502 | P9: ='AUD CURVE'!G11 -> 0.01502 | Q9: =(O9-P9)*10000 -> 7.4772202e-08
B10: =_xll.meDateFromTenor(Settings.COB,E10,"MOD_FOLLOWING","SYB:LNB","") -> 43423 | C10: =_xll.meDateFromTenor(B10,F10,) -> 43574 | E10: 1D | F10: 5M | G10: AUD_OIS | H10: PAY | I10: 1000000 | J10: 0.01 | K10: 0 | L10: 6 | M10: =_xll.meLWOSwapCreateFromGenerator("AUDOIS"&L10,G10,H10,I10,B10,C10,J10,K10,,,,,Settings.AllowCalibrationUpdates) -> AUDOIS6@29:0 | N10: AUDYC | O10: =_xll.meLWOSwapParRate(M10,N10) -> 0.0150375 | P10: ='AUD CURVE'!G12 -> 0.0150375 | Q10: =(O10-P10)*10000 -> -6.97074e-08
B11: =_xll.meDateFromTenor(Settings.COB,E11,"MOD_FOLLOWING","SYB:LNB","") -> 43423 | C11: =_xll.meDateFromTenor(B11,F11,) -> 43604 | E11: 1D | F11: 6M | G11: AUD_OIS | H11: PAY | I11: 1000000 | J11: 0.01 | K11: 0 | L11: 7 | M11: =_xll.meLWOSwapCreateFromGenerator("AUDOIS"&L11,G11,H11,I11,B11,C11,J11,K11,,,,,Settings.AllowCalibrationUpdates) -> AUDOIS7@3:0 | N11: AUDYC | O11: =_xll.meLWOSwapParRate(M11,N11) -> 0.01508 | P11: ='AUD CURVE'!G13 -> 0.01508 | Q11: =(O11-P11)*10000 -> -1.0074407e-09
B12: =_xll.meDateFromTenor(Settings.COB,E12,"MOD_FOLLOWING","SYB:LNB","") -> 43423 | C12: =_xll.meDateFromTenor(B12,F12,) -> 43696 | E12: 1D | F12: 9M | G12: AUD_OIS | H12: PAY | I12: 1000000 | J12: 0.01 | K12: 0 | L12: 8 | M12: =_xll.meLWOSwapCreateFromGenerator("AUDOIS"&L12,G12,H12,I12,B12,C12,J12,K12,,,,,Settings.AllowCalibrationUpdates) -> AUDOIS8@22:0 | N12: AUDYC | O12: =_xll.meLWOSwapParRate(M12,N12) -> 0.015225 | P12: ='AUD CURVE'!G14 -> 0.015225 | Q12: =(O12-P12)*10000 -> 2.8729987e-08
B13: =_xll.meDateFromTenor(Settings.COB,E13,"MOD_FOLLOWING","SYB:LNB","") -> 43423 | C13: =_xll.meDateFromTenor(B13,F13,) -> 43788 | E13: 1D | F13: 1Y | G13: AUD_OIS | H13: PAY | I13: 1000000 | J13: 0.01 | K13: 0 | L13: 9 | M13: =_xll.meLWOSwapCreateFromGenerator("AUDOIS"&L13,G13,H13,I13,B13,C13,J13,K13,,,,,Settings.AllowCalibrationUpdates) -> AUDOIS9@26:0 | N13: AUDYC | O13: =_xll.meLWOSwapParRate(M13,N13) -> 0.015475 | P13: ='AUD CURVE'!G15 -> 0.015475 | Q13: =(O13-P13)*10000 -> -1.2136124e-07
B14: =_xll.meDateFromTenor(Settings.COB,E14,"MOD_FOLLOWING","SYB:LNB","") -> 43423 | C14: =_xll.meDateFromTenor(B14,F14,) -> 44154 | E14: 1D | F14: 2Y | G14: AUD_OIS | H14: PAY | I14: 1000000 | J14: 0.01 | K14: 0 | L14: 10 | M14: =_xll.meLWOSwapCreateFromGenerator("AUDOIS"&L14,G14,H14,I14,B14,C14,J14,K14,,,,,Settings.AllowCalibrationUpdates) -> AUDOIS10@11:0 | N14: AUDYC | O14: =_xll.meLWOSwapParRate(M14,N14) -> 0.01675 | P14: ='AUD CURVE'!G16 -> 0.01675 | Q14: =(O14-P14)*10000 -> -1.7674414e-07
B17: Trade Dates | E17: SWAPS:AUD3ML/AUD6ML
C18: Unadjusted
B19: EffectiveDate | C19: MaturityDate | E19: EffectiveDate | F19: Maturity | G19: Generator | H19: PayRec | I19: Notional | J19: FixedRate | K19: Spread | M19: CreateSwap | N19: CurveCollection | O19: ParRate | P19: Curve | Q19: +/- (Bps)
B20: =_xll.meDateFromTenor(Settings.COB,E20,"MOD_FOLLOWING","SYB:LNB","") -> 43423 | C20: =_xll.meDateFromTenor(B20,F20,) -> 44154 | E20: 1D | F20: 2Y | G20: AUD_3ML | H20: PAY | I20: 1000000 | J20: 0.01 | K20: 0 | L20: 1 | M20: =_xll.meLWOSwapCreateFromGenerator("AUDIRS"&L20,G20,H20,I20,B20,C20,J20,K20,,,,,Settings.AllowCalibrationUpdates) -> AUDIRS1@6:0 | N20: AUDYC | O20: =_xll.meLWOSwapParRate(M20,N20) -> 0.0208625 | P20: ='AUD CURVE'!S39 -> 0.0208625 | Q20: =(O20-P20)*10000 -> 3.1225023e-13
B21: =_xll.meDateFromTenor(Settings.COB,E21,"MOD_FOLLOWING","SYB:LNB","") -> 43423 | C21: =_xll.meDateFromTenor(B21,F21,) -> 44519 | E21: 1D | F21: 3Y | G21: AUD_3ML | H21: PAY | I21: 1000000 | J21: 0.01 | K21: 0 | L21: 2 | M21: =_xll.meLWOSwapCreateFromGenerator("AUDIRS"&L21,G21,H21,I21,B21,C21,J21,K21,,,,,Settings.AllowCalibrationUpdates) -> AUDIRS2@30:0 | N21: AUDYC | O21: =_xll.meLWOSwapParRate(M21,N21) -> 0.0218875 | P21: ='AUD CURVE'!S40 -> 0.0218875 | Q21: =(O21-P21)*10000 -> -6.9388939e-14
B22: =_xll.meDateFromTenor(Settings.COB,E22,"MOD_FOLLOWING","SYB:LNB","") -> 43423 | C22: =_xll.meDateFromTenor(B22,F22,) -> 43788 | E22: 1D | F22: 1Y | G22: AUD_6ML | H22: PAY | I22: 1000000 | J22: 0.01 | K22: 0 | L22: 3 | M22: =_xll.meLWOSwapCreateFromGenerator("AUDIRS"&L22,G22,H22,I22,B22,C22,J22,K22,,,,,Settings.AllowCalibrationUpdates) -> AUDIRS3@18:0 | N22: AUDYC | O22: =_xll.meLWOSwapParRate(M22,N22) -> 0.02145 | P22: ='AUD CURVE'!S73 -> 0.02145 | Q22: =(O22-P22)*10000 -> 1.700029e-12
B23: =_xll.meDateFromTenor(Settings.COB,E23,"MOD_FOLLOWING","SYB:LNB","") -> 43423 | C23: =_xll.meDateFromTenor(B23,F23,) -> 44154 | E23: 1D | F23: 2Y | G23: AUD_6ML | H23: PAY | I23: 1000000 | J23: 0.01 | K23: 0 | L23: 4 | M23: =_xll.meLWOSwapCreateFromGenerator("AUDIRS"&L23,G23,H23,I23,B23,C23,J23,K23,,,,,Settings.AllowCalibrationUpdates) -> AUDIRS4@13:0 | N23: AUDYC | O23: =_xll.meLWOSwapParRate(M23,N23) -> 0.02247 | P23: ='AUD CURVE'!S74 -> 0.02247 | Q23: =(O23-P23)*10000 -> 4.510281e-13
B24: =_xll.meDateFromTenor(Settings.COB,E24,"MOD_FOLLOWING","SYB:LNB","") -> 43423 | C24: =_xll.meDateFromTenor(B24,F24,) -> 44519 | E24: 1D | F24: 3Y | G24: AUD_6ML | H24: PAY | I24: 1000000 | J24: 0.01 | K24: 0 | L24: 5 | M24: =_xll.meLWOSwapCreateFromGenerator("AUDIRS"&L24,G24,H24,I24,B24,C24,J24,K24,,,,,Settings.AllowCalibrationUpdates) -> AUDIRS5@7:0 | N24: AUDYC | O24: =_xll.meLWOSwapParRate(M24,N24) -> 0.02345 | P24: ='AUD CURVE'!S75 -> 0.02345 | Q24: =(O24-P24)*10000 -> 1.5265567e-12
B25: =_xll.meDateFromTenor(Settings.COB,E25,"MOD_FOLLOWING","SYB:LNB","") -> 43423 | C25: =_xll.meDateFromTenor(B25,F25,) -> 44884 | E25: 1D | F25: 4Y | G25: AUD_6ML | H25: PAY | I25: 1000000 | J25: 0.01 | K25: 0 | L25: 6 | M25: =_xll.meLWOSwapCreateFromGenerator("AUDIRS"&L25,G25,H25,I25,B25,C25,J25,K25,,,,,Settings.AllowCalibrationUpdates) -> AUDIRS6@8:0 | N25: AUDYC | O25: =_xll.meLWOSwapParRate(M25,N25) -> 0.0244 | P25: ='AUD CURVE'!S76 -> 0.0244 | Q25: =(O25-P25)*10000 -> 1.3530843e-12
B26: =_xll.meDateFromTenor(Settings.COB,E26,"MOD_FOLLOWING","SYB:LNB","") -> 43423 | C26: =_xll.meDateFromTenor(B26,F26,) -> 45249 | E26: 1D | F26: 5Y | G26: AUD_6ML | H26: PAY | I26: 1000000 | J26: 0.01 | K26: 0 | L26: 7 | M26: =_xll.meLWOSwapCreateFromGenerator("AUDIRS"&L26,G26,H26,I26,B26,C26,J26,K26,,,,,Settings.AllowCalibrationUpdates) -> AUDIRS7@19:0 | N26: AUDYC | O26: =_xll.meLWOSwapParRate(M26,N26) -> 0.0253125 | P26: ='AUD CURVE'!S77 -> 0.0253125 | Q26: =(O26-P26)*10000 -> 1.7694179e-12
B27: =_xll.meDateFromTenor(Settings.COB,E27,"MOD_FOLLOWING","SYB:LNB","") -> 43423 | C27: =_xll.meDateFromTenor(B27,F27,) -> 45615 | E27: 1D | F27: 6Y | G27: AUD_6ML | H27: PAY | I27: 1000000 | J27: 0.01 | K27: 0 | L27: 8 | M27: =_xll.meLWOSwapCreateFromGenerator("AUDIRS"&L27,G27,H27,I27,B27,C27,J27,K27,,,,,Settings.AllowCalibrationUpdates) -> AUDIRS8@9:0 | N27: AUDYC | O27: =_xll.meLWOSwapParRate(M27,N27) -> 0.0261625 | P27: ='AUD CURVE'!S78 -> 0.0261625 | Q27: =(O27-P27)*10000 -> 1.4571677e-12
B28: =_xll.meDateFromTenor(Settings.COB,E28,"MOD_FOLLOWING","SYB:LNB","") -> 43423 | C28: =_xll.meDateFromTenor(B28,F28,) -> 45980 | E28: 1D | F28: 7Y | G28: AUD_6ML | H28: PAY | I28: 1000000 | J28: 0.01 | K28: 0 | L28: 9 | M28: =_xll.meLWOSwapCreateFromGenerator("AUDIRS"&L28,G28,H28,I28,B28,C28,J28,K28,,,,,Settings.AllowCalibrationUpdates) -> AUDIRS9@28:0 | N28: AUDYC | O28: =_xll.meLWOSwapParRate(M28,N28) -> 0.026925 | P28: ='AUD CURVE'!S79 -> 0.026925 | Q28: =(O28-P28)*10000 -> 1.4571677e-12
B29: =_xll.meDateFromTenor(Settings.COB,E29,"MOD_FOLLOWING","SYB:LNB","") -> 43423 | C29: =_xll.meDateFromTenor(B29,F29,) -> 46345 | E29: 1D | F29: 8Y | G29: AUD_6ML | H29: PAY | I29: 1000000 | J29: 0.01 | K29: 0 | L29: 10 | M29: =_xll.meLWOSwapCreateFromGenerator("AUDIRS"&L29,G29,H29,I29,B29,C29,J29,K29,,,,,Settings.AllowCalibrationUpdates) -> AUDIRS10@16:0 | N29: AUDYC | O29: =_xll.meLWOSwapParRate(M29,N29) -> 0.0276 | P29: ='AUD CURVE'!S80 -> 0.0276 | Q29: =(O29-P29)*10000 -> 1.0408341e-12
B30: =_xll.meDateFromTenor(Settings.COB,E30,"MOD_FOLLOWING","SYB:LNB","") -> 43423 | C30: =_xll.meDateFromTenor(B30,F30,) -> 46710 | E30: 1D | F30: 9Y | G30: AUD_6ML | H30: PAY | I30: 1000000 | J30: 0.01 | K30: 0 | L30: 11 | M30: =_xll.meLWOSwapCreateFromGenerator("AUDIRS"&L30,G30,H30,I30,B30,C30,J30,K30,,,,,Settings.AllowCalibrationUpdates) -> AUDIRS11@17:0 | N30: AUDYC | O30: =_xll.meLWOSwapParRate(M30,N30) -> 0.0281875 | P30: ='AUD CURVE'!S81 -> 0.0281875 | Q30: =(O30-P30)*10000 -> 1.1449175e-12
B31: =_xll.meDateFromTenor(Settings.COB,E31,"MOD_FOLLOWING","SYB:LNB","") -> 43423 | C31: =_xll.meDateFromTenor(B31,F31,) -> 47076 | E31: 1D | F31: 10Y | G31: AUD_6ML | H31: PAY | I31: 1000000 | J31: 0.01 | K31: 0 | L31: 12 | M31: =_xll.meLWOSwapCreateFromGenerator("AUDIRS"&L31,G31,H31,I31,B31,C31,J31,K31,,,,,Settings.AllowCalibrationUpdates) -> AUDIRS12@24:0 | N31: AUDYC | O31: =_xll.meLWOSwapParRate(M31,N31) -> 0.0287125 | P31: ='AUD CURVE'!S82 -> 0.0287125 | Q31: =(O31-P31)*10000 -> 1.0408341e-12
B32: =_xll.meDateFromTenor(Settings.COB,E32,"MOD_FOLLOWING","SYB:LNB","") -> 43423 | C32: =_xll.meDateFromTenor(B32,F32,) -> 47806 | E32: 1D | F32: 12Y | G32: AUD_6ML | H32: PAY | I32: 1000000 | J32: 0.01 | K32: 0 | L32: 13 | M32: =_xll.meLWOSwapCreateFromGenerator("AUDIRS"&L32,G32,H32,I32,B32,C32,J32,K32,,,,,Settings.AllowCalibrationUpdates) -> AUDIRS13@10:0 | N32: AUDYC | O32: =_xll.meLWOSwapParRate(M32,N32) -> 0.0296375 | P32: ='AUD CURVE'!S83 -> 0.0296375 | Q32: =(O32-P32)*10000 -> 1.0755286e-12
B33: =_xll.meDateFromTenor(Settings.COB,E33,"MOD_FOLLOWING","SYB:LNB","") -> 43423 | C33: =_xll.meDateFromTenor(B33,F33,) -> 48902 | E33: 1D | F33: 15Y | G33: AUD_6ML | H33: PAY | I33: 1000000 | J33: 0.01 | K33: 0 | L33: 14 | M33: =_xll.meLWOSwapCreateFromGenerator("AUDIRS"&L33,G33,H33,I33,B33,C33,J33,K33,,,,,Settings.AllowCalibrationUpdates) -> AUDIRS14@23:0 | N33: AUDYC | O33: =_xll.meLWOSwapParRate(M33,N33) -> 0.0305875 | P33: ='AUD CURVE'!S84 -> 0.0305875 | Q33: =(O33-P33)*10000 -> 1.110223e-12
... B36: =_xll.meDateFromTenor(Settings.COB,E36,"MOD_FOLLOWING","SYB:LNB","") -> 43423 | C36: =_xll.meDateFromTenor(B36,F36,) -> 54381 | E36: 1D | F36: 30Y | G36: AUD_6ML | H36: PAY | I36: 1000000 | J36: 0.01 | K36: 0 | L36: 17 | M36: =_xll.meLWOSwapCreateFromGenerator("AUDIRS"&L36,G36,H36,I36,B36,C36,J36,K36,,,,,Settings.AllowCalibrationUpdates) -> AUDIRS17@20:0 | N36: AUDYC | O36: =_xll.meLWOSwapParRate(M36,N36) -> 0.0310375 | P36: ='AUD CURVE'!S87 -> 0.0310375 | Q36: =(O36-P36)*10000 -> 5.8980598e-13

Sheet SYNDICATE AUD IRS
N1: … BENCHMARK LEVEL | Z1: … FIXING INFO
B3: SETTLEMENT DATE | E3: BENCHMARK LEVEL | N3: SWAP
B4: AsOfDay | C4: =Settings.COB -> 43420 | J4: =$C$32 -> MID | N4: Handle Name | O4: AUD_SWAP
B5: ValuationLag | C5: 2D | E5: 3Y Bond Future | F5: Rate | G5: Bid | H5: Ask | I5: Mid | J5: Use | N5: Create Swap | O5: =IF('AUD CURVE'!$D$99,_xll.meLWOSwapCreate(O4,N8:P40),"#LOAD CURVE") -> AUD_SWAP@68:3
B6: BusDayAdjustment | C6: MOD_FOLLOWING | E6: YMA Comdty | F6: =(100-J6)% -> 0.021725 | G6: =_xll.BDP($E$6,$G$5) -> 97.825 | H6: =_xll.BDP($E$6,$H$5) -> 97.83 | I6: =AVERAGE(G6:H6) -> 97.8275 | J6: =IF($J$4="BID",G6,IF($J$4="ASK",H6,I6)) -> 97.8275
B7: Calendar | C7: SYB | J7: =$C$32 -> MID | N7: SWAP | O7: BOND LEG | P7: FUNDING LEG
B8: ValuationDate | C8: =_xll.meDateFromTenor(C4,C5,C6,C7) -> 43424 | E8: 10Y Bond Future | G8: Bid | H8: Ask | I8: Mid | J8: Use | N8: LegType | O8: Leg1:Fixed | P8: Leg2:Float | R8: FULL FIRST RESET RATE
E9: XMA Comdty | F9: =(100-J9)% -> 0.027025 | G9: =_xll.BDP($E$9,$G$5) -> 97.295 | H9: =_xll.BDP($E$9,$H$5) -> 97.3 | I9: =AVERAGE(G9:H9) -> 97.2975 | J9: =IF($J$7="BID",G9,IF($J$7="ASK",H9,I9)) -> 97.2975 | N9: Notional | O9: =$C$12 -> 1000000 | P9: =$C$12 -> 1000000 | R9: =IF(COUNT(T16)=1,T16%,"#ERROR: BBG DATA") -> 0.0193
B10: BOND SPECIFICATION | N10: NotionalExchange | O10: START_AND_END | P10: START_AND_END
B11: BondIdentifier | C11: MYNEWBOND | E11: Exchange for Physical, EFP | J11: =$C$32 -> MID | N11: PayReceive | O11: PAY | P11: RECEIVE | R11: FRONT STUB RATE | T11: RESET LOOKUP
B12: FaceValue | C12: 1000000 | E12: Tenor | F12: Ticker | G12: Bid | H12: Ask | I12: Mid | J12: Use | K12: SWP Q | L12: SWP S | N12: ForecastCurve | P12: =IF(P24="QUARTERLY","AUD3ML","AUD6ML") -> AUD3ML | R12: =IF(U22<C4,"RESET REQUIRED",IF('AUD CURVE'!$D$99,_xll.meProductSwapStubRate($X$22:$X$24,$Y$22:$Y$24,,$T$22:$U$34),"#LOAD CURVE")) -> 0.0193 | T12: =IF(P24="QUARTERLY",X40,X41) -> ADBB3M Curncy
B13: BondAccrualFrequency | C13: SEMI-ANNUAL | E13: 1Y | F13: ADSF1Q WBCA Curncy | G13: =_xll.BDP($F13,$G$12) -> -17.75 | H13: =_xll.BDP($F13,$H$12) -> -17.75 | I13: =AVERAGE(G13:H13) -> -17.75 | J13: =IF($J$11="BID",G13,IF($J$11="ASK",H13,I13)) -> -17.75 | K13: =IF(COUNT($F$6,J13)=2,$F$6+J13/10000,"#WAIT: BBG") -> 0.01995 | L13: =IF(COUNT(K13,J31)=2,K13+J31/10000,"#WAIT: BBG") -> 0.0215625 | N13: DiscountCurve | O13: AUDOIS | P13: AUDOIS | T13: PX_ASK
B14: BondPaymentFrequency | C14: SEMI-ANNUAL | E14: 2Y | F14: ADSF2Q IAUS Curncy | G14: =_xll.BDP($F14,$G$12) -> -9.625 | H14: =_xll.BDP($F14,$H$12) -> -4.625 | I14: =AVERAGE(G14:H14) -> -7.125 | J14: =IF($J$11="BID",G14,IF($J$11="ASK",H14,I14)) -> -7.125 | K14: =IF(COUNT($F$6,J14)=2,$F$6+J14/10000,"#WAIT: BBG") -> 0.0210125 | L14: =IF(COUNT(K14,J32)=2,K14+J32/10000,"#WAIT: BBG") -> 0.022575 | N14: Currency | O14: AUD | P14: AUD | T14: 2D
B15: Daycount | C15: ACT/ACT | E15: 3Y | F15: ADSF3Q IAUS Curncy | G15: =_xll.BDP($F15,$G$12) -> 1.125 | H15: =_xll.BDP($F15,$H$12) -> 5.125 | I15: =AVERAGE(G15:H15) -> 3.125 | J15: =IF($J$11="BID",G15,IF($J$11="ASK",H15,I15)) -> 3.125 | K15: =IF(COUNT($F$6,J15)=2,$F$6+J15/10000,"#WAIT: BBG") -> 0.0220375 | L15: =IF(COUNT(K15,J33)=2,K15+J33/10000,"#WAIT: BBG") -> 0.02355 | N15: Leverage | O15: 1 | P15: 1 | T15: =_xll.meDateFromTenor(P22,"-"&T14,"MOD_FOLLOWING","LNB:SYB") -> 43420
B16: ForwardStartTenor | E16: 4Y | F16: ADSF4 IAUS Curncy | G16: =_xll.BDP($F16,$G$12) -> 25.75 | H16: =_xll.BDP($F16,$H$12) -> 30.75 | I16: =AVERAGE(G16:H16) -> 28.25 | J16: =IF($J$11="BID",G16,IF($J$11="ASK",H16,I16)) -> 28.25 | K16: =IF(COUNT($F$6,J16)=2,$F$6+J16/10000,"#WAIT: BBG") -> 0.02455 | L16: =IF(COUNT(K16,J34)=2,K16+J34/10000,"#WAIT: BBG") -> 0.02605 | N16: FixedRate | O16: 0 | T16: =_xll.BDH(T12,T13,T15,T15) -> 1.93
B17: AccrualStartDate | C17: =IF(ISBLANK($C$16),C8,_xll.meDateFromTenor(Settings.COB,$C$16,$C$6,$C$7)) -> 43424 | E17: 5Y | F17: ADSF5 IAUS Curncy | G17: =_xll.BDP($F17,$G$12) -> 34.875 | H17: =_xll.BDP($F17,$H$12) -> 39.875 | I17: =AVERAGE(G17:H17) -> 37.375 | J17: =IF($J$11="BID",G17,IF($J$11="ASK",H17,I17)) -> 37.375 | K17: =IF(COUNT($F$6,J17)=2,$F$6+J17/10000,"#WAIT: BBG") -> 0.0254625 | L17: =IF(COUNT(K17,J35)=2,K17+J35/10000,"#WAIT: BBG") -> 0.0269375 | N17: FirstStubCurveIndex | P17: NATURAL
B18: MaturityOrTenor | C18: 10Y | E18: 6Y | F18: ADSF6 IAUS Curncy | G18: =_xll.BDP($F18,$G$12) -> -9.625 | H18: =_xll.BDP($F18,$H$12) -> -4.625 | I18: =AVERAGE(G18:H18) -> -7.125 | J18: =IF($J$11="BID",G18,IF($J$11="ASK",H18,I18)) -> -7.125 | K18: =IF(COUNT($F$6,J18)=2,$F$6+J18/10000,"#WAIT: BBG") -> 0.0210125 | L18: =IF(COUNT(K18,J36)=2,K18+J36/10000,"#WAIT: BBG") -> 0.0224375 | N18: LastStubCurveIndex | P18: NATURAL | R18: FIRST FLOAT RESET
E19: 7Y | F19: ADSF7 IAUS Curncy | G19: =_xll.BDP($F19,$G$12) -> -2 | H19: =_xll.BDP($F19,$H$12) -> 3 | I19: =AVERAGE(G19:H19) -> 0.5 | J19: =IF($J$11="BID",G19,IF($J$11="ASK",H19,I19)) -> 0.5 | K19: =IF(COUNT(L19,J37)=2,L19-J37/10000,"#WAIT: BBG") -> 0.0257 | L19: =IF(COUNT($F$9,J19)=2,$F$9+J19/10000,"#WAIT: BBG") -> 0.027075 | N19: FirstFixing | P19: =IF(ISBLANK($R$19),"",$R$19) -> 0.0193 | R19: =IF(ISBLANK($R$22),IF($C$23,$R$9,$R$12),$R$22) -> 0.0193
B20: SWAP SPECIFICATION | E20: 8Y | F20: ADSF8 IAUS Curncy | G20: =_xll.BDP($F20,$G$12) -> 4.75 | H20: =_xll.BDP($F20,$H$12) -> 9.75 | I20: =AVERAGE(G20:H20) -> 7.25 | J20: =IF($J$11="BID",G20,IF($J$11="ASK",H20,I20)) -> 7.25 | K20: =IF(COUNT(L20,J38)=2,L20-J38/10000,"#WAIT: BBG") -> 0.0264375 | L20: =IF(COUNT($F$9,J20)=2,$F$9+J20/10000,"#WAIT: BBG") -> 0.02775 | N20: LastFixing
B21: FundingAccrualFrequency | C21: QUARTERLY | E21: 9Y | F21: ADSF9 IAUS Curncy | G21: =_xll.BDP($F21,$G$12) -> 10.625 | H21: =_xll.BDP($F21,$H$12) -> 15.625 | I21: =AVERAGE(G21:H21) -> 13.125 | J21: =IF($J$11="BID",G21,IF($J$11="ASK",H21,I21)) -> 13.125 | K21: =IF(COUNT(L21,J39)=2,L21-J39/10000,"#WAIT: BBG") -> 0.027075 | L21: =IF(COUNT($F$9,J21)=2,$F$9+J21/10000,"#WAIT: BBG") -> 0.0283375 | N21: FloatSpread | P21: =$C$36 -> 90 | R21: OVERRIDE | T21: STUB RATE FLOAT LEG LVB | X21: CurveIndex | Y21: Tenor
B22: FundingPaymentFrequency | C22: SEMI-ANNUAL | E22: 10Y | F22: ADSF10 IAUS Curncy | G22: =_xll.BDP($F22,$G$12) -> 15.875 | H22: =_xll.BDP($F22,$H$12) -> 20.875 | I22: =AVERAGE(G22:H22) -> 18.375 | J22: =IF($J$11="BID",G22,IF($J$11="ASK",H22,I22)) -> 18.375 | K22: =IF(COUNT(L22,J40)=2,L22-J40/10000,"#WAIT: BBG") -> 0.0276625 | L22: =IF(COUNT($F$9,J22)=2,$F$9+J22/10000,"#WAIT: BBG") -> 0.0288625 | N22: EffectiveDate | O22: =C17 -> 43424 | P22: =$C$17 -> 43424 | T22: EffectiveDate | U22: =P22 -> 43424 | X22: AUDDF | Y22: 1D
B23: IncludeAccrued * | C23: TRUE | E23: 12Y | F23: ADSF12 IAUS Curncy | G23: =_xll.BDP($F23,$G$12) -> 24.625 | H23: =_xll.BDP($F23,$H$12) -> 30.625 | I23: =AVERAGE(G23:H23) -> 27.625 | J23: =IF($J$11="BID",G23,IF($J$11="ASK",H23,I23)) -> 27.625 | K23: =IF(COUNT(L23,J41)=2,L23-J41/10000,"#WAIT: BBG") -> 0.0286875 | L23: =IF(COUNT($F$9,J23)=2,$F$9+J23/10000,"#WAIT: BBG") -> 0.0297875 | N23: MaturityDate | O23: =$C$18 -> 10Y | P23: =$C$18 -> 10Y | T23: MaturityDate | U23: =P23 -> 10Y | X23: AUD3ML | Y23: 3M
B24: * Funding Leg: TRUE = Full First Float Coupon | E24: 15Y | F24: ADSF15 IAUS Curncy | G24: =_xll.BDP($F24,$G$12) -> 34.125 | H24: =_xll.BDP($F24,$H$12) -> 40.125 | I24: =AVERAGE(G24:H24) -> 37.125 | J24: =IF($J$11="BID",G24,IF($J$11="ASK",H24,I24)) -> 37.125 | K24: =IF(COUNT(L24,J42)=2,L24-J42/10000,"#WAIT: BBG") -> 0.0296875 | L24: =IF(COUNT($F$9,J24)=2,$F$9+J24/10000,"#WAIT: BBG") -> 0.0307375 | N24: AccrualFrequency | O24: =$C$13 -> SEMI-ANNUAL | P24: =$C$21 -> QUARTERLY | T24: CurveCollection | U24: =$C$29 -> AUDYC | X24: AUD6ML | Y24: 6M
E25: 20Y | F25: ADSF20 IAUS Curncy | G25: =_xll.BDP($F25,$G$12) -> 40.875 | H25: =_xll.BDP($F25,$H$12) -> 46.875 | I25: =AVERAGE(G25:H25) -> 43.875 | J25: =IF($J$11="BID",G25,IF($J$11="ASK",H25,I25)) -> 43.875 | K25: =IF(COUNT(L25,J43)=2,L25-J43/10000,"#WAIT: BBG") -> 0.030375 | L25: =IF(COUNT($F$9,J25)=2,$F$9+J25/10000,"#WAIT: BBG") -> 0.0314125 | N25: PaymentFrequency | O25: =$C$14 -> SEMI-ANNUAL | P25: =$C$22 -> SEMI-ANNUAL | T25: UseCurveIndex | U25: =P17 -> NATURAL
E26: 25Y | F26: ADSF25 IAUS Curncy | G26: =_xll.BDP($F26,$G$12) -> 41.875 | H26: =_xll.BDP($F26,$H$12) -> 47.875 | I26: =AVERAGE(G26:H26) -> 44.875 | J26: =IF($J$11="BID",G26,IF($J$11="ASK",H26,I26)) -> 44.875 | K26: =IF(COUNT(L26,J44)=2,L26-J44/10000,"#WAIT: BBG") -> 0.03045 | L26: =IF(COUNT($F$9,J26)=2,$F$9+J26/10000,"#WAIT: BBG") -> 0.0315125 | N26: Daycount | O26: =$C$15 -> ACT/ACT | P26: ACT/365 | T26: FloatFrequency | U26: =P24 -> QUARTERLY
B27: VALUATION SETTINGS | E27: 30Y | F27: ADSF30 IAUS Curncy | G27: =_xll.BDP($F27,$G$12) -> 38.625 | H27: =_xll.BDP($F27,$H$12) -> 44.625 | I27: =AVERAGE(G27:H27) -> 41.625 | J27: =IF($J$11="BID",G27,IF($J$11="ASK",H27,I27)) -> 41.625 | K27: =IF(COUNT(L27,J45)=2,L27-J45/10000,"#WAIT: BBG") -> 0.030125 | L27: =IF(COUNT($F$9,J27)=2,$F$9+J27/10000,"#WAIT: BBG") -> 0.0311875 | N27: FixingBusinessDayAdjustment | P27: MOD_FOLLOWING | T27: FloatDaycount | U27: =P26 -> ACT/365
B28: ValuationDate | C28: =C8 -> 43424 | N28: FixingCalendar | P28: SYB | T28: FloatBusinessDayAdjustment | U28: =P29 -> MOD_FOLLOWING
B29: CurveCollection | C29: AUDYC | E29: Tenor Basis 3M vs 6M | J29: =$C$32 -> MID | N29: AccrualBusinessDayAdjustment | O29: MOD_FOLLOWING | P29: MOD_FOLLOWING | T29: FloatCalendar | U29: =P28 -> SYB
E30: Tenor | F30: Ticker | G30: Bid | H30: Ask | I30: Mid | J30: Use | N30: AccrualCalendar | O30: SYB | P30: SYB | T30: FloatRollDay
B31: PRICING INPUTS | E31: 1Y | F31: ADBBCF1 IAUS Curncy | G31: =_xll.BDP($F31,G$30) -> 15.125 | H31: =_xll.BDP($F31,H$30) -> 17.125 | I31: =AVERAGE(G31:H31) -> 16.125 | J31: =IF($J$29="BID",G31,IF($J$29="ASK",H31,I31)) -> 16.125 | N31: PaymentBusinessDayAdjustment | O31: MOD_FOLLOWING | P31: MOD_FOLLOWING | T31: FloatFixingLag | U31: 2D
B32: Benchmark Side | C32: MID | E32: 2Y | F32: ADBBCF2 IAUS Curncy | G32: =_xll.BDP($F32,G$30) -> 14.625 | H32: =_xll.BDP($F32,H$30) -> 16.625 | I32: =AVERAGE(G32:H32) -> 15.625 | J32: =IF($J$29="BID",G32,IF($J$29="ASK",H32,I32)) -> 15.625 | N32: PaymentCalendar | O32: SYB | P32: SYB | T32: FloatFirstStubDate | U32: =IF(ISBLANK($P$33),"",$P$33)
B33: Benchmark Tenor | C33: 10Y | E33: 3Y | F33: ADBBCF3 IAUS Curncy | G33: =_xll.BDP($F33,G$30) -> 14.125 | H33: =_xll.BDP($F33,H$30) -> 16.125 | I33: =AVERAGE(G33:H33) -> 15.125 | J33: =IF($J$29="BID",G33,IF($J$29="ASK",H33,I33)) -> 15.125 | N33: FirstStubDate | T33: FloatLastStubDate | U33: =IF(ISBLANK($P$34),"",$P$34)
B34: Benchmark Level (%) | C34: =IF(ISNUMBER(C35),C35,VLOOKUP($C$33,$E$13:$L$27,IF($C$13="QUARTERLY",7,8),FALSE)) -> 0.0288625 | E34: 4Y | F34: ADBBCF4 IAUS Curncy | G34: =_xll.BDP($F34,G$30) -> 14 | H34: =_xll.BDP($F34,H$30) -> 16 | I34: =AVERAGE(G34:H34) -> 15 | J34: =IF($J$29="BID",G34,IF($J$29="ASK",H34,I34)) -> 15 | N34: LastStubDate | T34: FloatStubType | U34: =IF(ISBLANK(P40),"",P40) -> SHORTSTART
B35: Override Benchmark (%) | E35: 5Y | F35: ADBBCF5 IAUS Curncy | G35: =_xll.BDP($F35,G$30) -> 13.75 | H35: =_xll.BDP($F35,H$30) -> 15.75 | I35: =AVERAGE(G35:H35) -> 14.75 | J35: =IF($J$29="BID",G35,IF($J$29="ASK",H35,I35)) -> 14.75 | N35: RollDay
B36: Credit Spread (bps) | C36: 90 | E36: 6Y | F36: ADBBCF6 IAUS Curncy | G36: =_xll.BDP($F36,G$30) -> 13.25 | H36: =_xll.BDP($F36,H$30) -> 15.25 | I36: =AVERAGE(G36:H36) -> 14.25 | J36: =IF($J$29="BID",G36,IF($J$29="ASK",H36,I36)) -> 14.25 | N36: FixingLag | P36: 0D | T36: STUB RATE TABLE | X36: STUB TICKERS
B37: New Issue Yield Approx (%) | C37: =IF(ISNUMBER($C$35),$C$35,$C$34+$C$36/10000) -> 0.0378625 | E37: 7Y | F37: ADBBCF7 IAUS Curncy | G37: =_xll.BDP($F37,G$30) -> 12.75 | H37: =_xll.BDP($F37,H$30) -> 14.75 | I37: =AVERAGE(G37:H37) -> 13.75 | J37: =IF($J$29="BID",G37,IF($J$29="ASK",H37,I37)) -> 13.75 | N37: FirstFixingLag | T37: Tenor | U37: CurveIndex | V37: ResetRate | X37: BloombergTicker | Y37: Field
E38: 8Y | F38: ADBBCF8 IAUS Curncy | G38: =_xll.BDP($F38,G$30) -> 12.125 | H38: =_xll.BDP($F38,H$30) -> 14.125 | I38: =AVERAGE(G38:H38) -> 13.125 | J38: =IF($J$29="BID",G38,IF($J$29="ASK",H38,I38)) -> 13.125 | N38: PaymentLag | O38: 0D | P38: 0D | T38: 1D | U38: AUDOIS | V38: =_xll.BDP(X38,Y38)% -> 0.015 | X38: RBACOR Index | Y38: PX_LAST
B39: RESULT | E39: 9Y | F39: ADBBCF9 IAUS Curncy | G39: =_xll.BDP($F39,G$30) -> 11.625 | H39: =_xll.BDP($F39,H$30) -> 13.625 | I39: =AVERAGE(G39:H39) -> 12.625 | J39: =IF($J$29="BID",G39,IF($J$29="ASK",H39,I39)) -> 12.625 | N39: CompoundMethod | P39: FLAT | T39: 1M | U39: AUD1ML | V39: =_xll.BDP(X39,Y39)% -> 0.0186 | X39: ADBB1M Curncy | Y39: PX_ASK
B40: ParRate (%) | C40: =_xll.meLWOSwapParRate(O5,B28:C29) -> 0.036585113 | E40: 10Y | F40: ADBBCF10 IAUS Curncy | G40: =_xll.BDP($F40,G$30) -> 11 | H40: =_xll.BDP($F40,H$30) -> 13 | I40: =AVERAGE(G40:H40) -> 12 | J40: =IF($J$29="BID",G40,IF($J$29="ASK",H40,I40)) -> 12 | N40: StubType | O40: SHORTSTART | P40: SHORTSTART | T40: 3M | U40: AUD3ML | V40: =_xll.BDP(X40,Y40)% -> 0.0193 | X40: ADBB3M Curncy | Y40: PX_ASK
E41: 12Y | F41: ADBBCF12 IAUS Curncy | G41: =_xll.BDP($F41,G$30) -> 9.5 | H41: =_xll.BDP($F41,H$30) -> 12.5 | I41: =AVERAGE(G41:H41) -> 11 | J41: =IF($J$29="BID",G41,IF($J$29="ASK",H41,I41)) -> 11 | T41: 6M | U41: AUD6ML | V41: =_xll.BDP(X41,Y41)% -> 0.0211 | X41: ADBB6M Curncy | Y41: PX_ASK
E42: 15Y | F42: ADBBCF15 IAUS Curncy | G42: =_xll.BDP($F42,G$30) -> 9 | H42: =_xll.BDP($F42,H$30) -> 12 | I42: =AVERAGE(G42:H42) -> 10.5 | J42: =IF($J$29="BID",G42,IF($J$29="ASK",H42,I42)) -> 10.5 | T42: 12M | U42: AUD12ML | V42: =_xll.BDP(X42,Y42)% -> 0.0215 | X42: ADBB12M Curncy | Y42: PX_ASK
E43: 20Y | F43: ADBBCF20 IAUS Curncy | G43: =_xll.BDP($F43,G$30) -> 8.875 | H43: =_xll.BDP($F43,H$30) -> 11.875 | I43: =AVERAGE(G43:H43) -> 10.375 | J43: =IF($J$29="BID",G43,IF($J$29="ASK",H43,I43)) -> 10.375
E44: 25Y | F44: ADBBCF25 IAUS Curncy | G44: =_xll.BDP($F44,G$30) -> 9.125 | H44: =_xll.BDP($F44,H$30) -> 12.125 | I44: =AVERAGE(G44:H44) -> 10.625 | J44: =IF($J$29="BID",G44,IF($J$29="ASK",H44,I44)) -> 10.625
E45: 30Y | F45: ADBBCF30 IAUS Curncy | G45: =_xll.BDP($F45,G$30) -> 9.125 | H45: =_xll.BDP($F45,H$30) -> 12.125 | I45: =AVERAGE(G45:H45) -> 10.625 | J45: =IF($J$29="BID",G45,IF($J$29="ASK",H45,I45)) -> 10.625

Sheet TAP AUD ASW
T1: … FIXING INFO
B2: SETTLEMENT DATE | E2: BOND | H2: ASSET SWAP
B3: AsOfDate | C3: =Settings.COB -> 43420 | E3: Handle Name | F3: =F10 -> AU3CB0250215 | H3: Handle Name | I3: AUD_ASSET_SWAP
B4: SettlementLag | C4: 2D | E4: Create Bond | F4: =IF('AUD CURVE'!$D$99,_xll.meLWOBondCreateFromLVB(F3,E7:F33),"#LOAD Curve") -> AU3CB0250215@69:4 | H4: Create Asset Swap | I4: =IF('AUD CURVE'!$D$99,_xll.meLWOSwapCreate(I3,H7:J47),"#LOAD Curve") -> AUD_ASSET_SWAP@70:4
B5: BusDayAdjustment | C5: MOD_FOLLOWING
B6: Calendar | C6: SYB | E6: BOND SPECIFICATION | H6: ASSET SWAP | I6: BOND LEG | J6: FUNDING LEG
B7: SettlementDate | C7: =_xll.meDateFromTenor(C3,C4,C5,C6) -> 43424 | E7: BondDescription | F7: =C12 -> AU3CB0250215 Corp | H7: LegType | I7: Leg1:FixedBond | J7: Leg2:Float | L7: FULL FIRST RESET RATE
E8: BondType | F8: FIXED | H8: Notional | I8: =F16 -> 1000000 | J8: =F16 -> 1000000 | L8: =IF(COUNT(N15)=1,N15%,"#ERROR: BBG DATA") -> 0.020288
B9: PRICING PARAMETERS | E9: Currency | F9: AUD | H9: NotionalExchange | I9: NONE | J9: =I9 -> NONE
B10: Side: Bid/Ask | C10: MID | E10: ISIN | F10: =LEFT(C12,12) -> AU3CB0250215 | H10: PayReceive | I10: PAY | J10: RECEIVE | L10: FRONT STUB RATE | N10: RESET LOOKUP
B11: Type: Govt/Corp | C11: GOVT | E11: YieldType | F11: YIELD-TO-MATURITY | H11: ForecastCurve | J11: =IF(J23="QUARTERLY","AUD3ML","AUD6ML") -> AUD3ML | L11: =IF($O$21<$C$3,"RESET REQUIRED",IF('AUD CURVE'!$D$99,_xll.meProductSwapStubRate($R$21:$R$23,$S$21:$S$23,,$N$21:$O$33),"#LOAD CURVE")) -> RESET REQUIRED | N11: =IF(J23="QUARTERLY",R40,R41) -> ADBB3M Curncy
B12: Bloomberg ID | C12: AU3CB0250215 Corp | E12: IsCleanPrice | F12: =$C$15="CLEAN" -> TRUE | H12: DiscountCurve | I12: AUDOIS | J12: AUDOIS | N12: PX_ASK
B13: Bloomberg Yield | C13: =IF($C$14="",_xll.BDP($C$12,"YAS_BOND_YLD"),$C$14) -> 3.264769 | E13: BondQuoteConvention | F13: QUOTE_TO_3_DECIMAL_PLACES | H13: Currency | I13: AUD | J13: AUD | N13: 2D
B14: Yield Override | E14: PayReceive | F14: RECEIVE | H14: Leverage | I14: 1 | J14: 1 | N14: =_xll.meDateFromTenor(J21,"-"&N13,"MOD_FOLLOWING","LNB:SYB") -> 43294
B15: BondQuoteCleanOrDirty | C15: CLEAN | E15: NotionalExchange | F15: START_AND_END | H15: FixedRate | I15: =F22 -> 0.0345 | N15: =_xll.BDH(N11,N12,N14,N14) -> 2.0288
B16: BondFrequency | C16: SEMI-ANNUAL | E16: FaceValue | F16: 1000000 | H16: FirstStubCurveIndex | J16: NATURAL
B17: BondDaycount | C17: ACT/ACT | E17: IssueDate | F17: =VALUE(_xll.BDP($C$12,"ISSUE_DT")) -> 43125 | H17: LastStubCurveIndex | J17: NATURAL | L17: FIRST FLOAT RESET
B18: FundingAccrualFrequency | C18: QUARTERLY | E18: AccrualStartDate | F18: =VALUE(_xll.BDP($C$12,"START_ACC_DT")) -> 43117 | H18: FirstFixing | J18: =IF(ISBLANK($L$18),"",$L$18) -> 0.020288 | L18: =IF(ISBLANK($L$21),IF($C$20,$L$8,$L$11),$L$21) -> 0.020288
B19: FundingPaymentFrequency | C19: QUARTERLY | E19: FirstCouponDate | F19: =VALUE(_xll.BDP($C$12,"FIRST_CPN_DT")) -> 43298 | H19: LastFixing
B20: FundingIncludeAccrued * | C20: TRUE | E20: LastCouponDate | F20: =VALUE(_xll.BDP($C$12,"PENULTIMATE_CPN_DT")) -> 46769 | H20: FloatSpread | L20: OVERRIDE | N20: STUB RATE FLOAT LEG LVB | R20: CurveIndex | S20: Tenor
B21: * Funding Leg: TRUE = Full First Float Coupon | E21: MaturityDate | F21: =VALUE(_xll.BDP($C$12,"MATURITY")) -> 46951 | H21: EffectiveDate | I21: =F34 -> 43298 | J21: =IF($C$20,$I$21,$C$7) -> 43298 | N21: EffectiveDate | O21: =$J$21 -> 43298 | R21: AUDDF | S21: 1D
E22: Coupon | F22: =_xll.BDP($C$12,"CPN")/100 -> 0.0345 | H22: MaturityDate | I22: =F21 -> 46951 | J22: =I22 -> 46951 | N22: MaturityDate | O22: =$J$22 -> 46951 | R22: AUD3ML | S22: 3M
B23: BOND RESULTS | E23: Frequency | F23: =$C$16 -> SEMI-ANNUAL | H23: AccrualFrequency | I23: =$C$16 -> SEMI-ANNUAL | J23: =$C$18 -> QUARTERLY | N23: CurveCollection | O23: =$C$42 -> AUDYC | R23: AUD6ML | S23: 6M
B24: Yield | C24: =IF(ISNUMBER($C$13),$C$13%,"#LOAD BBG DATA") -> 0.03264769 | E24: AccrualBusinessDayAdjustment | F24: NO_CHANGE | H24: PaymentFrequency | I24: =$C$16 -> SEMI-ANNUAL | J24: =$C$19 -> QUARTERLY | N24: UseCurveIndex | O24: =$J$16 -> NATURAL
B25: Quote Price | C25: =IF(ISNUMBER($C$13),_xll.meLWOBondPrice($F$4,$C$7,$C$24),"#LOAD BBG DATA") -> 101.521 | E25: AccrualCalendar | F25: SYB | H25: Daycount | I25: =F29 -> ACT/ACT | J25: ACT/365 | N25: FloatFrequency | O25: =$J$23 -> QUARTERLY
B26: Clean Price | C26: =IF(ISNUMBER($C$13),_xll.meLWOBondCleanPrice($F$4,$C$7,$C$24),"#LOAD BBG DATA") -> 101.521 | E26: PaymentBusinessDayAdjustment | F26: NO_CHANGE | H26: FixingBusinessDayAdjustment | J26: PRECEDING | N26: FloatDaycount | O26: =$J$25 -> ACT/365
B27: Dirty Price | C27: =IF(ISNUMBER($C$13),_xll.meLWOBondDirtyPrice($F$4,$C$7,$C$24),"#LOAD BBG DATA") -> 102.702 | E27: PaymentCalendar | F27: SYB | H27: FixingCalendar | J27: LNB:SYB | N27: FloatBusinessDayAdjustment | O27: =$J$26 -> PRECEDING
B28: AccruedInterestDays | C28: =_xll.meLWOBondAccruedInterestDays($F$4,$C$7) -> 126 | E28: PaymentLag | F28: 0D | H28: AccrualBusinessDayAdjustment | I28: NO_CHANGE | J28: NO_CHANGE | N28: FloatCalendar | O28: =$J$27 -> LNB:SYB
B29: AccruedInterest | C29: =_xll.meLWOBondAccruedInterest($F$4,$C$7) -> 11810 | E29: DayCount | F29: =$C$17 -> ACT/ACT | H29: AccrualCalendar | I29: SYB | J29: SYB | N29: FloatRollDay
B30: ModifiedDuration | C30: =IF(ISNUMBER($C$13),_xll.meLWOBondModifiedDuration($F$4,$C$7,$C$24),"#LOAD BBG DATA") -> 8.08124 | E30: Rollday | H30: PaymentBusinessDayAdjustment | I30: NO_CHANGE | J30: NO_CHANGE | N30: FloatFixingLag | O30: 2D
B31: DV01 | C31: =IF(ISNUMBER($C$13),_xll.meLWOBondDV01($F$4,$C$7,$C$24),"#LOAD BBG DATA") -> 829.95951 | E31: CalculationType | F31: ="TYPE"&_xll.BDP($C$12,"CALC_TYP") -> TYPE23 | H31: PaymentCalendar | I31: SYB | J31: SYB | N31: FloatFirstStubDate | O31: =IF(ISBLANK($J$33),"",$J$33)
E32: ExdividendTenor | F32: 7D | H32: FirstStubDate | I32: =F35 -> 43482 | N32: FloatLastStubDate | O32: =IF(ISBLANK($J$34),"",$J$34)
B33: BOND Z-SPREAD | E33: ExdividendBusinessDayAdjustment | F33: NO_CHANGE | H33: LastStubDate | I33: =F20 -> 46769 | N33: FloatStubType | O33: =$J$38 -> SHORTSTART
B34: BondName | C34: =$F$4 -> AU3CB0250215@69:4 | E34: PrevCouponDate | F34: =VALUE(_xll.BDP($C$12,"PREV_CPN_DT")) -> 43298 | H34: RollDay | I34: =IF(F30="","",F30)
B35: SettlementDate | C35: =$C$7 -> 43424 | E35: NextCouponDate | F35: =VALUE(_xll.BDP($C$12,"NXT_CPN_DT")) -> 43482 | H35: FixingLag | J35: 0D | N35: STUB RATE TABLE | R35: STUB TICKERS
B36: BondPrice | C36: =$C$25 -> 101.521 | H36: FirstFixingLag | N36: Tenor | O36: CurveIndex | P36: ResetRate | R36: BloombergTicker | S36: Field
B37: CurveCollection | C37: =$C$42 -> AUDYC | H37: PaymentLag | I37: 0D | J37: 0D | N37: 1D | O37: AUDOIS | P37: =_xll.BDP(R37,S37)% -> 0.015 | R37: RBACOR Index | S37: PX_LAST
B38: ForecastCurve | C38: =$J$11 -> AUD3ML | H38: StubType | J38: SHORTSTART | N38: 1M | O38: AUD1ML | P38: =_xll.BDP(R38,S38)% -> 0.0186 | R38: ADBB1M Curncy | S38: PX_ASK
B39: Z-Spread | C39: =IF(ISNUMBER($C$13),_xll.meLWOBondZSpread(C34,C35,C36,C37,C38),"#LOAD BBG DATA") -> 53.597308 | H39: CalculationType | I39: =F31 -> TYPE23 | N39: 2M | O39: AUD2ML | P39: =_xll.BDP(R39,S39)% -> 0.0191 | R39: ADBB2M Curncy | S39: PX_ASK
H40: ExdividendTenor | I40: =F32 -> 7D | N40: 3M | O40: AUD3ML | P40: =_xll.BDP(R40,S40)% -> 0.0193 | R40: ADBB3M Curncy | S40: PX_ASK
B41: ASSET SWAP RESULTS | H41: ExdividendBusinessDayAdjustment | I41: =F33 -> NO_CHANGE | N41: 6M | O41: AUD6ML | P41: =_xll.BDP(R41,S41)% -> 0.0211 | R41: ADBB6M Curncy | S41: PX_ASK
B42: CurveCollection | C42: AUDYC | N42: 12M | O42: AUD12ML | P42: =_xll.BDP(R42,S42)% -> 0.0215 | R42: ADBB12M Curncy | S42: PX_ASK
B43: ValuationDate | C43: =C7 -> 43424
B44: Asset Swap Spread (Bps) | C44: =IF($C$45,$C$45,_xll.meLWOAssetSwapSpread($I$4,$F$4,$C$25,$B$42:$C$43)) -> 53.857665
B45: Override ASW Spread (Bps)
B46: FromAssetSwapToBondCleanPrice | C46: =_xll.meLWOAssetSwapSpreadToCleanPrice(I4,C44,$B$42:$C$43) -> 101.521
B47: BondYield | C47: =_xll.meLWOBondYield($F$4,$C$7,C46,TRUE) -> 0.032647685

Sheet ACGB_BONDS
O1: … Bond Static
B3: Valuation Date | C3: Settlement Date | P3: Bond Generator
B4: =TODAY() -> 43420 | C4: =_xll.meDateFromTenor($B$4,$D$4,"MOD_FOLLOWING","SYB") -> 43424 | D4: 2D | P4: AUSTRALIAN_GOVT_TYPE23
C6: SECURITY_DES | D6: ID_ISIN | E6: ISSUE_DT | F6: START_ACC_DT | H6: FIRST_CPN_DT | I6: PENULTIMATE_CPN_DT | J6: CPN | K6: MATURITY | L6: DAY_CNT_DES | M6: MTY_YEARS | N6: PX_DIRTY_CLEAN | Q6: YLD_YTM_ASK | Y6: BID | Z6: ASK
B7: Bond Identifier | C7: BondDescription | D7: ISIN | E7: IssueDate | F7: AccrualStartDate | G7: RollDay | H7: FirstCouponDate | I7: LastCouponDate | J7: Coupon | K7: MaturityDate | L7: Daycount | M7: MaturityYears | N7: QuoteType | O7: Coupon Override | P7: CreateBond | Q7: BBG_YTM | R7: CleanPrice | S7: DirtyPrice | T7: Accrued Days | U7: Accrued Int | V7: ModDuration | W7: DV01 | X7: EFP Benchmark | Y7: EFP Bid | Z7: EFP Ask | AA7: EFP YTM | AB7: Spread
B8: EH807646 Corp | C8: =_xll.BDP($B8,C$6) -> ACGB 4 1/2 04/15/20 | D8: =_xll.BDP($B8,D$6) -> AU3TB0000036 | E8: =DATEVALUE(_xll.BDP($B8,E$6)) -> 39937 | F8: =DATEVALUE(_xll.BDP($B8,F$6)) -> 39918 | H8: =DATEVALUE(_xll.BDP($B8,H$6)) -> 40101 | I8: =DATEVALUE(_xll.BDP($B8,I$6)) -> 43753 | J8: =IF(ISNUMBER(O8),O8,_xll.BDP($B8,J$6)%) -> 0.045 | K8: =DATEVALUE(_xll.BDP($B8,K$6)) -> 43936 | L8: =_xll.BDP($B8,L$6) -> ACT/ACT | M8: =_xll.BDP($B8,M$6) -> 1.4017796 | N8: =_xll.BDP($B8,N$6) -> CLEAN | P8: =_xll.meLWOBondCreateFromGeneratorLVB(C8,$P$4&"_"&$N8,_xll.meUtilityLVBFromKeysValues($C$7:$K$7,C8:K8)) -> ACGB 4 1/2 04/15/20@31:7 | Q8: =_xll.BDP($B8,$Q$6)% -> 0.020067388 | R8: =_xll.meLWOBondCleanPrice($P8,$C$4,$Q8%) -> 106.276 | S8: =_xll.meLWOBondDirtyPrice($P8,$C$4,$Q8%) -> 106.721 | T8: =_xll.meLWOBondAccruedInterestDays(P8,$C$4) -> 36 | U8: =_xll.meLWOBondAccruedInterest(P8,$C$4) -> 4450 | V8: =_xll.meLWOBondModifiedDuration($P8,$C$4,$Q8%) -> 1.3693362 | W8: =_xll.meLWOBondDV01($P8,$C$4,$Q8%) -> 146.13693 | X8: =IF(M8<=6,"YMA Comdty","XMA Comdty") -> YMA Comdty | Y8: =_xll.BDP($X8,Y$6) -> 97.825 | Z8: =_xll.BDP($X8,Z$6) -> 97.83 | AA8: =(100-AVERAGE(Y8:Z8))% -> 0.021725 | AB8: =Q8-AA8 -> -0.0016576121
B9: GG728188 Corp | C9: =_xll.BDP($B9,C$6) -> ACGB 4 08/20/20 | D9: =_xll.BDP($B9,D$6) -> AU0000XCLWE2 | E9: =DATEVALUE(_xll.BDP($B9,E$6)) -> 35352 | F9: =DATEVALUE(_xll.BDP($B9,F$6)) -> 35297 | H9: =DATEVALUE(_xll.BDP($B9,H$6)) -> 35389 | I9: =DATEVALUE(_xll.BDP($B9,I$6)) -> 43971 | J9: =IF(ISNUMBER(O9),O9,_xll.BDP($B9,J$6)%) -> 0.04 | K9: =DATEVALUE(_xll.BDP($B9,K$6)) -> 44063 | L9: =_xll.BDP($B9,L$6) -> ACT/ACT | M9: =_xll.BDP($B9,M$6) -> 1.7494867 | N9: =_xll.BDP($B9,N$6) -> CLEAN | P9: =_xll.meLWOBondCreateFromGeneratorLVB(C9,$P$4&"_"&$N9,_xll.meUtilityLVBFromKeysValues($C$7:$K$7,C9:K9)) -> ACGB 4 08/20/20@54:7 | Q9: =_xll.BDP($B9,$Q$6)% -> 0.003752 | R9: =_xll.meLWOBondCleanPrice($P9,$C$4,$Q9%) -> 107.003 | S9: =_xll.meLWOBondDirtyPrice($P9,$C$4,$Q9%) -> 107.003 | T9: =_xll.meLWOBondAccruedInterestDays(P9,$C$4) -> 0 | U9: =_xll.meLWOBondAccruedInterest(P9,$C$4) -> 0 | V9: =_xll.meLWOBondModifiedDuration($P9,$C$4,$Q9%) -> 1.9438955 | W9: =_xll.meLWOBondDV01($P9,$C$4,$Q9%) -> 208.00265 | X9: =IF(M9<=6,"YMA Comdty","XMA Comdty") -> YMA Comdty | Y9: =_xll.BDP($X9,Y$6) -> 97.825 | Z9: =_xll.BDP($X9,Z$6) -> 97.83 | AA9: =(100-AVERAGE(Y9:Z9))% -> 0.021725 | AB9: =Q9-AA9 -> -0.017973
B10: EK841545 Corp | C10: =_xll.BDP($B10,C$6) -> ACGB 1 3/4 11/21/20 | D10: =_xll.BDP($B10,D$6) -> AU000XCLWAN8 | E10: =DATEVALUE(_xll.BDP($B10,E$6)) -> 42109 | F10: =DATEVALUE(_xll.BDP($B10,F$6)) -> 41964 | H10: =DATEVALUE(_xll.BDP($B10,H$6)) -> 42145 | I10: =DATEVALUE(_xll.BDP($B10,I$6)) -> 43972 | J10: =IF(ISNUMBER(O10),O10,_xll.BDP($B10,J$6)%) -> 0.0175 | K10: =DATEVALUE(_xll.BDP($B10,K$6)) -> 44156 | L10: =_xll.BDP($B10,L$6) -> ACT/ACT | M10: =_xll.BDP($B10,M$6) -> 2.0041068 | N10: =_xll.BDP($B10,N$6) -> CLEAN | P10: =_xll.meLWOBondCreateFromGeneratorLVB(C10,$P$4&"_"&$N10,_xll.meUtilityLVBFromKeysValues($C$7:$K$7,C10:K10)) -> ACGB 1 3/4 11/21/20@56:7 | Q10: =_xll.BDP($B10,$Q$6)% -> 0.020472012 | R10: =_xll.meLWOBondCleanPrice($P10,$C$4,$Q10%) -> 103.463 | S10: =_xll.meLWOBondDirtyPrice($P10,$C$4,$Q10%) -> 103.458 | T10: =_xll.meLWOBondAccruedInterestDays(P10,$C$4) -> -1 | U10: =_xll.meLWOBondAccruedInterest(P10,$C$4) -> -50 | V10: =_xll.meLWOBondModifiedDuration($P10,$C$4,$Q10%) -> 1.9771489 | W10: =_xll.meLWOBondDV01($P10,$C$4,$Q10%) -> 204.55187 | X10: =IF(M10<=6,"YMA Comdty","XMA Comdty") -> YMA Comdty | Y10: =_xll.BDP($X10,Y$6) -> 97.825 | Z10: =_xll.BDP($X10,Z$6) -> 97.83 | AA10: =(100-AVERAGE(Y10:Z10))% -> 0.021725 | AB10: =Q10-AA10 -> -0.0012529884
B11: EG821160 Corp | C11: =_xll.BDP($B11,C$6) -> ACGB 5 3/4 05/15/21 | D11: =_xll.BDP($B11,D$6) -> AU0000XCLWM5 | E11: =DATEVALUE(_xll.BDP($B11,E$6)) -> 39338 | F11: =DATEVALUE(_xll.BDP($B11,F$6)) -> 39217 | H11: =DATEVALUE(_xll.BDP($B11,H$6)) -> 39401 | I11: =DATEVALUE(_xll.BDP($B11,I$6)) -> 44150 | J11: =IF(ISNUMBER(O11),O11,_xll.BDP($B11,J$6)%) -> 0.0575 | K11: =DATEVALUE(_xll.BDP($B11,K$6)) -> 44331 | L11: =_xll.BDP($B11,L$6) -> ACT/ACT | M11: =_xll.BDP($B11,M$6) -> 2.4832307 | N11: =_xll.BDP($B11,N$6) -> CLEAN | P11: =_xll.meLWOBondCreateFromGeneratorLVB(C11,$P$4&"_"&$N11,_xll.meUtilityLVBFromKeysValues($C$7:$K$7,C11:K11)) -> ACGB 5 3/4 05/15/21@32:7 | Q11: =_xll.BDP($B11,$Q$6)% -> 0.020763292 | R11: =_xll.meLWOBondCleanPrice($P11,$C$4,$Q11%) -> 114.24 | S11: =_xll.meLWOBondDirtyPrice($P11,$C$4,$Q11%) -> 114.319 | T11: =_xll.meLWOBondAccruedInterestDays(P11,$C$4) -> 5 | U11: =_xll.meLWOBondAccruedInterest(P11,$C$4) -> 790 | V11: =_xll.meLWOBondModifiedDuration($P11,$C$4,$Q11%) -> 2.3602231 | W11: =_xll.meLWOBondDV01($P11,$C$4,$Q11%) -> 269.81834 | X11: =IF(M11<=6,"YMA Comdty","XMA Comdty") -> YMA Comdty | Y11: =_xll.BDP($X11,Y$6) -> 97.825 | Z11: =_xll.BDP($X11,Z$6) -> 97.83 | AA11: =(100-AVERAGE(Y11:Z11))% -> 0.021725 | AB11: =Q11-AA11 -> -0.00096170814
B12: AM152866 Corp | C12: =_xll.BDP($B12,C$6) -> ACGB 2 12/21/21 | D12: =_xll.BDP($B12,D$6) -> AU000XCLWAT5 | E12: =DATEVALUE(_xll.BDP($B12,E$6)) -> 42762 | F12: =DATEVALUE(_xll.BDP($B12,F$6)) -> 42725 | H12: =DATEVALUE(_xll.BDP($B12,H$6)) -> 42907 | I12: =DATEVALUE(_xll.BDP($B12,I$6)) -> 44368 | J12: =IF(ISNUMBER(O12),O12,_xll.BDP($B12,J$6)%) -> 0.02 | K12: =DATEVALUE(_xll.BDP($B12,K$6)) -> 44551 | L12: =_xll.BDP($B12,L$6) -> ACT/ACT | M12: =_xll.BDP($B12,M$6) -> 3.0855578 | N12: =_xll.BDP($B12,N$6) -> CLEAN | P12: =_xll.meLWOBondCreateFromGeneratorLVB(C12,$P$4&"_"&$N12,_xll.meUtilityLVBFromKeysValues($C$7:$K$7,C12:K12)) -> ACGB 2 12/21/21@48:7 | Q12: =_xll.BDP($B12,$Q$6)% -> 0.021356419 | R12: =_xll.meLWOBondCleanPrice($P12,$C$4,$Q12%) -> 106.101 | S12: =_xll.meLWOBondDirtyPrice($P12,$C$4,$Q12%) -> 106.932 | T12: =_xll.meLWOBondAccruedInterestDays(P12,$C$4) -> 152 | U12: =_xll.meLWOBondAccruedInterest(P12,$C$4) -> 8310 | V12: =_xll.meLWOBondModifiedDuration($P12,$C$4,$Q12%) -> 2.9862002 | W12: =_xll.meLWOBondDV01($P12,$C$4,$Q12%) -> 319.32036 | X12: =IF(M12<=6,"YMA Comdty","XMA Comdty") -> YMA Comdty | Y12: =_xll.BDP($X12,Y$6) -> 97.825 | Z12: =_xll.BDP($X12,Z$6) -> 97.83 | AA12: =(100-AVERAGE(Y12:Z12))% -> 0.021725 | AB12: =Q12-AA12 -> -0.0003685808
B13: EJ036821 Corp | C13: =_xll.BDP($B13,C$6) -> ACGB 1 1/4 02/21/22 | D13: =_xll.BDP($B13,D$6) -> AU000XCLWAB3 | E13: =DATEVALUE(_xll.BDP($B13,E$6)) -> 40967 | F13: =DATEVALUE(_xll.BDP($B13,F$6)) -> 40960 | H13: =DATEVALUE(_xll.BDP($B13,H$6)) -> 41050 | I13: =DATEVALUE(_xll.BDP($B13,I$6)) -> 44521 | J13: =IF(ISNUMBER(O13),O13,_xll.BDP($B13,J$6)%) -> 0.0125 | K13: =DATEVALUE(_xll.BDP($B13,K$6)) -> 44613 | L13: =_xll.BDP($B13,L$6) -> ACT/ACT | M13: =_xll.BDP($B13,M$6) -> 3.2553046 | N13: =_xll.BDP($B13,N$6) -> CLEAN | P13: =_xll.meLWOBondCreateFromGeneratorLVB(C13,$P$4&"_"&$N13,_xll.meUtilityLVBFromKeysValues($C$7:$K$7,C13:K13)) -> ACGB 1 1/4 02/21/22@57:7 | Q13: =_xll.BDP($B13,$Q$6)% -> 0.004656 | R13: =_xll.meLWOBondCleanPrice($P13,$C$4,$Q13%) -> 104.049 | S13: =_xll.meLWOBondDirtyPrice($P13,$C$4,$Q13%) -> 104.046 | T13: =_xll.meLWOBondAccruedInterestDays(P13,$C$4) -> -1 | U13: =_xll.meLWOBondAccruedInterest(P13,$C$4) -> -30 | V13: =_xll.meLWOBondModifiedDuration($P13,$C$4,$Q13%) -> 3.4395627 | W13: =_xll.meLWOBondDV01($P13,$C$4,$Q13%) -> 357.87274 | X13: =IF(M13<=6,"YMA Comdty","XMA Comdty") -> YMA Comdty | Y13: =_xll.BDP($X13,Y$6) -> 97.825 | Z13: =_xll.BDP($X13,Z$6) -> 97.83 | AA13: =(100-AVERAGE(Y13:Z13))% -> 0.021725 | AB13: =Q13-AA13 -> -0.017069
B14: EI214281 Corp | C14: =_xll.BDP($B14,C$6) -> ACGB 5 3/4 07/15/22 | D14: =_xll.BDP($B14,D$6) -> AU3TB0000051 | E14: =DATEVALUE(_xll.BDP($B14,E$6)) -> 40280 | F14: =DATEVALUE(_xll.BDP($B14,F$6)) -> 40193 | H14: =DATEVALUE(_xll.BDP($B14,H$6)) -> 40374 | I14: =DATEVALUE(_xll.BDP($B14,I$6)) -> 44576 | J14: =IF(ISNUMBER(O14),O14,_xll.BDP($B14,J$6)%) -> 0.0575 | K14: =DATEVALUE(_xll.BDP($B14,K$6)) -> 44757 | L14: =_xll.BDP($B14,L$6) -> ACT/ACT | M14: =_xll.BDP($B14,M$6) -> 3.6495551 | N14: =_xll.BDP($B14,N$6) -> CLEAN | P14: =_xll.meLWOBondCreateFromGeneratorLVB(C14,$P$4&"_"&$N14,_xll.meUtilityLVBFromKeysValues($C$7:$K$7,C14:K14)) -> ACGB 5 3/4 07/15/22@50:7 | Q14: =_xll.BDP($B14,$Q$6)% -> 0.021691312 | R14: =_xll.meLWOBondCleanPrice($P14,$C$4,$Q14%) -> 120.911 | S14: =_xll.meLWOBondDirtyPrice($P14,$C$4,$Q14%) -> 122.911 | T14: =_xll.meLWOBondAccruedInterestDays(P14,$C$4) -> 128 | U14: =_xll.meLWOBondAccruedInterest(P14,$C$4) -> 20000 | V14: =_xll.meLWOBondModifiedDuration($P14,$C$4,$Q14%) -> 3.3244322 | W14: =_xll.meLWOBondDV01($P14,$C$4,$Q14%) -> 408.60929 | X14: =IF(M14<=6,"YMA Comdty","XMA Comdty") -> YMA Comdty | Y14: =_xll.BDP($X14,Y$6) -> 97.825 | Z14: =_xll.BDP($X14,Z$6) -> 97.83 | AA14: =(100-AVERAGE(Y14:Z14))% -> 0.021725 | AB14: =Q14-AA14 -> -3.3687668e-05
B15: AP364296 Corp | C15: =_xll.BDP($B15,C$6) -> ACGB 2 1/4 11/21/22 | D15: =_xll.BDP($B15,D$6) -> AU000XCLWAW9 | E15: =DATEVALUE(_xll.BDP($B15,E$6)) -> 43021 | F15: =DATEVALUE(_xll.BDP($B15,F$6)) -> 42876 | H15: =DATEVALUE(_xll.BDP($B15,H$6)) -> 43060 | I15: =DATEVALUE(_xll.BDP($B15,I$6)) -> 44702 | J15: =IF(ISNUMBER(O15),O15,_xll.BDP($B15,J$6)%) -> 0.0225 | K15: =DATEVALUE(_xll.BDP($B15,K$6)) -> 44886 | L15: =_xll.BDP($B15,L$6) -> ACT/ACT | M15: =_xll.BDP($B15,M$6) -> 4.0027379 | N15: =_xll.BDP($B15,N$6) -> CLEAN | P15: =_xll.meLWOBondCreateFromGeneratorLVB(C15,$P$4&"_"&$N15,_xll.meUtilityLVBFromKeysValues($C$7:$K$7,C15:K15)) -> ACGB 2 1/4 11/21/22@35:7 | Q15: =_xll.BDP($B15,$Q$6)% -> 0.022284518 | R15: =_xll.meLWOBondCleanPrice($P15,$C$4,$Q15%) -> 108.912 | S15: =_xll.meLWOBondDirtyPrice($P15,$C$4,$Q15%) -> 108.906 | T15: =_xll.meLWOBondAccruedInterestDays(P15,$C$4) -> -1 | U15: =_xll.meLWOBondAccruedInterest(P15,$C$4) -> -60 | V15: =_xll.meLWOBondModifiedDuration($P15,$C$4,$Q15%) -> 3.857728 | W15: =_xll.meLWOBondDV01($P15,$C$4,$Q15%) -> 420.12972 | X15: =IF(M15<=6,"YMA Comdty","XMA Comdty") -> YMA Comdty | Y15: =_xll.BDP($X15,Y$6) -> 97.825 | Z15: =_xll.BDP($X15,Z$6) -> 97.83 | AA15: =(100-AVERAGE(Y15:Z15))% -> 0.021725 | AB15: =Q15-AA15 -> 0.00055951788
B16: EI683148 Corp | C16: =_xll.BDP($B16,C$6) -> ACGB 5 1/2 04/21/23 | D16: =_xll.BDP($B16,D$6) -> AU3TB0000101 | E16: =DATEVALUE(_xll.BDP($B16,E$6)) -> 40686 | F16: =DATEVALUE(_xll.BDP($B16,F$6)) -> 40654 | H16: =DATEVALUE(_xll.BDP($B16,H$6)) -> 40837 | I16: =DATEVALUE(_xll.BDP($B16,I$6)) -> 44855 | J16: =IF(ISNUMBER(O16),O16,_xll.BDP($B16,J$6)%) -> 0.055 | K16: =DATEVALUE(_xll.BDP($B16,K$6)) -> 45037 | L16: =_xll.BDP($B16,L$6) -> ACT/ACT | M16: =_xll.BDP($B16,M$6) -> 4.4161533 | N16: =_xll.BDP($B16,N$6) -> CLEAN | P16: =_xll.meLWOBondCreateFromGeneratorLVB(C16,$P$4&"_"&$N16,_xll.meUtilityLVBFromKeysValues($C$7:$K$7,C16:K16)) -> ACGB 5 1/2 04/21/23@41:7 | Q16: =_xll.BDP($B16,$Q$6)% -> 0.02258046 | R16: =_xll.meLWOBondCleanPrice($P16,$C$4,$Q16%) -> 124.184 | S16: =_xll.meLWOBondDirtyPrice($P16,$C$4,$Q16%) -> 124.637 | T16: =_xll.meLWOBondAccruedInterestDays(P16,$C$4) -> 30 | U16: =_xll.meLWOBondAccruedInterest(P16,$C$4) -> 4530 | V16: =_xll.meLWOBondModifiedDuration($P16,$C$4,$Q16%) -> 4.0201101 | W16: =_xll.meLWOBondDV01($P16,$C$4,$Q16%) -> 501.05446 | X16: =IF(M16<=6,"YMA Comdty","XMA Comdty") -> YMA Comdty | Y16: =_xll.BDP($X16,Y$6) -> 97.825 | Z16: =_xll.BDP($X16,Z$6) -> 97.83 | AA16: =(100-AVERAGE(Y16:Z16))% -> 0.021725 | AB16: =Q16-AA16 -> 0.00085546028
B17: EJ244569 Corp | C17: =_xll.BDP($B17,C$6) -> ACGB 2 3/4 04/21/24 | D17: =_xll.BDP($B17,D$6) -> AU3TB0000143 | E17: =DATEVALUE(_xll.BDP($B17,E$6)) -> 41085 | F17: =DATEVALUE(_xll.BDP($B17,F$6)) -> 41020 | H17: =DATEVALUE(_xll.BDP($B17,H$6)) -> 41203 | I17: =DATEVALUE(_xll.BDP($B17,I$6)) -> 45220 | J17: =IF(ISNUMBER(O17),O17,_xll.BDP($B17,J$6)%) -> 0.0275 | K17: =DATEVALUE(_xll.BDP($B17,K$6)) -> 45403 | L17: =_xll.BDP($B17,L$6) -> ACT/ACT | M17: =_xll.BDP($B17,M$6) -> 5.4182067 | N17: =_xll.BDP($B17,N$6) -> CLEAN | P17: =_xll.meLWOBondCreateFromGeneratorLVB(C17,$P$4&"_"&$N17,_xll.meUtilityLVBFromKeysValues($C$7:$K$7,C17:K17)) -> ACGB 2 3/4 04/21/24@51:7 | Q17: =_xll.BDP($B17,$Q$6)% -> 0.023770213 | R17: =_xll.meLWOBondCleanPrice($P17,$C$4,$Q17%) -> 114.759 | S17: =_xll.meLWOBondDirtyPrice($P17,$C$4,$Q17%) -> 114.986 | T17: =_xll.meLWOBondAccruedInterestDays(P17,$C$4) -> 30 | U17: =_xll.meLWOBondAccruedInterest(P17,$C$4) -> 2270 | V17: =_xll.meLWOBondModifiedDuration($P17,$C$4,$Q17%) -> 5.0882751 | W17: =_xll.meLWOBondDV01($P17,$C$4,$Q17%) -> 585.0804 | X17: =IF(M17<=6,"YMA Comdty","XMA Comdty") -> YMA Comdty | Y17: =_xll.BDP($X17,Y$6) -> 97.825 | Z17: =_xll.BDP($X17,Z$6) -> 97.83 | AA17: =(100-AVERAGE(Y17:Z17))% -> 0.021725 | AB17: =Q17-AA17 -> 0.0020452128
B18: EJ679130 Corp | C18: =_xll.BDP($B18,C$6) -> ACGB 3 1/4 04/21/25 | D18: =_xll.BDP($B18,D$6) -> AU3TB0000168 | E18: =DATEVALUE(_xll.BDP($B18,E$6)) -> 41423 | F18: =DATEVALUE(_xll.BDP($B18,F$6)) -> 41385 | H18: =DATEVALUE(_xll.BDP($B18,H$6)) -> 41568 | I18: =DATEVALUE(_xll.BDP($B18,I$6)) -> 45586 | J18: =IF(ISNUMBER(O18),O18,_xll.BDP($B18,J$6)%) -> 0.0325 | K18: =DATEVALUE(_xll.BDP($B18,K$6)) -> 45768 | L18: =_xll.BDP($B18,L$6) -> ACT/ACT | M18: =_xll.BDP($B18,M$6) -> 6.4175222 | N18: =_xll.BDP($B18,N$6) -> CLEAN | P18: =_xll.meLWOBondCreateFromGeneratorLVB(C18,$P$4&"_"&$N18,_xll.meUtilityLVBFromKeysValues($C$7:$K$7,C18:K18)) -> ACGB 3 1/4 04/21/25@52:7 | Q18: =_xll.BDP($B18,$Q$6)% -> 0.02465945 | R18: =_xll.meLWOBondCleanPrice($P18,$C$4,$Q18%) -> 120.681 | S18: =_xll.meLWOBondDirtyPrice($P18,$C$4,$Q18%) -> 120.949 | T18: =_xll.meLWOBondAccruedInterestDays(P18,$C$4) -> 30 | U18: =_xll.meLWOBondAccruedInterest(P18,$C$4) -> 2680 | V18: =_xll.meLWOBondModifiedDuration($P18,$C$4,$Q18%) -> 5.89317 | W18: =_xll.meLWOBondDV01($P18,$C$4,$Q18%) -> 712.77302 | X18: =IF(M18<=6,"YMA Comdty","XMA Comdty") -> XMA Comdty | Y18: =_xll.BDP($X18,Y$6) -> 97.295 | Z18: =_xll.BDP($X18,Z$6) -> 97.3 | AA18: =(100-AVERAGE(Y18:Z18))% -> 0.027025 | AB18: =Q18-AA18 -> -0.0023655496
B19: EH994413 Corp | C19: =_xll.BDP($B19,C$6) -> ACGB 3 09/20/25 | D19: =_xll.BDP($B19,D$6) -> AU0000XCLWP8 | E19: =DATEVALUE(_xll.BDP($B19,E$6)) -> 40094 | F19: =DATEVALUE(_xll.BDP($B19,F$6)) -> 40076 | H19: =DATEVALUE(_xll.BDP($B19,H$6)) -> 40167 | I19: =DATEVALUE(_xll.BDP($B19,I$6)) -> 45828 | J19: =IF(ISNUMBER(O19),O19,_xll.BDP($B19,J$6)%) -> 0.03 | K19: =DATEVALUE(_xll.BDP($B19,K$6)) -> 45920 | L19: =_xll.BDP($B19,L$6) -> ACT/ACT | M19: =_xll.BDP($B19,M$6) -> 6.8336756 | N19: =_xll.BDP($B19,N$6) -> CLEAN | P19: =_xll.meLWOBondCreateFromGeneratorLVB(C19,$P$4&"_"&$N19,_xll.meUtilityLVBFromKeysValues($C$7:$K$7,C19:K19)) -> ACGB 3 09/20/25@36:7 | Q19: =_xll.BDP($B19,$Q$6)% -> 0.006824 | R19: =_xll.meLWOBondCleanPrice($P19,$C$4,$Q19%) -> 120.443 | S19: =_xll.meLWOBondDirtyPrice($P19,$C$4,$Q19%) -> 121.697 | T19: =_xll.meLWOBondAccruedInterestDays(P19,$C$4) -> 153 | U19: =_xll.meLWOBondAccruedInterest(P19,$C$4) -> 12540 | V19: =_xll.meLWOBondModifiedDuration($P19,$C$4,$Q19%) -> 6.4347217 | W19: =_xll.meLWOBondDV01($P19,$C$4,$Q19%) -> 783.08633 | X19: =IF(M19<=6,"YMA Comdty","XMA Comdty") -> XMA Comdty | Y19: =_xll.BDP($X19,Y$6) -> 97.295 | Z19: =_xll.BDP($X19,Z$6) -> 97.3 | AA19: =(100-AVERAGE(Y19:Z19))% -> 0.027025 | AB19: =Q19-AA19 -> -0.020201
... B21: EI849265 Corp | C21: =_xll.BDP($B21,C$6) -> ACGB 4 3/4 04/21/27 | D21: =_xll.BDP($B21,D$6) -> AU3TB0000135 | E21: =DATEVALUE(_xll.BDP($B21,E$6)) -> 40843 | F21: =DATEVALUE(_xll.BDP($B21,F$6)) -> 40837 | H21: =DATEVALUE(_xll.BDP($B21,H$6)) -> 41020 | I21: =DATEVALUE(_xll.BDP($B21,I$6)) -> 46316 | J21: =IF(ISNUMBER(O21),O21,_xll.BDP($B21,J$6)%) -> 0.0475 | K21: =DATEVALUE(_xll.BDP($B21,K$6)) -> 46498 | L21: =_xll.BDP($B21,L$6) -> ACT/ACT | M21: =_xll.BDP($B21,M$6) -> 8.4161533 | N21: =_xll.BDP($B21,N$6) -> CLEAN | P21: =_xll.meLWOBondCreateFromGeneratorLVB(C21,$P$4&"_"&$N21,_xll.meUtilityLVBFromKeysValues($C$7:$K$7,C21:K21)) -> ACGB 4 3/4 04/21/27@46:7 | Q21: =_xll.BDP($B21,$Q$6)% -> 0.025990125 | R21: =_xll.meLWOBondCleanPrice($P21,$C$4,$Q21%) -> 139.719 | S21: =_xll.meLWOBondDirtyPrice($P21,$C$4,$Q21%) -> 140.11 | T21: =_xll.meLWOBondAccruedInterestDays(P21,$C$4) -> 30 | U21: =_xll.meLWOBondAccruedInterest(P21,$C$4) -> 3910 | V21: =_xll.meLWOBondModifiedDuration($P21,$C$4,$Q21%) -> 7.2648558 | W21: =_xll.meLWOBondDV01($P21,$C$4,$Q21%) -> 1017.8789 | X21: =IF(M21<=6,"YMA Comdty","XMA Comdty") -> XMA Comdty | Y21: =_xll.BDP($X21,Y$6) -> 97.295 | Z21: =_xll.BDP($X21,Z$6) -> 97.3 | AA21: =(100-AVERAGE(Y21:Z21))% -> 0.027025 | AB21: =Q21-AA21 -> -0.0010348749
B22: AO836930 Corp | C22: =_xll.BDP($B22,C$6) -> ACGB 0 3/4 11/21/27 | D22: =_xll.BDP($B22,D$6) -> AU000XCLWAV1 | E22: =DATEVALUE(_xll.BDP($B22,E$6)) -> 42978 | F22: =DATEVALUE(_xll.BDP($B22,F$6)) -> 42968 | H22: =DATEVALUE(_xll.BDP($B22,H$6)) -> 43060 | I22: =DATEVALUE(_xll.BDP($B22,I$6)) -> 46620 | J22: =IF(ISNUMBER(O22),O22,_xll.BDP($B22,J$6)%) -> 0.0075 | K22: =DATEVALUE(_xll.BDP($B22,K$6)) -> 46712 | L22: =_xll.BDP($B22,L$6) -> ACT/ACT | M22: =_xll.BDP($B22,M$6) -> 9.0020534 | N22: =_xll.BDP($B22,N$6) -> CLEAN | P22: =_xll.meLWOBondCreateFromGeneratorLVB(C22,$P$4&"_"&$N22,_xll.meUtilityLVBFromKeysValues($C$7:$K$7,C22:K22)) -> ACGB 0 3/4 11/21/27@34:7 | Q22: =_xll.BDP($B22,$Q$6)% -> 0.007506 | R22: =_xll.meLWOBondCleanPrice($P22,$C$4,$Q22) -> 99.82 | S22: =_xll.meLWOBondDirtyPrice($P22,$C$4,$Q22%) -> 106.866 | T22: =_xll.meLWOBondAccruedInterestDays(P22,$C$4) -> 91 | U22: =_xll.meLWOBondAccruedInterest(P22,$C$4) -> 1850 | V22: =_xll.meLWOBondModifiedDuration($P22,$C$4,$Q22%) -> 8.9523965 | W22: =_xll.meLWOBondDV01($P22,$C$4,$Q22%) -> 956.7068 | X22: =IF(M22<=6,"YMA Comdty","XMA Comdty") -> XMA Comdty | Y22: =_xll.BDP($X22,Y$6) -> 97.295 | Z22: =_xll.BDP($X22,Z$6) -> 97.3 | AA22: =(100-AVERAGE(Y22:Z22))% -> 0.027025 | AB22: =Q22-AA22 -> -0.019519
B23: JV319866 Corp | C23: =_xll.BDP($B23,C$6) -> ACGB 2 3/4 11/21/27 | D23: =_xll.BDP($B23,D$6) -> AU000XCLWAQ1 | E23: =DATEVALUE(_xll.BDP($B23,E$6)) -> 42397 | F23: =DATEVALUE(_xll.BDP($B23,F$6)) -> 42329 | H23: =DATEVALUE(_xll.BDP($B23,H$6)) -> 42511 | I23: =DATEVALUE(_xll.BDP($B23,I$6)) -> 46528 | J23: =IF(ISNUMBER(O23),O23,_xll.BDP($B23,J$6)%) -> 0.0275 | K23: =DATEVALUE(_xll.BDP($B23,K$6)) -> 46712 | L23: =_xll.BDP($B23,L$6) -> ACT/ACT | M23: =_xll.BDP($B23,M$6) -> 9.0020534 | N23: =_xll.BDP($B23,N$6) -> CLEAN | P23: =_xll.meLWOBondCreateFromGeneratorLVB(C23,$P$4&"_"&$N23,_xll.meUtilityLVBFromKeysValues($C$7:$K$7,C23:K23)) -> ACGB 2 3/4 11/21/27@47:7 | Q23: =_xll.BDP($B23,$Q$6)% -> 0.026489813 | R23: =_xll.meLWOBondCleanPrice($P23,$C$4,$Q23%) -> 124.488 | S23: =_xll.meLWOBondDirtyPrice($P23,$C$4,$Q23%) -> 124.481 | T23: =_xll.meLWOBondAccruedInterestDays(P23,$C$4) -> -1 | U23: =_xll.meLWOBondAccruedInterest(P23,$C$4) -> -70 | V23: =_xll.meLWOBondModifiedDuration($P23,$C$4,$Q23%) -> 8.1573148 | W23: =_xll.meLWOBondDV01($P23,$C$4,$Q23%) -> 1015.4307 | X23: =IF(M23<=6,"YMA Comdty","XMA Comdty") -> XMA Comdty | Y23: =_xll.BDP($X23,Y$6) -> 97.295 | Z23: =_xll.BDP($X23,Z$6) -> 97.3 | AA23: =(100-AVERAGE(Y23:Z23))% -> 0.027025 | AB23: =Q23-AA23 -> -0.00053518675
B24: LW020767 Corp | C24: =_xll.BDP($B24,C$6) -> ACGB 2 1/4 05/21/28 | D24: =_xll.BDP($B24,D$6) -> AU000XCLWAR9 | E24: =DATEVALUE(_xll.BDP($B24,E$6)) -> 42509 | F24: =DATEVALUE(_xll.BDP($B24,F$6)) -> 42329 | H24: =DATEVALUE(_xll.BDP($B24,H$6)) -> 42511 | I24: =DATEVALUE(_xll.BDP($B24,I$6)) -> 46712 | J24: =IF(ISNUMBER(O24),O24,_xll.BDP($B24,J$6)%) -> 0.0225 | K24: =DATEVALUE(_xll.BDP($B24,K$6)) -> 46894 | L24: =_xll.BDP($B24,L$6) -> ACT/ACT | M24: =_xll.BDP($B24,M$6) -> 9.5003422 | N24: =_xll.BDP($B24,N$6) -> CLEAN | P24: =_xll.meLWOBondCreateFromGeneratorLVB(C24,$P$4&"_"&$N24,_xll.meUtilityLVBFromKeysValues($C$7:$K$7,C24:K24)) -> ACGB 2 1/4 05/21/28@55:7 | Q24: =_xll.BDP($B24,$Q$6)% -> 0.026729809 | R24: =_xll.meLWOBondCleanPrice($P24,$C$4,$Q24%) -> 121.099 | S24: =_xll.meLWOBondDirtyPrice($P24,$C$4,$Q24%) -> 121.093 | T24: =_xll.meLWOBondAccruedInterestDays(P24,$C$4) -> -1 | U24: =_xll.meLWOBondAccruedInterest(P24,$C$4) -> -60 | V24: =_xll.meLWOBondModifiedDuration($P24,$C$4,$Q24%) -> 8.7079164 | W24: =_xll.meLWOBondDV01($P24,$C$4,$Q24%) -> 1054.4677 | X24: =IF(M24<=6,"YMA Comdty","XMA Comdty") -> XMA Comdty | Y24: =_xll.BDP($X24,Y$6) -> 97.295 | Z24: =_xll.BDP($X24,Z$6) -> 97.3 | AA24: =(100-AVERAGE(Y24:Z24))% -> 0.027025 | AB24: =Q24-AA24 -> -0.00029519079
B25: AM564740 Corp | C25: =_xll.BDP($B25,C$6) -> ACGB 2 3/4 11/21/28 | D25: =_xll.BDP($B25,D$6) -> AU000XCLWAU3 | E25: =DATEVALUE(_xll.BDP($B25,E$6)) -> 42796 | F25: =DATEVALUE(_xll.BDP($B25,F$6)) -> 42695 | H25: =DATEVALUE(_xll.BDP($B25,H$6)) -> 42876 | I25: =DATEVALUE(_xll.BDP($B25,I$6)) -> 46894 | J25: =IF(ISNUMBER(O25),O25,_xll.BDP($B25,J$6)%) -> 0.0275 | K25: =DATEVALUE(_xll.BDP($B25,K$6)) -> 47078 | L25: =_xll.BDP($B25,L$6) -> ACT/ACT | M25: =_xll.BDP($B25,M$6) -> 10.004107 | N25: =_xll.BDP($B25,N$6) -> CLEAN | P25: =_xll.meLWOBondCreateFromGeneratorLVB(C25,$P$4&"_"&$N25,_xll.meUtilityLVBFromKeysValues($C$7:$K$7,C25:K25)) -> ACGB 2 3/4 11/21/28@45:7 | Q25: =_xll.BDP($B25,$Q$6)% -> 0.02674542 | R25: =_xll.meLWOBondCleanPrice($P25,$C$4,$Q25%) -> 127.201 | S25: =_xll.meLWOBondDirtyPrice($P25,$C$4,$Q25%) -> 127.194 | T25: =_xll.meLWOBondAccruedInterestDays(P25,$C$4) -> -1 | U25: =_xll.meLWOBondAccruedInterest(P25,$C$4) -> -70 | V25: =_xll.meLWOBondModifiedDuration($P25,$C$4,$Q25%) -> 8.9755238 | W25: =_xll.meLWOBondDV01($P25,$C$4,$Q25%) -> 1141.6328 | X25: =IF(M25<=6,"YMA Comdty","XMA Comdty") -> XMA Comdty | Y25: =_xll.BDP($X25,Y$6) -> 97.295 | Z25: =_xll.BDP($X25,Z$6) -> 97.3 | AA25: =(100-AVERAGE(Y25:Z25))% -> 0.027025 | AB25: =Q25-AA25 -> -0.00027957999
B26: EJ393853 Corp | C26: =_xll.BDP($B26,C$6) -> ACGB 3 1/4 04/21/29 | D26: =_xll.BDP($B26,D$6) -> AU3TB0000150 | E26: =DATEVALUE(_xll.BDP($B26,E$6)) -> 41199 | F26: =DATEVALUE(_xll.BDP($B26,F$6)) -> 41203 | H26: =DATEVALUE(_xll.BDP($B26,H$6)) -> 41385 | I26: =DATEVALUE(_xll.BDP($B26,I$6)) -> 47047 | J26: =IF(ISNUMBER(O26),O26,_xll.BDP($B26,J$6)%) -> 0.0325 | K26: =DATEVALUE(_xll.BDP($B26,K$6)) -> 47229 | L26: =_xll.BDP($B26,L$6) -> ACT/ACT | M26: =_xll.BDP($B26,M$6) -> 10.417522 | N26: =_xll.BDP($B26,N$6) -> CLEAN | P26: =_xll.meLWOBondCreateFromGeneratorLVB(C26,$P$4&"_"&$N26,_xll.meUtilityLVBFromKeysValues($C$7:$K$7,C26:K26)) -> ACGB 3 1/4 04/21/29@61:7 | Q26: =_xll.BDP($B26,$Q$6)% -> 0.026789963 | R26: =_xll.meLWOBondCleanPrice($P26,$C$4,$Q26%) -> 133.529 | S26: =_xll.meLWOBondDirtyPrice($P26,$C$4,$Q26%) -> 133.797 | T26: =_xll.meLWOBondAccruedInterestDays(P26,$C$4) -> 30 | U26: =_xll.meLWOBondAccruedInterest(P26,$C$4) -> 2680 | V26: =_xll.meLWOBondModifiedDuration($P26,$C$4,$Q26%) -> 9.1423164 | W26: =_xll.meLWOBondDV01($P26,$C$4,$Q26%) -> 1223.2145 | X26: =IF(M26<=6,"YMA Comdty","XMA Comdty") -> XMA Comdty | Y26: =_xll.BDP($X26,Y$6) -> 97.295 | Z26: =_xll.BDP($X26,Z$6) -> 97.3 | AA26: =(100-AVERAGE(Y26:Z26))% -> 0.027025 | AB26: =Q26-AA26 -> -0.00023503736
B27: AQ762933 Corp | C27: =_xll.BDP($B27,C$6) -> ACGB 2 3/4 11/21/29 | D27: =_xll.BDP($B27,D$6) -> AU000XCLWAX7 | E27: =DATEVALUE(_xll.BDP($B27,E$6)) -> 43125 | F27: =DATEVALUE(_xll.BDP($B27,F$6)) -> 43060 | H27: =DATEVALUE(_xll.BDP($B27,H$6)) -> 43241 | I27: =DATEVALUE(_xll.BDP($B27,I$6)) -> 47259 | J27: =IF(ISNUMBER(O27),O27,_xll.BDP($B27,J$6)%) -> 0.0275 | K27: =DATEVALUE(_xll.BDP($B27,K$6)) -> 47443 | L27: =_xll.BDP($B27,L$6) -> ACT/ACT | M27: =_xll.BDP($B27,M$6) -> 11.003422 | N27: =_xll.BDP($B27,N$6) -> CLEAN | P27: =_xll.meLWOBondCreateFromGeneratorLVB(C27,$P$4&"_"&$N27,_xll.meUtilityLVBFromKeysValues($C$7:$K$7,C27:K27)) -> ACGB 2 3/4 11/21/29@59:7 | Q27: =_xll.BDP($B27,$Q$6)% -> 0.026903931 | R27: =_xll.meLWOBondCleanPrice($P27,$C$4,$Q27%) -> 129.915 | S27: =_xll.meLWOBondDirtyPrice($P27,$C$4,$Q27%) -> 129.908 | T27: =_xll.meLWOBondAccruedInterestDays(P27,$C$4) -> -1 | U27: =_xll.meLWOBondAccruedInterest(P27,$C$4) -> -70 | V27: =_xll.meLWOBondModifiedDuration($P27,$C$4,$Q27%) -> 9.780135 | W27: =_xll.meLWOBondDV01($P27,$C$4,$Q27%) -> 1270.5178 | X27: =IF(M27<=6,"YMA Comdty","XMA Comdty") -> XMA Comdty | Y27: =_xll.BDP($X27,Y$6) -> 97.295 | Z27: =_xll.BDP($X27,Z$6) -> 97.3 | AA27: =(100-AVERAGE(Y27:Z27))% -> 0.027025 | AB27: =Q27-AA27 -> -0.00012106902
B28: AS904985 Corp | C28: =_xll.BDP($B28,C$6) -> ACGB 2 1/2 05/21/30 | D28: =_xll.BDP($B28,D$6) -> AU0000013740 | E28: =DATEVALUE(_xll.BDP($B28,E$6)) -> 43264 | F28: =DATEVALUE(_xll.BDP($B28,F$6)) -> 43241 | H28: =DATEVALUE(_xll.BDP($B28,H$6)) -> 43425 | I28: =DATEVALUE(_xll.BDP($B28,I$6)) -> 47443 | J28: =IF(ISNUMBER(O28),O28,_xll.BDP($B28,J$6)%) -> 0.025 | K28: =DATEVALUE(_xll.BDP($B28,K$6)) -> 47624 | L28: =_xll.BDP($B28,L$6) -> ACT/ACT | M28: =_xll.BDP($B28,M$6) -> 11.498973 | N28: =_xll.BDP($B28,N$6) -> CLEAN | P28: =_xll.meLWOBondCreateFromGeneratorLVB(C28,$P$4&"_"&$N28,_xll.meUtilityLVBFromKeysValues($C$7:$K$7,C28:K28)) -> ACGB 2 1/2 05/21/30@40:7 | Q28: =_xll.BDP($B28,$Q$6)% -> 0.027224511 | R28: =_xll.meLWOBondCleanPrice($P28,$C$4,$Q28%) -> 128.397 | S28: =_xll.meLWOBondDirtyPrice($P28,$C$4,$Q28%) -> 128.39 | T28: =_xll.meLWOBondAccruedInterestDays(P28,$C$4) -> -1 | U28: =_xll.meLWOBondAccruedInterest(P28,$C$4) -> -70 | V28: =_xll.meLWOBondModifiedDuration($P28,$C$4,$Q28%) -> 10.271099 | W28: =_xll.meLWOBondDV01($P28,$C$4,$Q28%) -> 1318.7064 | X28: =IF(M28<=6,"YMA Comdty","XMA Comdty") -> XMA Comdty | Y28: =_xll.BDP($X28,Y$6) -> 97.295 | Z28: =_xll.BDP($X28,Z$6) -> 97.3 | AA28: =(100-AVERAGE(Y28:Z28))% -> 0.027025 | AB28: =Q28-AA28 -> 0.00019951123
B29: EI405114 Corp | C29: =_xll.BDP($B29,C$6) -> ACGB 2 1/2 09/20/30 | D29: =_xll.BDP($B29,D$6) -> AU0000XCLWV6 | E29: =DATEVALUE(_xll.BDP($B29,E$6)) -> 40442 | F29: =DATEVALUE(_xll.BDP($B29,F$6)) -> 40441 | H29: =DATEVALUE(_xll.BDP($B29,H$6)) -> 40532 | I29: =DATEVALUE(_xll.BDP($B29,I$6)) -> 47654 | J29: =IF(ISNUMBER(O29),O29,_xll.BDP($B29,J$6)%) -> 0.025 | K29: =DATEVALUE(_xll.BDP($B29,K$6)) -> 47746 | L29: =_xll.BDP($B29,L$6) -> ACT/ACT | M29: =_xll.BDP($B29,M$6) -> 11.832991 | N29: =_xll.BDP($B29,N$6) -> CLEAN | P29: =_xll.meLWOBondCreateFromGeneratorLVB(C29,$P$4&"_"&$N29,_xll.meUtilityLVBFromKeysValues($C$7:$K$7,C29:K29)) -> ACGB 2 1/2 09/20/30@53:7 | Q29: =_xll.BDP($B29,$Q$6)% -> 0.008141 | R29: =_xll.meLWOBondCleanPrice($P29,$C$4,$Q29%) -> 129.467 | S29: =_xll.meLWOBondDirtyPrice($P29,$C$4,$Q29%) -> 130.512 | T29: =_xll.meLWOBondAccruedInterestDays(P29,$C$4) -> 153 | U29: =_xll.meLWOBondAccruedInterest(P29,$C$4) -> 10450 | V29: =_xll.meLWOBondModifiedDuration($P29,$C$4,$Q29%) -> 10.645327 | W29: =_xll.meLWOBondDV01($P29,$C$4,$Q29%) -> 1389.3429 | X29: =IF(M29<=6,"YMA Comdty","XMA Comdty") -> XMA Comdty | Y29: =_xll.BDP($X29,Y$6) -> 97.295 | Z29: =_xll.BDP($X29,Z$6) -> 97.3 | AA29: =(100-AVERAGE(Y29:Z29))% -> 0.027025 | AB29: =Q29-AA29 -> -0.018884
B30: EJ943727 Corp | C30: =_xll.BDP($B30,C$6) -> ACGB 4 1/2 04/21/33 | D30: =_xll.BDP($B30,D$6) -> AU000XCLWAG2 | E30: =DATEVALUE(_xll.BDP($B30,E$6)) -> 41604 | F30: =DATEVALUE(_xll.BDP($B30,F$6)) -> 41568 | H30: =DATEVALUE(_xll.BDP($B30,H$6)) -> 41750 | I30: =DATEVALUE(_xll.BDP($B30,I$6)) -> 48508 | J30: =IF(ISNUMBER(O30),O30,_xll.BDP($B30,J$6)%) -> 0.045 | K30: =DATEVALUE(_xll.BDP($B30,K$6)) -> 48690 | L30: =_xll.BDP($B30,L$6) -> ACT/ACT | M30: =_xll.BDP($B30,M$6) -> 14.417522 | N30: =_xll.BDP($B30,N$6) -> CLEAN | P30: =_xll.meLWOBondCreateFromGeneratorLVB(C30,$P$4&"_"&$N30,_xll.meUtilityLVBFromKeysValues($C$7:$K$7,C30:K30)) -> ACGB 4 1/2 04/21/33@33:7 | Q30: =_xll.BDP($B30,$Q$6)% -> 0.028319673 | R30: =_xll.meLWOBondCleanPrice($P30,$C$4,$Q30%) -> 164.335 | S30: =_xll.meLWOBondDirtyPrice($P30,$C$4,$Q30%) -> 164.706 | T30: =_xll.meLWOBondAccruedInterestDays(P30,$C$4) -> 30 | U30: =_xll.meLWOBondAccruedInterest(P30,$C$4) -> 3710 | V30: =_xll.meLWOBondModifiedDuration($P30,$C$4,$Q30%) -> 11.646641 | W30: =_xll.meLWOBondDV01($P30,$C$4,$Q30%) -> 1918.2717 | X30: =IF(M30<=6,"YMA Comdty","XMA Comdty") -> XMA Comdty | Y30: =_xll.BDP($X30,Y$6) -> 97.295 | Z30: =_xll.BDP($X30,Z$6) -> 97.3 | AA30: =(100-AVERAGE(Y30:Z30))% -> 0.027025 | AB30: =Q30-AA30 -> 0.0012946731
B31: EK821167 Corp | C31: =_xll.BDP($B31,C$6) -> ACGB 2 3/4 06/21/35 | D31: =_xll.BDP($B31,D$6) -> AU000XCLWAM0 | E31: =DATEVALUE(_xll.BDP($B31,E$6)) -> 42094 | F31: =DATEVALUE(_xll.BDP($B31,F$6)) -> 41994 | H31: =DATEVALUE(_xll.BDP($B31,H$6)) -> 42176 | I31: =DATEVALUE(_xll.BDP($B31,I$6)) -> 49299 | J31: =IF(ISNUMBER(O31),O31,_xll.BDP($B31,J$6)%) -> 0.0275 | K31: =DATEVALUE(_xll.BDP($B31,K$6)) -> 49481 | L31: =_xll.BDP($B31,L$6) -> ACT/ACT | M31: =_xll.BDP($B31,M$6) -> 16.583162 | N31: =_xll.BDP($B31,N$6) -> CLEAN | P31: =_xll.meLWOBondCreateFromGeneratorLVB(C31,$P$4&"_"&$N31,_xll.meUtilityLVBFromKeysValues($C$7:$K$7,C31:K31)) -> ACGB 2 3/4 06/21/35@39:7 | Q31: =_xll.BDP($B31,$Q$6)% -> 0.029484733 | R31: =_xll.meLWOBondCleanPrice($P31,$C$4,$Q31%) -> 145.006 | S31: =_xll.meLWOBondDirtyPrice($P31,$C$4,$Q31%) -> 146.148 | T31: =_xll.meLWOBondAccruedInterestDays(P31,$C$4) -> 152 | U31: =_xll.meLWOBondAccruedInterest(P31,$C$4) -> 11420 | V31: =_xll.meLWOBondModifiedDuration($P31,$C$4,$Q31%) -> 13.947782 | W31: =_xll.meLWOBondDV01($P31,$C$4,$Q31%) -> 2038.4404 | X31: =IF(M31<=6,"YMA Comdty","XMA Comdty") -> XMA Comdty | Y31: =_xll.BDP($X31,Y$6) -> 97.295 | Z31: =_xll.BDP($X31,Z$6) -> 97.3 | AA31: =(100-AVERAGE(Y31:Z31))% -> 0.027025 | AB31: =Q31-AA31 -> 0.0024597334
B32: EJ847557 Corp | C32: =_xll.BDP($B32,C$6) -> ACGB 2 08/21/35 | D32: =_xll.BDP($B32,D$6) -> AU000XCLWAF4 | E32: =DATEVALUE(_xll.BDP($B32,E$6)) -> 41550 | F32: =DATEVALUE(_xll.BDP($B32,F$6)) -> 41507 | H32: =DATEVALUE(_xll.BDP($B32,H$6)) -> 41599 | I32: =DATEVALUE(_xll.BDP($B32,I$6)) -> 49450 | J32: =IF(ISNUMBER(O32),O32,_xll.BDP($B32,J$6)%) -> 0.02 | K32: =DATEVALUE(_xll.BDP($B32,K$6)) -> 49542 | L32: =_xll.BDP($B32,L$6) -> ACT/ACT | M32: =_xll.BDP($B32,M$6) -> 16.750171 | N32: =_xll.BDP($B32,N$6) -> CLEAN | P32: =_xll.meLWOBondCreateFromGeneratorLVB(C32,$P$4&"_"&$N32,_xll.meUtilityLVBFromKeysValues($C$7:$K$7,C32:K32)) -> ACGB 2 08/21/35@60:8 | Q32: =_xll.BDP($B32,$Q$6)% -> 0.00955 | R32: =_xll.meLWOBondCleanPrice($P32,$C$4,$Q32%) -> 133.323 | S32: =_xll.meLWOBondDirtyPrice($P32,$C$4,$Q32%) -> 133.318 | T32: =_xll.meLWOBondAccruedInterestDays(P32,$C$4) -> -1 | U32: =_xll.meLWOBondAccruedInterest(P32,$C$4) -> -50 | V32: =_xll.meLWOBondModifiedDuration($P32,$C$4,$Q32%) -> 14.899242 | W32: =_xll.meLWOBondDV01($P32,$C$4,$Q32%) -> 1986.3372 | X32: =IF(M32<=6,"YMA Comdty","XMA Comdty") -> XMA Comdty | Y32: =_xll.BDP($X32,Y$6) -> 97.295 | Z32: =_xll.BDP($X32,Z$6) -> 97.3 | AA32: =(100-AVERAGE(Y32:Z32))% -> 0.027025 | AB32: =Q32-AA32 -> -0.017475
B33: EK544675 Corp | C33: =_xll.BDP($B33,C$6) -> ACGB 3 3/4 04/21/37 | D33: =_xll.BDP($B33,D$6) -> AU3TB0000192 | E33: =DATEVALUE(_xll.BDP($B33,E$6)) -> 41933 | F33: =DATEVALUE(_xll.BDP($B33,F$6)) -> 41933 | H33: =DATEVALUE(_xll.BDP($B33,H$6)) -> 42115 | I33: =DATEVALUE(_xll.BDP($B33,I$6)) -> 49969 | J33: =IF(ISNUMBER(O33),O33,_xll.BDP($B33,J$6)%) -> 0.0375 | K33: =DATEVALUE(_xll.BDP($B33,K$6)) -> 50151 | L33: =_xll.BDP($B33,L$6) -> ACT/ACT | M33: =_xll.BDP($B33,M$6) -> 18.417522 | N33: =_xll.BDP($B33,N$6) -> CLEAN | P33: =_xll.meLWOBondCreateFromGeneratorLVB(C33,$P$4&"_"&$N33,_xll.meUtilityLVBFromKeysValues($C$7:$K$7,C33:K33)) -> ACGB 3 3/4 04/21/37@43:7 | Q33: =_xll.BDP($B33,$Q$6)% -> 0.030005117 | R33: =_xll.meLWOBondCleanPrice($P33,$C$4,$Q33%) -> 168.319 | S33: =_xll.meLWOBondDirtyPrice($P33,$C$4,$Q33%) -> 168.628 | T33: =_xll.meLWOBondAccruedInterestDays(P33,$C$4) -> 30 | U33: =_xll.meLWOBondAccruedInterest(P33,$C$4) -> 3090 | V33: =_xll.meLWOBondModifiedDuration($P33,$C$4,$Q33%) -> 14.719663 | W33: =_xll.meLWOBondDV01($P33,$C$4,$Q33%) -> 2482.1474 | X33: =IF(M33<=6,"YMA Comdty","XMA Comdty") -> XMA Comdty | Y33: =_xll.BDP($X33,Y$6) -> 97.295 | Z33: =_xll.BDP($X33,Z$6) -> 97.3 | AA33: =(100-AVERAGE(Y33:Z33))% -> 0.027025 | AB33: =Q33-AA33 -> 0.0029801175
B34: QJ152182 Corp | C34: =_xll.BDP($B34,C$6) -> ACGB 3 1/4 06/21/39 | D34: =_xll.BDP($B34,D$6) -> AU000XCLWAP3 | E34: =DATEVALUE(_xll.BDP($B34,E$6)) -> 42298 | F34: =DATEVALUE(_xll.BDP($B34,F$6)) -> 42176 | H34: =DATEVALUE(_xll.BDP($B34,H$6)) -> 42359 | I34: =DATEVALUE(_xll.BDP($B34,I$6)) -> 50760 | J34: =IF(ISNUMBER(O34),O34,_xll.BDP($B34,J$6)%) -> 0.0325 | K34: =DATEVALUE(_xll.BDP($B34,K$6)) -> 50942 | L34: =_xll.BDP($B34,L$6) -> ACT/ACT | M34: =_xll.BDP($B34,M$6) -> 20.583162 | N34: =_xll.BDP($B34,N$6) -> CLEAN | P34: =_xll.meLWOBondCreateFromGeneratorLVB(C34,$P$4&"_"&$N34,_xll.meUtilityLVBFromKeysValues($C$7:$K$7,C34:K34)) -> ACGB 3 1/4 06/21/39@44:7 | Q34: =_xll.BDP($B34,$Q$6)% -> 0.030664739 | R34: =_xll.meLWOBondCleanPrice($P34,$C$4,$Q34%) -> 166.055 | S34: =_xll.meLWOBondDirtyPrice($P34,$C$4,$Q34%) -> 167.405 | T34: =_xll.meLWOBondAccruedInterestDays(P34,$C$4) -> 152 | U34: =_xll.meLWOBondAccruedInterest(P34,$C$4) -> 13500 | V34: =_xll.meLWOBondModifiedDuration($P34,$C$4,$Q34%) -> 16.411957 | W34: =_xll.meLWOBondDV01($P34,$C$4,$Q34%) -> 2747.4437 | X34: =IF(M34<=6,"YMA Comdty","XMA Comdty") -> XMA Comdty | Y34: =_xll.BDP($X34,Y$6) -> 97.295 | Z34: =_xll.BDP($X34,Z$6) -> 97.3 | AA34: =(100-AVERAGE(Y34:Z34))% -> 0.027025 | AB34: =Q34-AA34 -> 0.0036397391
... B38: AU555712 Corp | C38: =_xll.BDP($B38,C$6) -> ACGB 1 02/21/50 | D38: =_xll.BDP($B38,D$6) -> AU0000024044 | E38: =DATEVALUE(_xll.BDP($B38,E$6)) -> 43368 | F38: =DATEVALUE(_xll.BDP($B38,F$6)) -> 43333 | H38: =DATEVALUE(_xll.BDP($B38,H$6)) -> 43425 | I38: =DATEVALUE(_xll.BDP($B38,I$6)) -> 54748 | J38: =IF(ISNUMBER(O38),O38,_xll.BDP($B38,J$6)%) -> 0.01 | K38: =DATEVALUE(_xll.BDP($B38,K$6)) -> 54840 | L38: =_xll.BDP($B38,L$6) -> ACT/ACT | M38: =_xll.BDP($B38,M$6) -> 31.255305 | N38: =_xll.BDP($B38,N$6) -> CLEAN | P38: =_xll.meLWOBondCreateFromGeneratorLVB(C38,$P$4&"_"&$N38,_xll.meUtilityLVBFromKeysValues($C$7:$K$7,C38:K38)) -> ACGB 1 02/21/50@38:7 | Q38: =_xll.BDP($B38,$Q$6)% -> 0.010913 | R38: =_xll.meLWOBondCleanPrice($P38,$C$4,$Q38%) -> 130.856 | S38: =_xll.meLWOBondDirtyPrice($P38,$C$4,$Q38%) -> 130.853 | T38: =_xll.meLWOBondAccruedInterestDays(P38,$C$4) -> -1 | U38: =_xll.meLWOBondAccruedInterest(P38,$C$4) -> -30 | V38: =_xll.meLWOBondModifiedDuration($P38,$C$4,$Q38%) -> 27.77419 | W38: =_xll.meLWOBondDV01($P38,$C$4,$Q38%) -> 3634.336 | X38: =IF(M38<=6,"YMA Comdty","XMA Comdty") -> XMA Comdty | Y38: =_xll.BDP($X38,Y$6) -> 97.295 | Z38: =_xll.BDP($X38,Z$6) -> 97.3 | AA38: =(100-AVERAGE(Y38:Z38))% -> 0.027025 | AB38: =Q38-AA38 -> -0.016112
