Workbook
Name COB: [1]Settings!$C$2
Name Settings.COB: SETTINGS!$B$3
Name Settings.FrequencyLookupTable: [1]Settings!$B$206:$C$210

Sheet SETTINGS
B2: COB | E2: LIBOR FIXING DATA | K2: SPOT FX DATA
B3: =TODAY() -> 44063
E4: USD | H4: AUD
E5: 1M | F5: 0.0123444 | H5: 1M | I5: 0.0159 | K5: AUDUSD | L5: 0.75
E6: 3M | F6: 0.0129556 | H6: 3M | I6: 0.0171
E7: 6M | F7: 0.0145556 | H7: 6M | I7: 0.0186
E8: 12M | F8: 0.0172789

Sheet USD-BONDS
B2: USD Bonds
Q3: USD Bond Template
B5: Bond Price | D5: Handle | E5: BondDescription | F5: ISIN | G5: IsCleanPrice | H5: IssueDate | I5: AccrualStartDate | J5: FirstCouponDate | K5: LastCouponDate | L5: MaturityDate | M5: Coupon | N5: DayCount | O5: Frequency | Q5: BondLVB
A6: 1 | B6: 96.021 | D6: =_xll.meLWOBondCreate(E6,_xll.meUtilityLVBFromMultipleKeysValues($E$5:$G$5,E6:G6,,$Q$6:$Q$9,$R$6:$R$9),_xll.meUtilityLVBFromMultipleKeysValues($H$5:$O$5,H6:O6,,$Q$16:$Q$24,$R$16:$R$24)) -> MIZUHO-3.2%-26-MAR-25-USD@118:3 | E6: MIZUHO-3.2%-26-MAR-25-USD | F6: USJ46186BC59 | G6: TRUE | H6: 42089 | I6: =H6 -> 42089 | L6: 45742 | M6: 0.032 | N6: 30E/360 | O6: SEMI-ANNUAL | Q6: BondType | R6: FIXED
A7: =A6+1 -> 2 | B7: 94.55 | D7: =_xll.meLWOBondCreate(E7,_xll.meUtilityLVBFromMultipleKeysValues($E$5:$G$5,E7:G7,,$Q$6:$Q$9,$R$6:$R$9),_xll.meUtilityLVBFromMultipleKeysValues($H$5:$O$5,H7:O7,,$Q$16:$Q$24,$R$16:$R$24)) -> MIZUHO-1.61-27-JUL-21-USD@96:3 | E7: MIZUHO-1.61-27-JUL-21-USD | F7: XS1447582930 | G7: TRUE | H7: 42566 | I7: 42578 | L7: 44404 | M7: 0.0161 | N7: 30E/360 | O7: SEMI-ANNUAL | Q7: Currency | R7: USD
A8: =A7+1 -> 3 | B8: 100 | D8: =_xll.meLWOBondCreate(E8,_xll.meUtilityLVBFromMultipleKeysValues($E$5:$G$5,E8:G8,,$Q$6:$Q$9,$R$6:$R$9),_xll.meUtilityLVBFromMultipleKeysValues($H$5:$O$5,H8:O8,,$Q$16:$Q$24,$R$16:$R$24)) -> USD-DUMMY-BOND2@109:3 | E8: USD-DUMMY-BOND2 | F8: ISIN2 | G8: TRUE | H8: 42089 | I8: =H8 -> 42089 | L8: 45742 | M8: 0.032 | N8: 30E/360 | O8: SEMI-ANNUAL | Q8: YieldType | R8: YIELD-TO-MATURITY
A9: =A8+1 -> 4 | B9: 100 | D9: =_xll.meLWOBondCreate(E9,_xll.meUtilityLVBFromMultipleKeysValues($E$5:$G$5,E9:G9,,$Q$6:$Q$9,$R$6:$R$9),_xll.meUtilityLVBFromMultipleKeysValues($H$5:$O$5,H9:O9,,$Q$16:$Q$24,$R$16:$R$24)) -> USD-DUMMY-BOND3@121:3 | E9: USD-DUMMY-BOND3 | F9: ISIN3 | G9: TRUE | H9: 42089 | I9: =H9 -> 42089 | L9: 45742 | M9: 0.032 | N9: 30E/360 | O9: SEMI-ANNUAL | Q9: BondQuoteConvention | R9: QUOTE_IN_32NDS
A10: =A9+1 -> 5 | B10: 100 | D10: =_xll.meLWOBondCreate(E10,_xll.meUtilityLVBFromMultipleKeysValues($E$5:$G$5,E10:G10,,$Q$6:$Q$9,$R$6:$R$9),_xll.meUtilityLVBFromMultipleKeysValues($H$5:$O$5,H10:O10,,$Q$16:$Q$24,$R$16:$R$24)) -> USD-DUMMY-BOND4@125:3 | E10: USD-DUMMY-BOND4 | F10: ISIN4 | G10: TRUE | H10: 42089 | I10: =H10 -> 42089 | L10: 45742 | M10: 0.032 | N10: 30E/360 | O10: SEMI-ANNUAL | Q10: BondDescription
A11: =A10+1 -> 6 | B11: 100 | D11: =_xll.meLWOBondCreate(E11,_xll.meUtilityLVBFromMultipleKeysValues($E$5:$G$5,E11:G11,,$Q$6:$Q$9,$R$6:$R$9),_xll.meUtilityLVBFromMultipleKeysValues($H$5:$O$5,H11:O11,,$Q$16:$Q$24,$R$16:$R$24)) -> USD-DUMMY-BOND5@122:3 | E11: USD-DUMMY-BOND5 | F11: ISIN5 | G11: TRUE | H11: 42089 | I11: =H11 -> 42089 | L11: 45742 | M11: 0.032 | N11: 30E/360 | O11: SEMI-ANNUAL | Q11: ISIN
A12: =A11+1 -> 7 | B12: 100 | D12: =_xll.meLWOBondCreate(E12,_xll.meUtilityLVBFromMultipleKeysValues($E$5:$G$5,E12:G12,,$Q$6:$Q$9,$R$6:$R$9),_xll.meUtilityLVBFromMultipleKeysValues($H$5:$O$5,H12:O12,,$Q$16:$Q$24,$R$16:$R$24)) -> USD-DUMMY-BOND6@117:3 | E12: USD-DUMMY-BOND6 | F12: ISIN6 | G12: TRUE | H12: 42089 | I12: =H12 -> 42089 | L12: 45742 | M12: 0.032 | N12: 30E/360 | O12: SEMI-ANNUAL | Q12: IsCleanPrice
A13: =A12+1 -> 8 | B13: 100 | D13: =_xll.meLWOBondCreate(E13,_xll.meUtilityLVBFromMultipleKeysValues($E$5:$G$5,E13:G13,,$Q$6:$Q$9,$R$6:$R$9),_xll.meUtilityLVBFromMultipleKeysValues($H$5:$O$5,H13:O13,,$Q$16:$Q$24,$R$16:$R$24)) -> USD-DUMMY-BOND7@145:3 | E13: USD-DUMMY-BOND7 | F13: ISIN7 | G13: TRUE | H13: 42089 | I13: =H13 -> 42089 | L13: 45742 | M13: 0.032 | N13: 30E/360 | O13: SEMI-ANNUAL
A14: =A13+1 -> 9 | B14: 100 | D14: =_xll.meLWOBondCreate(E14,_xll.meUtilityLVBFromMultipleKeysValues($E$5:$G$5,E14:G14,,$Q$6:$Q$9,$R$6:$R$9),_xll.meUtilityLVBFromMultipleKeysValues($H$5:$O$5,H14:O14,,$Q$16:$Q$24,$R$16:$R$24)) -> USD-DUMMY-BOND8@144:3 | E14: USD-DUMMY-BOND8 | F14: ISIN8 | G14: TRUE | H14: 42089 | I14: =H14 -> 42089 | L14: 45742 | M14: 0.032 | N14: 30E/360 | O14: SEMI-ANNUAL
A15: =A14+1 -> 10 | B15: 100 | D15: =_xll.meLWOBondCreate(E15,_xll.meUtilityLVBFromMultipleKeysValues($E$5:$G$5,E15:G15,,$Q$6:$Q$9,$R$6:$R$9),_xll.meUtilityLVBFromMultipleKeysValues($H$5:$O$5,H15:O15,,$Q$16:$Q$24,$R$16:$R$24)) -> USD-DUMMY-BOND9@115:3 | E15: USD-DUMMY-BOND9 | F15: ISIN9 | G15: TRUE | H15: 42089 | I15: =H15 -> 42089 | L15: 45742 | M15: 0.032 | N15: 30E/360 | O15: SEMI-ANNUAL | Q15: ScheduleLVB
A16: =A15+1 -> 11 | B16: 100 | D16: =_xll.meLWOBondCreate(E16,_xll.meUtilityLVBFromMultipleKeysValues($E$5:$G$5,E16:G16,,$Q$6:$Q$9,$R$6:$R$9),_xll.meUtilityLVBFromMultipleKeysValues($H$5:$O$5,H16:O16,,$Q$16:$Q$24,$R$16:$R$24)) -> USD-DUMMY-BOND10@131:3 | E16: USD-DUMMY-BOND10 | F16: ISIN10 | G16: TRUE | H16: 42089 | I16: =H16 -> 42089 | L16: 45742 | M16: 0.032 | N16: 30E/360 | O16: SEMI-ANNUAL | Q16: PayReceive | R16: RECEIVE
A17: =A16+1 -> 12 | B17: 100 | D17: =_xll.meLWOBondCreate(E17,_xll.meUtilityLVBFromMultipleKeysValues($E$5:$G$5,E17:G17,,$Q$6:$Q$9,$R$6:$R$9),_xll.meUtilityLVBFromMultipleKeysValues($H$5:$O$5,H17:O17,,$Q$16:$Q$24,$R$16:$R$24)) -> USD-DUMMY-BOND11@134:3 | E17: USD-DUMMY-BOND11 | F17: ISIN11 | G17: TRUE | H17: 42089 | I17: =H17 -> 42089 | L17: 45742 | M17: 0.032 | N17: 30E/360 | O17: SEMI-ANNUAL | Q17: NotionalExchange | R17: START_AND_END
A18: =A17+1 -> 13 | B18: 100 | D18: =_xll.meLWOBondCreate(E18,_xll.meUtilityLVBFromMultipleKeysValues($E$5:$G$5,E18:G18,,$Q$6:$Q$9,$R$6:$R$9),_xll.meUtilityLVBFromMultipleKeysValues($H$5:$O$5,H18:O18,,$Q$16:$Q$24,$R$16:$R$24)) -> USD-DUMMY-BOND12@100:3 | E18: USD-DUMMY-BOND12 | F18: ISIN12 | G18: TRUE | H18: 42089 | I18: =H18 -> 42089 | L18: 45742 | M18: 0.032 | N18: 30E/360 | O18: SEMI-ANNUAL | Q18: FaceValue | R18: 1000000
A19: =A18+1 -> 14 | B19: 100 | D19: =_xll.meLWOBondCreate(E19,_xll.meUtilityLVBFromMultipleKeysValues($E$5:$G$5,E19:G19,,$Q$6:$Q$9,$R$6:$R$9),_xll.meUtilityLVBFromMultipleKeysValues($H$5:$O$5,H19:O19,,$Q$16:$Q$24,$R$16:$R$24)) -> USD-DUMMY-BOND13@139:3 | E19: USD-DUMMY-BOND13 | F19: ISIN13 | G19: TRUE | H19: 42089 | I19: =H19 -> 42089 | L19: 45742 | M19: 0.032 | N19: 30E/360 | O19: SEMI-ANNUAL | Q19: AccrualBusinessDayAdjustment | R19: MOD_FOLLOWING
A20: =A19+1 -> 15 | B20: 100 | D20: =_xll.meLWOBondCreate(E20,_xll.meUtilityLVBFromMultipleKeysValues($E$5:$G$5,E20:G20,,$Q$6:$Q$9,$R$6:$R$9),_xll.meUtilityLVBFromMultipleKeysValues($H$5:$O$5,H20:O20,,$Q$16:$Q$24,$R$16:$R$24)) -> USD-DUMMY-BOND14@116:3 | E20: USD-DUMMY-BOND14 | F20: ISIN14 | G20: TRUE | H20: 42089 | I20: =H20 -> 42089 | L20: 45742 | M20: 0.032 | N20: 30E/360 | O20: SEMI-ANNUAL | Q20: AccrualCalendar | R20: NYB
A21: =A20+1 -> 16 | B21: 100 | D21: =_xll.meLWOBondCreate(E21,_xll.meUtilityLVBFromMultipleKeysValues($E$5:$G$5,E21:G21,,$Q$6:$Q$9,$R$6:$R$9),_xll.meUtilityLVBFromMultipleKeysValues($H$5:$O$5,H21:O21,,$Q$16:$Q$24,$R$16:$R$24)) -> USD-DUMMY-BOND15@110:3 | E21: USD-DUMMY-BOND15 | F21: ISIN15 | G21: TRUE | H21: 42089 | I21: =H21 -> 42089 | L21: 45742 | M21: 0.032 | N21: 30E/360 | O21: SEMI-ANNUAL | Q21: PaymentBusinessDayAdjustment | R21: NO_CHANGE
A22: =A21+1 -> 17 | B22: 100 | D22: =_xll.meLWOBondCreate(E22,_xll.meUtilityLVBFromMultipleKeysValues($E$5:$G$5,E22:G22,,$Q$6:$Q$9,$R$6:$R$9),_xll.meUtilityLVBFromMultipleKeysValues($H$5:$O$5,H22:O22,,$Q$16:$Q$24,$R$16:$R$24)) -> USD-DUMMY-BOND16@97:3 | E22: USD-DUMMY-BOND16 | F22: ISIN16 | G22: TRUE | H22: 42089 | I22: =H22 -> 42089 | L22: 45742 | M22: 0.032 | N22: 30E/360 | O22: SEMI-ANNUAL | Q22: PaymentCalendar | R22: NYB
A23: =A22+1 -> 18 | B23: 100 | D23: =_xll.meLWOBondCreate(E23,_xll.meUtilityLVBFromMultipleKeysValues($E$5:$G$5,E23:G23,,$Q$6:$Q$9,$R$6:$R$9),_xll.meUtilityLVBFromMultipleKeysValues($H$5:$O$5,H23:O23,,$Q$16:$Q$24,$R$16:$R$24)) -> USD-DUMMY-BOND17@130:3 | E23: USD-DUMMY-BOND17 | F23: ISIN17 | G23: TRUE | H23: 42089 | I23: =H23 -> 42089 | L23: 45742 | M23: 0.032 | N23: 30E/360 | O23: SEMI-ANNUAL | Q23: PaymentLag | R23: 0D
A24: =A23+1 -> 19 | B24: 100 | D24: =_xll.meLWOBondCreate(E24,_xll.meUtilityLVBFromMultipleKeysValues($E$5:$G$5,E24:G24,,$Q$6:$Q$9,$R$6:$R$9),_xll.meUtilityLVBFromMultipleKeysValues($H$5:$O$5,H24:O24,,$Q$16:$Q$24,$R$16:$R$24)) -> USD-DUMMY-BOND18@135:3 | E24: USD-DUMMY-BOND18 | F24: ISIN18 | G24: TRUE | H24: 42089 | I24: =H24 -> 42089 | L24: 45742 | M24: 0.032 | N24: 30E/360 | O24: SEMI-ANNUAL | Q24: CalculationType | R24: TYPE1_STREET_CONVENTION
A25: =A24+1 -> 20 | B25: 100 | D25: =_xll.meLWOBondCreate(E25,_xll.meUtilityLVBFromMultipleKeysValues($E$5:$G$5,E25:G25,,$Q$6:$Q$9,$R$6:$R$9),_xll.meUtilityLVBFromMultipleKeysValues($H$5:$O$5,H25:O25,,$Q$16:$Q$24,$R$16:$R$24)) -> USD-DUMMY-BOND19@99:3 | E25: USD-DUMMY-BOND19 | F25: ISIN19 | G25: TRUE | H25: 42089 | I25: =H25 -> 42089 | L25: 45742 | M25: 0.032 | N25: 30E/360 | O25: SEMI-ANNUAL | Q25: IssueDate
A26: =A25+1 -> 21 | B26: 100 | D26: =_xll.meLWOBondCreate(E26,_xll.meUtilityLVBFromMultipleKeysValues($E$5:$G$5,E26:G26,,$Q$6:$Q$9,$R$6:$R$9),_xll.meUtilityLVBFromMultipleKeysValues($H$5:$O$5,H26:O26,,$Q$16:$Q$24,$R$16:$R$24)) -> USD-DUMMY-BOND20@111:3 | E26: USD-DUMMY-BOND20 | F26: ISIN20 | G26: TRUE | H26: 42089 | I26: =H26 -> 42089 | L26: 45742 | M26: 0.032 | N26: 30E/360 | O26: SEMI-ANNUAL | Q26: AccrualStartDate
A27: =A26+1 -> 22 | B27: 100 | D27: =_xll.meLWOBondCreate(E27,_xll.meUtilityLVBFromMultipleKeysValues($E$5:$G$5,E27:G27,,$Q$6:$Q$9,$R$6:$R$9),_xll.meUtilityLVBFromMultipleKeysValues($H$5:$O$5,H27:O27,,$Q$16:$Q$24,$R$16:$R$24)) -> USD-DUMMY-BOND21@95:3 | E27: USD-DUMMY-BOND21 | F27: ISIN21 | G27: TRUE | H27: 42089 | I27: =H27 -> 42089 | L27: 45742 | M27: 0.032 | N27: 30E/360 | O27: SEMI-ANNUAL | Q27: FirstCouponDate
A28: =A27+1 -> 23 | B28: 100 | D28: =_xll.meLWOBondCreate(E28,_xll.meUtilityLVBFromMultipleKeysValues($E$5:$G$5,E28:G28,,$Q$6:$Q$9,$R$6:$R$9),_xll.meUtilityLVBFromMultipleKeysValues($H$5:$O$5,H28:O28,,$Q$16:$Q$24,$R$16:$R$24)) -> USD-DUMMY-BOND22@140:3 | E28: USD-DUMMY-BOND22 | F28: ISIN22 | G28: TRUE | H28: 42089 | I28: =H28 -> 42089 | L28: 45742 | M28: 0.032 | N28: 30E/360 | O28: SEMI-ANNUAL | Q28: LastCouponDate
A29: =A28+1 -> 24 | B29: 100 | D29: =_xll.meLWOBondCreate(E29,_xll.meUtilityLVBFromMultipleKeysValues($E$5:$G$5,E29:G29,,$Q$6:$Q$9,$R$6:$R$9),_xll.meUtilityLVBFromMultipleKeysValues($H$5:$O$5,H29:O29,,$Q$16:$Q$24,$R$16:$R$24)) -> USD-DUMMY-BOND23@132:3 | E29: USD-DUMMY-BOND23 | F29: ISIN23 | G29: TRUE | H29: 42089 | I29: =H29 -> 42089 | L29: 45742 | M29: 0.032 | N29: 30E/360 | O29: SEMI-ANNUAL | Q29: MaturityDate
A30: =A29+1 -> 25 | B30: 100 | D30: =_xll.meLWOBondCreate(E30,_xll.meUtilityLVBFromMultipleKeysValues($E$5:$G$5,E30:G30,,$Q$6:$Q$9,$R$6:$R$9),_xll.meUtilityLVBFromMultipleKeysValues($H$5:$O$5,H30:O30,,$Q$16:$Q$24,$R$16:$R$24)) -> USD-DUMMY-BOND24@141:3 | E30: USD-DUMMY-BOND24 | F30: ISIN24 | G30: TRUE | H30: 42089 | I30: =H30 -> 42089 | L30: 45742 | M30: 0.032 | N30: 30E/360 | O30: SEMI-ANNUAL | Q30: Coupon
A31: =A30+1 -> 26 | B31: 100 | D31: =_xll.meLWOBondCreate(E31,_xll.meUtilityLVBFromMultipleKeysValues($E$5:$G$5,E31:G31,,$Q$6:$Q$9,$R$6:$R$9),_xll.meUtilityLVBFromMultipleKeysValues($H$5:$O$5,H31:O31,,$Q$16:$Q$24,$R$16:$R$24)) -> USD-DUMMY-BOND25@103:3 | E31: USD-DUMMY-BOND25 | F31: ISIN25 | G31: TRUE | H31: 42089 | I31: =H31 -> 42089 | L31: 45742 | M31: 0.032 | N31: 30E/360 | O31: SEMI-ANNUAL | Q31: DayCount
A32: =A31+1 -> 27 | B32: 100 | D32: =_xll.meLWOBondCreate(E32,_xll.meUtilityLVBFromMultipleKeysValues($E$5:$G$5,E32:G32,,$Q$6:$Q$9,$R$6:$R$9),_xll.meUtilityLVBFromMultipleKeysValues($H$5:$O$5,H32:O32,,$Q$16:$Q$24,$R$16:$R$24)) -> USD-DUMMY-BOND26@129:3 | E32: USD-DUMMY-BOND26 | F32: ISIN26 | G32: TRUE | H32: 42089 | I32: =H32 -> 42089 | L32: 45742 | M32: 0.032 | N32: 30E/360 | O32: SEMI-ANNUAL | Q32: Frequency

Sheet AUD-BONDS
B2: AUD Bonds
Q3: AUD Bond Template
B5: Bond Price | D5: Handle | E5: BondDescription | F5: ISIN | G5: IsCleanPrice | H5: IssueDate | I5: AccrualStartDate | J5: FirstCouponDate | K5: LastCouponDate | L5: MaturityDate | M5: Coupon | N5: DayCount | O5: Frequency | Q5: BondLVB
A6: 1 | B6: 95.483 | D6: =_xll.meLWOBondCreate(E6,_xll.meUtilityLVBFromMultipleKeysValues($E$5:$G$5,E6:G6,,$Q$6:$Q$9,$R$6:$R$9),_xll.meUtilityLVBFromMultipleKeysValues($H$5:$O$5,H6:O6,,$Q$16:$Q$24,$R$16:$R$24)) -> MIZUHO-3.92%-15-JAN-26 AUD@101:3 | E6: MIZUHO-3.92%-15-JAN-26 AUD | F6: XS1344710857 | G6: TRUE | H6: 42566 | I6: 42566 | L6: 46037 | M6: 0.0392 | N6: 30E/360 | O6: SEMI-ANNUAL | Q6: BondType | R6: FIXED
A7: =A6+1 -> 2 | B7: 100 | D7: =_xll.meLWOBondCreate(E7,_xll.meUtilityLVBFromMultipleKeysValues($E$5:$G$5,E7:G7,,$Q$6:$Q$9,$R$6:$R$9),_xll.meUtilityLVBFromMultipleKeysValues($H$5:$O$5,H7:O7,,$Q$16:$Q$24,$R$16:$R$24)) -> MIZUHO-2.62%27-JUL-21-AUD@98:3 | E7: MIZUHO-2.62%27-JUL-21-AUD | F7: XS1447583664 | G7: TRUE | H7: 42578 | I7: 42578 | L7: 44404 | M7: 0.0262 | N7: 30E/360 | O7: SEMI-ANNUAL | Q7: Currency | R7: AUD
A8: =A7+1 -> 3 | B8: 100 | D8: =_xll.meLWOBondCreate(E8,_xll.meUtilityLVBFromMultipleKeysValues($E$5:$G$5,E8:G8,,$Q$6:$Q$9,$R$6:$R$9),_xll.meUtilityLVBFromMultipleKeysValues($H$5:$O$5,H8:O8,,$Q$16:$Q$24,$R$16:$R$24)) -> AUD_DUMMY_BOND2@123:3 | E8: AUD_DUMMY_BOND2 | F8: ISIN2 | G8: TRUE | H8: 42566 | I8: 42566 | L8: 46037 | M8: 0.0392 | N8: 30E/360 | O8: SEMI-ANNUAL | Q8: YieldType | R8: YIELD-TO-MATURITY
A9: =A8+1 -> 4 | B9: 100 | D9: =_xll.meLWOBondCreate(E9,_xll.meUtilityLVBFromMultipleKeysValues($E$5:$G$5,E9:G9,,$Q$6:$Q$9,$R$6:$R$9),_xll.meUtilityLVBFromMultipleKeysValues($H$5:$O$5,H9:O9,,$Q$16:$Q$24,$R$16:$R$24)) -> AUD_DUMMY_BOND3@124:3 | E9: AUD_DUMMY_BOND3 | F9: ISIN3 | G9: TRUE | H9: 42566 | I9: 42566 | L9: 46037 | M9: 0.0392 | N9: 30E/360 | O9: SEMI-ANNUAL | Q9: BondQuoteConvention | R9: QUOTE_IN_32NDS
A10: =A9+1 -> 5 | B10: 100 | D10: =_xll.meLWOBondCreate(E10,_xll.meUtilityLVBFromMultipleKeysValues($E$5:$G$5,E10:G10,,$Q$6:$Q$9,$R$6:$R$9),_xll.meUtilityLVBFromMultipleKeysValues($H$5:$O$5,H10:O10,,$Q$16:$Q$24,$R$16:$R$24)) -> AUD_DUMMY_BOND4@94:3 | E10: AUD_DUMMY_BOND4 | F10: ISIN4 | G10: TRUE | H10: 42566 | I10: 42566 | L10: 46037 | M10: 0.0392 | N10: 30E/360 | O10: SEMI-ANNUAL | Q10: BondDescription
A11: =A10+1 -> 6 | B11: 100 | D11: =_xll.meLWOBondCreate(E11,_xll.meUtilityLVBFromMultipleKeysValues($E$5:$G$5,E11:G11,,$Q$6:$Q$9,$R$6:$R$9),_xll.meUtilityLVBFromMultipleKeysValues($H$5:$O$5,H11:O11,,$Q$16:$Q$24,$R$16:$R$24)) -> AUD_DUMMY_BOND5@108:3 | E11: AUD_DUMMY_BOND5 | F11: ISIN5 | G11: TRUE | H11: 42566 | I11: 42566 | L11: 46037 | M11: 0.0392 | N11: 30E/360 | O11: SEMI-ANNUAL | Q11: ISIN
A12: =A11+1 -> 7 | B12: 100 | D12: =_xll.meLWOBondCreate(E12,_xll.meUtilityLVBFromMultipleKeysValues($E$5:$G$5,E12:G12,,$Q$6:$Q$9,$R$6:$R$9),_xll.meUtilityLVBFromMultipleKeysValues($H$5:$O$5,H12:O12,,$Q$16:$Q$24,$R$16:$R$24)) -> AUD_DUMMY_BOND6@105:3 | E12: AUD_DUMMY_BOND6 | F12: ISIN6 | G12: TRUE | H12: 42566 | I12: 42566 | L12: 46037 | M12: 0.0392 | N12: 30E/360 | O12: SEMI-ANNUAL | Q12: IsCleanPrice
A13: =A12+1 -> 8 | B13: 100 | D13: =_xll.meLWOBondCreate(E13,_xll.meUtilityLVBFromMultipleKeysValues($E$5:$G$5,E13:G13,,$Q$6:$Q$9,$R$6:$R$9),_xll.meUtilityLVBFromMultipleKeysValues($H$5:$O$5,H13:O13,,$Q$16:$Q$24,$R$16:$R$24)) -> AUD_DUMMY_BOND7@114:3 | E13: AUD_DUMMY_BOND7 | F13: ISIN7 | G13: TRUE | H13: 42566 | I13: 42566 | L13: 46037 | M13: 0.0392 | N13: 30E/360 | O13: SEMI-ANNUAL
A14: =A13+1 -> 9 | B14: 100 | D14: =_xll.meLWOBondCreate(E14,_xll.meUtilityLVBFromMultipleKeysValues($E$5:$G$5,E14:G14,,$Q$6:$Q$9,$R$6:$R$9),_xll.meUtilityLVBFromMultipleKeysValues($H$5:$O$5,H14:O14,,$Q$16:$Q$24,$R$16:$R$24)) -> AUD_DUMMY_BOND8@112:3 | E14: AUD_DUMMY_BOND8 | F14: ISIN8 | G14: TRUE | H14: 42566 | I14: 42566 | L14: 46037 | M14: 0.0392 | N14: 30E/360 | O14: SEMI-ANNUAL
A15: =A14+1 -> 10 | B15: 100 | D15: =_xll.meLWOBondCreate(E15,_xll.meUtilityLVBFromMultipleKeysValues($E$5:$G$5,E15:G15,,$Q$6:$Q$9,$R$6:$R$9),_xll.meUtilityLVBFromMultipleKeysValues($H$5:$O$5,H15:O15,,$Q$16:$Q$24,$R$16:$R$24)) -> AUD_DUMMY_BOND9@138:3 | E15: AUD_DUMMY_BOND9 | F15: ISIN9 | G15: TRUE | H15: 42566 | I15: 42566 | L15: 46037 | M15: 0.0392 | N15: 30E/360 | O15: SEMI-ANNUAL | Q15: ScheduleLVB
A16: =A15+1 -> 11 | B16: 100 | D16: =_xll.meLWOBondCreate(E16,_xll.meUtilityLVBFromMultipleKeysValues($E$5:$G$5,E16:G16,,$Q$6:$Q$9,$R$6:$R$9),_xll.meUtilityLVBFromMultipleKeysValues($H$5:$O$5,H16:O16,,$Q$16:$Q$24,$R$16:$R$24)) -> AUD_DUMMY_BOND10@128:3 | E16: AUD_DUMMY_BOND10 | F16: ISIN10 | G16: TRUE | H16: 42566 | I16: 42566 | L16: 46037 | M16: 0.0392 | N16: 30E/360 | O16: SEMI-ANNUAL | Q16: PayReceive | R16: RECEIVE
A17: =A16+1 -> 12 | B17: 100 | D17: =_xll.meLWOBondCreate(E17,_xll.meUtilityLVBFromMultipleKeysValues($E$5:$G$5,E17:G17,,$Q$6:$Q$9,$R$6:$R$9),_xll.meUtilityLVBFromMultipleKeysValues($H$5:$O$5,H17:O17,,$Q$16:$Q$24,$R$16:$R$24)) -> AUD_DUMMY_BOND11@119:3 | E17: AUD_DUMMY_BOND11 | F17: ISIN11 | G17: TRUE | H17: 42566 | I17: 42566 | L17: 46037 | M17: 0.0392 | N17: 30E/360 | O17: SEMI-ANNUAL | Q17: NotionalExchange | R17: START_AND_END
A18: =A17+1 -> 13 | B18: 100 | D18: =_xll.meLWOBondCreate(E18,_xll.meUtilityLVBFromMultipleKeysValues($E$5:$G$5,E18:G18,,$Q$6:$Q$9,$R$6:$R$9),_xll.meUtilityLVBFromMultipleKeysValues($H$5:$O$5,H18:O18,,$Q$16:$Q$24,$R$16:$R$24)) -> AUD_DUMMY_BOND12@102:3 | E18: AUD_DUMMY_BOND12 | F18: ISIN12 | G18: TRUE | H18: 42566 | I18: 42566 | L18: 46037 | M18: 0.0392 | N18: 30E/360 | O18: SEMI-ANNUAL | Q18: FaceValue | R18: 1000000
A19: =A18+1 -> 14 | B19: 100 | D19: =_xll.meLWOBondCreate(E19,_xll.meUtilityLVBFromMultipleKeysValues($E$5:$G$5,E19:G19,,$Q$6:$Q$9,$R$6:$R$9),_xll.meUtilityLVBFromMultipleKeysValues($H$5:$O$5,H19:O19,,$Q$16:$Q$24,$R$16:$R$24)) -> AUD_DUMMY_BOND13@92:3 | E19: AUD_DUMMY_BOND13 | F19: ISIN13 | G19: TRUE | H19: 42566 | I19: 42566 | L19: 46037 | M19: 0.0392 | N19: 30E/360 | O19: SEMI-ANNUAL | Q19: AccrualBusinessDayAdjustment | R19: MOD_FOLLOWING
A20: =A19+1 -> 15 | B20: 100 | D20: =_xll.meLWOBondCreate(E20,_xll.meUtilityLVBFromMultipleKeysValues($E$5:$G$5,E20:G20,,$Q$6:$Q$9,$R$6:$R$9),_xll.meUtilityLVBFromMultipleKeysValues($H$5:$O$5,H20:O20,,$Q$16:$Q$24,$R$16:$R$24)) -> AUD_DUMMY_BOND14@107:3 | E20: AUD_DUMMY_BOND14 | F20: ISIN14 | G20: TRUE | H20: 42566 | I20: 42566 | L20: 46037 | M20: 0.0392 | N20: 30E/360 | O20: SEMI-ANNUAL | Q20: AccrualCalendar | R20: SYB
A21: =A20+1 -> 16 | B21: 100 | D21: =_xll.meLWOBondCreate(E21,_xll.meUtilityLVBFromMultipleKeysValues($E$5:$G$5,E21:G21,,$Q$6:$Q$9,$R$6:$R$9),_xll.meUtilityLVBFromMultipleKeysValues($H$5:$O$5,H21:O21,,$Q$16:$Q$24,$R$16:$R$24)) -> AUD_DUMMY_BOND15@91:3 | E21: AUD_DUMMY_BOND15 | F21: ISIN15 | G21: TRUE | H21: 42566 | I21: 42566 | L21: 46037 | M21: 0.0392 | N21: 30E/360 | O21: SEMI-ANNUAL | Q21: PaymentBusinessDayAdjustment | R21: NO_CHANGE
A22: =A21+1 -> 17 | B22: 100 | D22: =_xll.meLWOBondCreate(E22,_xll.meUtilityLVBFromMultipleKeysValues($E$5:$G$5,E22:G22,,$Q$6:$Q$9,$R$6:$R$9),_xll.meUtilityLVBFromMultipleKeysValues($H$5:$O$5,H22:O22,,$Q$16:$Q$24,$R$16:$R$24)) -> AUD_DUMMY_BOND16@126:3 | E22: AUD_DUMMY_BOND16 | F22: ISIN16 | G22: TRUE | H22: 42566 | I22: 42566 | L22: 46037 | M22: 0.0392 | N22: 30E/360 | O22: SEMI-ANNUAL | Q22: PaymentCalendar | R22: SYB
A23: =A22+1 -> 18 | B23: 100 | D23: =_xll.meLWOBondCreate(E23,_xll.meUtilityLVBFromMultipleKeysValues($E$5:$G$5,E23:G23,,$Q$6:$Q$9,$R$6:$R$9),_xll.meUtilityLVBFromMultipleKeysValues($H$5:$O$5,H23:O23,,$Q$16:$Q$24,$R$16:$R$24)) -> AUD_DUMMY_BOND17@136:3 | E23: AUD_DUMMY_BOND17 | F23: ISIN17 | G23: TRUE | H23: 42566 | I23: 42566 | L23: 46037 | M23: 0.0392 | N23: 30E/360 | O23: SEMI-ANNUAL | Q23: PaymentLag | R23: 0D
A24: =A23+1 -> 19 | B24: 100 | D24: =_xll.meLWOBondCreate(E24,_xll.meUtilityLVBFromMultipleKeysValues($E$5:$G$5,E24:G24,,$Q$6:$Q$9,$R$6:$R$9),_xll.meUtilityLVBFromMultipleKeysValues($H$5:$O$5,H24:O24,,$Q$16:$Q$24,$R$16:$R$24)) -> AUD_DUMMY_BOND18@133:3 | E24: AUD_DUMMY_BOND18 | F24: ISIN18 | G24: TRUE | H24: 42566 | I24: 42566 | L24: 46037 | M24: 0.0392 | N24: 30E/360 | O24: SEMI-ANNUAL | Q24: CalculationType | R24: TYPE23
A25: =A24+1 -> 20 | B25: 100 | D25: =_xll.meLWOBondCreate(E25,_xll.meUtilityLVBFromMultipleKeysValues($E$5:$G$5,E25:G25,,$Q$6:$Q$9,$R$6:$R$9),_xll.meUtilityLVBFromMultipleKeysValues($H$5:$O$5,H25:O25,,$Q$16:$Q$24,$R$16:$R$24)) -> AUD_DUMMY_BOND19@137:3 | E25: AUD_DUMMY_BOND19 | F25: ISIN19 | G25: TRUE | H25: 42566 | I25: 42566 | L25: 46037 | M25: 0.0392 | N25: 30E/360 | O25: SEMI-ANNUAL | Q25: IssueDate
A26: =A25+1 -> 21 | B26: 100 | D26: =_xll.meLWOBondCreate(E26,_xll.meUtilityLVBFromMultipleKeysValues($E$5:$G$5,E26:G26,,$Q$6:$Q$9,$R$6:$R$9),_xll.meUtilityLVBFromMultipleKeysValues($H$5:$O$5,H26:O26,,$Q$16:$Q$24,$R$16:$R$24)) -> AUD_DUMMY_BOND20@127:3 | E26: AUD_DUMMY_BOND20 | F26: ISIN20 | G26: TRUE | H26: 42566 | I26: 42566 | L26: 46037 | M26: 0.0392 | N26: 30E/360 | O26: SEMI-ANNUAL | Q26: AccrualStartDate
A27: =A26+1 -> 22 | B27: 100 | D27: =_xll.meLWOBondCreate(E27,_xll.meUtilityLVBFromMultipleKeysValues($E$5:$G$5,E27:G27,,$Q$6:$Q$9,$R$6:$R$9),_xll.meUtilityLVBFromMultipleKeysValues($H$5:$O$5,H27:O27,,$Q$16:$Q$24,$R$16:$R$24)) -> AUD_DUMMY_BOND21@120:3 | E27: AUD_DUMMY_BOND21 | F27: ISIN21 | G27: TRUE | H27: 42566 | I27: 42566 | L27: 46037 | M27: 0.0392 | N27: 30E/360 | O27: SEMI-ANNUAL | Q27: FirstCouponDate
A28: =A27+1 -> 23 | B28: 100 | D28: =_xll.meLWOBondCreate(E28,_xll.meUtilityLVBFromMultipleKeysValues($E$5:$G$5,E28:G28,,$Q$6:$Q$9,$R$6:$R$9),_xll.meUtilityLVBFromMultipleKeysValues($H$5:$O$5,H28:O28,,$Q$16:$Q$24,$R$16:$R$24)) -> AUD_DUMMY_BOND22@93:3 | E28: AUD_DUMMY_BOND22 | F28: ISIN22 | G28: TRUE | H28: 42566 | I28: 42566 | L28: 46037 | M28: 0.0392 | N28: 30E/360 | O28: SEMI-ANNUAL | Q28: LastCouponDate
A29: =A28+1 -> 24 | B29: 100 | D29: =_xll.meLWOBondCreate(E29,_xll.meUtilityLVBFromMultipleKeysValues($E$5:$G$5,E29:G29,,$Q$6:$Q$9,$R$6:$R$9),_xll.meUtilityLVBFromMultipleKeysValues($H$5:$O$5,H29:O29,,$Q$16:$Q$24,$R$16:$R$24)) -> AUD_DUMMY_BOND23@142:3 | E29: AUD_DUMMY_BOND23 | F29: ISIN23 | G29: TRUE | H29: 42566 | I29: 42566 | L29: 46037 | M29: 0.0392 | N29: 30E/360 | O29: SEMI-ANNUAL | Q29: MaturityDate
A30: =A29+1 -> 25 | B30: 100 | D30: =_xll.meLWOBondCreate(E30,_xll.meUtilityLVBFromMultipleKeysValues($E$5:$G$5,E30:G30,,$Q$6:$Q$9,$R$6:$R$9),_xll.meUtilityLVBFromMultipleKeysValues($H$5:$O$5,H30:O30,,$Q$16:$Q$24,$R$16:$R$24)) -> AUD_DUMMY_BOND24@113:3 | E30: AUD_DUMMY_BOND24 | F30: ISIN24 | G30: TRUE | H30: 42566 | I30: 42566 | L30: 46037 | M30: 0.0392 | N30: 30E/360 | O30: SEMI-ANNUAL | Q30: Coupon
A31: =A30+1 -> 26 | B31: 100 | D31: =_xll.meLWOBondCreate(E31,_xll.meUtilityLVBFromMultipleKeysValues($E$5:$G$5,E31:G31,,$Q$6:$Q$9,$R$6:$R$9),_xll.meUtilityLVBFromMultipleKeysValues($H$5:$O$5,H31:O31,,$Q$16:$Q$24,$R$16:$R$24)) -> AUD_DUMMY_BOND25@106:3 | E31: AUD_DUMMY_BOND25 | F31: ISIN25 | G31: TRUE | H31: 42566 | I31: 42566 | L31: 46037 | M31: 0.0392 | N31: 30E/360 | O31: SEMI-ANNUAL | Q31: DayCount
A32: =A31+1 -> 27 | B32: 100 | D32: =_xll.meLWOBondCreate(E32,_xll.meUtilityLVBFromMultipleKeysValues($E$5:$G$5,E32:G32,,$Q$6:$Q$9,$R$6:$R$9),_xll.meUtilityLVBFromMultipleKeysValues($H$5:$O$5,H32:O32,,$Q$16:$Q$24,$R$16:$R$24)) -> AUD_DUMMY_BOND26@143:3 | E32: AUD_DUMMY_BOND26 | F32: ISIN26 | G32: TRUE | H32: 42566 | I32: 42566 | L32: 46037 | M32: 0.0392 | N32: 30E/360 | O32: SEMI-ANNUAL | Q32: Frequency

Sheet EXAMPLE-ASW-PX
B2: Uridashi Bond Price | K2: =_xll.meLWOXccySwapCreate(J11,J12:L45,J49:K51) -> USD_AUD_XCCY_SWAP@203:5
B3: =O8 -> 101.03512 | F3: Create Asset Swap | G3: =_xll.meLWOSwapCreate(F11,F12:H45,FALSE) -> USD_ASSET_SWAP@173:5 | J3: Create Xccy Swap | K3: Leg1:Float | L3: USDYC | N3: Create Asset Swap | O3: =_xll.meLWOSwapCreate(N11,N12:P45,FALSE) -> AUD_ASSET_SWAP@232:5
K4: Leg2:Float | L4: AUDYC | N4: ValuationDate | O4: =_xll.meDateFromTenor(TODAY(),"2D","MOD_FOLLOWING","SYB") -> 44067 | P4: BondSettlementDate
F5: ValuationDate | G5: =_xll.meDateFromTenor(TODAY(),"2D","MOD_FOLLOWING","SYB") -> 44067 | K5: FXSPOT | L5: 0.7187 | N5: CurveCollection | O5: AUDYC
B6: ValuationSettings | F6: CurveCollection | G6: USDYC | K6: ValuationDate | L6: =G5 -> 44067 | N6: FxSpot | O6: 0.7187
D7: BondSettlementDate
F8: USD Asset Swap Spread | G8: =_xll.meLWOAssetSwapSpread(G3,'USD-BONDS'!$D$6,C13,F5:G6) -> 370.97754 | J8: Xccy Par Spread | K8: =_xll.meLWOXccySwapParSpread(K2,K3:L6,,L12) -> 330.93586 | N8: Uridashi Price | O8: =_xll.meLWOAssetSwapSpreadToCleanPrice(O3,K8,N4:O5) -> 101.03512
J10: *** Non-MTM Xccy Used to Convert Proxy Funding Currency to Uridashi Funding Currency ***
B11: BOND SPECIFICATION | C11: Proxy Bond | D11: Uridashi Bond | F11: USD_ASSET_SWAP | G11: Proxy Bond Leg | H11: Funding Leg | J11: USD_AUD_XCCY_SWAP | K11: USD Funding | L11: AUD Funding | N11: AUD_ASSET_SWAP
B12: ISIN | C12: USJ46186BC59 | D12: XS1344710857 | F12: LegType | G12: Leg1:FixedBond | H12: Leg2:Float | J12: LegType | K12: Leg1:Float | L12: Leg2:Float | N12: LegType | O12: Leg1:FixedBond | P12: Leg2:Float
B13: BondPrice | C13: ='USD-BONDS'!B6 -> 96.021 | D13: =O8 -> 101.03512 | F13: Notional | G13: 1000000 | H13: 1000000 | J13: Notional | K13: 1000000 | L13: =K13/L5 -> 1391401.1 | N13: Notional | O13: 1000000 | P13: 1000000
B14: Notional | C14: 1000000 | D14: 1000000 | F14: NotionalExchange | G14: NONE | H14: NONE | J14: NotionalExchange | K14: START_AND_END | L14: START_AND_END | N14: NotionalExchange | O14: NONE | P14: NONE
B15: PayReceive | C15: PAYER | D15: PAYER | F15: PayReceive | G15: PAY | H15: REC | J15: PayReceive | K15: PAY | L15: REC | N15: PayReceive | O15: =K15 -> PAY | P15: REC
B16: IssueDate | C16: ='USD-BONDS'!$H$6 -> 42089 | D16: ='AUD-BONDS'!$H$6 -> 42566 | F16: ForecastCurve | H16: USD3ML | J16: ForecastCurve | K16: USD3ML | L16: AUD3ML | N16: ForecastCurve | P16: AUD3ML
B17: EffectiveDate | C17: =_xll.meDateFromTenor(Settings.COB,"2D","MOD_FOLLOWING","NYB") -> 44067 | D17: =_xll.meDateFromTenor(Settings.COB,"2D","MOD_FOLLOWING","SYB") -> 44067 | F17: DiscountCurve | G17: USDOIS | H17: USDOIS | J17: DiscountCurve | K17: USDOIS | L17: AUDDF_USDCSA | N17: DiscountCurve | O17: AUDOIS | P17: AUDOIS
B18: LastCouponDate | C18: =_xll.meLWOBondLastCouponDate('USD-BONDS'!D6,Settings.COB) -> 43916 | D18: =_xll.meLWOBondLastCouponDate('AUD-BONDS'!D6,Settings.COB) -> 44027 | F18: Currency | G18: USD | H18: USD | J18: Currency | K18: USD | L18: AUD | N18: Currency | O18: AUD | P18: AUD
B19: MaturityDate | C19: ='USD-BONDS'!$L$6 -> 45742 | D19: ='AUD-BONDS'!$L$6 -> 46037 | F19: Leverage | G19: 1 | H19: 1 | J19: Leverage | K19: 1 | L19: 1 | N19: Leverage | O19: =L19 -> 1 | P19: 1
B20: CurveCollection | C20: USDYC | D20: AUDYC | F20: FixedRate | G20: 0.032 | J20: FixedRate | N20: FixedRate | O20: =D25 -> 0.0392
B21: ForecastCurve | C21: USD3ML | D21: AUD6ML | F21: FirstStubCurveIndex | H21: NATURAL | J21: FirstStubCurveIndex | K21: NATURAL | L21: NATURAL | N21: FirstStubCurveIndex | P21: NATURAL
B22: DiscountCurve | C22: USDOIS | D22: AUDOIS | F22: LastStubCurveIndex | H22: NATURAL | J22: LastStubCurveIndex | K22: NATURAL | L22: NATURAL | N22: LastStubCurveIndex | P22: NATURAL
B23: isCleanPrice | C23: TRUE | D23: TRUE | F23: FirstFixing | H23: =SETTINGS!F6 -> 0.0129556 | J23: FirstFixing | K23: =SETTINGS!F6 -> 0.0129556 | L23: =SETTINGS!I6 -> 0.0171 | N23: FirstFixing | P23: =SETTINGS!I6 -> 0.0171
B24: FixedFrequency | C24: SEMI-ANNUAL | D24: SEMI-ANNUAL | F24: LastFixing | J24: LastFixing | N24: LastFixing
B25: FixedRate | C25: ='USD-BONDS'!$M$6 -> 0.032 | D25: ='AUD-BONDS'!$M$6 -> 0.0392 | F25: FloatSpread | G25: 0 | H25: 0 | J25: FloatSpread | K25: =G8 -> 370.97754 | L25: 0 | N25: FloatSpread | P25: =K8 -> 330.93586
B26: FixedDayCount | C26: 30E/360 | D26: 30E/360 | F26: EffectiveDate | G26: =C18 -> 43916 | H26: =C17 -> 44067 | J26: EffectiveDate | K26: =H26 -> 44067 | L26: =P26 -> 44067 | M26: * | N26: EffectiveDate | O26: =D18 -> 44027 | P26: =D17 -> 44067 | Q26: *
B27: FixedBusinessDayAdjustment | C27: NO_CHANGE | D27: MOD_FOLLOWING | F27: MaturityDate | G27: =$C$19 -> 45742 | H27: =$C$19 -> 45742 | J27: MaturityDate | K27: =$C$19 -> 45742 | L27: =$D$19 -> 46037 | N27: MaturityDate | O27: =$D$19 -> 46037 | P27: =$D$19 -> 46037
B28: FixedCalendar | C28: NYB | D28: SYB | F28: Frequency | G28: SEMI-ANNUAL | H28: QUARTERLY | J28: Frequency | K28: QUARTERLY | L28: QUARTERLY | N28: Frequency | O28: SEMI-ANNUAL | P28: QUARTERLY
B29: FixedFirstStubDate | F29: Daycount | G29: 30E/360 | H29: ACT/360 | J29: Daycount | K29: ACT/360 | L29: ACT/365 | N29: Daycount | O29: 30E/360 | P29: ACT/365
B30: FixedLastStubDate | F30: FixingBusinessDayAdjustment | G30: NO_CHANGE | H30: NO_CHANGE | J30: FixingBusinessDayAdjustment | K30: NO_CHANGE | L30: NO_CHANGE | N30: FixingBusinessDayAdjustment | O30: NO_CHANGE | P30: NO_CHANGE
B31: FixedRollDay | C31: NORMAL | D31: NORMAL | F31: FixingCalendar | G31: NYB | H31: NYB | J31: FixingCalendar | K31: NYB | L31: SYB | N31: FixingCalendar | O31: SYB | P31: SYB
B32: FixedStubType | C32: ShortStart | D32: ShortStart | F32: AccrualBusinessDayAdjustment | G32: NO_CHANGE | H32: NO_CHANGE | J32: AccrualBusinessDayAdjustment | K32: NO_CHANGE | L32: NO_CHANGE | N32: AccrualBusinessDayAdjustment | O32: NO_CHANGE | P32: NO_CHANGE
B33: FixedPaymentLag | C33: 0D | D33: 0D | F33: AccrualCalendar | G33: NYB | H33: NYB | J33: AccrualCalendar | K33: NYB | L33: SYB | N33: AccrualCalendar | O33: SYB | P33: SYB
F34: PaymentBusinessDayAdjustment | G34: NO_CHANGE | H34: NO_CHANGE | J34: PaymentBusinessDayAdjustment | K34: NO_CHANGE | L34: NO_CHANGE | N34: PaymentBusinessDayAdjustment | O34: NO_CHANGE | P34: NO_CHANGE
F35: PaymentCalendar | G35: NYB | H35: NYB | J35: PaymentCalendar | K35: NYB | L35: SYB | N35: PaymentCalendar | O35: SYB | P35: SYB
F36: FirstStubDate | J36: FirstStubDate | N36: FirstStubDate
F37: LastStubDate | J37: LastStubDate | N37: LastStubDate
F38: RollDay | G38: NORMAL | H38: NORMAL | J38: RollDay | K38: NORMAL | L38: NORMAL | N38: RollDay | O38: NORMAL | P38: NORMAL
F39: FixingLag | H39: 0D | J39: FixingLag | K39: 0D | L39: 0D | N39: FixingLag | P39: 0D
F40: FirstFixingLag | J40: FirstFixingLag | N40: FirstFixingLag
F41: PaymentLag | G41: 0D | H41: 0D | J41: PaymentLag | K41: 0D | L41: 0D | N41: PaymentLag | O41: 0D | P41: 0D
F42: StubType | G42: ShortStart | H42: ShortStart | J42: StubType | K42: ShortStart | L42: ShortStart | N42: StubType | O42: ShortStart | P42: ShortStart
F43: CalculationType | G43: Type1 | J43: ISFWDINTER | K43: FALSE | L43: FALSE | N43: CalculationType | O43: Type1
F44: ISFWDINTER | H44: FALSE | N44: ISFWDINTER | P44: FALSE
F46: * Set effective date to the last coupon date to include accrued, use meLWOBondLastCouponDate
J48: Xccy Swap Properties
J49: MTM | K49: FALSE | L49: <--- Non-MTM for ASW Same Currency Proxy Method
J50: ValuationCurrency | K50: USD
J51: NotionalFxResetLeg

Sheet EXAMPLE-XCCY-ASW-PX
B2: Uridashi Bond Price
B3: =K10 -> 101.03479 | F3: Create Asset Swap | G3: =_xll.meLWOXccySwapCreate(F13,F14:H46,F50:G52,TRUE) -> PROXY_XCCY_ASSET_SWAP@175:2 | J3: Create Asset Swap | K3: =_xll.meLWOSwapCreate(J13,J14:L46,FALSE) -> URIDASHI_ASSET_SWAP@204:4
G4: Leg1:FixedBond | H4: USDYC | J4: CurveCollection | K4: AUDYC
G5: Leg2:Float | H5: AUDYC | J5: ValuationDate | K5: =B10 -> 44067
G6: FXSPOT | H6: =SETTINGS!L5 -> 0.75
G7: ValuationDate | H7: =B10 -> 44067
G8: ValuationCurrency | H8: =G51 -> USD
B9: Valuation Date (for Accrued Int)
B10: =_xll.meDateFromTenor(TODAY(),"2D","MOD_FOLLOWING","SYB") -> 44067 | F10: Xccy Asset Swap Spread | G10: =_xll.meLWOAssetSwapSpreadFromPrice(G3,C15,B10,C25,G4:H8) -> 330.94196 | J10: Uridashi Price | K10: =_xll.meLWOAssetSwapSpreadToCleanPrice(K3,L27,J4:K5) -> 101.03479
B13: BOND SPECIFICATION | C13: Proxy Bond | D13: Uridashi Bond | F13: PROXY_XCCY_ASSET_SWAP | G13: Proxy Bond Leg | H13: AUD Funding | J13: URIDASHI_ASSET_SWAP
B14: ISIN | C14: USJ46186BC59 | D14: XS1344710857 | F14: LegType | G14: Leg1:FixedBond | H14: Leg2:Float | J14: LegType | K14: Leg1:FixedBond | L14: Leg2:Float
B15: BondPrice | C15: ='USD-BONDS'!B6 -> 96.021 | D15: =K10 -> 101.03479 | F15: Notional | G15: 1000000 | H15: =G15/H6 -> 1333333.3 | J15: Notional | K15: 1000000 | L15: 1000000
B16: Notional | C16: 1000000 | D16: 1000000 | F16: NotionalExchange | G16: END | H16: END | J16: NotionalExchange | K16: NONE | L16: NONE
B17: PayReceive | C17: PAYER | D17: PAYER | F17: PayReceive | G17: PAY | H17: REC | J17: PayReceive | K17: PAY | L17: REC
B18: IssueDate | C18: ='USD-BONDS'!$H$6 -> 42089 | D18: ='AUD-BONDS'!$H$6 -> 42566 | F18: ForecastCurve | H18: AUD3ML | J18: ForecastCurve | L18: AUD3ML
B19: EffectiveDate | C19: =_xll.meDateFromTenor(Settings.COB,"2D","MOD_FOLLOWING","NYB") -> 44067 | D19: =_xll.meDateFromTenor(Settings.COB,"2D","MOD_FOLLOWING","SYB") -> 44067 | F19: DiscountCurve | G19: USDOIS | H19: AUDDF_USDCSA | J19: DiscountCurve | K19: AUDOIS | L19: AUDOIS
B20: LastCouponDate | C20: =_xll.meLWOBondLastCouponDate('USD-BONDS'!D6,Settings.COB) -> 43916 | D20: =_xll.meLWOBondLastCouponDate('AUD-BONDS'!D6,Settings.COB) -> 44027 | F20: Currency | G20: USD | H20: AUD | J20: Currency | K20: AUD | L20: AUD
B21: MaturityDate | C21: ='USD-BONDS'!$L$6 -> 45742 | D21: ='AUD-BONDS'!$L$6 -> 46037 | F21: Leverage | G21: 1 | H21: 1 | J21: Leverage | K21: =H21 -> 1 | L21: 1
B22: CurveCollection | C22: USDYC | D22: AUDYC | F22: FixedRate | G22: =C27 -> 0.032 | J22: FixedRate | K22: =D27 -> 0.0392
B23: ForecastCurve | C23: USD3ML | D23: AUD6ML | F23: FirstStubCurveIndex | H23: NATURAL | J23: FirstStubCurveIndex | L23: NATURAL
B24: DiscountCurve | C24: USDOIS | D24: AUDOIS | F24: LastStubCurveIndex | H24: NATURAL | J24: LastStubCurveIndex | L24: NATURAL
B25: isCleanPrice | C25: TRUE | D25: TRUE | F25: FirstFixing | H25: =SETTINGS!I6 -> 0.0171 | J25: FirstFixing | L25: =SETTINGS!I6 -> 0.0171
B26: FixedFrequency | C26: SEMI-ANNUAL | D26: SEMI-ANNUAL | F26: LastFixing | J26: LastFixing
B27: FixedRate | C27: ='USD-BONDS'!$M$6 -> 0.032 | D27: ='AUD-BONDS'!$M$6 -> 0.0392 | F27: FloatSpread | G27: 0 | H27: 0 | J27: FloatSpread | L27: =G10 -> 330.94196
B28: FixedDayCount | C28: 30E/360 | D28: 30E/360 | F28: EffectiveDate | G28: =C20 -> 43916 | H28: =C19 -> 44067 | I28: * | J28: EffectiveDate | K28: =D20 -> 44027 | L28: =D19 -> 44067 | M28: *
B29: FixedBusinessDayAdjustment | C29: NO_CHANGE | D29: MOD_FOLLOWING | F29: MaturityDate | G29: =$C$21 -> 45742 | H29: =L29 -> 46037 | J29: MaturityDate | K29: =$D$21 -> 46037 | L29: =K29 -> 46037
B30: FixedCalendar | C30: NYB | D30: SYB | F30: Frequency | G30: SEMI-ANNUAL | H30: QUARTERLY | J30: Frequency | K30: SEMI-ANNUAL | L30: QUARTERLY
B31: FixedFirstStubDate | F31: Daycount | G31: 30E/360 | H31: ACT/365 | J31: Daycount | K31: 30E/360 | L31: ACT/365
B32: FixedLastStubDate | F32: FixingBusinessDayAdjustment | G32: NO_CHANGE | H32: NO_CHANGE | J32: FixingBusinessDayAdjustment | K32: NO_CHANGE | L32: NO_CHANGE
B33: FixedRollDay | C33: NORMAL | D33: NORMAL | F33: FixingCalendar | G33: NYB | H33: SYB | J33: FixingCalendar | K33: SYB | L33: SYB
B34: FixedStubType | C34: ShortStart | D34: ShortStart | F34: AccrualBusinessDayAdjustment | G34: NO_CHANGE | H34: NO_CHANGE | J34: AccrualBusinessDayAdjustment | K34: NO_CHANGE | L34: NO_CHANGE
B35: FixedPaymentLag | C35: 0D | D35: 0D | F35: AccrualCalendar | G35: NYB | H35: SYB | J35: AccrualCalendar | K35: SYB | L35: SYB
B36: CalculationType | C36: Type1 | F36: PaymentBusinessDayAdjustment | G36: NO_CHANGE | H36: NO_CHANGE | J36: PaymentBusinessDayAdjustment | K36: NO_CHANGE | L36: NO_CHANGE
F37: PaymentCalendar | G37: NYB | H37: SYB | J37: PaymentCalendar | K37: SYB | L37: SYB
F38: FirstStubDate | J38: FirstStubDate
F39: LastStubDate | J39: LastStubDate
F40: RollDay | G40: NORMAL | H40: NORMAL | J40: RollDay | K40: NORMAL | L40: NORMAL
F41: FixingLag | H41: 0D | J41: FixingLag | L41: 0D
F42: FirstFixingLag | J42: FirstFixingLag
F43: PaymentLag | G43: 0D | H43: 0D | J43: PaymentLag | K43: 0D | L43: 0D
F44: CalculationType | G44: TYPE1 | J44: CalculationType | K44: TYPE1
F45: ISFWDINTER | G45: FALSE | H45: FALSE | J45: ISFWDINTER | L45: FALSE
F46: StubType | G46: ShortStart | H46: ShortStart | J46: StubType | K46: ShortStart | L46: ShortStart
F47: * Set effective date to the last coupon date to include accrued, use meLWOBondLastCouponDate
F49: Xccy Swap Properties
F50: MTM | G50: FALSE
F51: ValuationCurrency | G51: USD
F52: NotionalFxResetLeg

Sheet AUD-URIDASHI-PX
BT1: USD_ASW | BZ1: VALUATION SETTINGS | CC1: XCCY SETTINGS | EI1: XCCY_SWAP | HE1: AUD_ASW
E2: =E8 -> 370.96728 | BZ2: Leg1:Float | CA2: USDYC | CC2: MTM | CD2: FALSE
B3: USD BOND PROXY | D3: SETTLEMENT DATE (NYB) | G3: USD ASSET SWAP | J3: CURVE COLLECTION | AN3: USD ASSET SWAP | BU3: USD/AUD XCCY SWAP | BX3: USD/AUD XCCY SWAP | BZ3: Leg2:Float | CA3: AUDYC | CC3: ValuationCurrency | CD3: USD | DD3: USD/AUD XCCY SWAP | EJ3: AUD URIDASHI BOND | EK3: SETTLEMENT DATE (SYB) | EN3: BOND CALCULATIONS | ET3: AUD ASSET SWAP | EW3: CURVE COLLECTION | FZ3: AUD ASSET SWAP | HF3: BOND CASHFLOWS | HH3: SELECT BOND | HQ3: BOND INDEX
D4: =_xll.meDateFromTenor(Settings.COB,"2D","MOD_FOLLOWING","NYB") -> 44067 | J4: CurveCollection | K4: USDYC | BZ4: FXSPOT | CA4: =CD4 -> 0.75 | CC4: FxRate | CD4: =SETTINGS!$L$5 -> 0.75 | CE4: AUDUSD | EK4: =_xll.meDateFromTenor(Settings.COB,"2D","MOD_FOLLOWING","SYB") -> 44067 | EW4: AUDYC | HH4: XS1447583664 | HQ4: =MATCH(HH4,'AUD-BONDS'!$F$6:$F$32,0) -> 2
G5: PROXY BOND LEG (FIXED) | J5: ValuationDate | K5: =D4 -> 44067 | AN5: FUNDING LEG (FLOAT) | BZ5: ValuationDate | CA5: ='EXAMPLE-XCCY-ASW-PX'!B10 -> 44067 | CC5: NotionalFxResetLeg | ET5: PROXY BOND LEG (FIXED) | FZ5: FUNDING LEG (FLOAT)
BX6: USD FUNDING LEG | BZ6: ValuationCurrency | CA6: =BZ49 -> 0 | DD6: AUD FUNDING LEG
B7: ISIN | C7: PROXY PRICE | D7: USD_ASW | E7: USD_ASW_SPREAD | G7: LegType | H7: Notional | I7: NotionalExchange | J7: PayReceive | K7: ForecastCurve | L7: DiscountCurve | M7: Currency | N7: Leverage | O7: FixedRate | P7: FirstStubCurveIndex | Q7: LastStubCurveIndex | R7: FirstFixing | S7: LastFixing | T7: FloatSpread | U7: EffectiveDate | V7: MaturityDate | W7: Frequency | X7: Daycount | Y7: FixingBusinessDayAdjustment | Z7: FixingCalendar | AA7: AccrualBusinessDayAdjustment | AB7: AccrualCalendar | AC7: PaymentBusinessDayAdjustment | AD7: PaymentCalendar | AE7: FirstStubDate | AF7: LastStubDate | AG7: RollDay | AH7: FixingLag | AI7: FirstFixingLag | AJ7: PaymentLag | AK7: CalculationType | AL7: StubType | AN7: LegType | AO7: Notional | AP7: NotionalExchange | AQ7: PayReceive | AR7: ForecastCurve | AS7: DiscountCurve | AT7: Currency | AU7: Leverage | AV7: FixedRate | AW7: FirstStubCurveIndex | AX7: LastStubCurveIndex | AY7: FirstFixing | AZ7: LastFixing | BA7: FloatSpread | BB7: EffectiveDate | BC7: MaturityDate | BD7: Frequency | BE7: Daycount | BF7: FixingBusinessDayAdjustment | BG7: FixingCalendar | BH7: AccrualBusinessDayAdjustment | BI7: AccrualCalendar | BJ7: PaymentBusinessDayAdjustment | BK7: PaymentCalendar | BL7: FirstStubDate | BM7: LastStubDate | BN7: RollDay | BO7: FixingLag | BP7: FirstFixingLag | BQ7: PaymentLag | BR7: CalculationType | BS7: StubType | BU7: XCCY_SWAP | BV7: XCCY_PAR_SPREAD | BW7: 1 | BX7: LegType | BY7: Notional | BZ7: NotionalExchange | CA7: PayReceive | CB7: ForecastCurve | CC7: DiscountCurve | CD7: Currency | CE7: Leverage | CF7: FixedRate | CG7: FirstStubCurveIndex | CH7: LastStubCurveIndex | CI7: FirstFixing | CJ7: LastFixing | CK7: FloatSpread | CL7: EffectiveDate | CM7: MaturityDate | CN7: Frequency | CO7: Daycount | CP7: FixingBusinessDayAdjustment | CQ7: FixingCalendar | CR7: AccrualBusinessDayAdjustment | CS7: AccrualCalendar | CT7: PaymentBusinessDayAdjustment | CU7: PaymentCalendar | CV7: FirstStubDate | CW7: LastStubDate | CX7: RollDay | CY7: FixingLag | CZ7: FirstFixingLag | DA7: PaymentLag | DB7: StubType | DC7: 1 | DD7: LegType | DE7: Notional | DF7: NotionalExchange | DG7: PayReceive | DH7: ForecastCurve | DI7: DiscountCurve | DJ7: Currency | DK7: Leverage | DL7: FixedRate | DM7: FirstStubCurveIndex | DN7: LastStubCurveIndex | DO7: FirstFixing | DP7: LastFixing | DQ7: FloatSpread | DR7: EffectiveDate | DS7: MaturityDate | DT7: Frequency | DU7: Daycount | DV7: FixingBusinessDayAdjustment | DW7: FixingCalendar | DX7: AccrualBusinessDayAdjustment | DY7: AccrualCalendar | DZ7: PaymentBusinessDayAdjustment | EA7: PaymentCalendar | EB7: FirstStubDate | EC7: LastStubDate | ED7: RollDay | EE7: FixingLag | EF7: FirstFixingLag | EG7: PaymentLag | EH7: StubType | EJ7: ISIN | EK7: AUD_ASW | EL7: URISASHI PRICE | EN7: YIELD | EO7: CLEAN PX | EP7: DIRTY PX | EQ7: ACCRUED INT | ER7: ACCRUED DAYS | ET7: LegType | EU7: Notional | EV7: NotionalExchange | EW7: PayReceive | EX7: ForecastCurve | EY7: DiscountCurve | EZ7: Currency | FA7: Leverage | FB7: FixedRate | FC7: FirstStubCurveIndex | FD7: LastStubCurveIndex | FE7: FirstFixing | FF7: LastFixing | FG7: FloatSpread | FH7: EffectiveDate | FI7: MaturityDate | FJ7: Frequency | FK7: Daycount | FL7: FixingBusinessDayAdjustment | FM7: FixingCalendar | FN7: AccrualBusinessDayAdjustment | FO7: AccrualCalendar | FP7: PaymentBusinessDayAdjustment | FQ7: PaymentCalendar | FR7: FirstStubDate | FS7: LastStubDate | FT7: RollDay | FU7: FixingLag | FV7: FirstFixingLag | FW7: PaymentLag | FX7: StubType | FZ7: LegType | GA7: Notional | GB7: NotionalExchange | GC7: PayReceive | GD7: ForecastCurve | GE7: DiscountCurve | GF7: Currency | GG7: Leverage | GH7: FixedRate | GI7: FirstStubCurveIndex | GJ7: LastStubCurveIndex | GK7: FirstFixing | GL7: LastFixing | GM7: FloatSpread | GN7: EffectiveDate | GO7: MaturityDate | GP7: Frequency | GQ7: Daycount | GR7: FixingBusinessDayAdjustment | GS7: FixingCalendar | GT7: AccrualBusinessDayAdjustment | GU7: AccrualCalendar | GV7: PaymentBusinessDayAdjustment | GW7: PaymentCalendar | GX7: FirstStubDate | GY7: LastStubDate | GZ7: RollDay | HA7: FixingLag | HB7: FirstFixingLag | HC7: PaymentLag | HD7: StubType | HF7: {=_xll.meUtilityResize(_xll.meLWOBondDisplayCashflows(OFFSET('AUD-BONDS'!$D6,$HQ$4-1,0),$EK$4,OFFSET(EN$8,$HQ$4-1,0)),100,100)} -> #Error: No range or empty range specified | HG7: #Error: No range or empty range specified | HH7: #Error: No range or empty range specified | HI7: #Error: No range or empty range specified | HJ7: #Error: No range or empty range specified | HK7: #Error: No range or empty range specified | HL7: #Error: No range or empty range specified | HM7: #Error: No range or empty range specified | HN7: #Error: No range or empty range specified | HO7: #Error: No range or empty range specified | HP7: #Error: No range or empty range specified | HQ7: #Error: No range or empty range specified
A8: 1 | B8: ='USD-BONDS'!F6 -> USJ46186BC59 | C8: ='USD-BONDS'!B6 -> 96.021 | D8: =_xll.meLWOSwapCreate($D$7&"_"&B8,_xll.meUtilityLVBFromKeysAndMultipleValues($G$7:$AL$7,G8:AL8,AN8:BS8)) -> USD_ASW_USJ46186BC59@172:6 | E8: =_xll.meLWOAssetSwapSpread(D8,'USD-BONDS'!D6,C8,$J$4:$K$5) -> 370.96728 | F8: 1 | G8: Leg1:FixedBond | H8: 1000000 | I8: NONE | J8: PAY | L8: USDOIS | M8: USD | N8: 1 | O8: ='USD-BONDS'!M6 -> 0.032 | U8: =_xll.meLWOBondLastCouponDate('USD-BONDS'!D6,Settings.COB) -> 43916 | V8: ='USD-BONDS'!L6 -> 45742 | W8: ='USD-BONDS'!O6 -> SEMI-ANNUAL | X8: ='USD-BONDS'!N6 -> 30E/360 | Y8: NO_CHANGE | Z8: NYB | AA8: NO_CHANGE | AB8: NYB | AC8: NO_CHANGE | AD8: NYB | AG8: NORMAL | AJ8: 0D | AK8: TYPE1 | AL8: ShortStart | AM8: 1 | AN8: Leg2:Float | AO8: 1000000 | AP8: NONE | AQ8: REC | AR8: USD3ML | AS8: USDOIS | AT8: USD | AU8: 1 | AW8: NATURAL | AX8: NATURAL | AY8: =SETTINGS!$F$6 -> 0.0129556 | BA8: 0 | BB8: =_xll.meLWOBondLastCouponDate('USD-BONDS'!D6,Settings.COB) -> 43916 | BC8: ='USD-BONDS'!L6 -> 45742 | BD8: QUARTERLY | BE8: ACT/360 | BF8: NO_CHANGE | BG8: NYB | BH8: NO_CHANGE | BI8: NYB | BJ8: NO_CHANGE | BK8: NYB | BN8: NORMAL | BO8: 0D | BQ8: 0D | BS8: ShortStart | BT8: 1 | BU8: =_xll.meLWOXccySwapCreate($BU$7&"_"&B8,_xll.meUtilityLVBFromKeysAndMultipleValues($BX$7:$DB$7,BX8:DB8,DD8:EH8),$CC$2:$CD$5) -> XCCY_SWAP_USJ46186BC59@176:6 | BV8: =_xll.meLWOXccySwapParSpread(BU8,$BZ$2:$CA$6,,$BZ$3) -> 335.8653 | BW8: =BW7+1 -> 2 | BX8: Leg1:Float | BY8: 1000000 | BZ8: START_AND_END | CA8: PAY | CB8: USD3ML | CC8: USDOIS | CD8: USD | CE8: 1 | CG8: NATURAL | CH8: NATURAL | CI8: =SETTINGS!$F$6 -> 0.0129556 | CK8: =$E8 -> 370.96728 | CL8: =_xll.meLWOBondLastCouponDate('USD-BONDS'!D6,Settings.COB) -> 43916 | CM8: ='USD-BONDS'!L6 -> 45742 | CN8: QUARTERLY | CO8: ACT/360 | CP8: NO_CHANGE | CQ8: NYB | CR8: NO_CHANGE | CS8: NYB | CT8: NO_CHANGE | CU8: NYB | CX8: NORMAL | CY8: 0D | DA8: 0D | DB8: ShortStart | DC8: =DC7+1 -> 2 | DD8: Leg2:Float | DE8: =BY8/$CD$4 -> 1333333.3 | DF8: START_AND_END | DG8: REC | DH8: AUD3ML | DI8: AUDDF_USDCSA | DJ8: AUD | DK8: 1 | DM8: NATURAL | DN8: NATURAL | DO8: =SETTINGS!$I$6 -> 0.0171 | DQ8: 0 | DR8: =_xll.meLWOBondLastCouponDate('AUD-BONDS'!D6,Settings.COB) -> 44027 | DS8: ='AUD-BONDS'!L6 -> 46037 | DT8: QUARTERLY | DU8: ACT/365 | DV8: NO_CHANGE | DW8: SYB | DX8: NO_CHANGE | DY8: SYB | DZ8: NO_CHANGE | EA8: SYB | ED8: NORMAL | EE8: 0D | EG8: 0D | EH8: ShortStart | EI8: 1 | EJ8: ='AUD-BONDS'!F6 -> XS1344710857 | EK8: =_xll.meLWOSwapCreate($EK$7&"_"&EJ8,_xll.meUtilityLVBFromKeysAndMultipleValues($ET$7:$FX$7,ET8:FX8,FZ8:HD8)) -> #Error: Missing key 'CALCULATIONTYPE'. This key is mandatory and must be included in the Label Value Block , 'scheduleLVB'. | EL8: =_xll.meLWOAssetSwapSpreadToCleanPrice($EK8,$EK$4,$BV8,$EW$4) -> #Error: Swap #ERROR does not exist | EM8: 1 | EN8: =_xll.meLWOBondYield('AUD-BONDS'!D6,$EK$4,$EL8) -> #Error: Invalid input, numerical input required | EO8: =_xll.meLWOBondCleanPrice('AUD-BONDS'!$D6,$EK$4,$EN8) -> #Error: Invalid Vector Data: Input Contains Errors | EP8: =_xll.meLWOBondDirtyPrice('AUD-BONDS'!$D6,$EK$4,$EN8) -> #Error: Invalid Vector Data: Input Contains Errors | EQ8: =_xll.meLWOBondAccruedInterest('AUD-BONDS'!$D6,'AUD-URIDASHI-PX'!$EK$4) -> 4250 | ER8: =_xll.meLWOBondAccruedInterestDays('AUD-BONDS'!$D6,'AUD-URIDASHI-PX'!$EK$4) -> 39 | ES8: 1 | ET8: Leg1:FixedBond | EU8: =$DE8 -> 1333333.3 | EV8: NONE | EW8: PAY | EY8: AUDOIS | EZ8: AUD | FA8: 1 | FB8: ='AUD-BONDS'!M6 -> 0.0392 | FH8: =_xll.meLWOBondLastCouponDate('AUD-BONDS'!D6,Settings.COB) -> 44027 | FI8: ='AUD-BONDS'!L6 -> 46037 | FJ8: ='AUD-BONDS'!O6 -> SEMI-ANNUAL | FK8: ='AUD-BONDS'!N6 -> 30E/360 | FL8: NO_CHANGE | FM8: NYB | FN8: NO_CHANGE | FO8: NYB | FP8: NO_CHANGE | FQ8: NYB | FT8: NORMAL | FW8: 0D | FX8: ShortStart | FY8: 1 | FZ8: Leg2:Float | GA8: =$DE8 -> 1333333.3 | GB8: NONE | GC8: REC | GD8: AUD3ML | GE8: AUDOIS | GF8: AUD | GG8: 1 | GI8: NATURAL | GJ8: NATURAL | GK8: =SETTINGS!$I$6 -> 0.0171 | GM8: =$BV8 -> 335.8653 | GN8: =_xll.meLWOBondLastCouponDate('AUD-BONDS'!D6,Settings.COB) -> 44027 | GO8: ='AUD-BONDS'!L6 -> 46037 | GP8: QUARTERLY | GQ8: ACT/360 | GR8: NO_CHANGE | GS8: SYB | GT8: NO_CHANGE | GU8: SYB | GV8: NO_CHANGE | GW8: SYB | GZ8: NORMAL | HA8: 0D | HC8: 0D | HD8: ShortStart | HF8: #Error: No range or empty range specified | HG8: #Error: No range or empty range specified | HH8: #Error: No range or empty range specified | HI8: #Error: No range or empty range specified | HJ8: #Error: No range or empty range specified | HK8: #Error: No range or empty range specified | HL8: #Error: No range or empty range specified | HM8: #Error: No range or empty range specified | HN8: #Error: No range or empty range specified | HO8: #Error: No range or empty range specified | HP8: #Error: No range or empty range specified | HQ8: #Error: No range or empty range specified
A9: =A8+1 -> 2 | B9: ='USD-BONDS'!F7 -> XS1447582930 | C9: ='USD-BONDS'!B7 -> 94.55 | D9: =_xll.meLWOSwapCreate($D$7&"_"&B9,_xll.meUtilityLVBFromKeysAndMultipleValues($G$7:$AL$7,G9:AL9,AN9:BS9)) -> USD_ASW_XS1447582930@153:6 | E9: =_xll.meLWOAssetSwapSpread(D9,'USD-BONDS'!D7,C9,$J$4:$K$5) -> 698.9286 | F9: =F8+1 -> 2 | G9: Leg1:FixedBond | H9: 1000000 | I9: NONE | J9: PAY | L9: USDOIS | M9: USD | N9: 1 | O9: ='USD-BONDS'!M7 -> 0.0161 | U9: =_xll.meLWOBondLastCouponDate('USD-BONDS'!D7,Settings.COB) -> 44039 | V9: ='USD-BONDS'!L7 -> 44404 | W9: ='USD-BONDS'!O7 -> SEMI-ANNUAL | X9: ='USD-BONDS'!N7 -> 30E/360 | Y9: NO_CHANGE | Z9: NYB | AA9: NO_CHANGE | AB9: NYB | AC9: NO_CHANGE | AD9: NYB | AG9: NORMAL | AJ9: 0D | AK9: TYPE1 | AL9: ShortStart | AM9: =AM8+1 -> 2 | AN9: Leg2:Float | AO9: 1000000 | AP9: NONE | AQ9: REC | AR9: USD3ML | AS9: USDOIS | AT9: USD | AU9: 1 | AW9: NATURAL | AX9: NATURAL | AY9: =SETTINGS!$F$6 -> 0.0129556 | BA9: 0 | BB9: =_xll.meLWOBondLastCouponDate('USD-BONDS'!D7,Settings.COB) -> 44039 | BC9: ='USD-BONDS'!L7 -> 44404 | BD9: QUARTERLY | BE9: ACT/360 | BF9: NO_CHANGE | BG9: NYB | BH9: NO_CHANGE | BI9: NYB | BJ9: NO_CHANGE | BK9: NYB | BN9: NORMAL | BO9: 0D | BQ9: 0D | BS9: ShortStart | BT9: =BT8+1 -> 2 | BU9: =_xll.meLWOXccySwapCreate($BU$7&"_"&B9,_xll.meUtilityLVBFromKeysAndMultipleValues($BX$7:$DB$7,BX9:DB9,DD9:EH9),$CC$2:$CD$5) -> XCCY_SWAP_XS1447582930@199:6 | BV9: =_xll.meLWOXccySwapParSpread(BU9,$BZ$2:$CA$6,,$BZ$3) -> 703.51586 | BW9: =BW8+1 -> 3 | BX9: Leg1:Float | BY9: 1000000 | BZ9: START_AND_END | CA9: PAY | CB9: USD3ML | CC9: USDOIS | CD9: USD | CE9: 1 | CG9: NATURAL | CH9: NATURAL | CI9: =SETTINGS!$F$6 -> 0.0129556 | CK9: =$E9 -> 698.9286 | CL9: =_xll.meLWOBondLastCouponDate('USD-BONDS'!D7,Settings.COB) -> 44039 | CM9: ='USD-BONDS'!L7 -> 44404 | CN9: QUARTERLY | CO9: ACT/360 | CP9: NO_CHANGE | CQ9: NYB | CR9: NO_CHANGE | CS9: NYB | CT9: NO_CHANGE | CU9: NYB | CX9: NORMAL | CY9: 0D | DA9: 0D | DB9: ShortStart | DC9: =DC8+1 -> 3 | DD9: Leg2:Float | DE9: =BY9/$CD$4 -> 1333333.3 | DF9: START_AND_END | DG9: REC | DH9: AUD3ML | DI9: AUDDF_USDCSA | DJ9: AUD | DK9: 1 | DM9: NATURAL | DN9: NATURAL | DO9: =SETTINGS!$I$6 -> 0.0171 | DQ9: 0 | DR9: =_xll.meLWOBondLastCouponDate('AUD-BONDS'!D7,Settings.COB) -> 44039 | DS9: ='AUD-BONDS'!L7 -> 44404 | DT9: QUARTERLY | DU9: ACT/365 | DV9: NO_CHANGE | DW9: SYB | DX9: NO_CHANGE | DY9: SYB | DZ9: NO_CHANGE | EA9: SYB | ED9: NORMAL | EE9: 0D | EG9: 0D | EH9: ShortStart | EI9: =EI8+1 -> 2 | EJ9: ='AUD-BONDS'!F7 -> XS1447583664 | EK9: =_xll.meLWOSwapCreate($EK$7&"_"&EJ9,_xll.meUtilityLVBFromKeysAndMultipleValues($ET$7:$FX$7,ET9:FX9,FZ9:HD9)) -> #Error: Missing key 'CALCULATIONTYPE'. This key is mandatory and must be included in the Label Value Block , 'scheduleLVB'. | EL9: =_xll.meLWOAssetSwapSpreadToCleanPrice($EK9,$EK$4,$BV9,$EW$4) -> #Error: Swap #ERROR does not exist | EM9: =EM8+1 -> 2 | EN9: =_xll.meLWOBondYield('AUD-BONDS'!D7,$EK$4,$EL9) -> #Error: Invalid input, numerical input required | EO9: =_xll.meLWOBondCleanPrice('AUD-BONDS'!$D7,$EK$4,$EN9) -> #Error: Invalid Vector Data: Input Contains Errors | EP9: =_xll.meLWOBondDirtyPrice('AUD-BONDS'!$D7,$EK$4,$EN9) -> #Error: Invalid Vector Data: Input Contains Errors | EQ9: =_xll.meLWOBondAccruedInterest('AUD-BONDS'!$D7,'AUD-URIDASHI-PX'!$EK$4) -> 1970 | ER9: =_xll.meLWOBondAccruedInterestDays('AUD-BONDS'!$D7,'AUD-URIDASHI-PX'!$EK$4) -> 27 | ES9: =ES8+1 -> 2 | ET9: Leg1:FixedBond | EU9: =$DE9 -> 1333333.3 | EV9: NONE | EW9: PAY | EY9: AUDOIS | EZ9: AUD | FA9: 1 | FB9: ='AUD-BONDS'!M7 -> 0.0262 | FH9: =_xll.meLWOBondLastCouponDate('AUD-BONDS'!D7,Settings.COB) -> 44039 | FI9: ='AUD-BONDS'!L7 -> 44404 | FJ9: ='AUD-BONDS'!O7 -> SEMI-ANNUAL | FK9: ='AUD-BONDS'!N7 -> 30E/360 | FL9: NO_CHANGE | FM9: NYB | FN9: NO_CHANGE | FO9: NYB | FP9: NO_CHANGE | FQ9: NYB | FT9: NORMAL | FW9: 0D | FX9: ShortStart | FY9: =FY8+1 -> 2 | FZ9: Leg2:Float | GA9: =$DE9 -> 1333333.3 | GB9: NONE | GC9: REC | GD9: AUD3ML | GE9: AUDOIS | GF9: AUD | GG9: 1 | GI9: NATURAL | GJ9: NATURAL | GK9: =SETTINGS!$I$6 -> 0.0171 | GM9: =$BV9 -> 703.51586 | GN9: =_xll.meLWOBondLastCouponDate('AUD-BONDS'!D7,Settings.COB) -> 44039 | GO9: ='AUD-BONDS'!L7 -> 44404 | GP9: QUARTERLY | GQ9: ACT/360 | GR9: NO_CHANGE | GS9: SYB | GT9: NO_CHANGE | GU9: SYB | GV9: NO_CHANGE | GW9: SYB | GZ9: NORMAL | HA9: 0D | HC9: 0D | HD9: ShortStart | HF9: #Error: No range or empty range specified | HG9: #Error: No range or empty range specified | HH9: #Error: No range or empty range specified | HI9: #Error: No range or empty range specified | HJ9: #Error: No range or empty range specified | HK9: #Error: No range or empty range specified | HL9: #Error: No range or empty range specified | HM9: #Error: No range or empty range specified | HN9: #Error: No range or empty range specified | HO9: #Error: No range or empty range specified | HP9: #Error: No range or empty range specified | HQ9: #Error: No range or empty range specified
A10: =A9+1 -> 3 | B10: ='USD-BONDS'!F8 -> ISIN2 | C10: ='USD-BONDS'!B8 -> 100 | D10: =_xll.meLWOSwapCreate($D$7&"_"&B10,_xll.meUtilityLVBFromKeysAndMultipleValues($G$7:$AL$7,G10:AL10,AN10:BS10)) -> USD_ASW_ISIN2@152:6 | E10: =_xll.meLWOAssetSwapSpread(D10,'USD-BONDS'!D8,C10,$J$4:$K$5) -> 285.35446 | F10: =F9+1 -> 3 | G10: Leg1:FixedBond | H10: 1000000 | I10: NONE | J10: PAY | L10: USDOIS | M10: USD | N10: 1 | O10: ='USD-BONDS'!M8 -> 0.032 | U10: =_xll.meLWOBondLastCouponDate('USD-BONDS'!D8,Settings.COB) -> 43916 | V10: ='USD-BONDS'!L8 -> 45742 | W10: ='USD-BONDS'!O8 -> SEMI-ANNUAL | X10: ='USD-BONDS'!N8 -> 30E/360 | Y10: NO_CHANGE | Z10: NYB | AA10: NO_CHANGE | AB10: NYB | AC10: NO_CHANGE | AD10: NYB | AG10: NORMAL | AJ10: 0D | AK10: TYPE1 | AL10: ShortStart | AM10: =AM9+1 -> 3 | AN10: Leg2:Float | AO10: 1000000 | AP10: NONE | AQ10: REC | AR10: USD3ML | AS10: USDOIS | AT10: USD | AU10: 1 | AW10: NATURAL | AX10: NATURAL | AY10: =SETTINGS!$F$6 -> 0.0129556 | BA10: 0 | BB10: =_xll.meLWOBondLastCouponDate('USD-BONDS'!D8,Settings.COB) -> 43916 | BC10: ='USD-BONDS'!L8 -> 45742 | BD10: QUARTERLY | BE10: ACT/360 | BF10: NO_CHANGE | BG10: NYB | BH10: NO_CHANGE | BI10: NYB | BJ10: NO_CHANGE | BK10: NYB | BN10: NORMAL | BO10: 0D | BQ10: 0D | BS10: ShortStart | BT10: =BT9+1 -> 3 | BU10: =_xll.meLWOXccySwapCreate($BU$7&"_"&B10,_xll.meUtilityLVBFromKeysAndMultipleValues($BX$7:$DB$7,BX10:DB10,DD10:EH10),$CC$2:$CD$5) -> XCCY_SWAP_ISIN2@185:6 | BV10: =_xll.meLWOXccySwapParSpread(BU10,$BZ$2:$CA$6,,$BZ$3) -> 260.66732 | BW10: =BW9+1 -> 4 | BX10: Leg1:Float | BY10: 1000000 | BZ10: START_AND_END | CA10: PAY | CB10: USD3ML | CC10: USDOIS | CD10: USD | CE10: 1 | CG10: NATURAL | CH10: NATURAL | CI10: =SETTINGS!$F$6 -> 0.0129556 | CK10: =$E10 -> 285.35446 | CL10: =_xll.meLWOBondLastCouponDate('USD-BONDS'!D8,Settings.COB) -> 43916 | CM10: ='USD-BONDS'!L8 -> 45742 | CN10: QUARTERLY | CO10: ACT/360 | CP10: NO_CHANGE | CQ10: NYB | CR10: NO_CHANGE | CS10: NYB | CT10: NO_CHANGE | CU10: NYB | CX10: NORMAL | CY10: 0D | DA10: 0D | DB10: ShortStart | DC10: =DC9+1 -> 4 | DD10: Leg2:Float | DE10: =BY10/$CD$4 -> 1333333.3 | DF10: START_AND_END | DG10: REC | DH10: AUD3ML | DI10: AUDDF_USDCSA | DJ10: AUD | DK10: 1 | DM10: NATURAL | DN10: NATURAL | DO10: =SETTINGS!$I$6 -> 0.0171 | DQ10: 0 | DR10: =_xll.meLWOBondLastCouponDate('AUD-BONDS'!D8,Settings.COB) -> 44027 | DS10: ='AUD-BONDS'!L8 -> 46037 | DT10: QUARTERLY | DU10: ACT/365 | DV10: NO_CHANGE | DW10: SYB | DX10: NO_CHANGE | DY10: SYB | DZ10: NO_CHANGE | EA10: SYB | ED10: NORMAL | EE10: 0D | EG10: 0D | EH10: ShortStart | EI10: =EI9+1 -> 3 | EJ10: ='AUD-BONDS'!F8 -> ISIN2 | EK10: =_xll.meLWOSwapCreate($EK$7&"_"&EJ10,_xll.meUtilityLVBFromKeysAndMultipleValues($ET$7:$FX$7,ET10:FX10,FZ10:HD10)) -> #Error: Missing key 'CALCULATIONTYPE'. This key is mandatory and must be included in the Label Value Block , 'scheduleLVB'. | EL10: =_xll.meLWOAssetSwapSpreadToCleanPrice($EK10,$EK$4,$BV10,$EW$4) -> #Error: Swap #ERROR does not exist | EM10: =EM9+1 -> 3 | EN10: =_xll.meLWOBondYield('AUD-BONDS'!D8,$EK$4,$EL10) -> #Error: Invalid input, numerical input required | EO10: =_xll.meLWOBondCleanPrice('AUD-BONDS'!$D8,$EK$4,$EN10) -> #Error: Invalid Vector Data: Input Contains Errors | EP10: =_xll.meLWOBondDirtyPrice('AUD-BONDS'!$D8,$EK$4,$EN10) -> #Error: Invalid Vector Data: Input Contains Errors | EQ10: =_xll.meLWOBondAccruedInterest('AUD-BONDS'!$D8,'AUD-URIDASHI-PX'!$EK$4) -> 4250 | ER10: =_xll.meLWOBondAccruedInterestDays('AUD-BONDS'!$D8,'AUD-URIDASHI-PX'!$EK$4) -> 39 | ES10: =ES9+1 -> 3 | ET10: Leg1:FixedBond | EU10: =$DE10 -> 1333333.3 | EV10: NONE | EW10: PAY | EY10: AUDOIS | EZ10: AUD | FA10: 1 | FB10: ='AUD-BONDS'!M8 -> 0.0392 | FH10: =_xll.meLWOBondLastCouponDate('AUD-BONDS'!D8,Settings.COB) -> 44027 | FI10: ='AUD-BONDS'!L8 -> 46037 | FJ10: ='AUD-BONDS'!O8 -> SEMI-ANNUAL | FK10: ='AUD-BONDS'!N8 -> 30E/360 | FL10: NO_CHANGE | FM10: NYB | FN10: NO_CHANGE | FO10: NYB | FP10: NO_CHANGE | FQ10: NYB | FT10: NORMAL | FW10: 0D | FX10: ShortStart | FY10: =FY9+1 -> 3 | FZ10: Leg2:Float | GA10: =$DE10 -> 1333333.3 | GB10: NONE | GC10: REC | GD10: AUD3ML | GE10: AUDOIS | GF10: AUD | GG10: 1 | GI10: NATURAL | GJ10: NATURAL | GK10: =SETTINGS!$I$6 -> 0.0171 | GM10: =$BV10 -> 260.66732 | GN10: =_xll.meLWOBondLastCouponDate('AUD-BONDS'!D8,Settings.COB) -> 44027 | GO10: ='AUD-BONDS'!L8 -> 46037 | GP10: QUARTERLY | GQ10: ACT/360 | GR10: NO_CHANGE | GS10: SYB | GT10: NO_CHANGE | GU10: SYB | GV10: NO_CHANGE | GW10: SYB | GZ10: NORMAL | HA10: 0D | HC10: 0D | HD10: ShortStart | HF10: #Error: No range or empty range specified | HG10: #Error: No range or empty range specified | HH10: #Error: No range or empty range specified | HI10: #Error: No range or empty range specified | HJ10: #Error: No range or empty range specified | HK10: #Error: No range or empty range specified | HL10: #Error: No range or empty range specified | HM10: #Error: No range or empty range specified | HN10: #Error: No range or empty range specified | HO10: #Error: No range or empty range specified | HP10: #Error: No range or empty range specified | HQ10: #Error: No range or empty range specified
A11: =A10+1 -> 4 | B11: ='USD-BONDS'!F9 -> ISIN3 | C11: ='USD-BONDS'!B9 -> 100 | D11: =_xll.meLWOSwapCreate($D$7&"_"&B11,_xll.meUtilityLVBFromKeysAndMultipleValues($G$7:$AL$7,G11:AL11,AN11:BS11)) -> USD_ASW_ISIN3@147:6 | E11: =_xll.meLWOAssetSwapSpread(D11,'USD-BONDS'!D9,C11,$J$4:$K$5) -> 285.35446 | F11: =F10+1 -> 4 | G11: Leg1:FixedBond | H11: 1000000 | I11: NONE | J11: PAY | L11: USDOIS | M11: USD | N11: 1 | O11: ='USD-BONDS'!M9 -> 0.032 | U11: =_xll.meLWOBondLastCouponDate('USD-BONDS'!D9,Settings.COB) -> 43916 | V11: ='USD-BONDS'!L9 -> 45742 | W11: ='USD-BONDS'!O9 -> SEMI-ANNUAL | X11: ='USD-BONDS'!N9 -> 30E/360 | Y11: NO_CHANGE | Z11: NYB | AA11: NO_CHANGE | AB11: NYB | AC11: NO_CHANGE | AD11: NYB | AG11: NORMAL | AJ11: 0D | AK11: TYPE1 | AL11: ShortStart | AM11: =AM10+1 -> 4 | AN11: Leg2:Float | AO11: 1000000 | AP11: NONE | AQ11: REC | AR11: USD3ML | AS11: USDOIS | AT11: USD | AU11: 1 | AW11: NATURAL | AX11: NATURAL | AY11: =SETTINGS!$F$6 -> 0.0129556 | BA11: 0 | BB11: =_xll.meLWOBondLastCouponDate('USD-BONDS'!D9,Settings.COB) -> 43916 | BC11: ='USD-BONDS'!L9 -> 45742 | BD11: QUARTERLY | BE11: ACT/360 | BF11: NO_CHANGE | BG11: NYB | BH11: NO_CHANGE | BI11: NYB | BJ11: NO_CHANGE | BK11: NYB | BN11: NORMAL | BO11: 0D | BQ11: 0D | BS11: ShortStart | BT11: =BT10+1 -> 4 | BU11: =_xll.meLWOXccySwapCreate($BU$7&"_"&B11,_xll.meUtilityLVBFromKeysAndMultipleValues($BX$7:$DB$7,BX11:DB11,DD11:EH11),$CC$2:$CD$5) -> XCCY_SWAP_ISIN3@196:6 | BV11: =_xll.meLWOXccySwapParSpread(BU11,$BZ$2:$CA$6,,$BZ$3) -> 260.66732 | BW11: =BW10+1 -> 5 | BX11: Leg1:Float | BY11: 1000000 | BZ11: START_AND_END | CA11: PAY | CB11: USD3ML | CC11: USDOIS | CD11: USD | CE11: 1 | CG11: NATURAL | CH11: NATURAL | CI11: =SETTINGS!$F$6 -> 0.0129556 | CK11: =$E11 -> 285.35446 | CL11: =_xll.meLWOBondLastCouponDate('USD-BONDS'!D9,Settings.COB) -> 43916 | CM11: ='USD-BONDS'!L9 -> 45742 | CN11: QUARTERLY | CO11: ACT/360 | CP11: NO_CHANGE | CQ11: NYB | CR11: NO_CHANGE | CS11: NYB | CT11: NO_CHANGE | CU11: NYB | CX11: NORMAL | CY11: 0D | DA11: 0D | DB11: ShortStart | DC11: =DC10+1 -> 5 | DD11: Leg2:Float | DE11: =BY11/$CD$4 -> 1333333.3 | DF11: START_AND_END | DG11: REC | DH11: AUD3ML | DI11: AUDDF_USDCSA | DJ11: AUD | DK11: 1 | DM11: NATURAL | DN11: NATURAL | DO11: =SETTINGS!$I$6 -> 0.0171 | DQ11: 0 | DR11: =_xll.meLWOBondLastCouponDate('AUD-BONDS'!D9,Settings.COB) -> 44027 | DS11: ='AUD-BONDS'!L9 -> 46037 | DT11: QUARTERLY | DU11: ACT/365 | DV11: NO_CHANGE | DW11: SYB | DX11: NO_CHANGE | DY11: SYB | DZ11: NO_CHANGE | EA11: SYB | ED11: NORMAL | EE11: 0D | EG11: 0D | EH11: ShortStart | EI11: =EI10+1 -> 4 | EJ11: ='AUD-BONDS'!F9 -> ISIN3 | EK11: =_xll.meLWOSwapCreate($EK$7&"_"&EJ11,_xll.meUtilityLVBFromKeysAndMultipleValues($ET$7:$FX$7,ET11:FX11,FZ11:HD11)) -> #Error: Missing key 'CALCULATIONTYPE'. This key is mandatory and must be included in the Label Value Block , 'scheduleLVB'. | EL11: =_xll.meLWOAssetSwapSpreadToCleanPrice($EK11,$EK$4,$BV11,$EW$4) -> #Error: Swap #ERROR does not exist | EM11: =EM10+1 -> 4 | EN11: =_xll.meLWOBondYield('AUD-BONDS'!D9,$EK$4,$EL11) -> #Error: Invalid input, numerical input required | EO11: =_xll.meLWOBondCleanPrice('AUD-BONDS'!$D9,$EK$4,$EN11) -> #Error: Invalid Vector Data: Input Contains Errors | EP11: =_xll.meLWOBondDirtyPrice('AUD-BONDS'!$D9,$EK$4,$EN11) -> #Error: Invalid Vector Data: Input Contains Errors | EQ11: =_xll.meLWOBondAccruedInterest('AUD-BONDS'!$D9,'AUD-URIDASHI-PX'!$EK$4) -> 4250 | ER11: =_xll.meLWOBondAccruedInterestDays('AUD-BONDS'!$D9,'AUD-URIDASHI-PX'!$EK$4) -> 39 | ES11: =ES10+1 -> 4 | ET11: Leg1:FixedBond | EU11: =$DE11 -> 1333333.3 | EV11: NONE | EW11: PAY | EY11: AUDOIS | EZ11: AUD | FA11: 1 | FB11: ='AUD-BONDS'!M9 -> 0.0392 | FH11: =_xll.meLWOBondLastCouponDate('AUD-BONDS'!D9,Settings.COB) -> 44027 | FI11: ='AUD-BONDS'!L9 -> 46037 | FJ11: ='AUD-BONDS'!O9 -> SEMI-ANNUAL | FK11: ='AUD-BONDS'!N9 -> 30E/360 | FL11: NO_CHANGE | FM11: NYB | FN11: NO_CHANGE | FO11: NYB | FP11: NO_CHANGE | FQ11: NYB | FT11: NORMAL | FW11: 0D | FX11: ShortStart | FY11: =FY10+1 -> 4 | FZ11: Leg2:Float | GA11: =$DE11 -> 1333333.3 | GB11: NONE | GC11: REC | GD11: AUD3ML | GE11: AUDOIS | GF11: AUD | GG11: 1 | GI11: NATURAL | GJ11: NATURAL | GK11: =SETTINGS!$I$6 -> 0.0171 | GM11: =$BV11 -> 260.66732 | GN11: =_xll.meLWOBondLastCouponDate('AUD-BONDS'!D9,Settings.COB) -> 44027 | GO11: ='AUD-BONDS'!L9 -> 46037 | GP11: QUARTERLY | GQ11: ACT/360 | GR11: NO_CHANGE | GS11: SYB | GT11: NO_CHANGE | GU11: SYB | GV11: NO_CHANGE | GW11: SYB | GZ11: NORMAL | HA11: 0D | HC11: 0D | HD11: ShortStart | HF11: #Error: No range or empty range specified | HG11: #Error: No range or empty range specified | HH11: #Error: No range or empty range specified | HI11: #Error: No range or empty range specified | HJ11: #Error: No range or empty range specified | HK11: #Error: No range or empty range specified | HL11: #Error: No range or empty range specified | HM11: #Error: No range or empty range specified | HN11: #Error: No range or empty range specified | HO11: #Error: No range or empty range specified | HP11: #Error: No range or empty range specified | HQ11: #Error: No range or empty range specified
A12: =A11+1 -> 5 | B12: ='USD-BONDS'!F10 -> ISIN4 | C12: ='USD-BONDS'!B10 -> 100 | D12: =_xll.meLWOSwapCreate($D$7&"_"&B12,_xll.meUtilityLVBFromKeysAndMultipleValues($G$7:$AL$7,G12:AL12,AN12:BS12)) -> USD_ASW_ISIN4@151:6 | E12: =_xll.meLWOAssetSwapSpread(D12,'USD-BONDS'!D10,C12,$J$4:$K$5) -> 285.35446 | F12: =F11+1 -> 5 | G12: Leg1:FixedBond | H12: 1000000 | I12: NONE | J12: PAY | L12: USDOIS | M12: USD | N12: 1 | O12: ='USD-BONDS'!M10 -> 0.032 | U12: =_xll.meLWOBondLastCouponDate('USD-BONDS'!D10,Settings.COB) -> 43916 | V12: ='USD-BONDS'!L10 -> 45742 | W12: ='USD-BONDS'!O10 -> SEMI-ANNUAL | X12: ='USD-BONDS'!N10 -> 30E/360 | Y12: NO_CHANGE | Z12: NYB | AA12: NO_CHANGE | AB12: NYB | AC12: NO_CHANGE | AD12: NYB | AG12: NORMAL | AJ12: 0D | AK12: TYPE1 | AL12: ShortStart | AM12: =AM11+1 -> 5 | AN12: Leg2:Float | AO12: 1000000 | AP12: NONE | AQ12: REC | AR12: USD3ML | AS12: USDOIS | AT12: USD | AU12: 1 | AW12: NATURAL | AX12: NATURAL | AY12: =SETTINGS!$F$6 -> 0.0129556 | BA12: 0 | BB12: =_xll.meLWOBondLastCouponDate('USD-BONDS'!D10,Settings.COB) -> 43916 | BC12: ='USD-BONDS'!L10 -> 45742 | BD12: QUARTERLY | BE12: ACT/360 | BF12: NO_CHANGE | BG12: NYB | BH12: NO_CHANGE | BI12: NYB | BJ12: NO_CHANGE | BK12: NYB | BN12: NORMAL | BO12: 0D | BQ12: 0D | BS12: ShortStart | BT12: =BT11+1 -> 5 | BU12: =_xll.meLWOXccySwapCreate($BU$7&"_"&B12,_xll.meUtilityLVBFromKeysAndMultipleValues($BX$7:$DB$7,BX12:DB12,DD12:EH12),$CC$2:$CD$5) -> XCCY_SWAP_ISIN4@198:6 | BV12: =_xll.meLWOXccySwapParSpread(BU12,$BZ$2:$CA$6,,$BZ$3) -> 260.66732 | BW12: =BW11+1 -> 6 | BX12: Leg1:Float | BY12: 1000000 | BZ12: START_AND_END | CA12: PAY | CB12: USD3ML | CC12: USDOIS | CD12: USD | CE12: 1 | CG12: NATURAL | CH12: NATURAL | CI12: =SETTINGS!$F$6 -> 0.0129556 | CK12: =$E12 -> 285.35446 | CL12: =_xll.meLWOBondLastCouponDate('USD-BONDS'!D10,Settings.COB) -> 43916 | CM12: ='USD-BONDS'!L10 -> 45742 | CN12: QUARTERLY | CO12: ACT/360 | CP12: NO_CHANGE | CQ12: NYB | CR12: NO_CHANGE | CS12: NYB | CT12: NO_CHANGE | CU12: NYB | CX12: NORMAL | CY12: 0D | DA12: 0D | DB12: ShortStart | DC12: =DC11+1 -> 6 | DD12: Leg2:Float | DE12: =BY12/$CD$4 -> 1333333.3 | DF12: START_AND_END | DG12: REC | DH12: AUD3ML | DI12: AUDDF_USDCSA | DJ12: AUD | DK12: 1 | DM12: NATURAL | DN12: NATURAL | DO12: =SETTINGS!$I$6 -> 0.0171 | DQ12: 0 | DR12: =_xll.meLWOBondLastCouponDate('AUD-BONDS'!D10,Settings.COB) -> 44027 | DS12: ='AUD-BONDS'!L10 -> 46037 | DT12: QUARTERLY | DU12: ACT/365 | DV12: NO_CHANGE | DW12: SYB | DX12: NO_CHANGE | DY12: SYB | DZ12: NO_CHANGE | EA12: SYB | ED12: NORMAL | EE12: 0D | EG12: 0D | EH12: ShortStart | EI12: =EI11+1 -> 5 | EJ12: ='AUD-BONDS'!F10 -> ISIN4 | EK12: =_xll.meLWOSwapCreate($EK$7&"_"&EJ12,_xll.meUtilityLVBFromKeysAndMultipleValues($ET$7:$FX$7,ET12:FX12,FZ12:HD12)) -> #Error: Missing key 'CALCULATIONTYPE'. This key is mandatory and must be included in the Label Value Block , 'scheduleLVB'. | EL12: =_xll.meLWOAssetSwapSpreadToCleanPrice($EK12,$EK$4,$BV12,$EW$4) -> #Error: Swap #ERROR does not exist | EM12: =EM11+1 -> 5 | EN12: =_xll.meLWOBondYield('AUD-BONDS'!D10,$EK$4,$EL12) -> #Error: Invalid input, numerical input required | EO12: =_xll.meLWOBondCleanPrice('AUD-BONDS'!$D10,$EK$4,$EN12) -> #Error: Invalid Vector Data: Input Contains Errors | EP12: =_xll.meLWOBondDirtyPrice('AUD-BONDS'!$D10,$EK$4,$EN12) -> #Error: Invalid Vector Data: Input Contains Errors | EQ12: =_xll.meLWOBondAccruedInterest('AUD-BONDS'!$D10,'AUD-URIDASHI-PX'!$EK$4) -> 4250 | ER12: =_xll.meLWOBondAccruedInterestDays('AUD-BONDS'!$D10,'AUD-URIDASHI-PX'!$EK$4) -> 39 | ES12: =ES11+1 -> 5 | ET12: Leg1:FixedBond | EU12: =$DE12 -> 1333333.3 | EV12: NONE | EW12: PAY | EY12: AUDOIS | EZ12: AUD | FA12: 1 | FB12: ='AUD-BONDS'!M10 -> 0.0392 | FH12: =_xll.meLWOBondLastCouponDate('AUD-BONDS'!D10,Settings.COB) -> 44027 | FI12: ='AUD-BONDS'!L10 -> 46037 | FJ12: ='AUD-BONDS'!O10 -> SEMI-ANNUAL | FK12: ='AUD-BONDS'!N10 -> 30E/360 | FL12: NO_CHANGE | FM12: NYB | FN12: NO_CHANGE | FO12: NYB | FP12: NO_CHANGE | FQ12: NYB | FT12: NORMAL | FW12: 0D | FX12: ShortStart | FY12: =FY11+1 -> 5 | FZ12: Leg2:Float | GA12: =$DE12 -> 1333333.3 | GB12: NONE | GC12: REC | GD12: AUD3ML | GE12: AUDOIS | GF12: AUD | GG12: 1 | GI12: NATURAL | GJ12: NATURAL | GK12: =SETTINGS!$I$6 -> 0.0171 | GM12: =$BV12 -> 260.66732 | GN12: =_xll.meLWOBondLastCouponDate('AUD-BONDS'!D10,Settings.COB) -> 44027 | GO12: ='AUD-BONDS'!L10 -> 46037 | GP12: QUARTERLY | GQ12: ACT/360 | GR12: NO_CHANGE | GS12: SYB | GT12: NO_CHANGE | GU12: SYB | GV12: NO_CHANGE | GW12: SYB | GZ12: NORMAL | HA12: 0D | HC12: 0D | HD12: ShortStart | HF12: #Error: No range or empty range specified | HG12: #Error: No range or empty range specified | HH12: #Error: No range or empty range specified | HI12: #Error: No range or empty range specified | HJ12: #Error: No range or empty range specified | HK12: #Error: No range or empty range specified | HL12: #Error: No range or empty range specified | HM12: #Error: No range or empty range specified | HN12: #Error: No range or empty range specified | HO12: #Error: No range or empty range specified | HP12: #Error: No range or empty range specified | HQ12: #Error: No range or empty range specified
A13: =A12+1 -> 6 | B13: ='USD-BONDS'!F11 -> ISIN5 | C13: ='USD-BONDS'!B11 -> 100 | D13: =_xll.meLWOSwapCreate($D$7&"_"&B13,_xll.meUtilityLVBFromKeysAndMultipleValues($G$7:$AL$7,G13:AL13,AN13:BS13)) -> USD_ASW_ISIN5@165:6 | E13: =_xll.meLWOAssetSwapSpread(D13,'USD-BONDS'!D11,C13,$J$4:$K$5) -> 285.35446 | F13: =F12+1 -> 6 | G13: Leg1:FixedBond | H13: 1000000 | I13: NONE | J13: PAY | L13: USDOIS | M13: USD | N13: 1 | O13: ='USD-BONDS'!M11 -> 0.032 | U13: =_xll.meLWOBondLastCouponDate('USD-BONDS'!D11,Settings.COB) -> 43916 | V13: ='USD-BONDS'!L11 -> 45742 | W13: ='USD-BONDS'!O11 -> SEMI-ANNUAL | X13: ='USD-BONDS'!N11 -> 30E/360 | Y13: NO_CHANGE | Z13: NYB | AA13: NO_CHANGE | AB13: NYB | AC13: NO_CHANGE | AD13: NYB | AG13: NORMAL | AJ13: 0D | AK13: TYPE1 | AL13: ShortStart | AM13: =AM12+1 -> 6 | AN13: Leg2:Float | AO13: 1000000 | AP13: NONE | AQ13: REC | AR13: USD3ML | AS13: USDOIS | AT13: USD | AU13: 1 | AW13: NATURAL | AX13: NATURAL | AY13: =SETTINGS!$F$6 -> 0.0129556 | BA13: 0 | BB13: =_xll.meLWOBondLastCouponDate('USD-BONDS'!D11,Settings.COB) -> 43916 | BC13: ='USD-BONDS'!L11 -> 45742 | BD13: QUARTERLY | BE13: ACT/360 | BF13: NO_CHANGE | BG13: NYB | BH13: NO_CHANGE | BI13: NYB | BJ13: NO_CHANGE | BK13: NYB | BN13: NORMAL | BO13: 0D | BQ13: 0D | BS13: ShortStart | BT13: =BT12+1 -> 6 | BU13: =_xll.meLWOXccySwapCreate($BU$7&"_"&B13,_xll.meUtilityLVBFromKeysAndMultipleValues($BX$7:$DB$7,BX13:DB13,DD13:EH13),$CC$2:$CD$5) -> XCCY_SWAP_ISIN5@182:6 | BV13: =_xll.meLWOXccySwapParSpread(BU13,$BZ$2:$CA$6,,$BZ$3) -> 260.66732 | BW13: =BW12+1 -> 7 | BX13: Leg1:Float | BY13: 1000000 | BZ13: START_AND_END | CA13: PAY | CB13: USD3ML | CC13: USDOIS | CD13: USD | CE13: 1 | CG13: NATURAL | CH13: NATURAL | CI13: =SETTINGS!$F$6 -> 0.0129556 | CK13: =$E13 -> 285.35446 | CL13: =_xll.meLWOBondLastCouponDate('USD-BONDS'!D11,Settings.COB) -> 43916 | CM13: ='USD-BONDS'!L11 -> 45742 | CN13: QUARTERLY | CO13: ACT/360 | CP13: NO_CHANGE | CQ13: NYB | CR13: NO_CHANGE | CS13: NYB | CT13: NO_CHANGE | CU13: NYB | CX13: NORMAL | CY13: 0D | DA13: 0D | DB13: ShortStart | DC13: =DC12+1 -> 7 | DD13: Leg2:Float | DE13: =BY13/$CD$4 -> 1333333.3 | DF13: START_AND_END | DG13: REC | DH13: AUD3ML | DI13: AUDDF_USDCSA | DJ13: AUD | DK13: 1 | DM13: NATURAL | DN13: NATURAL | DO13: =SETTINGS!$I$6 -> 0.0171 | DQ13: 0 | DR13: =_xll.meLWOBondLastCouponDate('AUD-BONDS'!D11,Settings.COB) -> 44027 | DS13: ='AUD-BONDS'!L11 -> 46037 | DT13: QUARTERLY | DU13: ACT/365 | DV13: NO_CHANGE | DW13: SYB | DX13: NO_CHANGE | DY13: SYB | DZ13: NO_CHANGE | EA13: SYB | ED13: NORMAL | EE13: 0D | EG13: 0D | EH13: ShortStart | EI13: =EI12+1 -> 6 | EJ13: ='AUD-BONDS'!F11 -> ISIN5 | EK13: =_xll.meLWOSwapCreate($EK$7&"_"&EJ13,_xll.meUtilityLVBFromKeysAndMultipleValues($ET$7:$FX$7,ET13:FX13,FZ13:HD13)) -> #Error: Missing key 'CALCULATIONTYPE'. This key is mandatory and must be included in the Label Value Block , 'scheduleLVB'. | EL13: =_xll.meLWOAssetSwapSpreadToCleanPrice($EK13,$EK$4,$BV13,$EW$4) -> #Error: Swap #ERROR does not exist | EM13: =EM12+1 -> 6 | EN13: =_xll.meLWOBondYield('AUD-BONDS'!D11,$EK$4,$EL13) -> #Error: Invalid input, numerical input required | EO13: =_xll.meLWOBondCleanPrice('AUD-BONDS'!$D11,$EK$4,$EN13) -> #Error: Invalid Vector Data: Input Contains Errors | EP13: =_xll.meLWOBondDirtyPrice('AUD-BONDS'!$D11,$EK$4,$EN13) -> #Error: Invalid Vector Data: Input Contains Errors | EQ13: =_xll.meLWOBondAccruedInterest('AUD-BONDS'!$D11,'AUD-URIDASHI-PX'!$EK$4) -> 4250 | ER13: =_xll.meLWOBondAccruedInterestDays('AUD-BONDS'!$D11,'AUD-URIDASHI-PX'!$EK$4) -> 39 | ES13: =ES12+1 -> 6 | ET13: Leg1:FixedBond | EU13: =$DE13 -> 1333333.3 | EV13: NONE | EW13: PAY | EY13: AUDOIS | EZ13: AUD | FA13: 1 | FB13: ='AUD-BONDS'!M11 -> 0.0392 | FH13: =_xll.meLWOBondLastCouponDate('AUD-BONDS'!D11,Settings.COB) -> 44027 | FI13: ='AUD-BONDS'!L11 -> 46037 | FJ13: ='AUD-BONDS'!O11 -> SEMI-ANNUAL | FK13: ='AUD-BONDS'!N11 -> 30E/360 | FL13: NO_CHANGE | FM13: NYB | FN13: NO_CHANGE | FO13: NYB | FP13: NO_CHANGE | FQ13: NYB | FT13: NORMAL | FW13: 0D | FX13: ShortStart | FY13: =FY12+1 -> 6 | FZ13: Leg2:Float | GA13: =$DE13 -> 1333333.3 | GB13: NONE | GC13: REC | GD13: AUD3ML | GE13: AUDOIS | GF13: AUD | GG13: 1 | GI13: NATURAL | GJ13: NATURAL | GK13: =SETTINGS!$I$6 -> 0.0171 | GM13: =$BV13 -> 260.66732 | GN13: =_xll.meLWOBondLastCouponDate('AUD-BONDS'!D11,Settings.COB) -> 44027 | GO13: ='AUD-BONDS'!L11 -> 46037 | GP13: QUARTERLY | GQ13: ACT/360 | GR13: NO_CHANGE | GS13: SYB | GT13: NO_CHANGE | GU13: SYB | GV13: NO_CHANGE | GW13: SYB | GZ13: NORMAL | HA13: 0D | HC13: 0D | HD13: ShortStart | HF13: #Error: No range or empty range specified | HG13: #Error: No range or empty range specified | HH13: #Error: No range or empty range specified | HI13: #Error: No range or empty range specified | HJ13: #Error: No range or empty range specified | HK13: #Error: No range or empty range specified | HL13: #Error: No range or empty range specified | HM13: #Error: No range or empty range specified | HN13: #Error: No range or empty range specified | HO13: #Error: No range or empty range specified | HP13: #Error: No range or empty range specified | HQ13: #Error: No range or empty range specified
A14: =A13+1 -> 7 | B14: ='USD-BONDS'!F12 -> ISIN6 | C14: ='USD-BONDS'!B12 -> 100 | D14: =_xll.meLWOSwapCreate($D$7&"_"&B14,_xll.meUtilityLVBFromKeysAndMultipleValues($G$7:$AL$7,G14:AL14,AN14:BS14)) -> USD_ASW_ISIN6@160:6 | E14: =_xll.meLWOAssetSwapSpread(D14,'USD-BONDS'!D12,C14,$J$4:$K$5) -> 285.35446 | F14: =F13+1 -> 7 | G14: Leg1:FixedBond | H14: 1000000 | I14: NONE | J14: PAY | L14: USDOIS | M14: USD | N14: 1 | O14: ='USD-BONDS'!M12 -> 0.032 | U14: =_xll.meLWOBondLastCouponDate('USD-BONDS'!D12,Settings.COB) -> 43916 | V14: ='USD-BONDS'!L12 -> 45742 | W14: ='USD-BONDS'!O12 -> SEMI-ANNUAL | X14: ='USD-BONDS'!N12 -> 30E/360 | Y14: NO_CHANGE | Z14: NYB | AA14: NO_CHANGE | AB14: NYB | AC14: NO_CHANGE | AD14: NYB | AG14: NORMAL | AJ14: 0D | AK14: TYPE1 | AL14: ShortStart | AM14: =AM13+1 -> 7 | AN14: Leg2:Float | AO14: 1000000 | AP14: NONE | AQ14: REC | AR14: USD3ML | AS14: USDOIS | AT14: USD | AU14: 1 | AW14: NATURAL | AX14: NATURAL | AY14: =SETTINGS!$F$6 -> 0.0129556 | BA14: 0 | BB14: =_xll.meLWOBondLastCouponDate('USD-BONDS'!D12,Settings.COB) -> 43916 | BC14: ='USD-BONDS'!L12 -> 45742 | BD14: QUARTERLY | BE14: ACT/360 | BF14: NO_CHANGE | BG14: NYB | BH14: NO_CHANGE | BI14: NYB | BJ14: NO_CHANGE | BK14: NYB | BN14: NORMAL | BO14: 0D | BQ14: 0D | BS14: ShortStart | BT14: =BT13+1 -> 7 | BU14: =_xll.meLWOXccySwapCreate($BU$7&"_"&B14,_xll.meUtilityLVBFromKeysAndMultipleValues($BX$7:$DB$7,BX14:DB14,DD14:EH14),$CC$2:$CD$5) -> XCCY_SWAP_ISIN6@191:6 | BV14: =_xll.meLWOXccySwapParSpread(BU14,$BZ$2:$CA$6,,$BZ$3) -> 260.66732 | BW14: =BW13+1 -> 8 | BX14: Leg1:Float | BY14: 1000000 | BZ14: START_AND_END | CA14: PAY | CB14: USD3ML | CC14: USDOIS | CD14: USD | CE14: 1 | CG14: NATURAL | CH14: NATURAL | CI14: =SETTINGS!$F$6 -> 0.0129556 | CK14: =$E14 -> 285.35446 | CL14: =_xll.meLWOBondLastCouponDate('USD-BONDS'!D12,Settings.COB) -> 43916 | CM14: ='USD-BONDS'!L12 -> 45742 | CN14: QUARTERLY | CO14: ACT/360 | CP14: NO_CHANGE | CQ14: NYB | CR14: NO_CHANGE | CS14: NYB | CT14: NO_CHANGE | CU14: NYB | CX14: NORMAL | CY14: 0D | DA14: 0D | DB14: ShortStart | DC14: =DC13+1 -> 8 | DD14: Leg2:Float | DE14: =BY14/$CD$4 -> 1333333.3 | DF14: START_AND_END | DG14: REC | DH14: AUD3ML | DI14: AUDDF_USDCSA | DJ14: AUD | DK14: 1 | DM14: NATURAL | DN14: NATURAL | DO14: =SETTINGS!$I$6 -> 0.0171 | DQ14: 0 | DR14: =_xll.meLWOBondLastCouponDate('AUD-BONDS'!D12,Settings.COB) -> 44027 | DS14: ='AUD-BONDS'!L12 -> 46037 | DT14: QUARTERLY | DU14: ACT/365 | DV14: NO_CHANGE | DW14: SYB | DX14: NO_CHANGE | DY14: SYB | DZ14: NO_CHANGE | EA14: SYB | ED14: NORMAL | EE14: 0D | EG14: 0D | EH14: ShortStart | EI14: =EI13+1 -> 7 | EJ14: ='AUD-BONDS'!F12 -> ISIN6 | EK14: =_xll.meLWOSwapCreate($EK$7&"_"&EJ14,_xll.meUtilityLVBFromKeysAndMultipleValues($ET$7:$FX$7,ET14:FX14,FZ14:HD14)) -> #Error: Missing key 'CALCULATIONTYPE'. This key is mandatory and must be included in the Label Value Block , 'scheduleLVB'. | EL14: =_xll.meLWOAssetSwapSpreadToCleanPrice($EK14,$EK$4,$BV14,$EW$4) -> #Error: Swap #ERROR does not exist | EM14: =EM13+1 -> 7 | EN14: =_xll.meLWOBondYield('AUD-BONDS'!D12,$EK$4,$EL14) -> #Error: Invalid input, numerical input required | EO14: =_xll.meLWOBondCleanPrice('AUD-BONDS'!$D12,$EK$4,$EN14) -> #Error: Invalid Vector Data: Input Contains Errors | EP14: =_xll.meLWOBondDirtyPrice('AUD-BONDS'!$D12,$EK$4,$EN14) -> #Error: Invalid Vector Data: Input Contains Errors | EQ14: =_xll.meLWOBondAccruedInterest('AUD-BONDS'!$D12,'AUD-URIDASHI-PX'!$EK$4) -> 4250 | ER14: =_xll.meLWOBondAccruedInterestDays('AUD-BONDS'!$D12,'AUD-URIDASHI-PX'!$EK$4) -> 39 | ES14: =ES13+1 -> 7 | ET14: Leg1:FixedBond | EU14: =$DE14 -> 1333333.3 | EV14: NONE | EW14: PAY | EY14: AUDOIS | EZ14: AUD | FA14: 1 | FB14: ='AUD-BONDS'!M12 -> 0.0392 | FH14: =_xll.meLWOBondLastCouponDate('AUD-BONDS'!D12,Settings.COB) -> 44027 | FI14: ='AUD-BONDS'!L12 -> 46037 | FJ14: ='AUD-BONDS'!O12 -> SEMI-ANNUAL | FK14: ='AUD-BONDS'!N12 -> 30E/360 | FL14: NO_CHANGE | FM14: NYB | FN14: NO_CHANGE | FO14: NYB | FP14: NO_CHANGE | FQ14: NYB | FT14: NORMAL | FW14: 0D | FX14: ShortStart | FY14: =FY13+1 -> 7 | FZ14: Leg2:Float | GA14: =$DE14 -> 1333333.3 | GB14: NONE | GC14: REC | GD14: AUD3ML | GE14: AUDOIS | GF14: AUD | GG14: 1 | GI14: NATURAL | GJ14: NATURAL | GK14: =SETTINGS!$I$6 -> 0.0171 | GM14: =$BV14 -> 260.66732 | GN14: =_xll.meLWOBondLastCouponDate('AUD-BONDS'!D12,Settings.COB) -> 44027 | GO14: ='AUD-BONDS'!L12 -> 46037 | GP14: QUARTERLY | GQ14: ACT/360 | GR14: NO_CHANGE | GS14: SYB | GT14: NO_CHANGE | GU14: SYB | GV14: NO_CHANGE | GW14: SYB | GZ14: NORMAL | HA14: 0D | HC14: 0D | HD14: ShortStart | HF14: #Error: No range or empty range specified | HG14: #Error: No range or empty range specified | HH14: #Error: No range or empty range specified | HI14: #Error: No range or empty range specified | HJ14: #Error: No range or empty range specified | HK14: #Error: No range or empty range specified | HL14: #Error: No range or empty range specified | HM14: #Error: No range or empty range specified | HN14: #Error: No range or empty range specified | HO14: #Error: No range or empty range specified | HP14: #Error: No range or empty range specified | HQ14: #Error: No range or empty range specified
A15: =A14+1 -> 8 | B15: ='USD-BONDS'!F13 -> ISIN7 | C15: ='USD-BONDS'!B13 -> 100 | D15: =_xll.meLWOSwapCreate($D$7&"_"&B15,_xll.meUtilityLVBFromKeysAndMultipleValues($G$7:$AL$7,G15:AL15,AN15:BS15)) -> USD_ASW_ISIN7@146:6 | E15: =_xll.meLWOAssetSwapSpread(D15,'USD-BONDS'!D13,C15,$J$4:$K$5) -> 285.35446 | F15: =F14+1 -> 8 | G15: Leg1:FixedBond | H15: 1000000 | I15: NONE | J15: PAY | L15: USDOIS | M15: USD | N15: 1 | O15: ='USD-BONDS'!M13 -> 0.032 | U15: =_xll.meLWOBondLastCouponDate('USD-BONDS'!D13,Settings.COB) -> 43916 | V15: ='USD-BONDS'!L13 -> 45742 | W15: ='USD-BONDS'!O13 -> SEMI-ANNUAL | X15: ='USD-BONDS'!N13 -> 30E/360 | Y15: NO_CHANGE | Z15: NYB | AA15: NO_CHANGE | AB15: NYB | AC15: NO_CHANGE | AD15: NYB | AG15: NORMAL | AJ15: 0D | AK15: TYPE1 | AL15: ShortStart | AM15: =AM14+1 -> 8 | AN15: Leg2:Float | AO15: 1000000 | AP15: NONE | AQ15: REC | AR15: USD3ML | AS15: USDOIS | AT15: USD | AU15: 1 | AW15: NATURAL | AX15: NATURAL | AY15: =SETTINGS!$F$6 -> 0.0129556 | BA15: 0 | BB15: =_xll.meLWOBondLastCouponDate('USD-BONDS'!D13,Settings.COB) -> 43916 | BC15: ='USD-BONDS'!L13 -> 45742 | BD15: QUARTERLY | BE15: ACT/360 | BF15: NO_CHANGE | BG15: NYB | BH15: NO_CHANGE | BI15: NYB | BJ15: NO_CHANGE | BK15: NYB | BN15: NORMAL | BO15: 0D | BQ15: 0D | BS15: ShortStart | BT15: =BT14+1 -> 8 | BU15: =_xll.meLWOXccySwapCreate($BU$7&"_"&B15,_xll.meUtilityLVBFromKeysAndMultipleValues($BX$7:$DB$7,BX15:DB15,DD15:EH15),$CC$2:$CD$5) -> XCCY_SWAP_ISIN7@193:6 | BV15: =_xll.meLWOXccySwapParSpread(BU15,$BZ$2:$CA$6,,$BZ$3) -> 260.66732 | BW15: =BW14+1 -> 9 | BX15: Leg1:Float | BY15: 1000000 | BZ15: START_AND_END | CA15: PAY | CB15: USD3ML | CC15: USDOIS | CD15: USD | CE15: 1 | CG15: NATURAL | CH15: NATURAL | CI15: =SETTINGS!$F$6 -> 0.0129556 | CK15: =$E15 -> 285.35446 | CL15: =_xll.meLWOBondLastCouponDate('USD-BONDS'!D13,Settings.COB) -> 43916 | CM15: ='USD-BONDS'!L13 -> 45742 | CN15: QUARTERLY | CO15: ACT/360 | CP15: NO_CHANGE | CQ15: NYB | CR15: NO_CHANGE | CS15: NYB | CT15: NO_CHANGE | CU15: NYB | CX15: NORMAL | CY15: 0D | DA15: 0D | DB15: ShortStart | DC15: =DC14+1 -> 9 | DD15: Leg2:Float | DE15: =BY15/$CD$4 -> 1333333.3 | DF15: START_AND_END | DG15: REC | DH15: AUD3ML | DI15: AUDDF_USDCSA | DJ15: AUD | DK15: 1 | DM15: NATURAL | DN15: NATURAL | DO15: =SETTINGS!$I$6 -> 0.0171 | DQ15: 0 | DR15: =_xll.meLWOBondLastCouponDate('AUD-BONDS'!D13,Settings.COB) -> 44027 | DS15: ='AUD-BONDS'!L13 -> 46037 | DT15: QUARTERLY | DU15: ACT/365 | DV15: NO_CHANGE | DW15: SYB | DX15: NO_CHANGE | DY15: SYB | DZ15: NO_CHANGE | EA15: SYB | ED15: NORMAL | EE15: 0D | EG15: 0D | EH15: ShortStart | EI15: =EI14+1 -> 8 | EJ15: ='AUD-BONDS'!F13 -> ISIN7 | EK15: =_xll.meLWOSwapCreate($EK$7&"_"&EJ15,_xll.meUtilityLVBFromKeysAndMultipleValues($ET$7:$FX$7,ET15:FX15,FZ15:HD15)) -> #Error: Missing key 'CALCULATIONTYPE'. This key is mandatory and must be included in the Label Value Block , 'scheduleLVB'. | EL15: =_xll.meLWOAssetSwapSpreadToCleanPrice($EK15,$EK$4,$BV15,$EW$4) -> #Error: Swap #ERROR does not exist | EM15: =EM14+1 -> 8 | EN15: =_xll.meLWOBondYield('AUD-BONDS'!D13,$EK$4,$EL15) -> #Error: Invalid input, numerical input required | EO15: =_xll.meLWOBondCleanPrice('AUD-BONDS'!$D13,$EK$4,$EN15) -> #Error: Invalid Vector Data: Input Contains Errors | EP15: =_xll.meLWOBondDirtyPrice('AUD-BONDS'!$D13,$EK$4,$EN15) -> #Error: Invalid Vector Data: Input Contains Errors | EQ15: =_xll.meLWOBondAccruedInterest('AUD-BONDS'!$D13,'AUD-URIDASHI-PX'!$EK$4) -> 4250 | ER15: =_xll.meLWOBondAccruedInterestDays('AUD-BONDS'!$D13,'AUD-URIDASHI-PX'!$EK$4) -> 39 | ES15: =ES14+1 -> 8 | ET15: Leg1:FixedBond | EU15: =$DE15 -> 1333333.3 | EV15: NONE | EW15: PAY | EY15: AUDOIS | EZ15: AUD | FA15: 1 | FB15: ='AUD-BONDS'!M13 -> 0.0392 | FH15: =_xll.meLWOBondLastCouponDate('AUD-BONDS'!D13,Settings.COB) -> 44027 | FI15: ='AUD-BONDS'!L13 -> 46037 | FJ15: ='AUD-BONDS'!O13 -> SEMI-ANNUAL | FK15: ='AUD-BONDS'!N13 -> 30E/360 | FL15: NO_CHANGE | FM15: NYB | FN15: NO_CHANGE | FO15: NYB | FP15: NO_CHANGE | FQ15: NYB | FT15: NORMAL | FW15: 0D | FX15: ShortStart | FY15: =FY14+1 -> 8 | FZ15: Leg2:Float | GA15: =$DE15 -> 1333333.3 | GB15: NONE | GC15: REC | GD15: AUD3ML | GE15: AUDOIS | GF15: AUD | GG15: 1 | GI15: NATURAL | GJ15: NATURAL | GK15: =SETTINGS!$I$6 -> 0.0171 | GM15: =$BV15 -> 260.66732 | GN15: =_xll.meLWOBondLastCouponDate('AUD-BONDS'!D13,Settings.COB) -> 44027 | GO15: ='AUD-BONDS'!L13 -> 46037 | GP15: QUARTERLY | GQ15: ACT/360 | GR15: NO_CHANGE | GS15: SYB | GT15: NO_CHANGE | GU15: SYB | GV15: NO_CHANGE | GW15: SYB | GZ15: NORMAL | HA15: 0D | HC15: 0D | HD15: ShortStart | HF15: #Error: No range or empty range specified | HG15: #Error: No range or empty range specified | HH15: #Error: No range or empty range specified | HI15: #Error: No range or empty range specified | HJ15: #Error: No range or empty range specified | HK15: #Error: No range or empty range specified | HL15: #Error: No range or empty range specified | HM15: #Error: No range or empty range specified | HN15: #Error: No range or empty range specified | HO15: #Error: No range or empty range specified | HP15: #Error: No range or empty range specified | HQ15: #Error: No range or empty range specified
A16: =A15+1 -> 9 | B16: ='USD-BONDS'!F14 -> ISIN8 | C16: ='USD-BONDS'!B14 -> 100 | D16: =_xll.meLWOSwapCreate($D$7&"_"&B16,_xll.meUtilityLVBFromKeysAndMultipleValues($G$7:$AL$7,G16:AL16,AN16:BS16)) -> USD_ASW_ISIN8@150:6 | E16: =_xll.meLWOAssetSwapSpread(D16,'USD-BONDS'!D14,C16,$J$4:$K$5) -> 285.35446 | F16: =F15+1 -> 9 | G16: Leg1:FixedBond | H16: 1000000 | I16: NONE | J16: PAY | L16: USDOIS | M16: USD | N16: 1 | O16: ='USD-BONDS'!M14 -> 0.032 | U16: =_xll.meLWOBondLastCouponDate('USD-BONDS'!D14,Settings.COB) -> 43916 | V16: ='USD-BONDS'!L14 -> 45742 | W16: ='USD-BONDS'!O14 -> SEMI-ANNUAL | X16: ='USD-BONDS'!N14 -> 30E/360 | Y16: NO_CHANGE | Z16: NYB | AA16: NO_CHANGE | AB16: NYB | AC16: NO_CHANGE | AD16: NYB | AG16: NORMAL | AJ16: 0D | AK16: TYPE1 | AL16: ShortStart | AM16: =AM15+1 -> 9 | AN16: Leg2:Float | AO16: 1000000 | AP16: NONE | AQ16: REC | AR16: USD3ML | AS16: USDOIS | AT16: USD | AU16: 1 | AW16: NATURAL | AX16: NATURAL | AY16: =SETTINGS!$F$6 -> 0.0129556 | BA16: 0 | BB16: =_xll.meLWOBondLastCouponDate('USD-BONDS'!D14,Settings.COB) -> 43916 | BC16: ='USD-BONDS'!L14 -> 45742 | BD16: QUARTERLY | BE16: ACT/360 | BF16: NO_CHANGE | BG16: NYB | BH16: NO_CHANGE | BI16: NYB | BJ16: NO_CHANGE | BK16: NYB | BN16: NORMAL | BO16: 0D | BQ16: 0D | BS16: ShortStart | BT16: =BT15+1 -> 9 | BU16: =_xll.meLWOXccySwapCreate($BU$7&"_"&B16,_xll.meUtilityLVBFromKeysAndMultipleValues($BX$7:$DB$7,BX16:DB16,DD16:EH16),$CC$2:$CD$5) -> XCCY_SWAP_ISIN8@181:6 | BV16: =_xll.meLWOXccySwapParSpread(BU16,$BZ$2:$CA$6,,$BZ$3) -> 260.66732 | BW16: =BW15+1 -> 10 | BX16: Leg1:Float | BY16: 1000000 | BZ16: START_AND_END | CA16: PAY | CB16: USD3ML | CC16: USDOIS | CD16: USD | CE16: 1 | CG16: NATURAL | CH16: NATURAL | CI16: =SETTINGS!$F$6 -> 0.0129556 | CK16: =$E16 -> 285.35446 | CL16: =_xll.meLWOBondLastCouponDate('USD-BONDS'!D14,Settings.COB) -> 43916 | CM16: ='USD-BONDS'!L14 -> 45742 | CN16: QUARTERLY | CO16: ACT/360 | CP16: NO_CHANGE | CQ16: NYB | CR16: NO_CHANGE | CS16: NYB | CT16: NO_CHANGE | CU16: NYB | CX16: NORMAL | CY16: 0D | DA16: 0D | DB16: ShortStart | DC16: =DC15+1 -> 10 | DD16: Leg2:Float | DE16: =BY16/$CD$4 -> 1333333.3 | DF16: START_AND_END | DG16: REC | DH16: AUD3ML | DI16: AUDDF_USDCSA | DJ16: AUD | DK16: 1 | DM16: NATURAL | DN16: NATURAL | DO16: =SETTINGS!$I$6 -> 0.0171 | DQ16: 0 | DR16: =_xll.meLWOBondLastCouponDate('AUD-BONDS'!D14,Settings.COB) -> 44027 | DS16: ='AUD-BONDS'!L14 -> 46037 | DT16: QUARTERLY | DU16: ACT/365 | DV16: NO_CHANGE | DW16: SYB | DX16: NO_CHANGE | DY16: SYB | DZ16: NO_CHANGE | EA16: SYB | ED16: NORMAL | EE16: 0D | EG16: 0D | EH16: ShortStart | EI16: =EI15+1 -> 9 | EJ16: ='AUD-BONDS'!F14 -> ISIN8 | EK16: =_xll.meLWOSwapCreate($EK$7&"_"&EJ16,_xll.meUtilityLVBFromKeysAndMultipleValues($ET$7:$FX$7,ET16:FX16,FZ16:HD16)) -> #Error: Missing key 'CALCULATIONTYPE'. This key is mandatory and must be included in the Label Value Block , 'scheduleLVB'. | EL16: =_xll.meLWOAssetSwapSpreadToCleanPrice($EK16,$EK$4,$BV16,$EW$4) -> #Error: Swap #ERROR does not exist | EM16: =EM15+1 -> 9 | EN16: =_xll.meLWOBondYield('AUD-BONDS'!D14,$EK$4,$EL16) -> #Error: Invalid input, numerical input required | EO16: =_xll.meLWOBondCleanPrice('AUD-BONDS'!$D14,$EK$4,$EN16) -> #Error: Invalid Vector Data: Input Contains Errors | EP16: =_xll.meLWOBondDirtyPrice('AUD-BONDS'!$D14,$EK$4,$EN16) -> #Error: Invalid Vector Data: Input Contains Errors | EQ16: =_xll.meLWOBondAccruedInterest('AUD-BONDS'!$D14,'AUD-URIDASHI-PX'!$EK$4) -> 4250 | ER16: =_xll.meLWOBondAccruedInterestDays('AUD-BONDS'!$D14,'AUD-URIDASHI-PX'!$EK$4) -> 39 | ES16: =ES15+1 -> 9 | ET16: Leg1:FixedBond | EU16: =$DE16 -> 1333333.3 | EV16: NONE | EW16: PAY | EY16: AUDOIS | EZ16: AUD | FA16: 1 | FB16: ='AUD-BONDS'!M14 -> 0.0392 | FH16: =_xll.meLWOBondLastCouponDate('AUD-BONDS'!D14,Settings.COB) -> 44027 | FI16: ='AUD-BONDS'!L14 -> 46037 | FJ16: ='AUD-BONDS'!O14 -> SEMI-ANNUAL | FK16: ='AUD-BONDS'!N14 -> 30E/360 | FL16: NO_CHANGE | FM16: NYB | FN16: NO_CHANGE | FO16: NYB | FP16: NO_CHANGE | FQ16: NYB | FT16: NORMAL | FW16: 0D | FX16: ShortStart | FY16: =FY15+1 -> 9 | FZ16: Leg2:Float | GA16: =$DE16 -> 1333333.3 | GB16: NONE | GC16: REC | GD16: AUD3ML | GE16: AUDOIS | GF16: AUD | GG16: 1 | GI16: NATURAL | GJ16: NATURAL | GK16: =SETTINGS!$I$6 -> 0.0171 | GM16: =$BV16 -> 260.66732 | GN16: =_xll.meLWOBondLastCouponDate('AUD-BONDS'!D14,Settings.COB) -> 44027 | GO16: ='AUD-BONDS'!L14 -> 46037 | GP16: QUARTERLY | GQ16: ACT/360 | GR16: NO_CHANGE | GS16: SYB | GT16: NO_CHANGE | GU16: SYB | GV16: NO_CHANGE | GW16: SYB | GZ16: NORMAL | HA16: 0D | HC16: 0D | HD16: ShortStart | HF16: #Error: No range or empty range specified | HG16: #Error: No range or empty range specified | HH16: #Error: No range or empty range specified | HI16: #Error: No range or empty range specified | HJ16: #Error: No range or empty range specified | HK16: #Error: No range or empty range specified | HL16: #Error: No range or empty range specified | HM16: #Error: No range or empty range specified | HN16: #Error: No range or empty range specified | HO16: #Error: No range or empty range specified | HP16: #Error: No range or empty range specified | HQ16: #Error: No range or empty range specified
A17: =A16+1 -> 10 | B17: ='USD-BONDS'!F15 -> ISIN9 | C17: ='USD-BONDS'!B15 -> 100 | D17: =_xll.meLWOSwapCreate($D$7&"_"&B17,_xll.meUtilityLVBFromKeysAndMultipleValues($G$7:$AL$7,G17:AL17,AN17:BS17)) -> USD_ASW_ISIN9@174:6 | E17: =_xll.meLWOAssetSwapSpread(D17,'USD-BONDS'!D15,C17,$J$4:$K$5) -> 285.35446 | F17: =F16+1 -> 10 | G17: Leg1:FixedBond | H17: 1000000 | I17: NONE | J17: PAY | L17: USDOIS | M17: USD | N17: 1 | O17: ='USD-BONDS'!M15 -> 0.032 | U17: =_xll.meLWOBondLastCouponDate('USD-BONDS'!D15,Settings.COB) -> 43916 | V17: ='USD-BONDS'!L15 -> 45742 | W17: ='USD-BONDS'!O15 -> SEMI-ANNUAL | X17: ='USD-BONDS'!N15 -> 30E/360 | Y17: NO_CHANGE | Z17: NYB | AA17: NO_CHANGE | AB17: NYB | AC17: NO_CHANGE | AD17: NYB | AG17: NORMAL | AJ17: 0D | AK17: TYPE1 | AL17: ShortStart | AM17: =AM16+1 -> 10 | AN17: Leg2:Float | AO17: 1000000 | AP17: NONE | AQ17: REC | AR17: USD3ML | AS17: USDOIS | AT17: USD | AU17: 1 | AW17: NATURAL | AX17: NATURAL | AY17: =SETTINGS!$F$6 -> 0.0129556 | BA17: 0 | BB17: =_xll.meLWOBondLastCouponDate('USD-BONDS'!D15,Settings.COB) -> 43916 | BC17: ='USD-BONDS'!L15 -> 45742 | BD17: QUARTERLY | BE17: ACT/360 | BF17: NO_CHANGE | BG17: NYB | BH17: NO_CHANGE | BI17: NYB | BJ17: NO_CHANGE | BK17: NYB | BN17: NORMAL | BO17: 0D | BQ17: 0D | BS17: ShortStart | BT17: =BT16+1 -> 10 | BU17: =_xll.meLWOXccySwapCreate($BU$7&"_"&B17,_xll.meUtilityLVBFromKeysAndMultipleValues($BX$7:$DB$7,BX17:DB17,DD17:EH17),$CC$2:$CD$5) -> XCCY_SWAP_ISIN9@183:6 | BV17: =_xll.meLWOXccySwapParSpread(BU17,$BZ$2:$CA$6,,$BZ$3) -> 260.66732 | BW17: =BW16+1 -> 11 | BX17: Leg1:Float | BY17: 1000000 | BZ17: START_AND_END | CA17: PAY | CB17: USD3ML | CC17: USDOIS | CD17: USD | CE17: 1 | CG17: NATURAL | CH17: NATURAL | CI17: =SETTINGS!$F$6 -> 0.0129556 | CK17: =$E17 -> 285.35446 | CL17: =_xll.meLWOBondLastCouponDate('USD-BONDS'!D15,Settings.COB) -> 43916 | CM17: ='USD-BONDS'!L15 -> 45742 | CN17: QUARTERLY | CO17: ACT/360 | CP17: NO_CHANGE | CQ17: NYB | CR17: NO_CHANGE | CS17: NYB | CT17: NO_CHANGE | CU17: NYB | CX17: NORMAL | CY17: 0D | DA17: 0D | DB17: ShortStart | DC17: =DC16+1 -> 11 | DD17: Leg2:Float | DE17: =BY17/$CD$4 -> 1333333.3 | DF17: START_AND_END | DG17: REC | DH17: AUD3ML | DI17: AUDDF_USDCSA | DJ17: AUD | DK17: 1 | DM17: NATURAL | DN17: NATURAL | DO17: =SETTINGS!$I$6 -> 0.0171 | DQ17: 0 | DR17: =_xll.meLWOBondLastCouponDate('AUD-BONDS'!D15,Settings.COB) -> 44027 | DS17: ='AUD-BONDS'!L15 -> 46037 | DT17: QUARTERLY | DU17: ACT/365 | DV17: NO_CHANGE | DW17: SYB | DX17: NO_CHANGE | DY17: SYB | DZ17: NO_CHANGE | EA17: SYB | ED17: NORMAL | EE17: 0D | EG17: 0D | EH17: ShortStart | EI17: =EI16+1 -> 10 | EJ17: ='AUD-BONDS'!F15 -> ISIN9 | EK17: =_xll.meLWOSwapCreate($EK$7&"_"&EJ17,_xll.meUtilityLVBFromKeysAndMultipleValues($ET$7:$FX$7,ET17:FX17,FZ17:HD17)) -> #Error: Missing key 'CALCULATIONTYPE'. This key is mandatory and must be included in the Label Value Block , 'scheduleLVB'. | EL17: =_xll.meLWOAssetSwapSpreadToCleanPrice($EK17,$EK$4,$BV17,$EW$4) -> #Error: Swap #ERROR does not exist | EM17: =EM16+1 -> 10 | EN17: =_xll.meLWOBondYield('AUD-BONDS'!D15,$EK$4,$EL17) -> #Error: Invalid input, numerical input required | EO17: =_xll.meLWOBondCleanPrice('AUD-BONDS'!$D15,$EK$4,$EN17) -> #Error: Invalid Vector Data: Input Contains Errors | EP17: =_xll.meLWOBondDirtyPrice('AUD-BONDS'!$D15,$EK$4,$EN17) -> #Error: Invalid Vector Data: Input Contains Errors | EQ17: =_xll.meLWOBondAccruedInterest('AUD-BONDS'!$D15,'AUD-URIDASHI-PX'!$EK$4) -> 4250 | ER17: =_xll.meLWOBondAccruedInterestDays('AUD-BONDS'!$D15,'AUD-URIDASHI-PX'!$EK$4) -> 39 | ES17: =ES16+1 -> 10 | ET17: Leg1:FixedBond | EU17: =$DE17 -> 1333333.3 | EV17: NONE | EW17: PAY | EY17: AUDOIS | EZ17: AUD | FA17: 1 | FB17: ='AUD-BONDS'!M15 -> 0.0392 | FH17: =_xll.meLWOBondLastCouponDate('AUD-BONDS'!D15,Settings.COB) -> 44027 | FI17: ='AUD-BONDS'!L15 -> 46037 | FJ17: ='AUD-BONDS'!O15 -> SEMI-ANNUAL | FK17: ='AUD-BONDS'!N15 -> 30E/360 | FL17: NO_CHANGE | FM17: NYB | FN17: NO_CHANGE | FO17: NYB | FP17: NO_CHANGE | FQ17: NYB | FT17: NORMAL | FW17: 0D | FX17: ShortStart | FY17: =FY16+1 -> 10 | FZ17: Leg2:Float | GA17: =$DE17 -> 1333333.3 | GB17: NONE | GC17: REC | GD17: AUD3ML | GE17: AUDOIS | GF17: AUD | GG17: 1 | GI17: NATURAL | GJ17: NATURAL | GK17: =SETTINGS!$I$6 -> 0.0171 | GM17: =$BV17 -> 260.66732 | GN17: =_xll.meLWOBondLastCouponDate('AUD-BONDS'!D15,Settings.COB) -> 44027 | GO17: ='AUD-BONDS'!L15 -> 46037 | GP17: QUARTERLY | GQ17: ACT/360 | GR17: NO_CHANGE | GS17: SYB | GT17: NO_CHANGE | GU17: SYB | GV17: NO_CHANGE | GW17: SYB | GZ17: NORMAL | HA17: 0D | HC17: 0D | HD17: ShortStart | HF17: #Error: No range or empty range specified | HG17: #Error: No range or empty range specified | HH17: #Error: No range or empty range specified | HI17: #Error: No range or empty range specified | HJ17: #Error: No range or empty range specified | HK17: #Error: No range or empty range specified | HL17: #Error: No range or empty range specified | HM17: #Error: No range or empty range specified | HN17: #Error: No range or empty range specified | HO17: #Error: No range or empty range specified | HP17: #Error: No range or empty range specified | HQ17: #Error: No range or empty range specified
A18: =A17+1 -> 11 | B18: ='USD-BONDS'!F16 -> ISIN10 | C18: ='USD-BONDS'!B16 -> 100 | D18: =_xll.meLWOSwapCreate($D$7&"_"&B18,_xll.meUtilityLVBFromKeysAndMultipleValues($G$7:$AL$7,G18:AL18,AN18:BS18)) -> USD_ASW_ISIN10@161:6 | E18: =_xll.meLWOAssetSwapSpread(D18,'USD-BONDS'!D16,C18,$J$4:$K$5) -> 285.35446 | F18: =F17+1 -> 11 | G18: Leg1:FixedBond | H18: 1000000 | I18: NONE | J18: PAY | L18: USDOIS | M18: USD | N18: 1 | O18: ='USD-BONDS'!M16 -> 0.032 | U18: =_xll.meLWOBondLastCouponDate('USD-BONDS'!D16,Settings.COB) -> 43916 | V18: ='USD-BONDS'!L16 -> 45742 | W18: ='USD-BONDS'!O16 -> SEMI-ANNUAL | X18: ='USD-BONDS'!N16 -> 30E/360 | Y18: NO_CHANGE | Z18: NYB | AA18: NO_CHANGE | AB18: NYB | AC18: NO_CHANGE | AD18: NYB | AG18: NORMAL | AJ18: 0D | AK18: TYPE1 | AL18: ShortStart | AM18: =AM17+1 -> 11 | AN18: Leg2:Float | AO18: 1000000 | AP18: NONE | AQ18: REC | AR18: USD3ML | AS18: USDOIS | AT18: USD | AU18: 1 | AW18: NATURAL | AX18: NATURAL | AY18: =SETTINGS!$F$6 -> 0.0129556 | BA18: 0 | BB18: =_xll.meLWOBondLastCouponDate('USD-BONDS'!D16,Settings.COB) -> 43916 | BC18: ='USD-BONDS'!L16 -> 45742 | BD18: QUARTERLY | BE18: ACT/360 | BF18: NO_CHANGE | BG18: NYB | BH18: NO_CHANGE | BI18: NYB | BJ18: NO_CHANGE | BK18: NYB | BN18: NORMAL | BO18: 0D | BQ18: 0D | BS18: ShortStart | BT18: =BT17+1 -> 11 | BU18: =_xll.meLWOXccySwapCreate($BU$7&"_"&B18,_xll.meUtilityLVBFromKeysAndMultipleValues($BX$7:$DB$7,BX18:DB18,DD18:EH18),$CC$2:$CD$5) -> XCCY_SWAP_ISIN10@187:6 | BV18: =_xll.meLWOXccySwapParSpread(BU18,$BZ$2:$CA$6,,$BZ$3) -> 260.66732 | BW18: =BW17+1 -> 12 | BX18: Leg1:Float | BY18: 1000000 | BZ18: START_AND_END | CA18: PAY | CB18: USD3ML | CC18: USDOIS | CD18: USD | CE18: 1 | CG18: NATURAL | CH18: NATURAL | CI18: =SETTINGS!$F$6 -> 0.0129556 | CK18: =$E18 -> 285.35446 | CL18: =_xll.meLWOBondLastCouponDate('USD-BONDS'!D16,Settings.COB) -> 43916 | CM18: ='USD-BONDS'!L16 -> 45742 | CN18: QUARTERLY | CO18: ACT/360 | CP18: NO_CHANGE | CQ18: NYB | CR18: NO_CHANGE | CS18: NYB | CT18: NO_CHANGE | CU18: NYB | CX18: NORMAL | CY18: 0D | DA18: 0D | DB18: ShortStart | DC18: =DC17+1 -> 12 | DD18: Leg2:Float | DE18: =BY18/$CD$4 -> 1333333.3 | DF18: START_AND_END | DG18: REC | DH18: AUD3ML | DI18: AUDDF_USDCSA | DJ18: AUD | DK18: 1 | DM18: NATURAL | DN18: NATURAL | DO18: =SETTINGS!$I$6 -> 0.0171 | DQ18: 0 | DR18: =_xll.meLWOBondLastCouponDate('AUD-BONDS'!D16,Settings.COB) -> 44027 | DS18: ='AUD-BONDS'!L16 -> 46037 | DT18: QUARTERLY | DU18: ACT/365 | DV18: NO_CHANGE | DW18: SYB | DX18: NO_CHANGE | DY18: SYB | DZ18: NO_CHANGE | EA18: SYB | ED18: NORMAL | EE18: 0D | EG18: 0D | EH18: ShortStart | EI18: =EI17+1 -> 11 | EJ18: ='AUD-BONDS'!F16 -> ISIN10 | EK18: =_xll.meLWOSwapCreate($EK$7&"_"&EJ18,_xll.meUtilityLVBFromKeysAndMultipleValues($ET$7:$FX$7,ET18:FX18,FZ18:HD18)) -> #Error: Missing key 'CALCULATIONTYPE'. This key is mandatory and must be included in the Label Value Block , 'scheduleLVB'. | EL18: =_xll.meLWOAssetSwapSpreadToCleanPrice($EK18,$EK$4,$BV18,$EW$4) -> #Error: Swap #ERROR does not exist | EM18: =EM17+1 -> 11 | EN18: =_xll.meLWOBondYield('AUD-BONDS'!D16,$EK$4,$EL18) -> #Error: Invalid input, numerical input required | EO18: =_xll.meLWOBondCleanPrice('AUD-BONDS'!$D16,$EK$4,$EN18) -> #Error: Invalid Vector Data: Input Contains Errors | EP18: =_xll.meLWOBondDirtyPrice('AUD-BONDS'!$D16,$EK$4,$EN18) -> #Error: Invalid Vector Data: Input Contains Errors | EQ18: =_xll.meLWOBondAccruedInterest('AUD-BONDS'!$D16,'AUD-URIDASHI-PX'!$EK$4) -> 4250 | ER18: =_xll.meLWOBondAccruedInterestDays('AUD-BONDS'!$D16,'AUD-URIDASHI-PX'!$EK$4) -> 39 | ES18: =ES17+1 -> 11 | ET18: Leg1:FixedBond | EU18: =$DE18 -> 1333333.3 | EV18: NONE | EW18: PAY | EY18: AUDOIS | EZ18: AUD | FA18: 1 | FB18: ='AUD-BONDS'!M16 -> 0.0392 | FH18: =_xll.meLWOBondLastCouponDate('AUD-BONDS'!D16,Settings.COB) -> 44027 | FI18: ='AUD-BONDS'!L16 -> 46037 | FJ18: ='AUD-BONDS'!O16 -> SEMI-ANNUAL | FK18: ='AUD-BONDS'!N16 -> 30E/360 | FL18: NO_CHANGE | FM18: NYB | FN18: NO_CHANGE | FO18: NYB | FP18: NO_CHANGE | FQ18: NYB | FT18: NORMAL | FW18: 0D | FX18: ShortStart | FY18: =FY17+1 -> 11 | FZ18: Leg2:Float | GA18: =$DE18 -> 1333333.3 | GB18: NONE | GC18: REC | GD18: AUD3ML | GE18: AUDOIS | GF18: AUD | GG18: 1 | GI18: NATURAL | GJ18: NATURAL | GK18: =SETTINGS!$I$6 -> 0.0171 | GM18: =$BV18 -> 260.66732 | GN18: =_xll.meLWOBondLastCouponDate('AUD-BONDS'!D16,Settings.COB) -> 44027 | GO18: ='AUD-BONDS'!L16 -> 46037 | GP18: QUARTERLY | GQ18: ACT/360 | GR18: NO_CHANGE | GS18: SYB | GT18: NO_CHANGE | GU18: SYB | GV18: NO_CHANGE | GW18: SYB | GZ18: NORMAL | HA18: 0D | HC18: 0D | HD18: ShortStart | HF18: #Error: No range or empty range specified | HG18: #Error: No range or empty range specified | HH18: #Error: No range or empty range specified | HI18: #Error: No range or empty range specified | HJ18: #Error: No range or empty range specified | HK18: #Error: No range or empty range specified | HL18: #Error: No range or empty range specified | HM18: #Error: No range or empty range specified | HN18: #Error: No range or empty range specified | HO18: #Error: No range or empty range specified | HP18: #Error: No range or empty range specified | HQ18: #Error: No range or empty range specified
A19: =A18+1 -> 12 | B19: ='USD-BONDS'!F17 -> ISIN11 | C19: ='USD-BONDS'!B17 -> 100 | D19: =_xll.meLWOSwapCreate($D$7&"_"&B19,_xll.meUtilityLVBFromKeysAndMultipleValues($G$7:$AL$7,G19:AL19,AN19:BS19)) -> USD_ASW_ISIN11@170:6 | E19: =_xll.meLWOAssetSwapSpread(D19,'USD-BONDS'!D17,C19,$J$4:$K$5) -> 285.35446 | F19: =F18+1 -> 12 | G19: Leg1:FixedBond | H19: 1000000 | I19: NONE | J19: PAY | L19: USDOIS | M19: USD | N19: 1 | O19: ='USD-BONDS'!M17 -> 0.032 | U19: =_xll.meLWOBondLastCouponDate('USD-BONDS'!D17,Settings.COB) -> 43916 | V19: ='USD-BONDS'!L17 -> 45742 | W19: ='USD-BONDS'!O17 -> SEMI-ANNUAL | X19: ='USD-BONDS'!N17 -> 30E/360 | Y19: NO_CHANGE | Z19: NYB | AA19: NO_CHANGE | AB19: NYB | AC19: NO_CHANGE | AD19: NYB | AG19: NORMAL | AJ19: 0D | AK19: TYPE1 | AL19: ShortStart | AM19: =AM18+1 -> 12 | AN19: Leg2:Float | AO19: 1000000 | AP19: NONE | AQ19: REC | AR19: USD3ML | AS19: USDOIS | AT19: USD | AU19: 1 | AW19: NATURAL | AX19: NATURAL | AY19: =SETTINGS!$F$6 -> 0.0129556 | BA19: 0 | BB19: =_xll.meLWOBondLastCouponDate('USD-BONDS'!D17,Settings.COB) -> 43916 | BC19: ='USD-BONDS'!L17 -> 45742 | BD19: QUARTERLY | BE19: ACT/360 | BF19: NO_CHANGE | BG19: NYB | BH19: NO_CHANGE | BI19: NYB | BJ19: NO_CHANGE | BK19: NYB | BN19: NORMAL | BO19: 0D | BQ19: 0D | BS19: ShortStart | BT19: =BT18+1 -> 12 | BU19: =_xll.meLWOXccySwapCreate($BU$7&"_"&B19,_xll.meUtilityLVBFromKeysAndMultipleValues($BX$7:$DB$7,BX19:DB19,DD19:EH19),$CC$2:$CD$5) -> XCCY_SWAP_ISIN11@179:6 | BV19: =_xll.meLWOXccySwapParSpread(BU19,$BZ$2:$CA$6,,$BZ$3) -> 260.66732 | BW19: =BW18+1 -> 13 | BX19: Leg1:Float | BY19: 1000000 | BZ19: START_AND_END | CA19: PAY | CB19: USD3ML | CC19: USDOIS | CD19: USD | CE19: 1 | CG19: NATURAL | CH19: NATURAL | CI19: =SETTINGS!$F$6 -> 0.0129556 | CK19: =$E19 -> 285.35446 | CL19: =_xll.meLWOBondLastCouponDate('USD-BONDS'!D17,Settings.COB) -> 43916 | CM19: ='USD-BONDS'!L17 -> 45742 | CN19: QUARTERLY | CO19: ACT/360 | CP19: NO_CHANGE | CQ19: NYB | CR19: NO_CHANGE | CS19: NYB | CT19: NO_CHANGE | CU19: NYB | CX19: NORMAL | CY19: 0D | DA19: 0D | DB19: ShortStart | DC19: =DC18+1 -> 13 | DD19: Leg2:Float | DE19: =BY19/$CD$4 -> 1333333.3 | DF19: START_AND_END | DG19: REC | DH19: AUD3ML | DI19: AUDDF_USDCSA | DJ19: AUD | DK19: 1 | DM19: NATURAL | DN19: NATURAL | DO19: =SETTINGS!$I$6 -> 0.0171 | DQ19: 0 | DR19: =_xll.meLWOBondLastCouponDate('AUD-BONDS'!D17,Settings.COB) -> 44027 | DS19: ='AUD-BONDS'!L17 -> 46037 | DT19: QUARTERLY | DU19: ACT/365 | DV19: NO_CHANGE | DW19: SYB | DX19: NO_CHANGE | DY19: SYB | DZ19: NO_CHANGE | EA19: SYB | ED19: NORMAL | EE19: 0D | EG19: 0D | EH19: ShortStart | EI19: =EI18+1 -> 12 | EJ19: ='AUD-BONDS'!F17 -> ISIN11 | EK19: =_xll.meLWOSwapCreate($EK$7&"_"&EJ19,_xll.meUtilityLVBFromKeysAndMultipleValues($ET$7:$FX$7,ET19:FX19,FZ19:HD19)) -> #Error: Missing key 'CALCULATIONTYPE'. This key is mandatory and must be included in the Label Value Block , 'scheduleLVB'. | EL19: =_xll.meLWOAssetSwapSpreadToCleanPrice($EK19,$EK$4,$BV19,$EW$4) -> #Error: Swap #ERROR does not exist | EM19: =EM18+1 -> 12 | EN19: =_xll.meLWOBondYield('AUD-BONDS'!D17,$EK$4,$EL19) -> #Error: Invalid input, numerical input required | EO19: =_xll.meLWOBondCleanPrice('AUD-BONDS'!$D17,$EK$4,$EN19) -> #Error: Invalid Vector Data: Input Contains Errors | EP19: =_xll.meLWOBondDirtyPrice('AUD-BONDS'!$D17,$EK$4,$EN19) -> #Error: Invalid Vector Data: Input Contains Errors | EQ19: =_xll.meLWOBondAccruedInterest('AUD-BONDS'!$D17,'AUD-URIDASHI-PX'!$EK$4) -> 4250 | ER19: =_xll.meLWOBondAccruedInterestDays('AUD-BONDS'!$D17,'AUD-URIDASHI-PX'!$EK$4) -> 39 | ES19: =ES18+1 -> 12 | ET19: Leg1:FixedBond | EU19: =$DE19 -> 1333333.3 | EV19: NONE | EW19: PAY | EY19: AUDOIS | EZ19: AUD | FA19: 1 | FB19: ='AUD-BONDS'!M17 -> 0.0392 | FH19: =_xll.meLWOBondLastCouponDate('AUD-BONDS'!D17,Settings.COB) -> 44027 | FI19: ='AUD-BONDS'!L17 -> 46037 | FJ19: ='AUD-BONDS'!O17 -> SEMI-ANNUAL | FK19: ='AUD-BONDS'!N17 -> 30E/360 | FL19: NO_CHANGE | FM19: NYB | FN19: NO_CHANGE | FO19: NYB | FP19: NO_CHANGE | FQ19: NYB | FT19: NORMAL | FW19: 0D | FX19: ShortStart | FY19: =FY18+1 -> 12 | FZ19: Leg2:Float | GA19: =$DE19 -> 1333333.3 | GB19: NONE | GC19: REC | GD19: AUD3ML | GE19: AUDOIS | GF19: AUD | GG19: 1 | GI19: NATURAL | GJ19: NATURAL | GK19: =SETTINGS!$I$6 -> 0.0171 | GM19: =$BV19 -> 260.66732 | GN19: =_xll.meLWOBondLastCouponDate('AUD-BONDS'!D17,Settings.COB) -> 44027 | GO19: ='AUD-BONDS'!L17 -> 46037 | GP19: QUARTERLY | GQ19: ACT/360 | GR19: NO_CHANGE | GS19: SYB | GT19: NO_CHANGE | GU19: SYB | GV19: NO_CHANGE | GW19: SYB | GZ19: NORMAL | HA19: 0D | HC19: 0D | HD19: ShortStart | HF19: #Error: No range or empty range specified | HG19: #Error: No range or empty range specified | HH19: #Error: No range or empty range specified | HI19: #Error: No range or empty range specified | HJ19: #Error: No range or empty range specified | HK19: #Error: No range or empty range specified | HL19: #Error: No range or empty range specified | HM19: #Error: No range or empty range specified | HN19: #Error: No range or empty range specified | HO19: #Error: No range or empty range specified | HP19: #Error: No range or empty range specified | HQ19: #Error: No range or empty range specified
A20: =A19+1 -> 13 | B20: ='USD-BONDS'!F18 -> ISIN12 | C20: ='USD-BONDS'!B18 -> 100 | D20: =_xll.meLWOSwapCreate($D$7&"_"&B20,_xll.meUtilityLVBFromKeysAndMultipleValues($G$7:$AL$7,G20:AL20,AN20:BS20)) -> USD_ASW_ISIN12@164:6 | E20: =_xll.meLWOAssetSwapSpread(D20,'USD-BONDS'!D18,C20,$J$4:$K$5) -> 285.35446 | F20: =F19+1 -> 13 | G20: Leg1:FixedBond | H20: 1000000 | I20: NONE | J20: PAY | L20: USDOIS | M20: USD | N20: 1 | O20: ='USD-BONDS'!M18 -> 0.032 | U20: =_xll.meLWOBondLastCouponDate('USD-BONDS'!D18,Settings.COB) -> 43916 | V20: ='USD-BONDS'!L18 -> 45742 | W20: ='USD-BONDS'!O18 -> SEMI-ANNUAL | X20: ='USD-BONDS'!N18 -> 30E/360 | Y20: NO_CHANGE | Z20: NYB | AA20: NO_CHANGE | AB20: NYB | AC20: NO_CHANGE | AD20: NYB | AG20: NORMAL | AJ20: 0D | AK20: TYPE1 | AL20: ShortStart | AM20: =AM19+1 -> 13 | AN20: Leg2:Float | AO20: 1000000 | AP20: NONE | AQ20: REC | AR20: USD3ML | AS20: USDOIS | AT20: USD | AU20: 1 | AW20: NATURAL | AX20: NATURAL | AY20: =SETTINGS!$F$6 -> 0.0129556 | BA20: 0 | BB20: =_xll.meLWOBondLastCouponDate('USD-BONDS'!D18,Settings.COB) -> 43916 | BC20: ='USD-BONDS'!L18 -> 45742 | BD20: QUARTERLY | BE20: ACT/360 | BF20: NO_CHANGE | BG20: NYB | BH20: NO_CHANGE | BI20: NYB | BJ20: NO_CHANGE | BK20: NYB | BN20: NORMAL | BO20: 0D | BQ20: 0D | BS20: ShortStart | BT20: =BT19+1 -> 13 | BU20: =_xll.meLWOXccySwapCreate($BU$7&"_"&B20,_xll.meUtilityLVBFromKeysAndMultipleValues($BX$7:$DB$7,BX20:DB20,DD20:EH20),$CC$2:$CD$5) -> XCCY_SWAP_ISIN12@192:6 | BV20: =_xll.meLWOXccySwapParSpread(BU20,$BZ$2:$CA$6,,$BZ$3) -> 260.66732 | BW20: =BW19+1 -> 14 | BX20: Leg1:Float | BY20: 1000000 | BZ20: START_AND_END | CA20: PAY | CB20: USD3ML | CC20: USDOIS | CD20: USD | CE20: 1 | CG20: NATURAL | CH20: NATURAL | CI20: =SETTINGS!$F$6 -> 0.0129556 | CK20: =$E20 -> 285.35446 | CL20: =_xll.meLWOBondLastCouponDate('USD-BONDS'!D18,Settings.COB) -> 43916 | CM20: ='USD-BONDS'!L18 -> 45742 | CN20: QUARTERLY | CO20: ACT/360 | CP20: NO_CHANGE | CQ20: NYB | CR20: NO_CHANGE | CS20: NYB | CT20: NO_CHANGE | CU20: NYB | CX20: NORMAL | CY20: 0D | DA20: 0D | DB20: ShortStart | DC20: =DC19+1 -> 14 | DD20: Leg2:Float | DE20: =BY20/$CD$4 -> 1333333.3 | DF20: START_AND_END | DG20: REC | DH20: AUD3ML | DI20: AUDDF_USDCSA | DJ20: AUD | DK20: 1 | DM20: NATURAL | DN20: NATURAL | DO20: =SETTINGS!$I$6 -> 0.0171 | DQ20: 0 | DR20: =_xll.meLWOBondLastCouponDate('AUD-BONDS'!D18,Settings.COB) -> 44027 | DS20: ='AUD-BONDS'!L18 -> 46037 | DT20: QUARTERLY | DU20: ACT/365 | DV20: NO_CHANGE | DW20: SYB | DX20: NO_CHANGE | DY20: SYB | DZ20: NO_CHANGE | EA20: SYB | ED20: NORMAL | EE20: 0D | EG20: 0D | EH20: ShortStart | EI20: =EI19+1 -> 13 | EJ20: ='AUD-BONDS'!F18 -> ISIN12 | EK20: =_xll.meLWOSwapCreate($EK$7&"_"&EJ20,_xll.meUtilityLVBFromKeysAndMultipleValues($ET$7:$FX$7,ET20:FX20,FZ20:HD20)) -> #Error: Missing key 'CALCULATIONTYPE'. This key is mandatory and must be included in the Label Value Block , 'scheduleLVB'. | EL20: =_xll.meLWOAssetSwapSpreadToCleanPrice($EK20,$EK$4,$BV20,$EW$4) -> #Error: Swap #ERROR does not exist | EM20: =EM19+1 -> 13 | EN20: =_xll.meLWOBondYield('AUD-BONDS'!D18,$EK$4,$EL20) -> #Error: Invalid input, numerical input required | EO20: =_xll.meLWOBondCleanPrice('AUD-BONDS'!$D18,$EK$4,$EN20) -> #Error: Invalid Vector Data: Input Contains Errors | EP20: =_xll.meLWOBondDirtyPrice('AUD-BONDS'!$D18,$EK$4,$EN20) -> #Error: Invalid Vector Data: Input Contains Errors | EQ20: =_xll.meLWOBondAccruedInterest('AUD-BONDS'!$D18,'AUD-URIDASHI-PX'!$EK$4) -> 4250 | ER20: =_xll.meLWOBondAccruedInterestDays('AUD-BONDS'!$D18,'AUD-URIDASHI-PX'!$EK$4) -> 39 | ES20: =ES19+1 -> 13 | ET20: Leg1:FixedBond | EU20: =$DE20 -> 1333333.3 | EV20: NONE | EW20: PAY | EY20: AUDOIS | EZ20: AUD | FA20: 1 | FB20: ='AUD-BONDS'!M18 -> 0.0392 | FH20: =_xll.meLWOBondLastCouponDate('AUD-BONDS'!D18,Settings.COB) -> 44027 | FI20: ='AUD-BONDS'!L18 -> 46037 | FJ20: ='AUD-BONDS'!O18 -> SEMI-ANNUAL | FK20: ='AUD-BONDS'!N18 -> 30E/360 | FL20: NO_CHANGE | FM20: NYB | FN20: NO_CHANGE | FO20: NYB | FP20: NO_CHANGE | FQ20: NYB | FT20: NORMAL | FW20: 0D | FX20: ShortStart | FY20: =FY19+1 -> 13 | FZ20: Leg2:Float | GA20: =$DE20 -> 1333333.3 | GB20: NONE | GC20: REC | GD20: AUD3ML | GE20: AUDOIS | GF20: AUD | GG20: 1 | GI20: NATURAL | GJ20: NATURAL | GK20: =SETTINGS!$I$6 -> 0.0171 | GM20: =$BV20 -> 260.66732 | GN20: =_xll.meLWOBondLastCouponDate('AUD-BONDS'!D18,Settings.COB) -> 44027 | GO20: ='AUD-BONDS'!L18 -> 46037 | GP20: QUARTERLY | GQ20: ACT/360 | GR20: NO_CHANGE | GS20: SYB | GT20: NO_CHANGE | GU20: SYB | GV20: NO_CHANGE | GW20: SYB | GZ20: NORMAL | HA20: 0D | HC20: 0D | HD20: ShortStart | HF20: #Error: No range or empty range specified | HG20: #Error: No range or empty range specified | HH20: #Error: No range or empty range specified | HI20: #Error: No range or empty range specified | HJ20: #Error: No range or empty range specified | HK20: #Error: No range or empty range specified | HL20: #Error: No range or empty range specified | HM20: #Error: No range or empty range specified | HN20: #Error: No range or empty range specified | HO20: #Error: No range or empty range specified | HP20: #Error: No range or empty range specified | HQ20: #Error: No range or empty range specified
... A33: =A32+1 -> 26 | B33: ='USD-BONDS'!F31 -> ISIN25 | C33: ='USD-BONDS'!B31 -> 100 | D33: =_xll.meLWOSwapCreate($D$7&"_"&B33,_xll.meUtilityLVBFromKeysAndMultipleValues($G$7:$AL$7,G33:AL33,AN33:BS33)) -> USD_ASW_ISIN25@167:6 | E33: =_xll.meLWOAssetSwapSpread(D33,'USD-BONDS'!D31,C33,$J$4:$K$5) -> 285.35446 | F33: =F32+1 -> 26 | G33: Leg1:FixedBond | H33: 1000000 | I33: NONE | J33: PAY | L33: USDOIS | M33: USD | N33: 1 | O33: ='USD-BONDS'!M31 -> 0.032 | U33: =_xll.meLWOBondLastCouponDate('USD-BONDS'!D31,Settings.COB) -> 43916 | V33: ='USD-BONDS'!L31 -> 45742 | W33: ='USD-BONDS'!O31 -> SEMI-ANNUAL | X33: ='USD-BONDS'!N31 -> 30E/360 | Y33: NO_CHANGE | Z33: NYB | AA33: NO_CHANGE | AB33: NYB | AC33: NO_CHANGE | AD33: NYB | AG33: NORMAL | AJ33: 0D | AK33: TYPE1 | AL33: ShortStart | AM33: =AM32+1 -> 26 | AN33: Leg2:Float | AO33: 1000000 | AP33: NONE | AQ33: REC | AR33: USD3ML | AS33: USDOIS | AT33: USD | AU33: 1 | AW33: NATURAL | AX33: NATURAL | AY33: =SETTINGS!$F$6 -> 0.0129556 | BA33: 0 | BB33: =_xll.meLWOBondLastCouponDate('USD-BONDS'!D31,Settings.COB) -> 43916 | BC33: ='USD-BONDS'!L31 -> 45742 | BD33: QUARTERLY | BE33: ACT/360 | BF33: NO_CHANGE | BG33: NYB | BH33: NO_CHANGE | BI33: NYB | BJ33: NO_CHANGE | BK33: NYB | BN33: NORMAL | BO33: 0D | BQ33: 0D | BS33: ShortStart | BT33: =BT32+1 -> 26 | BU33: =_xll.meLWOXccySwapCreate($BU$7&"_"&B33,_xll.meUtilityLVBFromKeysAndMultipleValues($BX$7:$DB$7,BX33:DB33,DD33:EH33),$CC$2:$CD$5) -> XCCY_SWAP_ISIN25@202:6 | BV33: =_xll.meLWOXccySwapParSpread(BU33,$BZ$2:$CA$6,,$BZ$3) -> 260.66732 | BW33: =BW32+1 -> 27 | BX33: Leg1:Float | BY33: 1000000 | BZ33: START_AND_END | CA33: PAY | CB33: USD3ML | CC33: USDOIS | CD33: USD | CE33: 1 | CG33: NATURAL | CH33: NATURAL | CI33: =SETTINGS!$F$6 -> 0.0129556 | CK33: =$E33 -> 285.35446 | CL33: =_xll.meLWOBondLastCouponDate('USD-BONDS'!D31,Settings.COB) -> 43916 | CM33: ='USD-BONDS'!L31 -> 45742 | CN33: QUARTERLY | CO33: ACT/360 | CP33: NO_CHANGE | CQ33: NYB | CR33: NO_CHANGE | CS33: NYB | CT33: NO_CHANGE | CU33: NYB | CX33: NORMAL | CY33: 0D | DA33: 0D | DB33: ShortStart | DC33: =DC32+1 -> 27 | DD33: Leg2:Float | DE33: =BY33/$CD$4 -> 1333333.3 | DF33: START_AND_END | DG33: REC | DH33: AUD3ML | DI33: AUDDF_USDCSA | DJ33: AUD | DK33: 1 | DM33: NATURAL | DN33: NATURAL | DO33: =SETTINGS!$I$6 -> 0.0171 | DQ33: 0 | DR33: =_xll.meLWOBondLastCouponDate('AUD-BONDS'!D31,Settings.COB) -> 44027 | DS33: ='AUD-BONDS'!L31 -> 46037 | DT33: QUARTERLY | DU33: ACT/365 | DV33: NO_CHANGE | DW33: SYB | DX33: NO_CHANGE | DY33: SYB | DZ33: NO_CHANGE | EA33: SYB | ED33: NORMAL | EE33: 0D | EG33: 0D | EH33: ShortStart | EI33: =EI32+1 -> 26 | EJ33: ='AUD-BONDS'!F31 -> ISIN25 | EK33: =_xll.meLWOSwapCreate($EK$7&"_"&EJ33,_xll.meUtilityLVBFromKeysAndMultipleValues($ET$7:$FX$7,ET33:FX33,FZ33:HD33)) -> #Error: Missing key 'CALCULATIONTYPE'. This key is mandatory and must be included in the Label Value Block , 'scheduleLVB'. | EL33: =_xll.meLWOAssetSwapSpreadToCleanPrice($EK33,$EK$4,$BV33,$EW$4) -> #Error: Swap #ERROR does not exist | EM33: =EM32+1 -> 26 | EN33: =_xll.meLWOBondYield('AUD-BONDS'!D31,$EK$4,$EL33) -> #Error: Invalid input, numerical input required | EO33: =_xll.meLWOBondCleanPrice('AUD-BONDS'!$D31,$EK$4,$EN33) -> #Error: Invalid Vector Data: Input Contains Errors | EP33: =_xll.meLWOBondDirtyPrice('AUD-BONDS'!$D31,$EK$4,$EN33) -> #Error: Invalid Vector Data: Input Contains Errors | EQ33: =_xll.meLWOBondAccruedInterest('AUD-BONDS'!$D31,'AUD-URIDASHI-PX'!$EK$4) -> 4250 | ER33: =_xll.meLWOBondAccruedInterestDays('AUD-BONDS'!$D31,'AUD-URIDASHI-PX'!$EK$4) -> 39 | ES33: =ES32+1 -> 26 | ET33: Leg1:FixedBond | EU33: =$DE33 -> 1333333.3 | EV33: NONE | EW33: PAY | EY33: AUDOIS | EZ33: AUD | FA33: 1 | FB33: ='AUD-BONDS'!M31 -> 0.0392 | FH33: =_xll.meLWOBondLastCouponDate('AUD-BONDS'!D31,Settings.COB) -> 44027 | FI33: ='AUD-BONDS'!L31 -> 46037 | FJ33: ='AUD-BONDS'!O31 -> SEMI-ANNUAL | FK33: ='AUD-BONDS'!N31 -> 30E/360 | FL33: NO_CHANGE | FM33: NYB | FN33: NO_CHANGE | FO33: NYB | FP33: NO_CHANGE | FQ33: NYB | FT33: NORMAL | FW33: 0D | FX33: ShortStart | FY33: =FY32+1 -> 26 | FZ33: Leg2:Float | GA33: =$DE33 -> 1333333.3 | GB33: NONE | GC33: REC | GD33: AUD3ML | GE33: AUDOIS | GF33: AUD | GG33: 1 | GI33: NATURAL | GJ33: NATURAL | GK33: =SETTINGS!$I$6 -> 0.0171 | GM33: =$BV33 -> 260.66732 | GN33: =_xll.meLWOBondLastCouponDate('AUD-BONDS'!D31,Settings.COB) -> 44027 | GO33: ='AUD-BONDS'!L31 -> 46037 | GP33: QUARTERLY | GQ33: ACT/360 | GR33: NO_CHANGE | GS33: SYB | GT33: NO_CHANGE | GU33: SYB | GV33: NO_CHANGE | GW33: SYB | GZ33: NORMAL | HA33: 0D | HC33: 0D | HD33: ShortStart | HF33: #Error: No range or empty range specified | HG33: #Error: No range or empty range specified | HH33: #Error: No range or empty range specified | HI33: #Error: No range or empty range specified | HJ33: #Error: No range or empty range specified | HK33: #Error: No range or empty range specified | HL33: #Error: No range or empty range specified | HM33: #Error: No range or empty range specified | HN33: #Error: No range or empty range specified | HO33: #Error: No range or empty range specified | HP33: #Error: No range or empty range specified | HQ33: #Error: No range or empty range specified
A34: =A33+1 -> 27 | B34: ='USD-BONDS'!F32 -> ISIN26 | C34: ='USD-BONDS'!B32 -> 100 | D34: =_xll.meLWOSwapCreate($D$7&"_"&B34,_xll.meUtilityLVBFromKeysAndMultipleValues($G$7:$AL$7,G34:AL34,AN34:BS34)) -> USD_ASW_ISIN26@156:6 | E34: =_xll.meLWOAssetSwapSpread(D34,'USD-BONDS'!D32,C34,$J$4:$K$5) -> 285.35446 | F34: =F33+1 -> 27 | G34: Leg1:FixedBond | H34: 1000000 | I34: NONE | J34: PAY | L34: USDOIS | M34: USD | N34: 1 | O34: ='USD-BONDS'!M32 -> 0.032 | U34: =_xll.meLWOBondLastCouponDate('USD-BONDS'!D32,Settings.COB) -> 43916 | V34: ='USD-BONDS'!L32 -> 45742 | W34: ='USD-BONDS'!O32 -> SEMI-ANNUAL | X34: ='USD-BONDS'!N32 -> 30E/360 | Y34: NO_CHANGE | Z34: NYB | AA34: NO_CHANGE | AB34: NYB | AC34: NO_CHANGE | AD34: NYB | AG34: NORMAL | AJ34: 0D | AK34: TYPE1 | AL34: ShortStart | AM34: =AM33+1 -> 27 | AN34: Leg2:Float | AO34: 1000000 | AP34: NONE | AQ34: REC | AR34: USD3ML | AS34: USDOIS | AT34: USD | AU34: 1 | AW34: NATURAL | AX34: NATURAL | AY34: =SETTINGS!$F$6 -> 0.0129556 | BA34: 0 | BB34: =_xll.meLWOBondLastCouponDate('USD-BONDS'!D32,Settings.COB) -> 43916 | BC34: ='USD-BONDS'!L32 -> 45742 | BD34: QUARTERLY | BE34: ACT/360 | BF34: NO_CHANGE | BG34: NYB | BH34: NO_CHANGE | BI34: NYB | BJ34: NO_CHANGE | BK34: NYB | BN34: NORMAL | BO34: 0D | BQ34: 0D | BS34: ShortStart | BT34: =BT33+1 -> 27 | BU34: =_xll.meLWOXccySwapCreate($BU$7&"_"&B34,_xll.meUtilityLVBFromKeysAndMultipleValues($BX$7:$DB$7,BX34:DB34,DD34:EH34),$CC$2:$CD$5) -> XCCY_SWAP_ISIN26@178:6 | BV34: =_xll.meLWOXccySwapParSpread(BU34,$BZ$2:$CA$6,,$BZ$3) -> 260.66732 | BX34: Leg1:Float | BY34: 1000000 | BZ34: START_AND_END | CA34: PAY | CB34: USD3ML | CC34: USDOIS | CD34: USD | CE34: 1 | CG34: NATURAL | CH34: NATURAL | CI34: =SETTINGS!$F$6 -> 0.0129556 | CK34: =$E34 -> 285.35446 | CL34: =_xll.meLWOBondLastCouponDate('USD-BONDS'!D32,Settings.COB) -> 43916 | CM34: ='USD-BONDS'!L32 -> 45742 | CN34: QUARTERLY | CO34: ACT/360 | CP34: NO_CHANGE | CQ34: NYB | CR34: NO_CHANGE | CS34: NYB | CT34: NO_CHANGE | CU34: NYB | CX34: NORMAL | CY34: 0D | DA34: 0D | DB34: ShortStart | DD34: Leg2:Float | DE34: =BY34/$CD$4 -> 1333333.3 | DF34: START_AND_END | DG34: REC | DH34: AUD3ML | DI34: AUDDF_USDCSA | DJ34: AUD | DK34: 1 | DM34: NATURAL | DN34: NATURAL | DO34: =SETTINGS!$I$6 -> 0.0171 | DQ34: 0 | DR34: =_xll.meLWOBondLastCouponDate('AUD-BONDS'!D32,Settings.COB) -> 44027 | DS34: ='AUD-BONDS'!L32 -> 46037 | DT34: QUARTERLY | DU34: ACT/365 | DV34: NO_CHANGE | DW34: SYB | DX34: NO_CHANGE | DY34: SYB | DZ34: NO_CHANGE | EA34: SYB | ED34: NORMAL | EE34: 0D | EG34: 0D | EH34: ShortStart | EI34: =EI33+1 -> 27 | EJ34: ='AUD-BONDS'!F32 -> ISIN26 | EK34: =_xll.meLWOSwapCreate($EK$7&"_"&EJ34,_xll.meUtilityLVBFromKeysAndMultipleValues($ET$7:$FX$7,ET34:FX34,FZ34:HD34)) -> #Error: Missing key 'CALCULATIONTYPE'. This key is mandatory and must be included in the Label Value Block , 'scheduleLVB'. | EL34: =_xll.meLWOAssetSwapSpreadToCleanPrice($EK34,$EK$4,$BV34,$EW$4) -> #Error: Swap #ERROR does not exist | EM34: =EM33+1 -> 27 | EN34: =_xll.meLWOBondYield('AUD-BONDS'!D32,$EK$4,$EL34) -> #Error: Invalid input, numerical input required | EO34: =_xll.meLWOBondCleanPrice('AUD-BONDS'!$D32,$EK$4,$EN34) -> #Error: Invalid Vector Data: Input Contains Errors | EP34: =_xll.meLWOBondDirtyPrice('AUD-BONDS'!$D32,$EK$4,$EN34) -> #Error: Invalid Vector Data: Input Contains Errors | EQ34: =_xll.meLWOBondAccruedInterest('AUD-BONDS'!$D32,'AUD-URIDASHI-PX'!$EK$4) -> 4250 | ER34: =_xll.meLWOBondAccruedInterestDays('AUD-BONDS'!$D32,'AUD-URIDASHI-PX'!$EK$4) -> 39 | ES34: =ES33+1 -> 27 | ET34: Leg1:FixedBond | EU34: =$DE34 -> 1333333.3 | EV34: NONE | EW34: PAY | EY34: AUDOIS | EZ34: AUD | FA34: 1 | FB34: ='AUD-BONDS'!M32 -> 0.0392 | FH34: =_xll.meLWOBondLastCouponDate('AUD-BONDS'!D32,Settings.COB) -> 44027 | FI34: ='AUD-BONDS'!L32 -> 46037 | FJ34: ='AUD-BONDS'!O32 -> SEMI-ANNUAL | FK34: ='AUD-BONDS'!N32 -> 30E/360 | FL34: NO_CHANGE | FM34: NYB | FN34: NO_CHANGE | FO34: NYB | FP34: NO_CHANGE | FQ34: NYB | FT34: NORMAL | FW34: 0D | FX34: ShortStart | FY34: =FY33+1 -> 27 | FZ34: Leg2:Float | GA34: =$DE34 -> 1333333.3 | GB34: NONE | GC34: REC | GD34: AUD3ML | GE34: AUDOIS | GF34: AUD | GG34: 1 | GI34: NATURAL | GJ34: NATURAL | GK34: =SETTINGS!$I$6 -> 0.0171 | GM34: =$BV34 -> 260.66732 | GN34: =_xll.meLWOBondLastCouponDate('AUD-BONDS'!D32,Settings.COB) -> 44027 | GO34: ='AUD-BONDS'!L32 -> 46037 | GP34: QUARTERLY | GQ34: ACT/360 | GR34: NO_CHANGE | GS34: SYB | GT34: NO_CHANGE | GU34: SYB | GV34: NO_CHANGE | GW34: SYB | GZ34: NORMAL | HA34: 0D | HC34: 0D | HD34: ShortStart | HF34: #Error: No range or empty range specified | HG34: #Error: No range or empty range specified | HH34: #Error: No range or empty range specified | HI34: #Error: No range or empty range specified | HJ34: #Error: No range or empty range specified | HK34: #Error: No range or empty range specified | HL34: #Error: No range or empty range specified | HM34: #Error: No range or empty range specified | HN34: #Error: No range or empty range specified | HO34: #Error: No range or empty range specified | HP34: #Error: No range or empty range specified | HQ34: #Error: No range or empty range specified
HF35: #Error: No range or empty range specified | HG35: #Error: No range or empty range specified | HH35: #Error: No range or empty range specified | HI35: #Error: No range or empty range specified | HJ35: #Error: No range or empty range specified | HK35: #Error: No range or empty range specified | HL35: #Error: No range or empty range specified | HM35: #Error: No range or empty range specified | HN35: #Error: No range or empty range specified | HO35: #Error: No range or empty range specified | HP35: #Error: No range or empty range specified | HQ35: #Error: No range or empty range specified
HF36: #Error: No range or empty range specified | HG36: #Error: No range or empty range specified | HH36: #Error: No range or empty range specified | HI36: #Error: No range or empty range specified | HJ36: #Error: No range or empty range specified | HK36: #Error: No range or empty range specified | HL36: #Error: No range or empty range specified | HM36: #Error: No range or empty range specified | HN36: #Error: No range or empty range specified | HO36: #Error: No range or empty range specified | HP36: #Error: No range or empty range specified | HQ36: #Error: No range or empty range specified
HF37: #Error: No range or empty range specified | HG37: #Error: No range or empty range specified | HH37: #Error: No range or empty range specified | HI37: #Error: No range or empty range specified | HJ37: #Error: No range or empty range specified | HK37: #Error: No range or empty range specified | HL37: #Error: No range or empty range specified | HM37: #Error: No range or empty range specified | HN37: #Error: No range or empty range specified | HO37: #Error: No range or empty range specified | HP37: #Error: No range or empty range specified | HQ37: #Error: No range or empty range specified
HF38: #Error: No range or empty range specified | HG38: #Error: No range or empty range specified | HH38: #Error: No range or empty range specified | HI38: #Error: No range or empty range specified | HJ38: #Error: No range or empty range specified | HK38: #Error: No range or empty range specified | HL38: #Error: No range or empty range specified | HM38: #Error: No range or empty range specified | HN38: #Error: No range or empty range specified | HO38: #Error: No range or empty range specified | HP38: #Error: No range or empty range specified | HQ38: #Error: No range or empty range specified
HF39: #Error: No range or empty range specified | HG39: #Error: No range or empty range specified | HH39: #Error: No range or empty range specified | HI39: #Error: No range or empty range specified | HJ39: #Error: No range or empty range specified | HK39: #Error: No range or empty range specified | HL39: #Error: No range or empty range specified | HM39: #Error: No range or empty range specified | HN39: #Error: No range or empty range specified | HO39: #Error: No range or empty range specified | HP39: #Error: No range or empty range specified | HQ39: #Error: No range or empty range specified
HF40: #Error: No range or empty range specified | HG40: #Error: No range or empty range specified | HH40: #Error: No range or empty range specified | HI40: #Error: No range or empty range specified | HJ40: #Error: No range or empty range specified | HK40: #Error: No range or empty range specified | HL40: #Error: No range or empty range specified | HM40: #Error: No range or empty range specified | HN40: #Error: No range or empty range specified | HO40: #Error: No range or empty range specified | HP40: #Error: No range or empty range specified | HQ40: #Error: No range or empty range specified
HF41: #Error: No range or empty range specified | HG41: #Error: No range or empty range specified | HH41: #Error: No range or empty range specified | HI41: #Error: No range or empty range specified | HJ41: #Error: No range or empty range specified | HK41: #Error: No range or empty range specified | HL41: #Error: No range or empty range specified | HM41: #Error: No range or empty range specified | HN41: #Error: No range or empty range specified | HO41: #Error: No range or empty range specified | HP41: #Error: No range or empty range specified | HQ41: #Error: No range or empty range specified
HF42: #Error: No range or empty range specified | HG42: #Error: No range or empty range specified | HH42: #Error: No range or empty range specified | HI42: #Error: No range or empty range specified | HJ42: #Error: No range or empty range specified | HK42: #Error: No range or empty range specified | HL42: #Error: No range or empty range specified | HM42: #Error: No range or empty range specified | HN42: #Error: No range or empty range specified | HO42: #Error: No range or empty range specified | HP42: #Error: No range or empty range specified | HQ42: #Error: No range or empty range specified
HF43: #Error: No range or empty range specified | HG43: #Error: No range or empty range specified | HH43: #Error: No range or empty range specified | HI43: #Error: No range or empty range specified | HJ43: #Error: No range or empty range specified | HK43: #Error: No range or empty range specified | HL43: #Error: No range or empty range specified | HM43: #Error: No range or empty range specified | HN43: #Error: No range or empty range specified | HO43: #Error: No range or empty range specified | HP43: #Error: No range or empty range specified | HQ43: #Error: No range or empty range specified
HF44: #Error: No range or empty range specified | HG44: #Error: No range or empty range specified | HH44: #Error: No range or empty range specified | HI44: #Error: No range or empty range specified | HJ44: #Error: No range or empty range specified | HK44: #Error: No range or empty range specified | HL44: #Error: No range or empty range specified | HM44: #Error: No range or empty range specified | HN44: #Error: No range or empty range specified | HO44: #Error: No range or empty range specified | HP44: #Error: No range or empty range specified | HQ44: #Error: No range or empty range specified
HF45: #Error: No range or empty range specified | HG45: #Error: No range or empty range specified | HH45: #Error: No range or empty range specified | HI45: #Error: No range or empty range specified | HJ45: #Error: No range or empty range specified | HK45: #Error: No range or empty range specified | HL45: #Error: No range or empty range specified | HM45: #Error: No range or empty range specified | HN45: #Error: No range or empty range specified | HO45: #Error: No range or empty range specified | HP45: #Error: No range or empty range specified | HQ45: #Error: No range or empty range specified
HF46: #Error: No range or empty range specified | HG46: #Error: No range or empty range specified | HH46: #Error: No range or empty range specified | HI46: #Error: No range or empty range specified | HJ46: #Error: No range or empty range specified | HK46: #Error: No range or empty range specified | HL46: #Error: No range or empty range specified | HM46: #Error: No range or empty range specified | HN46: #Error: No range or empty range specified | HO46: #Error: No range or empty range specified | HP46: #Error: No range or empty range specified | HQ46: #Error: No range or empty range specified
... HF50: #Error: No range or empty range specified | HG50: #Error: No range or empty range specified | HH50: #Error: No range or empty range specified | HI50: #Error: No range or empty range specified | HJ50: #Error: No range or empty range specified | HK50: #Error: No range or empty range specified | HL50: #Error: No range or empty range specified | HM50: #Error: No range or empty range specified | HN50: #Error: No range or empty range specified | HO50: #Error: No range or empty range specified | HP50: #Error: No range or empty range specified | HQ50: #Error: No range or empty range specified

Sheet EXAMPLE-BOND-ANALYSIS
B2: Create Bond | C2: =_xll.meLWOBondCreate(C14,B14:C20,B23:C39) -> MIZUHO 3.2% 26/03/26 USD@104:3 | E2: Create Bond | F2: =_xll.meLWOBondCreate(F14,E14:F20,E23:F39) -> MIZUHO 3.92% 15-JAN-26 AUD@169:3
B4: Liquid Market Price | C4: ='EXAMPLE-XCCY-ASW-PX'!C15 -> 95.483 | E4: Derived Relative Value Price | F4: ='EXAMPLE-ASW-PX'!D13 -> 100.49514
E5: Yield | F5: =_xll.meLWOBondYield(F2,Settings.COB,F4) -> 0.038171126
E7: Clean Price | F7: =_xll.meLWOBondCleanPrice($F$2,Settings.COB,$F$5) -> 100.49514
E8: Dirty Price | F8: =_xll.meLWOBondDirtyPrice($F$2,Settings.COB,$F$5) -> 100.87625
E9: Accrued Interest | F9: =_xll.meLWOBondAccruedInterest($F$2,Settings.COB) -> 3811.1111
E10: Accrued Days | F10: =_xll.meLWOBondAccruedInterestDays($F$2,Settings.COB) -> 35
B13: BondLVB | C13: PROXY BOND | E13: BondLVB | F13: URIDASHI BOND
B14: BondDescription | C14: MIZUHO 3.2% 26/03/26 USD | E14: BondDescription | F14: MIZUHO 3.92% 15-JAN-26 AUD
B15: BondType | C15: FIXED | E15: BondType | F15: FIXED
B16: Currency | C16: USD | E16: Currency | F16: AUD
B17: ISIN | C17: USJ46186BC59 | E17: ISIN | F17: X1344710857
B18: YieldType | C18: YIELD-TO-MATURITY | E18: YieldType | F18: YIELD-TO-MATURITY
B19: IsCleanPrice | C19: TRUE | E19: IsCleanPrice | F19: TRUE
B20: BondQuoteConvention | C20: QUOTE_IN_32NDS | E20: BondQuoteConvention | F20: QUOTE_IN_32NDS
B22: ScheduleLVB | E22: ScheduleLVB
B23: PayReceive | C23: RECEIVE | E23: PayReceive | F23: RECEIVE
B24: NotionalExchange | C24: START_AND_END | E24: NotionalExchange | F24: START_AND_END
B25: FaceValue | C25: 1000000 | E25: FaceValue | F25: 1000000
B26: ISSUEDATE | C26: 42089 | E26: ISSUEDATE | F26: ='EXAMPLE-ASW-PX'!D16 -> 42566
B27: ACCRUALSTARTDATE | C27: =C26 -> 42089 | E27: ACCRUALSTARTDATE | F27: =F26 -> 42566
B28: FirstCouponDate | E28: FirstCouponDate
B29: LastCouponDate | E29: LastCouponDate
B30: MaturityDate | C30: 45742 | E30: MaturityDate | F30: ='EXAMPLE-ASW-PX'!D19 -> 46037
B31: Coupon | C31: 0.032 | E31: Coupon | F31: ='EXAMPLE-ASW-PX'!D25 -> 0.0392
B32: Frequency | C32: SEMI-ANNUAL | E32: Frequency | F32: SEMI-ANNUAL
B33: AccrualBusinessDayAdjustment | C33: MOD_FOLLOWING | E33: AccrualBusinessDayAdjustment | F33: MOD_FOLLOWING
B34: AccrualCalendar | C34: NYB | E34: AccrualCalendar | F34: SYB
B35: PaymentBusinessDayAdjustment | C35: NO_CHANGE | E35: PaymentBusinessDayAdjustment | F35: NO_CHANGE
B36: PaymentCalendar | C36: NYB | E36: PaymentCalendar | F36: SYB
B37: PaymentLag | C37: 0D | E37: PaymentLag | F37: 0D
B38: DayCount | C38: 30E/360 | E38: DayCount | F38: 30E/360
B39: CalculationType | C39: TYPE1_STREET_CONVENTION | E39: CalculationType | F39: TYPE1_STREET_CONVENTION
